Workbook

Sheet Overview
B2: Mallplaza — Tornado de Sensibilidad Operacional 2026–2028
B3: CFA Research Challenge | Supuestos operacionales declarados con fuente, fecha y tipo de dato
B5: Contenido del archivo
B6: Supuestos | C6: Variables incluidas en el tornado: valor base, rango min/max, fuente, fecha, tipo de dato
B8: Tornado Chart | C8: Cálculo del rango normalizado y gráfico tornado ordenado por magnitud
B10: Variables Excluidas | C10: Variables dejadas de lado (WACC y otras) con motivo de exclusión
B13: Nota metodológica
B14: El tornado mide, para cada variable operacional, el rango observado históricamente (mínimo–máximo) en reportes públicos de Mallplaza (CMF / Interactive Analyst Center), sin proyectar escenarios ni asumir elasticidades no divulgadas. Las barras se ordenan por amplitud relativa del rango respecto al valor base (mayor amplitud = mayor sensibilidad potencial). WACC y otras variables sin evidencia pública suficiente para un rango confiable fueron excluidas — ver hoja 'Variables Excluidas'.
B19: Generado: 2026-09-28 | Fecha de corte de datos: 2Q26 (30-jun-2026), salvo indicación contraria

Sheet Supuestos
B2: Supuestos Operacionales — Tornado de Sensibilidad 2026–2028
B3: Variables incluidas en el tornado (rango público suficiente). Texto azul = valor hardcoded con fuente exacta.
B5: VARIABLES INCLUIDAS EN EL TORNADO
B6: Variable | C6: Definición / unidad | D6: Base | E6: Mínimo | F6: Máximo | G6: Fecha dato | H6: Tipo | I6: Fuente exacta
B7: Ocupación | C7: % GLA arrendado sobre GLA arrendable, consolidado | D7: 0.956 | E7: 0.951 | F7: 0.966 | G7: 2024–2026 | H7: Histórico | I7: Earnings Release 1Q24 (95,1%); comunicado 4Q24 (96,6%); presentación 2Q26 (95,6%) — corporativo.mallplaza.com
B8: Same-store rent growth (SSR) | C8: % crecimiento anual renta, perímetro comparable | D8: 0.054 | E8: 0.037 | F8: 0.094 | G8: 2024–2026 | H8: Histórico | I8: Presentaciones 1Q24 (3,7%), 4Q24 (9,4%), 2Q26 (5,4%) — corporativo.mallplaza.com
B9: Same-store sales growth (SSS) | C9: % crecimiento anual ventas locatarios, perímetro comparable | D9: 0.037 | E9: 0.037 | F9: 0.099 | G9: 2025–2026 | H9: Histórico | I9: Earnings Release 1Q25 (9,9% consolidado; 10,3% Chile); presentación 2Q26 (3,7%) — corporativo.mallplaza.com
B10: Occupancy cost | C10: % ventas locatarios destinado a renta + gastos comunes, consolidado | D10: 0.096 | E10: 0.084 | F10: 0.115 | G10: 2023–2026 | H10: Histórico | I10: Presentaciones 3Q23 (11,5%), 2Q24 (8,4%), 2Q26 (9,6%) — corporativo.mallplaza.com
B11: Margen EBITDA | C11: % EBITDA sobre ingresos consolidados | D11: 0.806 | E11: 0.758 | F11: 0.813 | G11: 2023–2025 | H11: Histórico | I11: Earnings Releases 4Q23 (75,8%), 4Q24 (77,1%), 3Q25 (81,3%), 2Q26 (80,6%) — corporativo.mallplaza.com
B12: Visitas — crecimiento orgánico | C12: % variación anual flujo de visitantes en activos sin M&A reciente | D12: 0.098 | E12: 0.056 | F12: 0.173 | G12: 2024–2025 | H12: Histórico | I12: Comunicado 3Q24 (+5,6% consolidado); Mallplaza Vespucio +17,3% y Mallplaza Trujillo +10,2% (activos específicos, 1Q25/3Q25) — ver exclusión de picos M&A en hoja "Variables Excluidas"
B14: ⚠ Nota: el flujo total de visitas consolidado también creció 26,9% (2Q25) y 29,4% (1Q25) frente al año anterior, pero esos saltos están explicados mayoritariamente por la consolidación de activos peruanos adquiridos a Falabella en 2024 (operación de partes relacionadas), no por crecimiento orgánico. Por eso el rango usado en el tornado excluye esas observaciones y usa crecimientos de activos comparables (3Q24, Vespucio 1Q25, Trujillo 3Q25).

Sheet Tornado Chart
B2: Tornado de Sensibilidad Operacional — Mallplaza 2026–2028
B3: Rango histórico (mín–máx) por variable respecto al valor base, ordenado por amplitud relativa. Fuente: hoja "Supuestos".
B5: CÁLCULO DEL RANGO (referencia directa a hoja Supuestos)
B6: Variable | C6: Base | D6: Mínimo | E6: Máximo | F6: Δ Bajo (Min-Base) | G6: Δ Alto (Max-Base) | H6: Amplitud total
B7: =Supuestos!B7 | C7: =Supuestos!D7 | D7: =Supuestos!E7 | E7: =Supuestos!F7 | F7: =D7-C7 | G7: =E7-C7 | H7: =E7-D7
B8: =Supuestos!B8 | C8: =Supuestos!D8 | D8: =Supuestos!E8 | E8: =Supuestos!F8 | F8: =D8-C8 | G8: =E8-C8 | H8: =E8-D8
B9: =Supuestos!B9 | C9: =Supuestos!D9 | D9: =Supuestos!E9 | E9: =Supuestos!F9 | F9: =D9-C9 | G9: =E9-C9 | H9: =E9-D9
B10: =Supuestos!B10 | C10: =Supuestos!D10 | D10: =Supuestos!E10 | E10: =Supuestos!F10 | F10: =D10-C10 | G10: =E10-C10 | H10: =E10-D10
B11: =Supuestos!B11 | C11: =Supuestos!D11 | D11: =Supuestos!E11 | E11: =Supuestos!F11 | F11: =D11-C11 | G11: =E11-C11 | H11: =E11-D11
B12: =Supuestos!B12 | C12: =Supuestos!D12 | D12: =Supuestos!E12 | E12: =Supuestos!F12 | F12: =D12-C12 | G12: =E12-C12 | H12: =E12-D12
B15: DATOS PARA GRÁFICO (ordenado por amplitud, barra apilada Min→Max)
B16: Variable | C16: Mínimo (barra base invisible) | D16: Amplitud (Max-Min) | E16: Base | F16: Máximo
B17: =B12 | C17: =D12 | D17: =E12-D12 | E17: =C12 | F17: =E12
B18: =B9 | C18: =D9 | D18: =E9-D9 | E18: =C9 | F18: =E9
B19: =B8 | C19: =D8 | D19: =E8-D8 | E19: =C8 | F19: =E8
B20: =B11 | C20: =D11 | D20: =E11-D11 | E20: =C11 | F20: =E11
B21: =B10 | C21: =D10 | D21: =E10-D10 | E21: =C10 | F21: =E10
B22: =B7 | C22: =D7 | D22: =E7-D7 | E22: =C7 | F22: =E7
B48: Lectura: cada barra muestra el rango histórico observado (mínimo a máximo) de la variable en reportes trimestrales 2023–2026 de Mallplaza. No representa un escenario de estrés proyectado ni una sensibilidad de EBITDA en pesos — para traducir estos rangos a impacto en EBITDA/FCF se requiere una elasticidad explícita que Mallplaza no divulga (ver hoja 'Variables Excluidas').

Sheet Variables Excluidas
B2: Variables Dejadas de Lado (sin evidencia pública suficiente)
B3: Se excluyen del tornado por falta de rango confiable, no por juicio de irrelevancia.
B5: VARIABLES EXCLUIDAS Y MOTIVO
B6: Variable | C6: Motivo de exclusión | D6: Qué se necesitaría para incluirla
B7: WACC | C7: No es un supuesto operacional (es tasa de descuento). Mallplaza solo divulga rangos de WACC real después de impuestos por país para valorizar propiedades de inversión (Chile 5,47%–5,63%; Perú 5,75%–5,90%; Colombia 7,20%–7,35%), sin ponderación consolidada ni WACC nominal de equity — EEFF 2Q26, Nota 10, p. 44. | D7: Definir el WACC nominal consolidado del modelo propio del equipo (no es un dato que la compañía vaya a entregar) y usarlo como tasa de descuento separada, no como barra del tornado operacional.
B8: CAPEX (mantenimiento vs. crecimiento) | C8: Solo existe un punto de dato semestral (MMCLP 68.507 en 1H26, Nota 10 EEFF 2Q26, p. 42) sin serie histórica comparable ni apertura entre mantenimiento, expansión y adquisiciones. | D8: Preguntar a management el desembolso anual 2026–2028 separado por naturaleza (mantenimiento vs. crecimiento) y por país.
B9: ROIC por proyecto / retorno sobre nuevas inversiones | C9: Mallplaza no publica NOI estabilizado ni capital invertido por proyecto o activo individual. | D9: Construir cohortes propias por proyecto (CAPEX, fecha de apertura, GLA incorporado, ocupación y renta al año 1, 2 y 3) a partir de earnings releases, o solicitarlo directamente a management.
B10: Same-store NOI | C10: La compañía reporta same-store sales (SSS) y same-store rent (SSR) pero no combina esos ingresos con costos del mismo perímetro para obtener NOI comparable. | D10: Solicitar a management la apertura de costos operacionales por perímetro comparable, o aproximar con margen EBITDA consolidado como proxy (con caveat explícito de que no es igual a NOI same-store).
B11: GLA — crecimiento total (orgánico + M&A) | C11: El crecimiento de GLA reportado (4,2% en 2Q24 hasta 37,6% en 1Q25) mezcla expansión orgánica con la consolidación de activos peruanos adquiridos a Falabella en 2024, lo que distorsiona cualquier rango "orgánico" de crecimiento de superficie. | D11: Pedir a Mallplaza el desglose de GLA incorporado por apertura/expansión versus GLA incorporado por M&A, año a año.
B12: Occupancy cost / contratos por país o categoría | C12: Solo hay observaciones puntuales del dato consolidado; no se encontró serie histórica homogénea por país, categoría de locatario o tipo de contrato (fijo/variable/escalador). | D12: Solicitar a management la serie trimestral de occupancy cost por país y la apertura de renta fija vs. variable por categoría de tienda.
