Workbook

Sheet Valoracion_LTM
A1: Tabla de valoración principal — múltiplos LTM (precio al 30-sep-2026; EEFF LTM 3T25–2T26)
A2: Fuente: Bloomberg. Base LTM para todos porque el consenso NTM no es homogéneo (IRSA con 1 analista). Ver hoja Valoracion_NTM como referencia.
A4: Múltiplos LTM
A5: Empresa | B5: Grupo | C5: País | D5: Período | E5: Market Cap | F5: Deuda neta | G5: Minoritarios | H5: Enterprise Value | I5: Revenue | J5: EBITDA | K5: EBIT | L5: Net Income | M5: Book Value | N5: P/E | O5: EV/EBITDA | P5: EV/EBIT | Q5: EV/Revenue | R5: P/BV
E6: Montos en MM CLP
A7: Mallplaza | B7: Target | C7: Chile | D7: =Datos_BBG!F8 -> LTM | E7: =Datos_BBG!O8*Datos_BBG!S8 -> 7785450 | F7: =Datos_BBG!M8*Datos_BBG!S8 -> 1311568.6 | G7: =Datos_BBG!N8*Datos_BBG!S8 -> 50841.428 | H7: =Datos_BBG!T8*Datos_BBG!S8 -> 9147860 | I7: =Datos_BBG!G8*Datos_BBG!S8 -> 677333.31 | J7: =Datos_BBG!H8*Datos_BBG!S8 -> 544935 | K7: =Datos_BBG!J8*Datos_BBG!S8 -> 540372.73 | L7: =Datos_BBG!K8*Datos_BBG!S8 -> 1258052.7 | M7: =Datos_BBG!L8*Datos_BBG!S8 -> 4820897.8 | N7: =IF(OR(L7<=0,Datos_BBG!Q8=1),"NM",IF(E7/L7>Supuestos!$B$17,"NM",E7/L7)) -> 6.1884925 | O7: =IF(OR(J7<=0),"NM",IF(H7/J7>Supuestos!$B$17,"NM",H7/J7)) -> 16.787066 | P7: =IF(OR(K7<=0),"NM",IF(H7/K7>Supuestos!$B$17,"NM",H7/K7)) -> 16.928797 | Q7: =IF(OR(I7<=0),"NM",IF(H7/I7>Supuestos!$B$17,"NM",H7/I7)) -> 13.505699 | R7: =IF(OR(M7<=0),"NM",IF(E7/M7>Supuestos!$B$17,"NM",E7/M7)) -> 1.6149378
A8: Parque Arauco | B8: Core | C8: Chile | D8: =Datos_BBG!F13 -> LTM | E8: =Datos_BBG!O13*Datos_BBG!S13 -> 3440408.4 | F8: =Datos_BBG!M13*Datos_BBG!S13 -> 1602287.6 | G8: =Datos_BBG!N13*Datos_BBG!S13 -> 386791.14 | H8: =Datos_BBG!T13*Datos_BBG!S13 -> 5429487.2 | I8: =Datos_BBG!G13*Datos_BBG!S13 -> 416366.83 | J8: =Datos_BBG!H13*Datos_BBG!S13 -> 294411 | K8: =Datos_BBG!J13*Datos_BBG!S13 -> 289515.61 | L8: =Datos_BBG!K13*Datos_BBG!S13 -> 154352.78 | M8: =Datos_BBG!L13*Datos_BBG!S13 -> 1961393.2 | N8: =IF(OR(L8<=0,Datos_BBG!Q13=1),"NM",IF(E8/L8>Supuestos!$B$17,"NM",E8/L8)) -> 22.289255 | O8: =IF(OR(J8<=0),"NM",IF(H8/J8>Supuestos!$B$17,"NM",H8/J8)) -> 18.441862 | P8: =IF(OR(K8<=0),"NM",IF(H8/K8>Supuestos!$B$17,"NM",H8/K8)) -> 18.753694 | Q8: =IF(OR(I8<=0),"NM",IF(H8/I8>Supuestos!$B$17,"NM",H8/I8)) -> 13.040153 | R8: =IF(OR(M8<=0),"NM",IF(E8/M8>Supuestos!$B$17,"NM",E8/M8)) -> 1.7540636
A9: Cencosud Shopping | B9: Core | C9: Chile | D9: =Datos_BBG!F18 -> LTM | E9: =Datos_BBG!O18*Datos_BBG!S18 -> 3710182.6 | F9: =Datos_BBG!M18*Datos_BBG!S18 -> 852533.94 | G9: =Datos_BBG!N18*Datos_BBG!S18 -> 6464.021 | H9: =Datos_BBG!T18*Datos_BBG!S18 -> 4569180.6 | I9: =Datos_BBG!G18*Datos_BBG!S18 -> 390677.95 | J9: =Datos_BBG!H18*Datos_BBG!S18 -> 350561.25 | K9: =Datos_BBG!J18*Datos_BBG!S18 -> 349975.94 | L9: =Datos_BBG!K18*Datos_BBG!S18 -> 353938.28 | M9: =Datos_BBG!L18*Datos_BBG!S18 -> 3136456.8 | N9: =IF(OR(L9<=0,Datos_BBG!Q18=1),"NM",IF(E9/L9>Supuestos!$B$17,"NM",E9/L9)) -> 10.482569 | O9: =IF(OR(J9<=0),"NM",IF(H9/J9>Supuestos!$B$17,"NM",H9/J9)) -> 13.033901 | P9: =IF(OR(K9<=0),"NM",IF(H9/K9>Supuestos!$B$17,"NM",H9/K9)) -> 13.055699 | Q9: =IF(OR(I9<=0),"NM",IF(H9/I9>Supuestos!$B$17,"NM",H9/I9)) -> 11.695517 | R9: =IF(OR(M9<=0),"NM",IF(E9/M9>Supuestos!$B$17,"NM",E9/M9)) -> 1.1829216
A10: Multiplan | B10: Core | C10: Brasil | D10: =Datos_BBG!F23 -> LTM | E10: =Datos_BBG!O23*Datos_BBG!S23 -> 2907890.3 | F10: =Datos_BBG!M23*Datos_BBG!S23 -> 888983.2 | G10: =Datos_BBG!N23*Datos_BBG!S23 -> 33.049177 | H10: =Datos_BBG!T23*Datos_BBG!S23 -> 3796906.6 | I10: =Datos_BBG!G23*Datos_BBG!S23 -> 570440.4 | J10: =Datos_BBG!H23*Datos_BBG!S23 -> 421296.08 | K10: =Datos_BBG!J23*Datos_BBG!S23 -> 397146.06 | L10: =Datos_BBG!K23*Datos_BBG!S23 -> 247648.38 | M10: =Datos_BBG!L23*Datos_BBG!S23 -> 1206875.9 | N10: =IF(OR(L10<=0,Datos_BBG!Q23=1),"NM",IF(E10/L10>Supuestos!$B$17,"NM",E10/L10)) -> 11.742012 | O10: =IF(OR(J10<=0),"NM",IF(H10/J10>Supuestos!$B$17,"NM",H10/J10)) -> 9.0124423 | P10: =IF(OR(K10<=0),"NM",IF(H10/K10>Supuestos!$B$17,"NM",H10/K10)) -> 9.560479 | Q10: =IF(OR(I10<=0),"NM",IF(H10/I10>Supuestos!$B$17,"NM",H10/I10)) -> 6.6560969 | R10: =IF(OR(M10<=0),"NM",IF(E10/M10>Supuestos!$B$17,"NM",E10/M10)) -> 2.4094361
A11: Allos | B11: Core | C11: Brasil | D11: =Datos_BBG!F28 -> LTM | E11: =Datos_BBG!O28*Datos_BBG!S28 -> 2656187.5 | F11: =Datos_BBG!M28*Datos_BBG!S28 -> 1221640.7 | G11: =Datos_BBG!N28*Datos_BBG!S28 -> 17188.966 | H11: =Datos_BBG!T28*Datos_BBG!S28 -> 3895017.2 | I11: =Datos_BBG!G28*Datos_BBG!S28 -> 524937.58 | J11: =Datos_BBG!H28*Datos_BBG!S28 -> 388838.75 | K11: =Datos_BBG!J28*Datos_BBG!S28 -> 276308.45 | L11: =Datos_BBG!K28*Datos_BBG!S28 -> 166950.15 | M11: =Datos_BBG!L28*Datos_BBG!S28 -> 2296067.8 | N11: =IF(OR(L11<=0,Datos_BBG!Q28=1),"NM",IF(E11/L11>Supuestos!$B$17,"NM",E11/L11)) -> 15.910064 | O11: =IF(OR(J11<=0),"NM",IF(H11/J11>Supuestos!$B$17,"NM",H11/J11)) -> 10.01705 | P11: =IF(OR(K11<=0),"NM",IF(H11/K11>Supuestos!$B$17,"NM",H11/K11)) -> 14.096627 | Q11: =IF(OR(I11<=0),"NM",IF(H11/I11>Supuestos!$B$17,"NM",H11/I11)) -> 7.4199625 | R11: =IF(OR(M11<=0),"NM",IF(E11/M11>Supuestos!$B$17,"NM",E11/M11)) -> 1.1568419
A12: Iguatemi | B12: Core | C12: Brasil | D12: =Datos_BBG!F33 -> LTM | E12: =Datos_BBG!O33*Datos_BBG!S33 -> 1381189.7 | F12: =Datos_BBG!M33*Datos_BBG!S33 -> 382047.95 | G12: =Datos_BBG!N33*Datos_BBG!S33 -> 38.944435 | H12: =Datos_BBG!T33*Datos_BBG!S33 -> 1763276.6 | I12: =Datos_BBG!G33*Datos_BBG!S33 -> 272862.76 | J12: =Datos_BBG!H33*Datos_BBG!S33 -> 201422.94 | K12: =Datos_BBG!J33*Datos_BBG!S33 -> 178237.78 | L12: =Datos_BBG!K33*Datos_BBG!S33 -> 114077 | M12: =Datos_BBG!L33*Datos_BBG!S33 -> 881991.06 | N12: =IF(OR(L12<=0,Datos_BBG!Q33=1),"NM",IF(E12/L12>Supuestos!$B$17,"NM",E12/L12)) -> 12.107521 | O12: =IF(OR(J12<=0),"NM",IF(H12/J12>Supuestos!$B$17,"NM",H12/J12)) -> 8.7541002 | P12: =IF(OR(K12<=0),"NM",IF(H12/K12>Supuestos!$B$17,"NM",H12/K12)) -> 9.892833 | Q12: =IF(OR(I12<=0),"NM",IF(H12/I12>Supuestos!$B$17,"NM",H12/I12)) -> 6.4621374 | R12: =IF(OR(M12<=0),"NM",IF(E12/M12>Supuestos!$B$17,"NM",E12/M12)) -> 1.5659906
A13: IRSA | B13: Sensibilidad | C13: Argentina | D13: =Datos_BBG!F38 -> LTM | E13: =Datos_BBG!O38*Datos_BBG!S38 -> 1140416.5 | F13: =Datos_BBG!M38*Datos_BBG!S38 -> 561235.18 | G13: =Datos_BBG!N38*Datos_BBG!S38 -> 87538.904 | H13: =Datos_BBG!T38*Datos_BBG!S38 -> 1789190.5 | I13: =Datos_BBG!G38*Datos_BBG!S38 -> 409298.64 | J13: =Datos_BBG!H38*Datos_BBG!S38 -> 145686.2 | K13: =Datos_BBG!J38*Datos_BBG!S38 -> 135134.94 | L13: =Datos_BBG!K38*Datos_BBG!S38 -> 244905.54 | M13: =Datos_BBG!L38*Datos_BBG!S38 -> 1418831.5 | N13: =IF(OR(L13<=0,Datos_BBG!Q38=1),"NM",IF(E13/L13>Supuestos!$B$17,"NM",E13/L13)) -> 4.6565564 | O13: =IF(OR(J13<=0),"NM",IF(H13/J13>Supuestos!$B$17,"NM",H13/J13)) -> 12.281125 | P13: =IF(OR(K13<=0),"NM",IF(H13/K13>Supuestos!$B$17,"NM",H13/K13)) -> 13.240029 | Q13: =IF(OR(I13<=0),"NM",IF(H13/I13>Supuestos!$B$17,"NM",H13/I13)) -> 4.3713571 | R13: =IF(OR(M13<=0),"NM",IF(E13/M13>Supuestos!$B$17,"NM",E13/M13)) -> 0.80377159
A14: Fibra Danhos | B14: Sensibilidad | C14: México | D14: =Datos_BBG!F43 -> LTM | E14: =Datos_BBG!O43*Datos_BBG!S43 -> 2383999.4 | F14: =Datos_BBG!M43*Datos_BBG!S43 -> 618003.43 | G14: =Datos_BBG!N43*Datos_BBG!S43 -> 155940.9 | H14: =Datos_BBG!T43*Datos_BBG!S43 -> 3157943.8 | I14: =Datos_BBG!G43*Datos_BBG!S43 -> 417411.61 | J14: =Datos_BBG!H43*Datos_BBG!S43 -> 277625.06 | K14: =Datos_BBG!J43*Datos_BBG!S43 -> 276925.52 | L14: =Datos_BBG!K43*Datos_BBG!S43 -> 301542.11 | M14: =Datos_BBG!L43*Datos_BBG!S43 -> 3445417.1 | N14: =IF(OR(L14<=0,Datos_BBG!Q43=1),"NM",IF(E14/L14>Supuestos!$B$17,"NM",E14/L14)) -> 7.9060247 | O14: =IF(OR(J14<=0),"NM",IF(H14/J14>Supuestos!$B$17,"NM",H14/J14)) -> 11.374851 | P14: =IF(OR(K14<=0),"NM",IF(H14/K14>Supuestos!$B$17,"NM",H14/K14)) -> 11.403585 | Q14: =IF(OR(I14<=0),"NM",IF(H14/I14>Supuestos!$B$17,"NM",H14/I14)) -> 7.5655389 | R14: =IF(OR(M14<=0),"NM",IF(E14/M14>Supuestos!$B$17,"NM",E14/M14)) -> 0.69193348
A15: Mediana Core | N15: =IFERROR(MEDIAN(N8:N12),"NM") -> 12.107521 | O15: =IFERROR(MEDIAN(O8:O12),"NM") -> 10.01705 | P15: =IFERROR(MEDIAN(P8:P12),"NM") -> 13.055699 | Q15: =IFERROR(MEDIAN(Q8:Q12),"NM") -> 7.4199625 | R15: =IFERROR(MEDIAN(R8:R12),"NM") -> 1.5659906
A16: Promedio Core | N16: =IFERROR(AVERAGE(N8:N12),"NM") -> 14.506284 | O16: =IFERROR(AVERAGE(O8:O12),"NM") -> 11.851871 | P16: =IFERROR(AVERAGE(P8:P12),"NM") -> 13.071866 | Q16: =IFERROR(AVERAGE(Q8:Q12),"NM") -> 9.0547733 | R16: =IFERROR(AVERAGE(R8:R12),"NM") -> 1.6138508
A17: Mediana Core + Sensibilidad | N17: =IFERROR(MEDIAN(N8:N14),"NM") -> 11.742012 | O17: =IFERROR(MEDIAN(O8:O14),"NM") -> 11.374851 | P17: =IFERROR(MEDIAN(P8:P14),"NM") -> 13.055699 | Q17: =IFERROR(MEDIAN(Q8:Q14),"NM") -> 7.4199625 | R17: =IFERROR(MEDIAN(R8:R14),"NM") -> 1.1829216
A18: Promedio Core + Sensibilidad | N18: =IFERROR(AVERAGE(N8:N14),"NM") -> 12.156286 | O18: =IFERROR(AVERAGE(O8:O14),"NM") -> 11.845047 | P18: =IFERROR(AVERAGE(P8:P14),"NM") -> 12.857564 | Q18: =IFERROR(AVERAGE(Q8:Q14),"NM") -> 8.1729661 | R18: =IFERROR(AVERAGE(R8:R14),"NM") -> 1.3664227
A19: Mallplaza vs mediana Core (prima / (descuento)) | N19: =IFERROR(N7/N15-1,"NM") -> -0.48887204 | O19: =IFERROR(O7/O15-1,"NM") -> 0.67584932 | P19: =IFERROR(P7/P15-1,"NM") -> 0.29665954 | Q19: =IFERROR(Q7/Q15-1,"NM") -> 0.82018432 | R19: =IFERROR(R7/R15-1,"NM") -> 0.031256346
A21: NM = denominador ≤ 0, múltiplo sobre umbral (Supuestos!B17) o utilidad no recurrente. P/E de Mallplaza, Parque Arauco, Cencosud Shopping, IRSA y Danhos incluye revalorización de propiedades (valor razonable); los brasileños contabilizan a costo.

Sheet Valoracion_NTM
A1: Referencia — múltiplos NTM con consenso Bloomberg BEst (no usar como tabla principal)
A2: EV y Book Value al 30-jun-2026 / precio 30-sep-2026; flujos = consenso 12m forward. IRSA: 1 analista; Danhos: 9. P/BV es el mismo que LTM (no hay BV forward).
A4: Múltiplos NTM (BF)
A5: Empresa | B5: Grupo | C5: País | D5: Período | E5: Market Cap | F5: Deuda neta | G5: Minoritarios | H5: Enterprise Value | I5: Revenue | J5: EBITDA | K5: EBIT | L5: Net Income | M5: Book Value | N5: P/E | O5: EV/EBITDA | P5: EV/EBIT | Q5: EV/Revenue | R5: P/BV
E6: Montos en MM CLP
A7: Mallplaza | B7: Target | C7: Chile | D7: NTM (BF) | E7: =Datos_BBG!O8*Datos_BBG!S8 -> 7785450 | F7: =Datos_BBG!M8*Datos_BBG!S8 -> 1311568.6 | G7: =Datos_BBG!N8*Datos_BBG!S8 -> 50841.428 | H7: =Datos_BBG!T8*Datos_BBG!S8 -> 9147860 | I7: =Datos_BBG!G47*Datos_BBG!S47 -> 758569.53 | J7: =Datos_BBG!H47*Datos_BBG!S47 -> 617130.34 | K7: =Datos_BBG!I47*Datos_BBG!S47 -> 611889.82 | L7: =Datos_BBG!J47*Datos_BBG!S47 -> 488981.25 | M7: =Datos_BBG!L8*Datos_BBG!S8 -> 4820897.8 | N7: =IF(OR(L7<=0),"NM",IF(E7/L7>Supuestos!$B$17,"NM",E7/L7)) -> 15.921776 | O7: =IF(OR(J7<=0),"NM",IF(H7/J7>Supuestos!$B$17,"NM",H7/J7)) -> 14.823222 | P7: =IF(OR(K7<=0),"NM",IF(H7/K7>Supuestos!$B$17,"NM",H7/K7)) -> 14.950175 | Q7: =IF(OR(I7<=0),"NM",IF(H7/I7>Supuestos!$B$17,"NM",H7/I7)) -> 12.059356 | R7: =IF(OR(M7<=0),"NM",IF(E7/M7>Supuestos!$B$17,"NM",E7/M7)) -> 1.6149378
A8: Parque Arauco | B8: Core | C8: Chile | D8: NTM (BF) | E8: =Datos_BBG!O13*Datos_BBG!S13 -> 3440408.4 | F8: =Datos_BBG!M13*Datos_BBG!S13 -> 1602287.6 | G8: =Datos_BBG!N13*Datos_BBG!S13 -> 386791.14 | H8: =Datos_BBG!T13*Datos_BBG!S13 -> 5429487.2 | I8: =Datos_BBG!G48*Datos_BBG!S48 -> 475685.59 | J8: =Datos_BBG!H48*Datos_BBG!S48 -> 342581.95 | K8: =Datos_BBG!I48*Datos_BBG!S48 -> 347536.96 | L8: =Datos_BBG!J48*Datos_BBG!S48 -> 166719.85 | M8: =Datos_BBG!L13*Datos_BBG!S13 -> 1961393.2 | N8: =IF(OR(L8<=0),"NM",IF(E8/L8>Supuestos!$B$17,"NM",E8/L8)) -> 20.635866 | O8: =IF(OR(J8<=0),"NM",IF(H8/J8>Supuestos!$B$17,"NM",H8/J8)) -> 15.848725 | P8: =IF(OR(K8<=0),"NM",IF(H8/K8>Supuestos!$B$17,"NM",H8/K8)) -> 15.622762 | Q8: =IF(OR(I8<=0),"NM",IF(H8/I8>Supuestos!$B$17,"NM",H8/I8)) -> 11.414025 | R8: =IF(OR(M8<=0),"NM",IF(E8/M8>Supuestos!$B$17,"NM",E8/M8)) -> 1.7540636
A9: Cencosud Shopping | B9: Core | C9: Chile | D9: NTM (BF) | E9: =Datos_BBG!O18*Datos_BBG!S18 -> 3710182.6 | F9: =Datos_BBG!M18*Datos_BBG!S18 -> 852533.94 | G9: =Datos_BBG!N18*Datos_BBG!S18 -> 6464.021 | H9: =Datos_BBG!T18*Datos_BBG!S18 -> 4569180.6 | I9: =Datos_BBG!G49*Datos_BBG!S49 -> 436396.65 | J9: =Datos_BBG!H49*Datos_BBG!S49 -> 392093.8 | K9: =Datos_BBG!I49*Datos_BBG!S49 -> 395608.2 | L9: =Datos_BBG!J49*Datos_BBG!S49 -> 278140.73 | M9: =Datos_BBG!L18*Datos_BBG!S18 -> 3136456.8 | N9: =IF(OR(L9<=0),"NM",IF(E9/L9>Supuestos!$B$17,"NM",E9/L9)) -> 13.339228 | O9: =IF(OR(J9<=0),"NM",IF(H9/J9>Supuestos!$B$17,"NM",H9/J9)) -> 11.653284 | P9: =IF(OR(K9<=0),"NM",IF(H9/K9>Supuestos!$B$17,"NM",H9/K9)) -> 11.549762 | Q9: =IF(OR(I9<=0),"NM",IF(H9/I9>Supuestos!$B$17,"NM",H9/I9)) -> 10.470247 | R9: =IF(OR(M9<=0),"NM",IF(E9/M9>Supuestos!$B$17,"NM",E9/M9)) -> 1.1829216
A10: Multiplan | B10: Core | C10: Brasil | D10: NTM (BF) | E10: =Datos_BBG!O23*Datos_BBG!S23 -> 2907890.3 | F10: =Datos_BBG!M23*Datos_BBG!S23 -> 888983.2 | G10: =Datos_BBG!N23*Datos_BBG!S23 -> 33.049177 | H10: =Datos_BBG!T23*Datos_BBG!S23 -> 3796906.6 | I10: =Datos_BBG!G50*Datos_BBG!S50 -> 500704.76 | J10: =Datos_BBG!H50*Datos_BBG!S50 -> 376773.26 | K10: =Datos_BBG!I50*Datos_BBG!S50 -> 351478.35 | L10: =Datos_BBG!J50*Datos_BBG!S50 -> 230718.54 | M10: =Datos_BBG!L23*Datos_BBG!S23 -> 1206875.9 | N10: =IF(OR(L10<=0),"NM",IF(E10/L10>Supuestos!$B$17,"NM",E10/L10)) -> 12.603627 | O10: =IF(OR(J10<=0),"NM",IF(H10/J10>Supuestos!$B$17,"NM",H10/J10)) -> 10.077431 | P10: =IF(OR(K10<=0),"NM",IF(H10/K10>Supuestos!$B$17,"NM",H10/K10)) -> 10.802676 | Q10: =IF(OR(I10<=0),"NM",IF(H10/I10>Supuestos!$B$17,"NM",H10/I10)) -> 7.5831246 | R10: =IF(OR(M10<=0),"NM",IF(E10/M10>Supuestos!$B$17,"NM",E10/M10)) -> 2.4094361
A11: Allos | B11: Core | C11: Brasil | D11: NTM (BF) | E11: =Datos_BBG!O28*Datos_BBG!S28 -> 2656187.5 | F11: =Datos_BBG!M28*Datos_BBG!S28 -> 1221640.7 | G11: =Datos_BBG!N28*Datos_BBG!S28 -> 17188.966 | H11: =Datos_BBG!T28*Datos_BBG!S28 -> 3895017.2 | I11: =Datos_BBG!G51*Datos_BBG!S51 -> 556686.83 | J11: =Datos_BBG!H51*Datos_BBG!S51 -> 413640.61 | K11: =Datos_BBG!I51*Datos_BBG!S51 -> 307838.83 | L11: =Datos_BBG!J51*Datos_BBG!S51 -> 169670.61 | M11: =Datos_BBG!L28*Datos_BBG!S28 -> 2296067.8 | N11: =IF(OR(L11<=0),"NM",IF(E11/L11>Supuestos!$B$17,"NM",E11/L11)) -> 15.654966 | O11: =IF(OR(J11<=0),"NM",IF(H11/J11>Supuestos!$B$17,"NM",H11/J11)) -> 9.4164284 | P11: =IF(OR(K11<=0),"NM",IF(H11/K11>Supuestos!$B$17,"NM",H11/K11)) -> 12.652781 | Q11: =IF(OR(I11<=0),"NM",IF(H11/I11>Supuestos!$B$17,"NM",H11/I11)) -> 6.9967834 | R11: =IF(OR(M11<=0),"NM",IF(E11/M11>Supuestos!$B$17,"NM",E11/M11)) -> 1.1568419
A12: Iguatemi | B12: Core | C12: Brasil | D12: NTM (BF) | E12: =Datos_BBG!O33*Datos_BBG!S33 -> 1381189.7 | F12: =Datos_BBG!M33*Datos_BBG!S33 -> 382047.95 | G12: =Datos_BBG!N33*Datos_BBG!S33 -> 38.944435 | H12: =Datos_BBG!T33*Datos_BBG!S33 -> 1763276.6 | I12: =Datos_BBG!G52*Datos_BBG!S52 -> 318249.75 | J12: =Datos_BBG!H52*Datos_BBG!S52 -> 238273.43 | K12: =Datos_BBG!I52*Datos_BBG!S52 -> 198790.21 | L12: =Datos_BBG!J52*Datos_BBG!S52 -> 116096.06 | M12: =Datos_BBG!L33*Datos_BBG!S33 -> 881991.06 | N12: =IF(OR(L12<=0),"NM",IF(E12/L12>Supuestos!$B$17,"NM",E12/L12)) -> 11.896956 | O12: =IF(OR(J12<=0),"NM",IF(H12/J12>Supuestos!$B$17,"NM",H12/J12)) -> 7.4002234 | P12: =IF(OR(K12<=0),"NM",IF(H12/K12>Supuestos!$B$17,"NM",H12/K12)) -> 8.8700377 | Q12: =IF(OR(I12<=0),"NM",IF(H12/I12>Supuestos!$B$17,"NM",H12/I12)) -> 5.5405437 | R12: =IF(OR(M12<=0),"NM",IF(E12/M12>Supuestos!$B$17,"NM",E12/M12)) -> 1.5659906
A13: IRSA | B13: Sensibilidad | C13: Argentina | D13: NTM (BF) | E13: =Datos_BBG!O38*Datos_BBG!S38 -> 1140416.5 | F13: =Datos_BBG!M38*Datos_BBG!S38 -> 561235.18 | G13: =Datos_BBG!N38*Datos_BBG!S38 -> 87538.904 | H13: =Datos_BBG!T38*Datos_BBG!S38 -> 1789190.5 | I13: =Datos_BBG!G53*Datos_BBG!S53 -> 441170.17 | J13: =Datos_BBG!H53*Datos_BBG!S53 -> 286774.76 | K13: =Datos_BBG!I53*Datos_BBG!S53 -> 276449.27 | L13: =Datos_BBG!J53*Datos_BBG!S53 -> 124170.2 | M13: =Datos_BBG!L38*Datos_BBG!S38 -> 1418831.5 | N13: =IF(OR(L13<=0),"NM",IF(E13/L13>Supuestos!$B$17,"NM",E13/L13)) -> 9.1843005 | O13: =IF(OR(J13<=0),"NM",IF(H13/J13>Supuestos!$B$17,"NM",H13/J13)) -> 6.2390099 | P13: =IF(OR(K13<=0),"NM",IF(H13/K13>Supuestos!$B$17,"NM",H13/K13)) -> 6.4720393 | Q13: =IF(OR(I13<=0),"NM",IF(H13/I13>Supuestos!$B$17,"NM",H13/I13)) -> 4.0555564 | R13: =IF(OR(M13<=0),"NM",IF(E13/M13>Supuestos!$B$17,"NM",E13/M13)) -> 0.80377159
A14: Fibra Danhos | B14: Sensibilidad | C14: México | D14: NTM (BF) | E14: =Datos_BBG!O43*Datos_BBG!S43 -> 2383999.4 | F14: =Datos_BBG!M43*Datos_BBG!S43 -> 618003.43 | G14: =Datos_BBG!N43*Datos_BBG!S43 -> 155940.9 | H14: =Datos_BBG!T43*Datos_BBG!S43 -> 3157943.8 | I14: =Datos_BBG!G54*Datos_BBG!S54 -> 439412.66 | J14: =Datos_BBG!H54*Datos_BBG!S54 -> 313368.82 | K14: =Datos_BBG!I54*Datos_BBG!S54 -> 313955.14 | L14: =Datos_BBG!J54*Datos_BBG!S54 -> 280237.69 | M14: =Datos_BBG!L43*Datos_BBG!S43 -> 3445417.1 | N14: =IF(OR(L14<=0),"NM",IF(E14/L14>Supuestos!$B$17,"NM",E14/L14)) -> 8.507062 | O14: =IF(OR(J14<=0),"NM",IF(H14/J14>Supuestos!$B$17,"NM",H14/J14)) -> 10.077403 | P14: =IF(OR(K14<=0),"NM",IF(H14/K14>Supuestos!$B$17,"NM",H14/K14)) -> 10.058583 | Q14: =IF(OR(I14<=0),"NM",IF(H14/I14>Supuestos!$B$17,"NM",H14/I14)) -> 7.1867382 | R14: =IF(OR(M14<=0),"NM",IF(E14/M14>Supuestos!$B$17,"NM",E14/M14)) -> 0.69193348
A15: Mediana Core | N15: =IFERROR(MEDIAN(N8:N12),"NM") -> 13.339228 | O15: =IFERROR(MEDIAN(O8:O12),"NM") -> 10.077431 | P15: =IFERROR(MEDIAN(P8:P12),"NM") -> 11.549762 | Q15: =IFERROR(MEDIAN(Q8:Q12),"NM") -> 7.5831246 | R15: =IFERROR(MEDIAN(R8:R12),"NM") -> 1.5659906
A16: Promedio Core | N16: =IFERROR(AVERAGE(N8:N12),"NM") -> 14.826128 | O16: =IFERROR(AVERAGE(O8:O12),"NM") -> 10.879219 | P16: =IFERROR(AVERAGE(P8:P12),"NM") -> 11.899604 | Q16: =IFERROR(AVERAGE(Q8:Q12),"NM") -> 8.4009446 | R16: =IFERROR(AVERAGE(R8:R12),"NM") -> 1.6138508
A17: Mediana Core + Sensibilidad | N17: =IFERROR(MEDIAN(N8:N14),"NM") -> 12.603627 | O17: =IFERROR(MEDIAN(O8:O14),"NM") -> 10.077403 | P17: =IFERROR(MEDIAN(P8:P14),"NM") -> 10.802676 | Q17: =IFERROR(MEDIAN(Q8:Q14),"NM") -> 7.1867382 | R17: =IFERROR(MEDIAN(R8:R14),"NM") -> 1.1829216
A18: Promedio Core + Sensibilidad | N18: =IFERROR(AVERAGE(N8:N14),"NM") -> 13.117429 | O18: =IFERROR(AVERAGE(O8:O14),"NM") -> 10.101786 | P18: =IFERROR(AVERAGE(P8:P14),"NM") -> 10.861234 | Q18: =IFERROR(AVERAGE(Q8:Q14),"NM") -> 7.6067168 | R18: =IFERROR(AVERAGE(R8:R14),"NM") -> 1.3664227
A19: Mallplaza vs mediana Core (prima / (descuento)) | N19: =IFERROR(N7/N15-1,"NM") -> 0.19360554 | O19: =IFERROR(O7/O15-1,"NM") -> 0.47093259 | P19: =IFERROR(P7/P15-1,"NM") -> 0.29441414 | Q19: =IFERROR(Q7/Q15-1,"NM") -> 0.59028853 | R19: =IFERROR(R7/R15-1,"NM") -> 0.031256346

Sheet Historico
A1: Verificación histórica — FY2022 a FY2025 y LTM (misma definición para todos los peers)
A2: FY = precio y balance al cierre de cada ejercicio (IRSA: ejercicio jul-jun, cierre junio). Montos a CLP con TC fijo 30-jun-2026; los múltiplos no dependen del TC.
A4: FY2022
A5: Empresa | B5: Grupo | C5: País | D5: Período | E5: Market Cap | F5: Deuda neta | G5: Minoritarios | H5: Enterprise Value | I5: Revenue | J5: EBITDA | K5: EBIT | L5: Net Income | M5: Book Value | N5: P/E | O5: EV/EBITDA | P5: EV/EBIT | Q5: EV/Revenue | R5: P/BV
E6: Montos en MM CLP
A7: Mallplaza | B7: Target | C7: Chile | D7: =Datos_BBG!F4 -> FY2022 | E7: =Datos_BBG!O4*Datos_BBG!S4 -> 2073680 | F7: =Datos_BBG!M4*Datos_BBG!S4 -> 1011613.3 | G7: =Datos_BBG!N4*Datos_BBG!S4 -> 168378.48 | H7: =Datos_BBG!T4*Datos_BBG!S4 -> 3253671.8 | I7: =Datos_BBG!G4*Datos_BBG!S4 -> 370898.93 | J7: =Datos_BBG!H4*Datos_BBG!S4 -> 282699 | K7: =Datos_BBG!J4*Datos_BBG!S4 -> 280533.6 | L7: =Datos_BBG!K4*Datos_BBG!S4 -> 157666.76 | M7: =Datos_BBG!L4*Datos_BBG!S4 -> 2263298.5 | N7: =IF(OR(L7<=0,Datos_BBG!Q4=1),"NM",IF(E7/L7>Supuestos!$B$17,"NM",E7/L7)) -> 13.152297 | O7: =IF(OR(J7<=0),"NM",IF(H7/J7>Supuestos!$B$17,"NM",H7/J7)) -> 11.509315 | P7: =IF(OR(K7<=0),"NM",IF(H7/K7>Supuestos!$B$17,"NM",H7/K7)) -> 11.598153 | Q7: =IF(OR(I7<=0),"NM",IF(H7/I7>Supuestos!$B$17,"NM",H7/I7)) -> 8.7723946 | R7: =IF(OR(M7<=0),"NM",IF(E7/M7>Supuestos!$B$17,"NM",E7/M7)) -> 0.91622029
A8: Parque Arauco | B8: Core | C8: Chile | D8: =Datos_BBG!F9 -> FY2022 | E8: =Datos_BBG!O9*Datos_BBG!S9 -> 979894.01 | F8: =Datos_BBG!M9*Datos_BBG!S9 -> 989079.05 | G8: =Datos_BBG!N9*Datos_BBG!S9 -> 211136.22 | H8: =Datos_BBG!T9*Datos_BBG!S9 -> 2180109.3 | I8: =Datos_BBG!G9*Datos_BBG!S9 -> 243119.54 | J8: =Datos_BBG!H9*Datos_BBG!S9 -> 170697 | K8: =Datos_BBG!J9*Datos_BBG!S9 -> 165568.62 | L8: =Datos_BBG!K9*Datos_BBG!S9 -> 101031.63 | M8: =Datos_BBG!L9*Datos_BBG!S9 -> 1144928.9 | N8: =IF(OR(L8<=0,Datos_BBG!Q9=1),"NM",IF(E8/L8>Supuestos!$B$17,"NM",E8/L8)) -> 9.6988831 | O8: =IF(OR(J8<=0),"NM",IF(H8/J8>Supuestos!$B$17,"NM",H8/J8)) -> 12.771808 | P8: =IF(OR(K8<=0),"NM",IF(H8/K8>Supuestos!$B$17,"NM",H8/K8)) -> 13.167406 | Q8: =IF(OR(I8<=0),"NM",IF(H8/I8>Supuestos!$B$17,"NM",H8/I8)) -> 8.9672318 | R8: =IF(OR(M8<=0),"NM",IF(E8/M8>Supuestos!$B$17,"NM",E8/M8)) -> 0.85585581
A9: Cencosud Shopping | B9: Core | C9: Chile | D9: =Datos_BBG!F14 -> FY2022 | E9: =Datos_BBG!O14*Datos_BBG!S14 -> 2283766.6 | F9: =Datos_BBG!M14*Datos_BBG!S14 -> 636796.49 | G9: =Datos_BBG!N14*Datos_BBG!S14 -> 4966.978 | H9: =Datos_BBG!T14*Datos_BBG!S14 -> 2925530.1 | I9: =Datos_BBG!G14*Datos_BBG!S14 -> 286949.85 | J9: =Datos_BBG!H14*Datos_BBG!S14 -> 258583.7 | K9: =Datos_BBG!J14*Datos_BBG!S14 -> 258404.86 | L9: =Datos_BBG!K14*Datos_BBG!S14 -> 181875.55 | M9: =Datos_BBG!L14*Datos_BBG!S14 -> 2679608.6 | N9: =IF(OR(L9<=0,Datos_BBG!Q14=1),"NM",IF(E9/L9>Supuestos!$B$17,"NM",E9/L9)) -> 12.556755 | O9: =IF(OR(J9<=0),"NM",IF(H9/J9>Supuestos!$B$17,"NM",H9/J9)) -> 11.313668 | P9: =IF(OR(K9<=0),"NM",IF(H9/K9>Supuestos!$B$17,"NM",H9/K9)) -> 11.321498 | Q9: =IF(OR(I9<=0),"NM",IF(H9/I9>Supuestos!$B$17,"NM",H9/I9)) -> 10.195266 | R9: =IF(OR(M9<=0),"NM",IF(E9/M9>Supuestos!$B$17,"NM",E9/M9)) -> 0.8522762
A10: Multiplan | B10: Core | C10: Brasil | D10: =Datos_BBG!F19 -> FY2022 | E10: =Datos_BBG!O19*Datos_BBG!S19 -> 2350361.6 | F10: =Datos_BBG!M19*Datos_BBG!S19 -> 551326.19 | G10: =Datos_BBG!N19*Datos_BBG!S19 -> 36.264772 | H10: =Datos_BBG!T19*Datos_BBG!S19 -> 2901724 | I10: =Datos_BBG!G19*Datos_BBG!S19 -> 321131.71 | J10: =Datos_BBG!H19*Datos_BBG!S19 -> 227816.73 | K10: =Datos_BBG!J19*Datos_BBG!S19 -> 190881.86 | L10: =Datos_BBG!K19*Datos_BBG!S19 -> 137422.94 | M10: =Datos_BBG!L19*Datos_BBG!S19 -> 1175896.9 | N10: =IF(OR(L10<=0,Datos_BBG!Q19=1),"NM",IF(E10/L10>Supuestos!$B$17,"NM",E10/L10)) -> 17.103123 | O10: =IF(OR(J10<=0),"NM",IF(H10/J10>Supuestos!$B$17,"NM",H10/J10)) -> 12.737098 | P10: =IF(OR(K10<=0),"NM",IF(H10/K10>Supuestos!$B$17,"NM",H10/K10)) -> 15.201675 | Q10: =IF(OR(I10<=0),"NM",IF(H10/I10>Supuestos!$B$17,"NM",H10/I10)) -> 9.0359313 | R10: =IF(OR(M10<=0),"NM",IF(E10/M10>Supuestos!$B$17,"NM",E10/M10)) -> 1.9987821
A11: Allos | B11: Core | C11: Brasil | D11: =Datos_BBG!F24 -> FY2022 | E11: =Datos_BBG!O24*Datos_BBG!S24 -> 1800372.2 | F11: =Datos_BBG!M24*Datos_BBG!S24 -> 530234.38 | G11: =Datos_BBG!N24*Datos_BBG!S24 -> 191401.72 | H11: =Datos_BBG!T24*Datos_BBG!S24 -> 2522008.3 | I11: =Datos_BBG!G24*Datos_BBG!S24 -> 198531.05 | J11: =Datos_BBG!H24*Datos_BBG!S24 -> 145947.84 | K11: =Datos_BBG!J24*Datos_BBG!S24 -> 109842.07 | L11: =Datos_BBG!K24*Datos_BBG!S24 -> 27846.165 | M11: =Datos_BBG!L24*Datos_BBG!S24 -> 1215784.2 | N11: =IF(OR(L11<=0,Datos_BBG!Q24=1),"NM",IF(E11/L11>Supuestos!$B$17,"NM",E11/L11)) -> 64.654224 | O11: =IF(OR(J11<=0),"NM",IF(H11/J11>Supuestos!$B$17,"NM",H11/J11)) -> 17.280202 | P11: =IF(OR(K11<=0),"NM",IF(H11/K11>Supuestos!$B$17,"NM",H11/K11)) -> 22.960314 | Q11: =IF(OR(I11<=0),"NM",IF(H11/I11>Supuestos!$B$17,"NM",H11/I11)) -> 12.703344 | R11: =IF(OR(M11<=0),"NM",IF(E11/M11>Supuestos!$B$17,"NM",E11/M11)) -> 1.480832
A12: Iguatemi | B12: Core | C12: Brasil | D12: =Datos_BBG!F29 -> FY2022 | E12: =Datos_BBG!O29*Datos_BBG!S29 -> 1012431.4 | F12: =Datos_BBG!M29*Datos_BBG!S29 -> 213229 | G12: =Datos_BBG!N29*Datos_BBG!S29 -> 2565.1521 | H12: =Datos_BBG!T29*Datos_BBG!S29 -> 1228225.5 | I12: =Datos_BBG!G29*Datos_BBG!S29 -> 181563.42 | J12: =Datos_BBG!H29*Datos_BBG!S29 -> 116797.58 | K12: =Datos_BBG!J29*Datos_BBG!S29 -> 88387.79 | L12: =Datos_BBG!K29*Datos_BBG!S29 -> 1351.9793 | M12: =Datos_BBG!L29*Datos_BBG!S29 -> 731249.48 | N12: =IF(OR(L12<=0,Datos_BBG!Q29=1),"NM",IF(E12/L12>Supuestos!$B$17,"NM",E12/L12)) -> NM | O12: =IF(OR(J12<=0),"NM",IF(H12/J12>Supuestos!$B$17,"NM",H12/J12)) -> 10.515848 | P12: =IF(OR(K12<=0),"NM",IF(H12/K12>Supuestos!$B$17,"NM",H12/K12)) -> 13.895873 | Q12: =IF(OR(I12<=0),"NM",IF(H12/I12>Supuestos!$B$17,"NM",H12/I12)) -> 6.7647188 | R12: =IF(OR(M12<=0),"NM",IF(E12/M12>Supuestos!$B$17,"NM",E12/M12)) -> 1.3845225
A13: IRSA | B13: Sensibilidad | C13: Argentina | D13: =Datos_BBG!F34 -> FY2022 (jun) | E13: =Datos_BBG!O34*Datos_BBG!S34 -> 46633.672 | F13: =Datos_BBG!M34*Datos_BBG!S34 -> 84668.571 | G13: =Datos_BBG!N34*Datos_BBG!S34 -> 14590.025 | H13: =Datos_BBG!T34*Datos_BBG!S34 -> 145892.27 | I13: =Datos_BBG!G34*Datos_BBG!S34 -> 43129.042 | J13: =Datos_BBG!H34*Datos_BBG!S34 -> 18041.02 | K13: =Datos_BBG!J34*Datos_BBG!S34 -> 16791.94 | L13: =Datos_BBG!K34*Datos_BBG!S34 -> 46357.854 | M13: =Datos_BBG!L34*Datos_BBG!S34 -> 213132.11 | N13: =IF(OR(L13<=0,Datos_BBG!Q34=1),"NM",IF(E13/L13>Supuestos!$B$17,"NM",E13/L13)) -> 1.0059497 | O13: =IF(OR(J13<=0),"NM",IF(H13/J13>Supuestos!$B$17,"NM",H13/J13)) -> 8.0866972 | P13: =IF(OR(K13<=0),"NM",IF(H13/K13>Supuestos!$B$17,"NM",H13/K13)) -> 8.6882317 | Q13: =IF(OR(I13<=0),"NM",IF(H13/I13>Supuestos!$B$17,"NM",H13/I13)) -> 3.3826921 | R13: =IF(OR(M13<=0),"NM",IF(E13/M13>Supuestos!$B$17,"NM",E13/M13)) -> 0.21880172
A14: Fibra Danhos | B14: Sensibilidad | C14: México | D14: =Datos_BBG!F39 -> FY2022 | E14: =Datos_BBG!O39*Datos_BBG!S39 -> 1888961.6 | F14: =Datos_BBG!M39*Datos_BBG!S39 -> 304513.29 | G14: =Datos_BBG!N39*Datos_BBG!S39 -> 132514.15 | H14: =Datos_BBG!T39*Datos_BBG!S39 -> 2325989.1 | I14: =Datos_BBG!G39*Datos_BBG!S39 -> 290590.66 | J14: =Datos_BBG!H39*Datos_BBG!S39 -> 187038.53 | K14: =Datos_BBG!J39*Datos_BBG!S39 -> 186121.44 | L14: =Datos_BBG!K39*Datos_BBG!S39 -> 149656.3 | M14: =Datos_BBG!L39*Datos_BBG!S39 -> 3102425.7 | N14: =IF(OR(L14<=0,Datos_BBG!Q39=1),"NM",IF(E14/L14>Supuestos!$B$17,"NM",E14/L14)) -> 12.621999 | O14: =IF(OR(J14<=0),"NM",IF(H14/J14>Supuestos!$B$17,"NM",H14/J14)) -> 12.435882 | P14: =IF(OR(K14<=0),"NM",IF(H14/K14>Supuestos!$B$17,"NM",H14/K14)) -> 12.497158 | Q14: =IF(OR(I14<=0),"NM",IF(H14/I14>Supuestos!$B$17,"NM",H14/I14)) -> 8.004349 | R14: =IF(OR(M14<=0),"NM",IF(E14/M14>Supuestos!$B$17,"NM",E14/M14)) -> 0.60886602
A15: Mediana Core | N15: =IFERROR(MEDIAN(N8:N12),"NM") -> 14.829939 | O15: =IFERROR(MEDIAN(O8:O12),"NM") -> 12.737098 | P15: =IFERROR(MEDIAN(P8:P12),"NM") -> 13.895873 | Q15: =IFERROR(MEDIAN(Q8:Q12),"NM") -> 9.0359313 | R15: =IFERROR(MEDIAN(R8:R12),"NM") -> 1.3845225
A16: Promedio Core | N16: =IFERROR(AVERAGE(N8:N12),"NM") -> 26.003246 | O16: =IFERROR(AVERAGE(O8:O12),"NM") -> 12.923725 | P16: =IFERROR(AVERAGE(P8:P12),"NM") -> 15.309353 | Q16: =IFERROR(AVERAGE(Q8:Q12),"NM") -> 9.5332984 | R16: =IFERROR(AVERAGE(R8:R12),"NM") -> 1.3144537
A17: Mediana Core + Sensibilidad | N17: =IFERROR(MEDIAN(N8:N14),"NM") -> 12.589377 | O17: =IFERROR(MEDIAN(O8:O14),"NM") -> 12.435882 | P17: =IFERROR(MEDIAN(P8:P14),"NM") -> 13.167406 | Q17: =IFERROR(MEDIAN(Q8:Q14),"NM") -> 8.9672318 | R17: =IFERROR(MEDIAN(R8:R14),"NM") -> 0.85585581
A18: Promedio Core + Sensibilidad | N18: =IFERROR(AVERAGE(N8:N14),"NM") -> 19.606822 | O18: =IFERROR(AVERAGE(O8:O14),"NM") -> 12.163029 | P18: =IFERROR(AVERAGE(P8:P14),"NM") -> 13.961737 | Q18: =IFERROR(AVERAGE(Q8:Q14),"NM") -> 8.436219 | R18: =IFERROR(AVERAGE(R8:R14),"NM") -> 1.0571338
A19: Mallplaza vs mediana Core (prima / (descuento)) | N19: =IFERROR(N7/N15-1,"NM") -> -0.11312535 | O19: =IFERROR(O7/O15-1,"NM") -> -0.096394261 | P19: =IFERROR(P7/P15-1,"NM") -> -0.16535266 | Q19: =IFERROR(Q7/Q15-1,"NM") -> -0.029165414 | R19: =IFERROR(R7/R15-1,"NM") -> -0.33824095
A22: FY2023
A23: Empresa | B23: Grupo | C23: País | D23: Período | E23: Market Cap | F23: Deuda neta | G23: Minoritarios | H23: Enterprise Value | I23: Revenue | J23: EBITDA | K23: EBIT | L23: Net Income | M23: Book Value | N23: P/E | O23: EV/EBITDA | P23: EV/EBIT | Q23: EV/Revenue | R23: P/BV
E24: Montos en MM CLP
A25: Mallplaza | B25: Target | C25: Chile | D25: =Datos_BBG!F5 -> FY2023 | E25: =Datos_BBG!O5*Datos_BBG!S5 -> 2439612 | F25: =Datos_BBG!M5*Datos_BBG!S5 -> 1081082.3 | G25: =Datos_BBG!N5*Datos_BBG!S5 -> 31634.353 | H25: =Datos_BBG!T5*Datos_BBG!S5 -> 3552328.7 | I25: =Datos_BBG!G5*Datos_BBG!S5 -> 419903.78 | J25: =Datos_BBG!H5*Datos_BBG!S5 -> 322185 | K25: =Datos_BBG!J5*Datos_BBG!S5 -> 320031.49 | L25: =Datos_BBG!K5*Datos_BBG!S5 -> 349758.85 | M25: =Datos_BBG!L5*Datos_BBG!S5 -> 2601053.2 | N25: =IF(OR(L25<=0,Datos_BBG!Q5=1),"NM",IF(E25/L25>Supuestos!$B$17,"NM",E25/L25)) -> 6.9751258 | O25: =IF(OR(J25<=0),"NM",IF(H25/J25>Supuestos!$B$17,"NM",H25/J25)) -> 11.025742 | P25: =IF(OR(K25<=0),"NM",IF(H25/K25>Supuestos!$B$17,"NM",H25/K25)) -> 11.099935 | Q25: =IF(OR(I25<=0),"NM",IF(H25/I25>Supuestos!$B$17,"NM",H25/I25)) -> 8.4598635 | R25: =IF(OR(M25<=0),"NM",IF(E25/M25>Supuestos!$B$17,"NM",E25/M25)) -> 0.93793239
A26: Parque Arauco | B26: Core | C26: Chile | D26: =Datos_BBG!F10 -> FY2023 | E26: =Datos_BBG!O10*Datos_BBG!S10 -> 1286116.6 | F26: =Datos_BBG!M10*Datos_BBG!S10 -> 1113749.4 | G26: =Datos_BBG!N10*Datos_BBG!S10 -> 332049.13 | H26: =Datos_BBG!T10*Datos_BBG!S10 -> 2731915 | I26: =Datos_BBG!G10*Datos_BBG!S10 -> 264312.61 | J26: =Datos_BBG!H10*Datos_BBG!S10 -> 188159 | K26: =Datos_BBG!J10*Datos_BBG!S10 -> 182878.06 | L26: =Datos_BBG!K10*Datos_BBG!S10 -> 112345.33 | M26: =Datos_BBG!L10*Datos_BBG!S10 -> 1298911.3 | N26: =IF(OR(L26<=0,Datos_BBG!Q10=1),"NM",IF(E26/L26>Supuestos!$B$17,"NM",E26/L26)) -> 11.447886 | O26: =IF(OR(J26<=0),"NM",IF(H26/J26>Supuestos!$B$17,"NM",H26/J26)) -> 14.519184 | P26: =IF(OR(K26<=0),"NM",IF(H26/K26>Supuestos!$B$17,"NM",H26/K26)) -> 14.938451 | Q26: =IF(OR(I26<=0),"NM",IF(H26/I26>Supuestos!$B$17,"NM",H26/I26)) -> 10.335924 | R26: =IF(OR(M26<=0),"NM",IF(E26/M26>Supuestos!$B$17,"NM",E26/M26)) -> 0.99014963
A27: Cencosud Shopping | B27: Core | C27: Chile | D27: =Datos_BBG!F15 -> FY2023 | E27: =Datos_BBG!O15*Datos_BBG!S15 -> 2405221.8 | F27: =Datos_BBG!M15*Datos_BBG!S15 -> 650170.98 | G27: =Datos_BBG!N15*Datos_BBG!S15 -> 5991.871 | H27: =Datos_BBG!T15*Datos_BBG!S15 -> 3061384.7 | I27: =Datos_BBG!G15*Datos_BBG!S15 -> 314784.93 | J27: =Datos_BBG!H15*Datos_BBG!S15 -> 272791.98 | K27: =Datos_BBG!J15*Datos_BBG!S15 -> 272578.97 | L27: =Datos_BBG!K15*Datos_BBG!S15 -> 187329.71 | M27: =Datos_BBG!L15*Datos_BBG!S15 -> 2744754.9 | N27: =IF(OR(L27<=0,Datos_BBG!Q15=1),"NM",IF(E27/L27>Supuestos!$B$17,"NM",E27/L27)) -> 12.839511 | O27: =IF(OR(J27<=0),"NM",IF(H27/J27>Supuestos!$B$17,"NM",H27/J27)) -> 11.222415 | P27: =IF(OR(K27<=0),"NM",IF(H27/K27>Supuestos!$B$17,"NM",H27/K27)) -> 11.231184 | Q27: =IF(OR(I27<=0),"NM",IF(H27/I27>Supuestos!$B$17,"NM",H27/I27)) -> 9.7253216 | R27: =IF(OR(M27<=0),"NM",IF(E27/M27>Supuestos!$B$17,"NM",E27/M27)) -> 0.8762975
A28: Multiplan | B28: Core | C28: Brasil | D28: =Datos_BBG!F20 -> FY2023 | E28: =Datos_BBG!O20*Datos_BBG!S20 -> 3050103.9 | F28: =Datos_BBG!M20*Datos_BBG!S20 -> 554478.72 | G28: =Datos_BBG!N20*Datos_BBG!S20 -> 14.648824 | H28: =Datos_BBG!T20*Datos_BBG!S20 -> 3604597.3 | I28: =Datos_BBG!G20*Datos_BBG!S20 -> 362570.73 | J28: =Datos_BBG!H20*Datos_BBG!S20 -> 269127.49 | K28: =Datos_BBG!J20*Datos_BBG!S20 -> 238732.25 | L28: =Datos_BBG!K20*Datos_BBG!S20 -> 182286.75 | M28: =Datos_BBG!L20*Datos_BBG!S20 -> 1238703.9 | N28: =IF(OR(L28<=0,Datos_BBG!Q20=1),"NM",IF(E28/L28>Supuestos!$B$17,"NM",E28/L28)) -> 16.732449 | O28: =IF(OR(J28<=0),"NM",IF(H28/J28>Supuestos!$B$17,"NM",H28/J28)) -> 13.393642 | P28: =IF(OR(K28<=0),"NM",IF(H28/K28>Supuestos!$B$17,"NM",H28/K28)) -> 15.098912 | Q28: =IF(OR(I28<=0),"NM",IF(H28/I28>Supuestos!$B$17,"NM",H28/I28)) -> 9.9417769 | R28: =IF(OR(M28<=0),"NM",IF(E28/M28>Supuestos!$B$17,"NM",E28/M28)) -> 2.462335
A29: Allos | B29: Core | C29: Brasil | D29: =Datos_BBG!F25 -> FY2023 | E29: =Datos_BBG!O25*Datos_BBG!S25 -> 2722184.8 | F29: =Datos_BBG!M25*Datos_BBG!S25 -> 1006267.4 | G29: =Datos_BBG!N25*Datos_BBG!S25 -> 197732.33 | H29: =Datos_BBG!T25*Datos_BBG!S25 -> 3926184.5 | I29: =Datos_BBG!G25*Datos_BBG!S25 -> 500918.33 | J29: =Datos_BBG!H25*Datos_BBG!S25 -> 346773.58 | K29: =Datos_BBG!J25*Datos_BBG!S25 -> 224497.7 | L29: =Datos_BBG!K25*Datos_BBG!S25 -> 605060.4 | M29: =Datos_BBG!L25*Datos_BBG!S25 -> 2500640.4 | N29: =IF(OR(L29<=0,Datos_BBG!Q25=1),"NM",IF(E29/L29>Supuestos!$B$17,"NM",E29/L29)) -> NM | O29: =IF(OR(J29<=0),"NM",IF(H29/J29>Supuestos!$B$17,"NM",H29/J29)) -> 11.32204 | P29: =IF(OR(K29<=0),"NM",IF(H29/K29>Supuestos!$B$17,"NM",H29/K29)) -> 17.488752 | Q29: =IF(OR(I29<=0),"NM",IF(H29/I29>Supuestos!$B$17,"NM",H29/I29)) -> 7.8379732 | R29: =IF(OR(M29<=0),"NM",IF(E29/M29>Supuestos!$B$17,"NM",E29/M29)) -> 1.088595
A30: Iguatemi | B30: Core | C30: Brasil | D30: =Datos_BBG!F30 -> FY2023 | E30: =Datos_BBG!O30*Datos_BBG!S30 -> 1261170.6 | F30: =Datos_BBG!M30*Datos_BBG!S30 -> 313903.76 | G30: =Datos_BBG!N30*Datos_BBG!S30 -> 34.835619 | H30: =Datos_BBG!T30*Datos_BBG!S30 -> 1575109.2 | I30: =Datos_BBG!G30*Datos_BBG!S30 -> 206720.46 | J30: =Datos_BBG!H30*Datos_BBG!S30 -> 164299.78 | K30: =Datos_BBG!J30*Datos_BBG!S30 -> 133148.52 | L30: =Datos_BBG!K30*Datos_BBG!S30 -> 54435.21 | M30: =Datos_BBG!L30*Datos_BBG!S30 -> 746254.52 | N30: =IF(OR(L30<=0,Datos_BBG!Q30=1),"NM",IF(E30/L30>Supuestos!$B$17,"NM",E30/L30)) -> 23.168287 | O30: =IF(OR(J30<=0),"NM",IF(H30/J30>Supuestos!$B$17,"NM",H30/J30)) -> 9.5868 | P30: =IF(OR(K30<=0),"NM",IF(H30/K30>Supuestos!$B$17,"NM",H30/K30)) -> 11.829716 | Q30: =IF(OR(I30<=0),"NM",IF(H30/I30>Supuestos!$B$17,"NM",H30/I30)) -> 7.6195128 | R30: =IF(OR(M30<=0),"NM",IF(E30/M30>Supuestos!$B$17,"NM",E30/M30)) -> 1.6900006
A31: IRSA | B31: Sensibilidad | C31: Argentina | D31: =Datos_BBG!F35 -> FY2023 (jun) | E31: =Datos_BBG!O35*Datos_BBG!S35 -> 206211.11 | F31: =Datos_BBG!M35*Datos_BBG!S35 -> 235502.28 | G31: =Datos_BBG!N35*Datos_BBG!S35 -> 51634.236 | H31: =Datos_BBG!T35*Datos_BBG!S35 -> 493347.63 | I31: =Datos_BBG!G35*Datos_BBG!S35 -> 206450.44 | J31: =Datos_BBG!H35*Datos_BBG!S35 -> 57587.748 | K31: =Datos_BBG!J35*Datos_BBG!S35 -> 53196.364 | L31: =Datos_BBG!K35*Datos_BBG!S35 -> 132610.34 | M31: =Datos_BBG!L35*Datos_BBG!S35 -> 837157.36 | N31: =IF(OR(L31<=0,Datos_BBG!Q35=1),"NM",IF(E31/L31>Supuestos!$B$17,"NM",E31/L31)) -> 1.5550154 | O31: =IF(OR(J31<=0),"NM",IF(H31/J31>Supuestos!$B$17,"NM",H31/J31)) -> 8.5668853 | P31: =IF(OR(K31<=0),"NM",IF(H31/K31>Supuestos!$B$17,"NM",H31/K31)) -> 9.2740855 | Q31: =IF(OR(I31<=0),"NM",IF(H31/I31>Supuestos!$B$17,"NM",H31/I31)) -> 2.3896662 | R31: =IF(OR(M31<=0),"NM",IF(E31/M31>Supuestos!$B$17,"NM",E31/M31)) -> 0.246323
A32: Fibra Danhos | B32: Sensibilidad | C32: México | D32: =Datos_BBG!F40 -> FY2023 | E32: =Datos_BBG!O40*Datos_BBG!S40 -> 1721805.7 | F32: =Datos_BBG!M40*Datos_BBG!S40 -> 374442.81 | G32: =Datos_BBG!N40*Datos_BBG!S40 -> 146515.77 | H32: =Datos_BBG!T40*Datos_BBG!S40 -> 2242764.3 | I32: =Datos_BBG!G40*Datos_BBG!S40 -> 326217.65 | J32: =Datos_BBG!H40*Datos_BBG!S40 -> 208032.97 | K32: =Datos_BBG!J40*Datos_BBG!S40 -> 207153.41 | L32: =Datos_BBG!K40*Datos_BBG!S40 -> 174426.02 | M32: =Datos_BBG!L40*Datos_BBG!S40 -> 3124279.3 | N32: =IF(OR(L32<=0,Datos_BBG!Q40=1),"NM",IF(E32/L32>Supuestos!$B$17,"NM",E32/L32)) -> 9.8712664 | O32: =IF(OR(J32<=0),"NM",IF(H32/J32>Supuestos!$B$17,"NM",H32/J32)) -> 10.780812 | P32: =IF(OR(K32<=0),"NM",IF(H32/K32>Supuestos!$B$17,"NM",H32/K32)) -> 10.826587 | Q32: =IF(OR(I32<=0),"NM",IF(H32/I32>Supuestos!$B$17,"NM",H32/I32)) -> 6.8750551 | R32: =IF(OR(M32<=0),"NM",IF(E32/M32>Supuestos!$B$17,"NM",E32/M32)) -> 0.55110494
A33: Mediana Core | N33: =IFERROR(MEDIAN(N26:N30),"NM") -> 14.78598 | O33: =IFERROR(MEDIAN(O26:O30),"NM") -> 11.32204 | P33: =IFERROR(MEDIAN(P26:P30),"NM") -> 14.938451 | Q33: =IFERROR(MEDIAN(Q26:Q30),"NM") -> 9.7253216 | R33: =IFERROR(MEDIAN(R26:R30),"NM") -> 1.088595
A34: Promedio Core | N34: =IFERROR(AVERAGE(N26:N30),"NM") -> 16.047033 | O34: =IFERROR(AVERAGE(O26:O30),"NM") -> 12.008816 | P34: =IFERROR(AVERAGE(P26:P30),"NM") -> 14.117403 | Q34: =IFERROR(AVERAGE(Q26:Q30),"NM") -> 9.0921017 | R34: =IFERROR(AVERAGE(R26:R30),"NM") -> 1.4214756
A35: Mediana Core + Sensibilidad | N35: =IFERROR(MEDIAN(N26:N32),"NM") -> 12.143698 | O35: =IFERROR(MEDIAN(O26:O32),"NM") -> 11.222415 | P35: =IFERROR(MEDIAN(P26:P32),"NM") -> 11.829716 | Q35: =IFERROR(MEDIAN(Q26:Q32),"NM") -> 7.8379732 | R35: =IFERROR(MEDIAN(R26:R32),"NM") -> 0.99014963
A36: Promedio Core + Sensibilidad | N36: =IFERROR(AVERAGE(N26:N32),"NM") -> 12.602402 | O36: =IFERROR(AVERAGE(O26:O32),"NM") -> 11.341683 | P36: =IFERROR(AVERAGE(P26:P32),"NM") -> 12.955384 | Q36: =IFERROR(AVERAGE(Q26:Q32),"NM") -> 7.81789 | R36: =IFERROR(AVERAGE(R26:R32),"NM") -> 1.129258
A37: Mallplaza vs mediana Core (prima / (descuento)) | N37: =IFERROR(N25/N33-1,"NM") -> -0.52826084 | O37: =IFERROR(O25/O33-1,"NM") -> -0.026170063 | P37: =IFERROR(P25/P33-1,"NM") -> -0.25695546 | Q37: =IFERROR(Q25/Q33-1,"NM") -> -0.13011992 | R37: =IFERROR(R25/R33-1,"NM") -> -0.13840101
A40: FY2024
A41: Empresa | B41: Grupo | C41: País | D41: Período | E41: Market Cap | F41: Deuda neta | G41: Minoritarios | H41: Enterprise Value | I41: Revenue | J41: EBITDA | K41: EBIT | L41: Net Income | M41: Book Value | N41: P/E | O41: EV/EBITDA | P41: EV/EBIT | Q41: EV/Revenue | R41: P/BV
E42: Montos en MM CLP
A43: Mallplaza | B43: Target | C43: Chile | D43: =Datos_BBG!F6 -> FY2024 | E43: =Datos_BBG!O6*Datos_BBG!S6 -> 3569919 | F43: =Datos_BBG!M6*Datos_BBG!S6 -> 1458589.1 | G43: =Datos_BBG!N6*Datos_BBG!S6 -> 33186.747 | H43: =Datos_BBG!T6*Datos_BBG!S6 -> 5061694.9 | I43: =Datos_BBG!G6*Datos_BBG!S6 -> 494605.24 | J43: =Datos_BBG!H6*Datos_BBG!S6 -> 380637 | K43: =Datos_BBG!J6*Datos_BBG!S6 -> 378525.19 | L43: =Datos_BBG!K6*Datos_BBG!S6 -> 335933.78 | M43: =Datos_BBG!L6*Datos_BBG!S6 -> 3157863.1 | N43: =IF(OR(L43<=0,Datos_BBG!Q6=1),"NM",IF(E43/L43>Supuestos!$B$17,"NM",E43/L43)) -> 10.626853 | O43: =IF(OR(J43<=0),"NM",IF(H43/J43>Supuestos!$B$17,"NM",H43/J43)) -> 13.297958 | P43: =IF(OR(K43<=0),"NM",IF(H43/K43>Supuestos!$B$17,"NM",H43/K43)) -> 13.372148 | Q43: =IF(OR(I43<=0),"NM",IF(H43/I43>Supuestos!$B$17,"NM",H43/I43)) -> 10.233808 | R43: =IF(OR(M43<=0),"NM",IF(E43/M43>Supuestos!$B$17,"NM",E43/M43)) -> 1.1304857
A44: Parque Arauco | B44: Core | C44: Chile | D44: =Datos_BBG!F11 -> FY2024 | E44: =Datos_BBG!O11*Datos_BBG!S11 -> 1439092 | F44: =Datos_BBG!M11*Datos_BBG!S11 -> 1279923.4 | G44: =Datos_BBG!N11*Datos_BBG!S11 -> 323589.52 | H44: =Datos_BBG!T11*Datos_BBG!S11 -> 3042604.9 | I44: =Datos_BBG!G11*Datos_BBG!S11 -> 316775.71 | J44: =Datos_BBG!H11*Datos_BBG!S11 -> 227727 | K44: =Datos_BBG!J11*Datos_BBG!S11 -> 221208.09 | L44: =Datos_BBG!K11*Datos_BBG!S11 -> 120571.31 | M44: =Datos_BBG!L11*Datos_BBG!S11 -> 1464457.7 | N44: =IF(OR(L44<=0,Datos_BBG!Q11=1),"NM",IF(E44/L44>Supuestos!$B$17,"NM",E44/L44)) -> 11.935609 | O44: =IF(OR(J44<=0),"NM",IF(H44/J44>Supuestos!$B$17,"NM",H44/J44)) -> 13.360756 | P44: =IF(OR(K44<=0),"NM",IF(H44/K44>Supuestos!$B$17,"NM",H44/K44)) -> 13.754492 | Q44: =IF(OR(I44<=0),"NM",IF(H44/I44>Supuestos!$B$17,"NM",H44/I44)) -> 9.6049185 | R44: =IF(OR(M44<=0),"NM",IF(E44/M44>Supuestos!$B$17,"NM",E44/M44)) -> 0.98267907
A45: Cencosud Shopping | B45: Core | C45: Chile | D45: =Datos_BBG!F16 -> FY2024 | E45: =Datos_BBG!O16*Datos_BBG!S16 -> 2654273.2 | F45: =Datos_BBG!M16*Datos_BBG!S16 -> 679855.78 | G45: =Datos_BBG!N16*Datos_BBG!S16 -> 6467.54 | H45: =Datos_BBG!T16*Datos_BBG!S16 -> 3340596.5 | I45: =Datos_BBG!G16*Datos_BBG!S16 -> 353183.7 | J45: =Datos_BBG!H16*Datos_BBG!S16 -> 320677 | K45: =Datos_BBG!J16*Datos_BBG!S16 -> 320267.1 | L45: =Datos_BBG!K16*Datos_BBG!S16 -> 266953.08 | M45: =Datos_BBG!L16*Datos_BBG!S16 -> 2828031.7 | N45: =IF(OR(L45<=0,Datos_BBG!Q16=1),"NM",IF(E45/L45>Supuestos!$B$17,"NM",E45/L45)) -> 9.9428451 | O45: =IF(OR(J45<=0),"NM",IF(H45/J45>Supuestos!$B$17,"NM",H45/J45)) -> 10.417325 | P45: =IF(OR(K45<=0),"NM",IF(H45/K45>Supuestos!$B$17,"NM",H45/K45)) -> 10.430658 | Q45: =IF(OR(I45<=0),"NM",IF(H45/I45>Supuestos!$B$17,"NM",H45/I45)) -> 9.4585238 | R45: =IF(OR(M45<=0),"NM",IF(E45/M45>Supuestos!$B$17,"NM",E45/M45)) -> 0.93855848
A46: Multiplan | B46: Core | C46: Brasil | D46: =Datos_BBG!F21 -> FY2024 | E46: =Datos_BBG!O21*Datos_BBG!S21 -> 1955076.9 | F46: =Datos_BBG!M21*Datos_BBG!S21 -> 967638.81 | G46: =Datos_BBG!N21*Datos_BBG!S21 -> 44.66105 | H46: =Datos_BBG!T21*Datos_BBG!S21 -> 2922760.4 | I46: =Datos_BBG!G21*Datos_BBG!S21 -> 454611.79 | J46: =Datos_BBG!H21*Datos_BBG!S21 -> 330141.27 | K46: =Datos_BBG!J21*Datos_BBG!S21 -> 305397.62 | L46: =Datos_BBG!K21*Datos_BBG!S21 -> 239528.64 | M46: =Datos_BBG!L21*Datos_BBG!S21 -> 1008539.2 | N46: =IF(OR(L46<=0,Datos_BBG!Q21=1),"NM",IF(E46/L46>Supuestos!$B$17,"NM",E46/L46)) -> 8.1621842 | O46: =IF(OR(J46<=0),"NM",IF(H46/J46>Supuestos!$B$17,"NM",H46/J46)) -> 8.8530597 | P46: =IF(OR(K46<=0),"NM",IF(H46/K46>Supuestos!$B$17,"NM",H46/K46)) -> 9.5703444 | Q46: =IF(OR(I46<=0),"NM",IF(H46/I46>Supuestos!$B$17,"NM",H46/I46)) -> 6.4291345 | R46: =IF(OR(M46<=0),"NM",IF(E46/M46>Supuestos!$B$17,"NM",E46/M46)) -> 1.9385234
A47: Allos | B47: Core | C47: Brasil | D47: =Datos_BBG!F26 -> FY2024 | E47: =Datos_BBG!O26*Datos_BBG!S26 -> 1756534.7 | F47: =Datos_BBG!M26*Datos_BBG!S26 -> 1176662.3 | G47: =Datos_BBG!N26*Datos_BBG!S26 -> 137489.58 | H47: =Datos_BBG!T26*Datos_BBG!S26 -> 3070686.6 | I47: =Datos_BBG!G26*Datos_BBG!S26 -> 499713.2 | J47: =Datos_BBG!H26*Datos_BBG!S26 -> 356600.8 | K47: =Datos_BBG!J26*Datos_BBG!S26 -> 246050.23 | L47: =Datos_BBG!K26*Datos_BBG!S26 -> 124784.94 | M47: =Datos_BBG!L26*Datos_BBG!S26 -> 2387560.4 | N47: =IF(OR(L47<=0,Datos_BBG!Q26=1),"NM",IF(E47/L47>Supuestos!$B$17,"NM",E47/L47)) -> 14.076496 | O47: =IF(OR(J47<=0),"NM",IF(H47/J47>Supuestos!$B$17,"NM",H47/J47)) -> 8.6109921 | P47: =IF(OR(K47<=0),"NM",IF(H47/K47>Supuestos!$B$17,"NM",H47/K47)) -> 12.479918 | Q47: =IF(OR(I47<=0),"NM",IF(H47/I47>Supuestos!$B$17,"NM",H47/I47)) -> 6.144898 | R47: =IF(OR(M47<=0),"NM",IF(E47/M47>Supuestos!$B$17,"NM",E47/M47)) -> 0.73570272
A48: Iguatemi | B48: Core | C48: Brasil | D48: =Datos_BBG!F31 -> FY2024 | E48: =Datos_BBG!O31*Datos_BBG!S31 -> 905912.54 | F48: =Datos_BBG!M31*Datos_BBG!S31 -> 288482.51 | G48: =Datos_BBG!N31*Datos_BBG!S31 -> 38.587147 | H48: =Datos_BBG!T31*Datos_BBG!S31 -> 1194433.6 | I48: =Datos_BBG!G31*Datos_BBG!S31 -> 220865.86 | J48: =Datos_BBG!H31*Datos_BBG!S31 -> 163416.92 | K48: =Datos_BBG!J31*Datos_BBG!S31 -> 129428.97 | L48: =Datos_BBG!K31*Datos_BBG!S31 -> 71416.77 | M48: =Datos_BBG!L31*Datos_BBG!S31 -> 769921.48 | N48: =IF(OR(L48<=0,Datos_BBG!Q31=1),"NM",IF(E48/L48>Supuestos!$B$17,"NM",E48/L48)) -> 12.684871 | O48: =IF(OR(J48<=0),"NM",IF(H48/J48>Supuestos!$B$17,"NM",H48/J48)) -> 7.3091183 | P48: =IF(OR(K48<=0),"NM",IF(H48/K48>Supuestos!$B$17,"NM",H48/K48)) -> 9.2284874 | Q48: =IF(OR(I48<=0),"NM",IF(H48/I48>Supuestos!$B$17,"NM",H48/I48)) -> 5.4079595 | R48: =IF(OR(M48<=0),"NM",IF(E48/M48>Supuestos!$B$17,"NM",E48/M48)) -> 1.1766298
A49: IRSA | B49: Sensibilidad | C49: Argentina | D49: =Datos_BBG!F36 -> FY2024 (jun) | E49: =Datos_BBG!O36*Datos_BBG!S36 -> 559489 | F49: =Datos_BBG!M36*Datos_BBG!S36 -> 301536.72 | G49: =Datos_BBG!N36*Datos_BBG!S36 -> 64030.436 | H49: =Datos_BBG!T36*Datos_BBG!S36 -> 925056.16 | I49: =Datos_BBG!G36*Datos_BBG!S36 -> 285078.37 | J49: =Datos_BBG!H36*Datos_BBG!S36 -> 144423.38 | K49: =Datos_BBG!J36*Datos_BBG!S36 -> 138741.22 | L49: =Datos_BBG!K36*Datos_BBG!S36 -> -15945.528 | M49: =Datos_BBG!L36*Datos_BBG!S36 -> 935936.11 | N49: =IF(OR(L49<=0,Datos_BBG!Q36=1),"NM",IF(E49/L49>Supuestos!$B$17,"NM",E49/L49)) -> NM | O49: =IF(OR(J49<=0),"NM",IF(H49/J49>Supuestos!$B$17,"NM",H49/J49)) -> 6.4051689 | P49: =IF(OR(K49<=0),"NM",IF(H49/K49>Supuestos!$B$17,"NM",H49/K49)) -> 6.6674933 | Q49: =IF(OR(I49<=0),"NM",IF(H49/I49>Supuestos!$B$17,"NM",H49/I49)) -> 3.2449188 | R49: =IF(OR(M49<=0),"NM",IF(E49/M49>Supuestos!$B$17,"NM",E49/M49)) -> 0.59778546
A50: Fibra Danhos | B50: Sensibilidad | C50: México | D50: =Datos_BBG!F41 -> FY2024 | E50: =Datos_BBG!O41*Datos_BBG!S41 -> 1673054.4 | F50: =Datos_BBG!M41*Datos_BBG!S41 -> 472240.86 | G50: =Datos_BBG!N41*Datos_BBG!S41 -> 142009.35 | H50: =Datos_BBG!T41*Datos_BBG!S41 -> 2287304.6 | I50: =Datos_BBG!G41*Datos_BBG!S41 -> 357087.4 | J50: =Datos_BBG!H41*Datos_BBG!S41 -> 232183.67 | K50: =Datos_BBG!J41*Datos_BBG!S41 -> 231534.61 | L50: =Datos_BBG!K41*Datos_BBG!S41 -> 221443.15 | M50: =Datos_BBG!L41*Datos_BBG!S41 -> 3222458.5 | N50: =IF(OR(L50<=0,Datos_BBG!Q41=1),"NM",IF(E50/L50>Supuestos!$B$17,"NM",E50/L50)) -> 7.5552322 | O50: =IF(OR(J50<=0),"NM",IF(H50/J50>Supuestos!$B$17,"NM",H50/J50)) -> 9.8512725 | P50: =IF(OR(K50<=0),"NM",IF(H50/K50>Supuestos!$B$17,"NM",H50/K50)) -> 9.8788887 | Q50: =IF(OR(I50<=0),"NM",IF(H50/I50>Supuestos!$B$17,"NM",H50/I50)) -> 6.4054476 | R50: =IF(OR(M50<=0),"NM",IF(E50/M50>Supuestos!$B$17,"NM",E50/M50)) -> 0.51918571
A51: Mediana Core | N51: =IFERROR(MEDIAN(N44:N48),"NM") -> 11.935609 | O51: =IFERROR(MEDIAN(O44:O48),"NM") -> 8.8530597 | P51: =IFERROR(MEDIAN(P44:P48),"NM") -> 10.430658 | Q51: =IFERROR(MEDIAN(Q44:Q48),"NM") -> 6.4291345 | R51: =IFERROR(MEDIAN(R44:R48),"NM") -> 0.98267907
A52: Promedio Core | N52: =IFERROR(AVERAGE(N44:N48),"NM") -> 11.360401 | O52: =IFERROR(AVERAGE(O44:O48),"NM") -> 9.7102502 | P52: =IFERROR(AVERAGE(P44:P48),"NM") -> 11.09278 | Q52: =IFERROR(AVERAGE(Q44:Q48),"NM") -> 7.4090869 | R52: =IFERROR(AVERAGE(R44:R48),"NM") -> 1.1544187
A53: Mediana Core + Sensibilidad | N53: =IFERROR(MEDIAN(N44:N50),"NM") -> 10.939227 | O53: =IFERROR(MEDIAN(O44:O50),"NM") -> 8.8530597 | P53: =IFERROR(MEDIAN(P44:P50),"NM") -> 9.8788887 | Q53: =IFERROR(MEDIAN(Q44:Q50),"NM") -> 6.4054476 | R53: =IFERROR(MEDIAN(R44:R50),"NM") -> 0.93855848
A54: Promedio Core + Sensibilidad | N54: =IFERROR(AVERAGE(N44:N50),"NM") -> 10.726206 | O54: =IFERROR(AVERAGE(O44:O50),"NM") -> 9.2582418 | P54: =IFERROR(AVERAGE(P44:P50),"NM") -> 10.287183 | Q54: =IFERROR(AVERAGE(Q44:Q50),"NM") -> 6.6708287 | R54: =IFERROR(AVERAGE(R44:R50),"NM") -> 0.98415209
A55: Mallplaza vs mediana Core (prima / (descuento)) | N55: =IFERROR(N43/N51-1,"NM") -> -0.10965133 | O55: =IFERROR(O43/O51-1,"NM") -> 0.50207482 | P55: =IFERROR(P43/P51-1,"NM") -> 0.28200432 | Q55: =IFERROR(Q43/Q51-1,"NM") -> 0.59178621 | R55: =IFERROR(R43/R51-1,"NM") -> 0.15041189
A58: FY2025
A59: Empresa | B59: Grupo | C59: País | D59: Período | E59: Market Cap | F59: Deuda neta | G59: Minoritarios | H59: Enterprise Value | I59: Revenue | J59: EBITDA | K59: EBIT | L59: Net Income | M59: Book Value | N59: P/E | O59: EV/EBITDA | P59: EV/EBIT | Q59: EV/Revenue | R59: P/BV
E60: Montos en MM CLP
A61: Mallplaza | B61: Target | C61: Chile | D61: =Datos_BBG!F7 -> FY2025 | E61: =Datos_BBG!O7*Datos_BBG!S7 -> 6977559 | F61: =Datos_BBG!M7*Datos_BBG!S7 -> 1327147.4 | G61: =Datos_BBG!N7*Datos_BBG!S7 -> 41649.187 | H61: =Datos_BBG!T7*Datos_BBG!S7 -> 8346355.6 | I61: =Datos_BBG!G7*Datos_BBG!S7 -> 653911.09 | J61: =Datos_BBG!H7*Datos_BBG!S7 -> 526228 | K61: =Datos_BBG!J7*Datos_BBG!S7 -> 522618.46 | L61: =Datos_BBG!K7*Datos_BBG!S7 -> 1431011.6 | M61: =Datos_BBG!L7*Datos_BBG!S7 -> 4482903.9 | N61: =IF(OR(L61<=0,Datos_BBG!Q7=1),"NM",IF(E61/L61>Supuestos!$B$17,"NM",E61/L61)) -> 4.8759626 | O61: =IF(OR(J61<=0),"NM",IF(H61/J61>Supuestos!$B$17,"NM",H61/J61)) -> 15.860721 | P61: =IF(OR(K61<=0),"NM",IF(H61/K61>Supuestos!$B$17,"NM",H61/K61)) -> 15.970265 | Q61: =IF(OR(I61<=0),"NM",IF(H61/I61>Supuestos!$B$17,"NM",H61/I61)) -> 12.763747 | R61: =IF(OR(M61<=0),"NM",IF(E61/M61>Supuestos!$B$17,"NM",E61/M61)) -> 1.5564819
A62: Parque Arauco | B62: Core | C62: Chile | D62: =Datos_BBG!F12 -> FY2025 | E62: =Datos_BBG!O12*Datos_BBG!S12 -> 2708090.5 | F62: =Datos_BBG!M12*Datos_BBG!S12 -> 1631210.9 | G62: =Datos_BBG!N12*Datos_BBG!S12 -> 362360.84 | H62: =Datos_BBG!T12*Datos_BBG!S12 -> 4701662.2 | I62: =Datos_BBG!G12*Datos_BBG!S12 -> 383792.58 | J62: =Datos_BBG!H12*Datos_BBG!S12 -> 272233 | K62: =Datos_BBG!J12*Datos_BBG!S12 -> 267493.41 | L62: =Datos_BBG!K12*Datos_BBG!S12 -> 149972.7 | M62: =Datos_BBG!L12*Datos_BBG!S12 -> 1594521.9 | N62: =IF(OR(L62<=0,Datos_BBG!Q12=1),"NM",IF(E62/L62>Supuestos!$B$17,"NM",E62/L62)) -> 18.057223 | O62: =IF(OR(J62<=0),"NM",IF(H62/J62>Supuestos!$B$17,"NM",H62/J62)) -> 17.270728 | P62: =IF(OR(K62<=0),"NM",IF(H62/K62>Supuestos!$B$17,"NM",H62/K62)) -> 17.57674 | Q62: =IF(OR(I62<=0),"NM",IF(H62/I62>Supuestos!$B$17,"NM",H62/I62)) -> 12.250529 | R62: =IF(OR(M62<=0),"NM",IF(E62/M62>Supuestos!$B$17,"NM",E62/M62)) -> 1.6983715
A63: Cencosud Shopping | B63: Core | C63: Chile | D63: =Datos_BBG!F17 -> FY2025 | E63: =Datos_BBG!O17*Datos_BBG!S17 -> 3974586.4 | F63: =Datos_BBG!M17*Datos_BBG!S17 -> 769416.4 | G63: =Datos_BBG!N17*Datos_BBG!S17 -> 5505.4 | H63: =Datos_BBG!T17*Datos_BBG!S17 -> 4749508.2 | I63: =Datos_BBG!G17*Datos_BBG!S17 -> 377940.6 | J63: =Datos_BBG!H17*Datos_BBG!S17 -> 340557 | K63: =Datos_BBG!J17*Datos_BBG!S17 -> 340016.35 | L63: =Datos_BBG!K17*Datos_BBG!S17 -> 303966.19 | M63: =Datos_BBG!L17*Datos_BBG!S17 -> 2989170.6 | N63: =IF(OR(L63<=0,Datos_BBG!Q17=1),"NM",IF(E63/L63>Supuestos!$B$17,"NM",E63/L63)) -> 13.075752 | O63: =IF(OR(J63<=0),"NM",IF(H63/J63>Supuestos!$B$17,"NM",H63/J63)) -> 13.946294 | P63: =IF(OR(K63<=0),"NM",IF(H63/K63>Supuestos!$B$17,"NM",H63/K63)) -> 13.96847 | Q63: =IF(OR(I63<=0),"NM",IF(H63/I63>Supuestos!$B$17,"NM",H63/I63)) -> 12.566811 | R63: =IF(OR(M63<=0),"NM",IF(E63/M63>Supuestos!$B$17,"NM",E63/M63)) -> 1.3296619
A64: Multiplan | B64: Core | C64: Brasil | D64: =Datos_BBG!F22 -> FY2025 | E64: =Datos_BBG!O22*Datos_BBG!S22 -> 2498108.8 | F64: =Datos_BBG!M22*Datos_BBG!S22 -> 937685 | G64: =Datos_BBG!N22*Datos_BBG!S22 -> 42.338675 | H64: =Datos_BBG!T22*Datos_BBG!S22 -> 3435836.2 | I64: =Datos_BBG!G22*Datos_BBG!S22 -> 489321.11 | J64: =Datos_BBG!H22*Datos_BBG!S22 -> 357887.57 | K64: =Datos_BBG!J22*Datos_BBG!S22 -> 333278.08 | L64: =Datos_BBG!K22*Datos_BBG!S22 -> 203854.47 | M64: =Datos_BBG!L22*Datos_BBG!S22 -> 1125305.2 | N64: =IF(OR(L64<=0,Datos_BBG!Q22=1),"NM",IF(E64/L64>Supuestos!$B$17,"NM",E64/L64)) -> 12.254374 | O64: =IF(OR(J64<=0),"NM",IF(H64/J64>Supuestos!$B$17,"NM",H64/J64)) -> 9.6003227 | P64: =IF(OR(K64<=0),"NM",IF(H64/K64>Supuestos!$B$17,"NM",H64/K64)) -> 10.309217 | Q64: =IF(OR(I64<=0),"NM",IF(H64/I64>Supuestos!$B$17,"NM",H64/I64)) -> 7.021639 | R64: =IF(OR(M64<=0),"NM",IF(E64/M64>Supuestos!$B$17,"NM",E64/M64)) -> 2.219939
A65: Allos | B65: Core | C65: Brasil | D65: =Datos_BBG!F27 -> FY2025 | E65: =Datos_BBG!O27*Datos_BBG!S27 -> 2555308.3 | F65: =Datos_BBG!M27*Datos_BBG!S27 -> 1048992.5 | G65: =Datos_BBG!N27*Datos_BBG!S27 -> 134440.66 | H65: =Datos_BBG!T27*Datos_BBG!S27 -> 3738741.4 | I65: =Datos_BBG!G27*Datos_BBG!S27 -> 517993.68 | J65: =Datos_BBG!H27*Datos_BBG!S27 -> 369433.52 | K65: =Datos_BBG!J27*Datos_BBG!S27 -> 256025.72 | L65: =Datos_BBG!K27*Datos_BBG!S27 -> 149018.92 | M65: =Datos_BBG!L27*Datos_BBG!S27 -> 2348536.1 | N65: =IF(OR(L65<=0,Datos_BBG!Q27=1),"NM",IF(E65/L65>Supuestos!$B$17,"NM",E65/L65)) -> 17.147543 | O65: =IF(OR(J65<=0),"NM",IF(H65/J65>Supuestos!$B$17,"NM",H65/J65)) -> 10.120201 | P65: =IF(OR(K65<=0),"NM",IF(H65/K65>Supuestos!$B$17,"NM",H65/K65)) -> 14.602991 | Q65: =IF(OR(I65<=0),"NM",IF(H65/I65>Supuestos!$B$17,"NM",H65/I65)) -> 7.2177355 | R65: =IF(OR(M65<=0),"NM",IF(E65/M65>Supuestos!$B$17,"NM",E65/M65)) -> 1.088043
A66: Iguatemi | B66: Core | C66: Brasil | D66: =Datos_BBG!F32 -> FY2025 | E66: =Datos_BBG!O32*Datos_BBG!S32 -> 1305356.9 | F66: =Datos_BBG!M32*Datos_BBG!S32 -> 394838.69 | G66: =Datos_BBG!N32*Datos_BBG!S32 -> 39.301724 | H66: =Datos_BBG!T32*Datos_BBG!S32 -> 1700234.9 | I66: =Datos_BBG!G32*Datos_BBG!S32 -> 265614.09 | J66: =Datos_BBG!H32*Datos_BBG!S32 -> 183948.32 | K66: =Datos_BBG!J32*Datos_BBG!S32 -> 163589.5 | L66: =Datos_BBG!K32*Datos_BBG!S32 -> 104053.1 | M66: =Datos_BBG!L32*Datos_BBG!S32 -> 830989.22 | N66: =IF(OR(L66<=0,Datos_BBG!Q32=1),"NM",IF(E66/L66>Supuestos!$B$17,"NM",E66/L66)) -> 12.545103 | O66: =IF(OR(J66<=0),"NM",IF(H66/J66>Supuestos!$B$17,"NM",H66/J66)) -> 9.2430028 | P66: =IF(OR(K66<=0),"NM",IF(H66/K66>Supuestos!$B$17,"NM",H66/K66)) -> 10.393301 | Q66: =IF(OR(I66<=0),"NM",IF(H66/I66>Supuestos!$B$17,"NM",H66/I66)) -> 6.4011471 | R66: =IF(OR(M66<=0),"NM",IF(E66/M66>Supuestos!$B$17,"NM",E66/M66)) -> 1.570847
A67: IRSA | B67: Sensibilidad | C67: Argentina | D67: =Datos_BBG!F37 -> FY2025 (jun) | E67: =Datos_BBG!O37*Datos_BBG!S37 -> 784724.61 | F67: =Datos_BBG!M37*Datos_BBG!S37 -> 393612.64 | G67: =Datos_BBG!N37*Datos_BBG!S37 -> 78263.225 | H67: =Datos_BBG!T37*Datos_BBG!S37 -> 1256600.5 | I67: =Datos_BBG!G37*Datos_BBG!S37 -> 389778.89 | J67: =Datos_BBG!H37*Datos_BBG!S37 -> 157170.59 | K67: =Datos_BBG!J37*Datos_BBG!S37 -> 148436.37 | L67: =Datos_BBG!K37*Datos_BBG!S37 -> 162225.42 | M67: =Datos_BBG!L37*Datos_BBG!S37 -> 1311392 | N67: =IF(OR(L67<=0,Datos_BBG!Q37=1),"NM",IF(E67/L67>Supuestos!$B$17,"NM",E67/L67)) -> 4.8372483 | O67: =IF(OR(J67<=0),"NM",IF(H67/J67>Supuestos!$B$17,"NM",H67/J67)) -> 7.9951373 | P67: =IF(OR(K67<=0),"NM",IF(H67/K67>Supuestos!$B$17,"NM",H67/K67)) -> 8.4655834 | Q67: =IF(OR(I67<=0),"NM",IF(H67/I67>Supuestos!$B$17,"NM",H67/I67)) -> 3.2238803 | R67: =IF(OR(M67<=0),"NM",IF(E67/M67>Supuestos!$B$17,"NM",E67/M67)) -> 0.59839059
A68: Fibra Danhos | B68: Sensibilidad | C68: México | D68: =Datos_BBG!F42 -> FY2025 | E68: =Datos_BBG!O42*Datos_BBG!S42 -> 2372464.5 | F68: =Datos_BBG!M42*Datos_BBG!S42 -> 545843.48 | G68: =Datos_BBG!N42*Datos_BBG!S42 -> 150581.68 | H68: =Datos_BBG!T42*Datos_BBG!S42 -> 3068889.7 | I68: =Datos_BBG!G42*Datos_BBG!S42 -> 399348.65 | J68: =Datos_BBG!H42*Datos_BBG!S42 -> 264817.7 | K68: =Datos_BBG!J42*Datos_BBG!S42 -> 264130.12 | L68: =Datos_BBG!K42*Datos_BBG!S42 -> 265291.2 | M68: =Datos_BBG!L42*Datos_BBG!S42 -> 3362943 | N68: =IF(OR(L68<=0,Datos_BBG!Q42=1),"NM",IF(E68/L68>Supuestos!$B$17,"NM",E68/L68)) -> 8.9428692 | O68: =IF(OR(J68<=0),"NM",IF(H68/J68>Supuestos!$B$17,"NM",H68/J68)) -> 11.588688 | P68: =IF(OR(K68<=0),"NM",IF(H68/K68>Supuestos!$B$17,"NM",H68/K68)) -> 11.618855 | Q68: =IF(OR(I68<=0),"NM",IF(H68/I68>Supuestos!$B$17,"NM",H68/I68)) -> 7.6847379 | R68: =IF(OR(M68<=0),"NM",IF(E68/M68>Supuestos!$B$17,"NM",E68/M68)) -> 0.70547271
A69: Mediana Core | N69: =IFERROR(MEDIAN(N62:N66),"NM") -> 13.075752 | O69: =IFERROR(MEDIAN(O62:O66),"NM") -> 10.120201 | P69: =IFERROR(MEDIAN(P62:P66),"NM") -> 13.96847 | Q69: =IFERROR(MEDIAN(Q62:Q66),"NM") -> 7.2177355 | R69: =IFERROR(MEDIAN(R62:R66),"NM") -> 1.570847
A70: Promedio Core | N70: =IFERROR(AVERAGE(N62:N66),"NM") -> 14.615999 | O70: =IFERROR(AVERAGE(O62:O66),"NM") -> 12.03611 | P70: =IFERROR(AVERAGE(P62:P66),"NM") -> 13.370144 | Q70: =IFERROR(AVERAGE(Q62:Q66),"NM") -> 9.0915724 | R70: =IFERROR(AVERAGE(R62:R66),"NM") -> 1.5813725
A71: Mediana Core + Sensibilidad | N71: =IFERROR(MEDIAN(N62:N68),"NM") -> 12.545103 | O71: =IFERROR(MEDIAN(O62:O68),"NM") -> 10.120201 | P71: =IFERROR(MEDIAN(P62:P68),"NM") -> 11.618855 | Q71: =IFERROR(MEDIAN(Q62:Q68),"NM") -> 7.2177355 | R71: =IFERROR(MEDIAN(R62:R68),"NM") -> 1.3296619
A72: Promedio Core + Sensibilidad | N72: =IFERROR(AVERAGE(N62:N68),"NM") -> 12.408587 | O72: =IFERROR(AVERAGE(O62:O68),"NM") -> 11.394911 | P72: =IFERROR(AVERAGE(P62:P68),"NM") -> 12.419308 | Q72: =IFERROR(AVERAGE(Q62:Q68),"NM") -> 8.0523543 | R72: =IFERROR(AVERAGE(R62:R68),"NM") -> 1.315818
A73: Mallplaza vs mediana Core (prima / (descuento)) | N73: =IFERROR(N61/N69-1,"NM") -> -0.62709887 | O73: =IFERROR(O61/O69-1,"NM") -> 0.56723386 | P73: =IFERROR(P61/P69-1,"NM") -> 0.14330812 | Q73: =IFERROR(Q61/Q69-1,"NM") -> 0.76838661 | R73: =IFERROR(R61/R69-1,"NM") -> -0.0091447604
A76: LTM (3T25–2T26) al precio de corte
A77: Empresa | B77: Grupo | C77: País | D77: Período | E77: Market Cap | F77: Deuda neta | G77: Minoritarios | H77: Enterprise Value | I77: Revenue | J77: EBITDA | K77: EBIT | L77: Net Income | M77: Book Value | N77: P/E | O77: EV/EBITDA | P77: EV/EBIT | Q77: EV/Revenue | R77: P/BV
E78: Montos en MM CLP
A79: Mallplaza | B79: Target | C79: Chile | D79: =Datos_BBG!F8 -> LTM | E79: =Datos_BBG!O8*Datos_BBG!S8 -> 7785450 | F79: =Datos_BBG!M8*Datos_BBG!S8 -> 1311568.6 | G79: =Datos_BBG!N8*Datos_BBG!S8 -> 50841.428 | H79: =Datos_BBG!T8*Datos_BBG!S8 -> 9147860 | I79: =Datos_BBG!G8*Datos_BBG!S8 -> 677333.31 | J79: =Datos_BBG!H8*Datos_BBG!S8 -> 544935 | K79: =Datos_BBG!J8*Datos_BBG!S8 -> 540372.73 | L79: =Datos_BBG!K8*Datos_BBG!S8 -> 1258052.7 | M79: =Datos_BBG!L8*Datos_BBG!S8 -> 4820897.8 | N79: =IF(OR(L79<=0,Datos_BBG!Q8=1),"NM",IF(E79/L79>Supuestos!$B$17,"NM",E79/L79)) -> 6.1884925 | O79: =IF(OR(J79<=0),"NM",IF(H79/J79>Supuestos!$B$17,"NM",H79/J79)) -> 16.787066 | P79: =IF(OR(K79<=0),"NM",IF(H79/K79>Supuestos!$B$17,"NM",H79/K79)) -> 16.928797 | Q79: =IF(OR(I79<=0),"NM",IF(H79/I79>Supuestos!$B$17,"NM",H79/I79)) -> 13.505699 | R79: =IF(OR(M79<=0),"NM",IF(E79/M79>Supuestos!$B$17,"NM",E79/M79)) -> 1.6149378
A80: Parque Arauco | B80: Core | C80: Chile | D80: =Datos_BBG!F13 -> LTM | E80: =Datos_BBG!O13*Datos_BBG!S13 -> 3440408.4 | F80: =Datos_BBG!M13*Datos_BBG!S13 -> 1602287.6 | G80: =Datos_BBG!N13*Datos_BBG!S13 -> 386791.14 | H80: =Datos_BBG!T13*Datos_BBG!S13 -> 5429487.2 | I80: =Datos_BBG!G13*Datos_BBG!S13 -> 416366.83 | J80: =Datos_BBG!H13*Datos_BBG!S13 -> 294411 | K80: =Datos_BBG!J13*Datos_BBG!S13 -> 289515.61 | L80: =Datos_BBG!K13*Datos_BBG!S13 -> 154352.78 | M80: =Datos_BBG!L13*Datos_BBG!S13 -> 1961393.2 | N80: =IF(OR(L80<=0,Datos_BBG!Q13=1),"NM",IF(E80/L80>Supuestos!$B$17,"NM",E80/L80)) -> 22.289255 | O80: =IF(OR(J80<=0),"NM",IF(H80/J80>Supuestos!$B$17,"NM",H80/J80)) -> 18.441862 | P80: =IF(OR(K80<=0),"NM",IF(H80/K80>Supuestos!$B$17,"NM",H80/K80)) -> 18.753694 | Q80: =IF(OR(I80<=0),"NM",IF(H80/I80>Supuestos!$B$17,"NM",H80/I80)) -> 13.040153 | R80: =IF(OR(M80<=0),"NM",IF(E80/M80>Supuestos!$B$17,"NM",E80/M80)) -> 1.7540636
A81: Cencosud Shopping | B81: Core | C81: Chile | D81: =Datos_BBG!F18 -> LTM | E81: =Datos_BBG!O18*Datos_BBG!S18 -> 3710182.6 | F81: =Datos_BBG!M18*Datos_BBG!S18 -> 852533.94 | G81: =Datos_BBG!N18*Datos_BBG!S18 -> 6464.021 | H81: =Datos_BBG!T18*Datos_BBG!S18 -> 4569180.6 | I81: =Datos_BBG!G18*Datos_BBG!S18 -> 390677.95 | J81: =Datos_BBG!H18*Datos_BBG!S18 -> 350561.25 | K81: =Datos_BBG!J18*Datos_BBG!S18 -> 349975.94 | L81: =Datos_BBG!K18*Datos_BBG!S18 -> 353938.28 | M81: =Datos_BBG!L18*Datos_BBG!S18 -> 3136456.8 | N81: =IF(OR(L81<=0,Datos_BBG!Q18=1),"NM",IF(E81/L81>Supuestos!$B$17,"NM",E81/L81)) -> 10.482569 | O81: =IF(OR(J81<=0),"NM",IF(H81/J81>Supuestos!$B$17,"NM",H81/J81)) -> 13.033901 | P81: =IF(OR(K81<=0),"NM",IF(H81/K81>Supuestos!$B$17,"NM",H81/K81)) -> 13.055699 | Q81: =IF(OR(I81<=0),"NM",IF(H81/I81>Supuestos!$B$17,"NM",H81/I81)) -> 11.695517 | R81: =IF(OR(M81<=0),"NM",IF(E81/M81>Supuestos!$B$17,"NM",E81/M81)) -> 1.1829216
A82: Multiplan | B82: Core | C82: Brasil | D82: =Datos_BBG!F23 -> LTM | E82: =Datos_BBG!O23*Datos_BBG!S23 -> 2907890.3 | F82: =Datos_BBG!M23*Datos_BBG!S23 -> 888983.2 | G82: =Datos_BBG!N23*Datos_BBG!S23 -> 33.049177 | H82: =Datos_BBG!T23*Datos_BBG!S23 -> 3796906.6 | I82: =Datos_BBG!G23*Datos_BBG!S23 -> 570440.4 | J82: =Datos_BBG!H23*Datos_BBG!S23 -> 421296.08 | K82: =Datos_BBG!J23*Datos_BBG!S23 -> 397146.06 | L82: =Datos_BBG!K23*Datos_BBG!S23 -> 247648.38 | M82: =Datos_BBG!L23*Datos_BBG!S23 -> 1206875.9 | N82: =IF(OR(L82<=0,Datos_BBG!Q23=1),"NM",IF(E82/L82>Supuestos!$B$17,"NM",E82/L82)) -> 11.742012 | O82: =IF(OR(J82<=0),"NM",IF(H82/J82>Supuestos!$B$17,"NM",H82/J82)) -> 9.0124423 | P82: =IF(OR(K82<=0),"NM",IF(H82/K82>Supuestos!$B$17,"NM",H82/K82)) -> 9.560479 | Q82: =IF(OR(I82<=0),"NM",IF(H82/I82>Supuestos!$B$17,"NM",H82/I82)) -> 6.6560969 | R82: =IF(OR(M82<=0),"NM",IF(E82/M82>Supuestos!$B$17,"NM",E82/M82)) -> 2.4094361
A83: Allos | B83: Core | C83: Brasil | D83: =Datos_BBG!F28 -> LTM | E83: =Datos_BBG!O28*Datos_BBG!S28 -> 2656187.5 | F83: =Datos_BBG!M28*Datos_BBG!S28 -> 1221640.7 | G83: =Datos_BBG!N28*Datos_BBG!S28 -> 17188.966 | H83: =Datos_BBG!T28*Datos_BBG!S28 -> 3895017.2 | I83: =Datos_BBG!G28*Datos_BBG!S28 -> 524937.58 | J83: =Datos_BBG!H28*Datos_BBG!S28 -> 388838.75 | K83: =Datos_BBG!J28*Datos_BBG!S28 -> 276308.45 | L83: =Datos_BBG!K28*Datos_BBG!S28 -> 166950.15 | M83: =Datos_BBG!L28*Datos_BBG!S28 -> 2296067.8 | N83: =IF(OR(L83<=0,Datos_BBG!Q28=1),"NM",IF(E83/L83>Supuestos!$B$17,"NM",E83/L83)) -> 15.910064 | O83: =IF(OR(J83<=0),"NM",IF(H83/J83>Supuestos!$B$17,"NM",H83/J83)) -> 10.01705 | P83: =IF(OR(K83<=0),"NM",IF(H83/K83>Supuestos!$B$17,"NM",H83/K83)) -> 14.096627 | Q83: =IF(OR(I83<=0),"NM",IF(H83/I83>Supuestos!$B$17,"NM",H83/I83)) -> 7.4199625 | R83: =IF(OR(M83<=0),"NM",IF(E83/M83>Supuestos!$B$17,"NM",E83/M83)) -> 1.1568419
A84: Iguatemi | B84: Core | C84: Brasil | D84: =Datos_BBG!F33 -> LTM | E84: =Datos_BBG!O33*Datos_BBG!S33 -> 1381189.7 | F84: =Datos_BBG!M33*Datos_BBG!S33 -> 382047.95 | G84: =Datos_BBG!N33*Datos_BBG!S33 -> 38.944435 | H84: =Datos_BBG!T33*Datos_BBG!S33 -> 1763276.6 | I84: =Datos_BBG!G33*Datos_BBG!S33 -> 272862.76 | J84: =Datos_BBG!H33*Datos_BBG!S33 -> 201422.94 | K84: =Datos_BBG!J33*Datos_BBG!S33 -> 178237.78 | L84: =Datos_BBG!K33*Datos_BBG!S33 -> 114077 | M84: =Datos_BBG!L33*Datos_BBG!S33 -> 881991.06 | N84: =IF(OR(L84<=0,Datos_BBG!Q33=1),"NM",IF(E84/L84>Supuestos!$B$17,"NM",E84/L84)) -> 12.107521 | O84: =IF(OR(J84<=0),"NM",IF(H84/J84>Supuestos!$B$17,"NM",H84/J84)) -> 8.7541002 | P84: =IF(OR(K84<=0),"NM",IF(H84/K84>Supuestos!$B$17,"NM",H84/K84)) -> 9.892833 | Q84: =IF(OR(I84<=0),"NM",IF(H84/I84>Supuestos!$B$17,"NM",H84/I84)) -> 6.4621374 | R84: =IF(OR(M84<=0),"NM",IF(E84/M84>Supuestos!$B$17,"NM",E84/M84)) -> 1.5659906
A85: IRSA | B85: Sensibilidad | C85: Argentina | D85: =Datos_BBG!F38 -> LTM | E85: =Datos_BBG!O38*Datos_BBG!S38 -> 1140416.5 | F85: =Datos_BBG!M38*Datos_BBG!S38 -> 561235.18 | G85: =Datos_BBG!N38*Datos_BBG!S38 -> 87538.904 | H85: =Datos_BBG!T38*Datos_BBG!S38 -> 1789190.5 | I85: =Datos_BBG!G38*Datos_BBG!S38 -> 409298.64 | J85: =Datos_BBG!H38*Datos_BBG!S38 -> 145686.2 | K85: =Datos_BBG!J38*Datos_BBG!S38 -> 135134.94 | L85: =Datos_BBG!K38*Datos_BBG!S38 -> 244905.54 | M85: =Datos_BBG!L38*Datos_BBG!S38 -> 1418831.5 | N85: =IF(OR(L85<=0,Datos_BBG!Q38=1),"NM",IF(E85/L85>Supuestos!$B$17,"NM",E85/L85)) -> 4.6565564 | O85: =IF(OR(J85<=0),"NM",IF(H85/J85>Supuestos!$B$17,"NM",H85/J85)) -> 12.281125 | P85: =IF(OR(K85<=0),"NM",IF(H85/K85>Supuestos!$B$17,"NM",H85/K85)) -> 13.240029 | Q85: =IF(OR(I85<=0),"NM",IF(H85/I85>Supuestos!$B$17,"NM",H85/I85)) -> 4.3713571 | R85: =IF(OR(M85<=0),"NM",IF(E85/M85>Supuestos!$B$17,"NM",E85/M85)) -> 0.80377159
A86: Fibra Danhos | B86: Sensibilidad | C86: México | D86: =Datos_BBG!F43 -> LTM | E86: =Datos_BBG!O43*Datos_BBG!S43 -> 2383999.4 | F86: =Datos_BBG!M43*Datos_BBG!S43 -> 618003.43 | G86: =Datos_BBG!N43*Datos_BBG!S43 -> 155940.9 | H86: =Datos_BBG!T43*Datos_BBG!S43 -> 3157943.8 | I86: =Datos_BBG!G43*Datos_BBG!S43 -> 417411.61 | J86: =Datos_BBG!H43*Datos_BBG!S43 -> 277625.06 | K86: =Datos_BBG!J43*Datos_BBG!S43 -> 276925.52 | L86: =Datos_BBG!K43*Datos_BBG!S43 -> 301542.11 | M86: =Datos_BBG!L43*Datos_BBG!S43 -> 3445417.1 | N86: =IF(OR(L86<=0,Datos_BBG!Q43=1),"NM",IF(E86/L86>Supuestos!$B$17,"NM",E86/L86)) -> 7.9060247 | O86: =IF(OR(J86<=0),"NM",IF(H86/J86>Supuestos!$B$17,"NM",H86/J86)) -> 11.374851 | P86: =IF(OR(K86<=0),"NM",IF(H86/K86>Supuestos!$B$17,"NM",H86/K86)) -> 11.403585 | Q86: =IF(OR(I86<=0),"NM",IF(H86/I86>Supuestos!$B$17,"NM",H86/I86)) -> 7.5655389 | R86: =IF(OR(M86<=0),"NM",IF(E86/M86>Supuestos!$B$17,"NM",E86/M86)) -> 0.69193348
A87: Mediana Core | N87: =IFERROR(MEDIAN(N80:N84),"NM") -> 12.107521 | O87: =IFERROR(MEDIAN(O80:O84),"NM") -> 10.01705 | P87: =IFERROR(MEDIAN(P80:P84),"NM") -> 13.055699 | Q87: =IFERROR(MEDIAN(Q80:Q84),"NM") -> 7.4199625 | R87: =IFERROR(MEDIAN(R80:R84),"NM") -> 1.5659906
A88: Promedio Core | N88: =IFERROR(AVERAGE(N80:N84),"NM") -> 14.506284 | O88: =IFERROR(AVERAGE(O80:O84),"NM") -> 11.851871 | P88: =IFERROR(AVERAGE(P80:P84),"NM") -> 13.071866 | Q88: =IFERROR(AVERAGE(Q80:Q84),"NM") -> 9.0547733 | R88: =IFERROR(AVERAGE(R80:R84),"NM") -> 1.6138508
A89: Mediana Core + Sensibilidad | N89: =IFERROR(MEDIAN(N80:N86),"NM") -> 11.742012 | O89: =IFERROR(MEDIAN(O80:O86),"NM") -> 11.374851 | P89: =IFERROR(MEDIAN(P80:P86),"NM") -> 13.055699 | Q89: =IFERROR(MEDIAN(Q80:Q86),"NM") -> 7.4199625 | R89: =IFERROR(MEDIAN(R80:R86),"NM") -> 1.1829216
A90: Promedio Core + Sensibilidad | N90: =IFERROR(AVERAGE(N80:N86),"NM") -> 12.156286 | O90: =IFERROR(AVERAGE(O80:O86),"NM") -> 11.845047 | P90: =IFERROR(AVERAGE(P80:P86),"NM") -> 12.857564 | Q90: =IFERROR(AVERAGE(Q80:Q86),"NM") -> 8.1729661 | R90: =IFERROR(AVERAGE(R80:R86),"NM") -> 1.3664227
A91: Mallplaza vs mediana Core (prima / (descuento)) | N91: =IFERROR(N79/N87-1,"NM") -> -0.48887204 | O91: =IFERROR(O79/O87-1,"NM") -> 0.67584932 | P91: =IFERROR(P79/P87-1,"NM") -> 0.29665954 | Q91: =IFERROR(Q79/Q87-1,"NM") -> 0.82018432 | R91: =IFERROR(R79/R87-1,"NM") -> 0.031256346

Sheet Datos_BBG
A1: Datos Bloomberg en moneda local (millones). EBITDA = IS_COMPARABLE_EBITDA (salvo nota) · EBIT = EBITDA − D&A (CF_DEPR_AMORT) · LTM = suma 3T25–2T26 · Balance LTM al 30-jun-2026
A3: Empresa | B3: Ticker BBG | C3: Grupo | D3: País | E3: Moneda | F3: Período | G3: Revenue | H3: EBITDA | I3: D&A | J3: EBIT | K3: Net Income (controladora) | L3: Book Value (TOT_COMMON_EQY) | M3: Net Debt (BBG) | N3: Minoritarios | O3: Market Cap | P3: Precio | Q3: Forzar P/E NM | R3: Nota | S3: Factor a CLP | T3: EV (local)
A4: Mallplaza | B4: MALLPLAZ CI | C4: Target | D4: Chile | E4: CLP | F4: FY2022 | G4: 370898.93 | H4: 282699 | I4: 2165.395 | J4: =H4-I4 -> 280533.6 | K4: 157666.76 | L4: 2263298.5 | M4: 1011613.3 | N4: 168378.48 | O4: 2073680 | P4: 1050.647 | Q4: 0 | S4: =Supuestos!$C$11 -> 1 | T4: =O4+M4+N4 -> 3253671.8
A5: Mallplaza | B5: MALLPLAZ CI | C5: Target | D5: Chile | E5: CLP | F5: FY2023 | G5: 419903.78 | H5: 322185 | I5: 2153.51 | J5: =H5-I5 -> 320031.49 | K5: 349758.85 | L5: 2601053.2 | M5: 1081082.3 | N5: 31634.353 | O5: 2439612 | P5: 1236.049 | Q5: 0 | S5: =Supuestos!$C$11 -> 1 | T5: =O5+M5+N5 -> 3552328.7
A6: Mallplaza | B6: MALLPLAZ CI | C6: Target | D6: Chile | E6: CLP | F6: FY2024 | G6: 494605.24 | H6: 380637 | I6: 2111.809 | J6: =H6-I6 -> 378525.19 | K6: 335933.78 | L6: 3157863.1 | M6: 1458589.1 | N6: 33186.747 | O6: 3569919 | P6: 1630.1 | Q6: 0 | S6: =Supuestos!$C$11 -> 1 | T6: =O6+M6+N6 -> 5061694.9
A7: Mallplaza | B7: MALLPLAZ CI | C7: Target | D7: Chile | E7: CLP | F7: FY2025 | G7: 653911.09 | H7: 526228 | I7: 3609.536 | J7: =H7-I7 -> 522618.46 | K7: 1431011.6 | L7: 4482903.9 | M7: 1327147.4 | N7: 41649.187 | O7: 6977559 | P7: 3186.1 | Q7: 0 | R7: Net Income incluye revalorización de propiedades (~1,0 bn). | S7: =Supuestos!$C$11 -> 1 | T7: =O7+M7+N7 -> 8346355.6
A8: Mallplaza | B8: MALLPLAZ CI | C8: Target | D8: Chile | E8: CLP | F8: LTM | G8: 677333.31 | H8: 544935 | I8: 4562.274 | J8: =H8-I8 -> 540372.73 | K8: 1258052.7 | L8: 4820897.8 | M8: 1311568.6 | N8: 50841.428 | O8: 7785450 | P8: 3555 | Q8: 0 | S8: =Supuestos!$C$11 -> 1 | T8: =O8+M8+N8 -> 9147860
A9: Parque Arauco | B9: PARAUCO CI | C9: Core | D9: Chile | E9: CLP | F9: FY2022 | G9: 243119.54 | H9: 170697 | I9: 5128.377 | J9: =H9-I9 -> 165568.62 | K9: 101031.63 | L9: 1144928.9 | M9: 989079.05 | N9: 211136.22 | O9: 979894.01 | P9: 1067.16 | Q9: 0 | S9: =Supuestos!$C$11 -> 1 | T9: =O9+M9+N9 -> 2180109.3
A10: Parque Arauco | B10: PARAUCO CI | C10: Core | D10: Chile | E10: CLP | F10: FY2023 | G10: 264312.61 | H10: 188159 | I10: 5280.937 | J10: =H10-I10 -> 182878.06 | K10: 112345.33 | L10: 1298911.3 | M10: 1113749.4 | N10: 332049.13 | O10: 1286116.6 | P10: 1400.66 | Q10: 0 | S10: =Supuestos!$C$11 -> 1 | T10: =O10+M10+N10 -> 2731915
A11: Parque Arauco | B11: PARAUCO CI | C11: Core | D11: Chile | E11: CLP | F11: FY2024 | G11: 316775.71 | H11: 227727 | I11: 6518.906 | J11: =H11-I11 -> 221208.09 | K11: 120571.31 | L11: 1464457.7 | M11: 1279923.4 | N11: 323589.52 | O11: 1439092 | P11: 1567.26 | Q11: 0 | S11: =Supuestos!$C$11 -> 1 | T11: =O11+M11+N11 -> 3042604.9
A12: Parque Arauco | B12: PARAUCO CI | C12: Core | D12: Chile | E12: CLP | F12: FY2025 | G12: 383792.58 | H12: 272233 | I12: 4739.59 | J12: =H12-I12 -> 267493.41 | K12: 149972.7 | L12: 1594521.9 | M12: 1631210.9 | N12: 362360.84 | O12: 2708090.5 | P12: 2949.27 | Q12: 0 | S12: =Supuestos!$C$11 -> 1 | T12: =O12+M12+N12 -> 4701662.2
A13: Parque Arauco | B13: PARAUCO CI | C13: Core | D13: Chile | E13: CLP | F13: LTM | G13: 416366.83 | H13: 294411 | I13: 4895.39 | J13: =H13-I13 -> 289515.61 | K13: 154352.78 | L13: 1961393.2 | M13: 1602287.6 | N13: 386791.14 | O13: 3440408.4 | P13: 3505 | Q13: 0 | S13: =Supuestos!$C$11 -> 1 | T13: =O13+M13+N13 -> 5429487.2
A14: Cencosud Shopping | B14: CENCOMAL CI | C14: Core | D14: Chile | E14: CLP | F14: FY2022 | G14: 286949.85 | H14: 258583.7 | I14: 178.837 | J14: =H14-I14 -> 258404.86 | K14: 181875.55 | L14: 2679608.6 | M14: 636796.49 | N14: 4966.978 | O14: 2283766.6 | P14: 1338.8 | Q14: 0 | R14: EBITDA = EBITDA_ADJUSTED (comparable BBG incluía revalorización). | S14: =Supuestos!$C$11 -> 1 | T14: =O14+M14+N14 -> 2925530.1
A15: Cencosud Shopping | B15: CENCOMAL CI | C15: Core | D15: Chile | E15: CLP | F15: FY2023 | G15: 314784.93 | H15: 272791.98 | I15: 213.006 | J15: =H15-I15 -> 272578.97 | K15: 187329.71 | L15: 2744754.9 | M15: 650170.98 | N15: 5991.871 | O15: 2405221.8 | P15: 1410 | Q15: 0 | S15: =Supuestos!$C$11 -> 1 | T15: =O15+M15+N15 -> 3061384.7
A16: Cencosud Shopping | B16: CENCOMAL CI | C16: Core | D16: Chile | E16: CLP | F16: FY2024 | G16: 353183.7 | H16: 320677 | I16: 409.897 | J16: =H16-I16 -> 320267.1 | K16: 266953.08 | L16: 2828031.7 | M16: 679855.78 | N16: 6467.54 | O16: 2654273.2 | P16: 1556 | Q16: 0 | S16: =Supuestos!$C$11 -> 1 | T16: =O16+M16+N16 -> 3340596.5
A17: Cencosud Shopping | B17: CENCOMAL CI | C17: Core | D17: Chile | E17: CLP | F17: FY2025 | G17: 377940.6 | H17: 340557 | I17: 540.654 | J17: =H17-I17 -> 340016.35 | K17: 303966.19 | L17: 2989170.6 | M17: 769416.4 | N17: 5505.4 | O17: 3974586.4 | P17: 2330 | Q17: 0 | S17: =Supuestos!$C$11 -> 1 | T17: =O17+M17+N17 -> 4749508.2
A18: Cencosud Shopping | B18: CENCOMAL CI | C18: Core | D18: Chile | E18: CLP | F18: LTM | G18: 390677.95 | H18: 350561.25 | I18: 585.311 | J18: =H18-I18 -> 349975.94 | K18: 353938.28 | L18: 3136456.8 | M18: 852533.94 | N18: 6464.021 | O18: 3710182.6 | P18: 2175 | Q18: 0 | R18: Q1-26 EBITDA = EBITDA_ADJUSTED (comparable incluía revalorización). | S18: =Supuestos!$C$11 -> 1 | T18: =O18+M18+N18 -> 4569180.6
A19: Multiplan | B19: MULT3 BZ | C19: Core | D19: Brasil | E19: BRL | F19: FY2022 | G19: 1797.605 | H19: 1275.254 | I19: 206.751 | J19: =H19-I19 -> 1068.503 | K19: 769.255 | L19: 6582.34 | M19: 3086.169 | N19: 0.203 | O19: 13156.663 | P19: 21.9 | Q19: 0 | S19: =Supuestos!$C$13 -> 178.6442 | T19: =O19+M19+N19 -> 16243.035
A20: Multiplan | B20: MULT3 BZ | C20: Core | D20: Brasil | E20: BRL | F20: FY2023 | G20: 2029.569 | H20: 1506.5 | I20: 170.144 | J20: =H20-I20 -> 1336.356 | K20: 1020.39 | L20: 6933.916 | M20: 3103.816 | N20: 0.082 | O20: 17073.624 | P20: 28.42 | Q20: 0 | S20: =Supuestos!$C$13 -> 178.6442 | T20: =O20+M20+N20 -> 20177.522
A21: Multiplan | B21: MULT3 BZ | C21: Core | D21: Brasil | E21: BRL | F21: FY2024 | G21: 2544.789 | H21: 1848.038 | I21: 138.508 | J21: =H21-I21 -> 1709.53 | K21: 1340.814 | L21: 5645.519 | M21: 5416.57 | N21: 0.25 | O21: 10943.971 | P21: 21.08 | Q21: 0 | S21: =Supuestos!$C$13 -> 178.6442 | T21: =O21+M21+N21 -> 16360.791
A22: Multiplan | B22: MULT3 BZ | C22: Core | D22: Brasil | E22: BRL | F22: FY2025 | G22: 2739.082 | H22: 2003.354 | I22: 137.757 | J22: =H22-I22 -> 1865.597 | K22: 1141.12 | L22: 6299.142 | M22: 5248.897 | N22: 0.237 | O22: 13983.711 | P22: 27.25 | Q22: 0 | S22: =Supuestos!$C$13 -> 178.6442 | T22: =O22+M22+N22 -> 19232.845
A23: Multiplan | B23: MULT3 BZ | C23: Core | D23: Brasil | E23: BRL | F23: LTM | G23: 3193.165 | H23: 2358.297 | I23: 135.185 | J23: =H23-I23 -> 2223.112 | K23: 1386.266 | L23: 6755.752 | M23: 4976.278 | N23: 0.185 | O23: 16277.553 | P23: 31.72 | Q23: 0 | S23: =Supuestos!$C$13 -> 178.6442 | T23: =O23+M23+N23 -> 21254.016
A24: Allos | B24: ALOS3 BZ | C24: Core | D24: Brasil | E24: BRL | F24: FY2022 | G24: 1111.321 | H24: 816.975 | I24: 202.11 | J24: =H24-I24 -> 614.865 | K24: 155.875 | L24: 6805.618 | M24: 2968.103 | N24: 1071.413 | O24: 10077.977 | P24: 17.01 | Q24: 0 | S24: =Supuestos!$C$13 -> 178.6442 | T24: =O24+M24+N24 -> 14117.493
A25: Allos | B25: ALOS3 BZ | C25: Core | D25: Brasil | E25: BRL | F25: FY2023 | G25: 2804 | H25: 1941.141 | I25: 684.466 | J25: =H25-I25 -> 1256.675 | K25: 3386.958 | L25: 13997.882 | M25: 5632.802 | N25: 1106.85 | O25: 15238.025 | P25: 26.55 | Q25: 1 | R25: Revenue BBG 7.481 incluye ítems no recurrentes de la combinación con brMalls; se usa 2.804 (S&P). P/E NM por ganancia no recurrente. | S25: =Supuestos!$C$13 -> 178.6442 | T25: =O25+M25+N25 -> 21977.677
A26: Allos | B26: ALOS3 BZ | C26: Core | D26: Brasil | E26: BRL | F26: FY2024 | G26: 2797.254 | H26: 1996.151 | I26: 618.831 | J26: =H26-I26 -> 1377.32 | K26: 698.511 | L26: 13364.892 | M26: 6586.625 | N26: 769.628 | O26: 9832.5874 | P26: 18.11 | Q26: 0 | S26: =Supuestos!$C$13 -> 178.6442 | T26: =O26+M26+N26 -> 17188.84
A27: Allos | B27: ALOS3 BZ | C27: Core | D27: Brasil | E27: BRL | F27: FY2025 | G27: 2899.583 | H27: 2067.985 | I27: 634.825 | J27: =H27-I27 -> 1433.16 | K27: 834.166 | L27: 13146.445 | M27: 5871.965 | N27: 752.561 | O27: 14303.897 | P27: 28.37 | Q27: 0 | S27: =Supuestos!$C$13 -> 178.6442 | T27: =O27+M27+N27 -> 20928.423
A28: Allos | B28: ALOS3 BZ | C28: Core | D28: Brasil | E28: BRL | F28: LTM | G28: 2938.453 | H28: 2176.61 | I28: 629.913 | J28: =H28-I28 -> 1546.697 | K28: 934.54 | L28: 12852.742 | M28: 6838.401 | N28: 96.219 | O28: 14868.591 | P28: 29.49 | Q28: 0 | S28: =Supuestos!$C$13 -> 178.6442 | T28: =O28+M28+N28 -> 21803.211
A29: Iguatemi | B29: IGTI11 BZ | C29: Core | D29: Brasil | E29: BRL | F29: FY2022 | G29: 1016.341 | H29: 653.8 | I29: 159.03 | J29: =H29-I29 -> 494.77 | K29: 7.568 | L29: 4093.329 | M29: 1193.596 | N29: 14.359 | O29: 5667.3061 | P29: 18.5 | Q29: 0 | S29: =Supuestos!$C$13 -> 178.6442 | T29: =O29+M29+N29 -> 6875.2611
A30: Iguatemi | B30: IGTI11 BZ | C30: Core | D30: Brasil | E30: BRL | F30: FY2023 | G30: 1157.163 | H30: 919.704 | I30: 174.376 | J30: =H30-I30 -> 745.328 | K30: 304.713 | L30: 4177.323 | M30: 1757.145 | N30: 0.195 | O30: 7059.6783 | P30: 24.38 | Q30: 0 | S30: =Supuestos!$C$13 -> 178.6442 | T30: =O30+M30+N30 -> 8817.0183
A31: Iguatemi | B31: IGTI11 BZ | C31: Core | D31: Brasil | E31: BRL | F31: FY2024 | G31: 1236.345 | H31: 914.762 | I31: 190.255 | J31: =H31-I31 -> 724.507 | K31: 399.771 | L31: 4309.804 | M31: 1614.844 | N31: 0.216 | O31: 5071.0437 | P31: 17.27 | Q31: 0 | S31: =Supuestos!$C$13 -> 178.6442 | T31: =O31+M31+N31 -> 6686.1037
A32: Iguatemi | B32: IGTI11 BZ | C32: Core | D32: Brasil | E32: BRL | F32: FY2025 | G32: 1486.833 | H32: 1029.691 | I32: 113.963 | J32: =H32-I32 -> 915.728 | K32: 582.46 | L32: 4651.644 | M32: 2210.196 | N32: 0.22 | O32: 7307.0208 | P32: 25.57 | Q32: 0 | R32: EBITDA = EBITDA_ADJUSTED (comparable incluía ganancia por venta de activos). | S32: =Supuestos!$C$13 -> 178.6442 | T32: =O32+M32+N32 -> 9517.4368
A33: Iguatemi | B33: IGTI11 BZ | C33: Core | D33: Brasil | E33: BRL | F33: LTM | G33: 1527.409 | H33: 1127.509 | I33: 129.784 | J33: =H33-I33 -> 997.725 | K33: 638.571 | L33: 4937.138 | M33: 2138.597 | N33: 0.218 | O33: 7731.5118 | P33: 27.02 | Q33: 0 | R33: Q1-26 EBITDA = EBITDA_ADJUSTED. | S33: =Supuestos!$C$13 -> 178.6442 | T33: =O33+M33+N33 -> 9870.3268
A34: IRSA | B34: IRSA AR | C34: Sensibilidad | D34: Argentina | E34: ARS | F34: FY2022 (jun) | G34: 69299 | H34: 28988 | I34: 2007 | J34: =H34-I34 -> 26981 | K34: 74487 | L34: 342457 | M34: 136044 | N34: 23443 | O34: 74930.179 | P34: 97.185 | Q34: 0 | S34: =Supuestos!$C$15 -> 0.62236167 | T34: =O34+M34+N34 -> 234417.18
A35: IRSA | B35: IRSA AR | C35: Sensibilidad | D35: Argentina | E35: ARS | F35: FY2023 (jun) | G35: 331721 | H35: 92531 | I35: 7056 | J35: =H35-I35 -> 85475 | K35: 213076 | L35: 1345130 | M35: 378401 | N35: 82965 | O35: 331336.46 | P35: 433.728 | Q35: 0 | S35: =Supuestos!$C$15 -> 0.62236167 | T35: =O35+M35+N35 -> 792702.46
A36: IRSA | B36: IRSA AR | C36: Sensibilidad | D36: Argentina | E36: ARS | F36: FY2024 (jun) | G36: 458059 | H36: 232057 | I36: 9130 | J36: =H36-I36 -> 222927 | K36: -25621 | L36: 1503846 | M36: 484504 | N36: 102883 | O36: 898977.28 | P36: 1178.315 | Q36: 0 | R36: Utilidad negativa → P/E NM. | S36: =Supuestos!$C$15 -> 0.62236167 | T36: =O36+M36+N36 -> 1486364.3
A37: IRSA | B37: IRSA AR | C37: Sensibilidad | D37: Argentina | E37: ARS | F37: FY2025 (jun) | G37: 626290 | H37: 252539 | I37: 14034 | J37: =H37-I37 -> 238505 | K37: 260661 | L37: 2107122 | M37: 632450 | N37: 125752 | O37: 1260882 | P37: 1685 | Q37: 0 | S37: =Supuestos!$C$15 -> 0.62236167 | T37: =O37+M37+N37 -> 2019084
A38: IRSA | B38: IRSA AR | C38: Sensibilidad | D38: Argentina | E38: ARS | F38: LTM | G38: 657654 | H38: 234086.08 | I38: 16953.583 | J38: =H38-I38 -> 217132.49 | K38: 393510 | L38: 2279754 | M38: 901783 | N38: 140656 | O38: 1832401.5 | P38: 2260 | Q38: 0 | R38: FY jun-2026. Revenue y NI anuales (TRAIL_12M); EBITDA = Revenue × margen ajustado de los 4 trimestres (cifras NIC 29). | S38: =Supuestos!$C$15 -> 0.62236167 | T38: =O38+M38+N38 -> 2874840.5
A39: Fibra Danhos | B39: DANHOS13 MM | C39: Sensibilidad | D39: México | E39: MXN | F39: FY2022 | G39: 5513.0751 | H39: 3548.488 | I39: 17.399054 | J39: =H39-I39 -> 3531.0889 | K39: 2839.2736 | L39: 58859.105 | M39: 5777.2148 | N39: 2514.0535 | O39: 35837.309 | P39: 23.4 | Q39: 0 | S39: =Supuestos!$C$14 -> 52.70936 | T39: =O39+M39+N39 -> 44128.577
A40: Fibra Danhos | B40: DANHOS13 MM | C40: Sensibilidad | D40: México | E40: MXN | F40: FY2023 | G40: 6188.9891 | H40: 3946.7937 | I40: 16.68704 | J40: =H40-I40 -> 3930.1067 | K40: 3309.204 | L40: 59273.71 | M40: 7103.915 | N40: 2779.6918 | O40: 32666.034 | P40: 20.96 | Q40: 0 | S40: =Supuestos!$C$14 -> 52.70936 | T40: =O40+M40+N40 -> 42549.641
A41: Fibra Danhos | B41: DANHOS13 MM | C41: Sensibilidad | D41: México | E41: MXN | F41: FY2024 | G41: 6774.6488 | H41: 4404.9799 | I41: 12.314015 | J41: =H41-I41 -> 4392.6659 | K41: 4201.2111 | L41: 61136.362 | M41: 8959.336 | N41: 2694.196 | O41: 31741.125 | P41: 20.06 | Q41: 0 | S41: =Supuestos!$C$14 -> 52.70936 | T41: =O41+M41+N41 -> 43394.657
A42: Fibra Danhos | B42: DANHOS13 MM | C42: Sensibilidad | D42: México | E42: MXN | F42: FY2025 | G42: 7576.4276 | H42: 5024.1114 | I42: 13.044624 | J42: =H42-I42 -> 5011.0668 | K42: 5033.0947 | L42: 63801.629 | M42: 10355.722 | N42: 2856.8299 | O42: 45010.308 | P42: 28.06 | Q42: 0 | S42: =Supuestos!$C$14 -> 52.70936 | T42: =O42+M42+N42 -> 58222.86
A43: Fibra Danhos | B43: DANHOS13 MM | C43: Sensibilidad | D43: México | E43: MXN | F43: LTM | G43: 7919.1174 | H43: 5267.0922 | I43: 13.271624 | J43: =H43-I43 -> 5253.8206 | K43: 5720.8457 | L43: 65366.324 | M43: 11724.738 | N43: 2958.505 | O43: 45229.148 | P43: 27.94 | Q43: 0 | S43: =Supuestos!$C$14 -> 52.70936 | T43: =O43+M43+N43 -> 59912.391
A45: NTM — consenso Bloomberg BEst, 12 meses forward mezclado (BEST_FPERIOD_OVERRIDE = BF), al 07-oct-2026
A46: Empresa | B46: Ticker BBG | C46: Grupo | D46: País | E46: Moneda | F46: Período | G46: Revenue NTM | H46: EBITDA NTM | I46: EBIT NTM | J46: Net Income NTM | K46: Nº analistas (TOT_ANALYST_REC) | R46: Nota | S46: Factor a CLP
A47: Mallplaza | B47: MALLPLAZ CI | C47: Target | D47: Chile | E47: CLP | F47: NTM | G47: 758569.53 | H47: 617130.34 | I47: 611889.82 | J47: 488981.25 | K47: 13 | S47: =Supuestos!$C$11 -> 1
A48: Parque Arauco | B48: PARAUCO CI | C48: Core | D48: Chile | E48: CLP | F48: NTM | G48: 475685.59 | H48: 342581.95 | I48: 347536.96 | J48: 166719.85 | K48: 13 | R48: Consenso EBIT > EBITDA (distintos sets de analistas). | S48: =Supuestos!$C$11 -> 1
A49: Cencosud Shopping | B49: CENCOMAL CI | C49: Core | D49: Chile | E49: CLP | F49: NTM | G49: 436396.65 | H49: 392093.8 | I49: 395608.2 | J49: 278140.73 | K49: 11 | R49: Consenso EBIT > EBITDA (distintos sets de analistas). | S49: =Supuestos!$C$11 -> 1
A50: Multiplan | B50: MULT3 BZ | C50: Core | D50: Brasil | E50: BRL | F50: NTM | G50: 2802.8045 | H50: 2109.0708 | I50: 1967.477 | J50: 1291.4975 | K50: 15 | S50: =Supuestos!$C$13 -> 178.6442
A51: Allos | B51: ALOS3 BZ | C51: Core | D51: Brasil | E51: BRL | F51: NTM | G51: 3116.1764 | H51: 2315.4438 | I51: 1723.1952 | J51: 949.76836 | K51: 14 | S51: =Supuestos!$C$13 -> 178.6442
A52: Iguatemi | B52: IGTI11 BZ | C52: Core | D52: Brasil | E52: BRL | F52: NTM | G52: 1781.4726 | H52: 1333.7877 | I52: 1112.7717 | J52: 649.87309 | K52: 13 | S52: =Supuestos!$C$13 -> 178.6442
A53: IRSA | B53: IRSA AR | C53: Sensibilidad | D53: Argentina | E53: ARS | F53: NTM | G53: 708864.62 | H53: 460784.73 | I53: 444193.92 | J53: 199514.54 | K53: 1 | R53: Solo 1 analista: consenso no representativo. | S53: =Supuestos!$C$15 -> 0.62236167
A54: Fibra Danhos | B54: DANHOS13 MM | C54: Sensibilidad | D54: México | E54: MXN | F54: NTM | G54: 8336.5205 | H54: 5945.2215 | I54: 5956.3452 | J54: 5316.659 | K54: 9 | R54: Consenso EBIT > EBITDA (distintos sets de analistas). | S54: =Supuestos!$C$14 -> 52.70936

Sheet Supuestos
A1: Supuestos generales — Comparables Mallplaza (CFA Research Challenge)
A3: Fuente de datos | B3: Bloomberg Terminal (Excel Add-in BDP/BDH), extraído 07-oct-2026
A4: Fecha de corte (precios) | B4: 30-09-2026
A5: Último trimestre publicado | B5: 2T26 (30-jun-2026); IRSA: 4T FY2026 (30-jun-2026)
A6: Base tabla principal | B6: LTM — NTM no homogéneo (IRSA: 1 analista)
A7: Unidad de montos | B7: MM CLP
A9: Tipos de cambio (30-jun-2026, fecha del último EERR de Mallplaza)
A10: Moneda | B10: Unidades por USD | C10: CLP por unidad | D10: Fuente
A11: CLP | B11: — | C11: 1 | D11: —
A12: USD | B12: 1 | C12: 922.34 | D12: Dólar observado BCCh 30-jun-2026 = 922,34
A13: BRL | B13: 5.163 | C13: =$C$12/B13 -> 178.6442 | D13: Dólar comercial cierre 30-jun-2026
A14: MXN | B14: 17.4986 | C14: =$C$12/B14 -> 52.70936 | D14: Banxico, cierre 30-jun-2026
A15: ARS | B15: 1482 | C15: =$C$12/B15 -> 0.62236167 | D15: Dólar oficial mayorista cierre 30-jun-2026
A17: Umbral 'no significativo' (múltiplo mayor a → NM) | B17: 100
A19: Leyenda: azul = dato Bloomberg/ingresado · negro = fórmula · verde = vínculo a otra hoja · Target (Mallplaza) en naranjo, excluido de medianas.

Sheet Notas_Fuentes
A1: Metodología, advertencias y fuentes
A3: Fuente | B3: Bloomberg Terminal vía Excel Add-in (BDP/BDH), extraído el 07-oct-2026 desde el terminal del laboratorio. Tickers: MALLPLAZ CI, PARAUCO CI, CENCOMAL CI, MULT3 BZ, ALOS3 BZ, IGTI11 BZ, IRSA AR, DANHOS13 MM.
A4: Campos | B4: Revenue = SALES_REV_TURN · EBITDA = IS_COMPARABLE_EBITDA (excluye ítems no recurrentes) · D&A = CF_DEPR_AMORT · EBIT = EBITDA − D&A · Net Income = NET_INCOME (controladora, reportada) · Book Value = TOT_COMMON_EQY · Deuda neta = NET_DEBT · Minoritarios = MINORITY_NONCONTROLLING_INTEREST · Market Cap = CUR_MKT_CAP histórico (BDH) · Precio = PX_LAST.
A5: Por qué no el EBITDA 'normal' de Bloomberg | B5: El campo EBITDA estándar incluye la revalorización de propiedades para las empresas a valor razonable (ej. Mallplaza FY2025: 1,97 bn vs ingresos 0,65 bn). Por eso se usa el EBITDA comparable, y EBIT se reconstruye como EBITDA − D&A (el EBIT comparable de BBG era errático).
A6: Excepciones EBITDA | B6: Se usó EBITDA_ADJUSTED donde el comparable era inconsistente: Cencosud Shopping FY2022 y 1T26; Iguatemi FY2025 y 1T26; IRSA todos los períodos (su comparable venía con errores de escala/signo).
A7: LTM | B7: Suma de 3T25, 4T25, 1T26 y 2T26 (verificada contra TRAIL_12M de Bloomberg: Mallplaza revenue 677.333 = 677.334). Balance al 30-jun-2026. IRSA: FY2026 (jul-25 a jun-26).
A8: NTM | B8: Consenso BEst blended forward 12m. Cobertura: Mallplaza 13, Parque Arauco 13, Cencosud 11, Multiplan 15, Allos 14, Iguatemi 13, Fibra Danhos 9, IRSA 1 analista. Como IRSA no tiene consenso representativo, la tabla principal es LTM (regla: no mezclar).
A9: Moneda | B9: MM CLP con TC fijo del 30-jun-2026 (dólar observado 922,34) y cruces vía USD. Los múltiplos no cambian con el TC.
A10: Allos FY2023 | B10: Revenue de Bloomberg (7.481) incluye efectos de la combinación con brMalls; se reemplazó por 2.804 (S&P Global) para que EV/Revenue sea comparable. P/E FY2023 NM.
A11: IRSA | B11: Ejercicio jul-jun; cifras bajo NIC 29 en moneda de cada cierre: los múltiplos de cada columna son consistentes, los montos históricos en CLP no son comparables entre años.
A12: Valor razonable | B12: Mallplaza, Parque Arauco, Cencosud Shopping, IRSA y Danhos registran revalorizaciones en resultados → P/E bajo y volátil. Para comparar con Mallplaza, priorizar EV/EBITDA.
A13: Cambios vs versión anterior | B13: Fuente cambiada de S&P/StockAnalysis a Bloomberg; se agrega FY2022; precios al 30-sep-2026 exactos; balance 2T26 de Danhos actualizado; Mallplaza agregado como fila Target (excluida de medianas).
