Workbook

Sheet Cambios
A1: Mallplaza (Plaza S.A.) — Valorización consolidada v4
A2: Resumen y cambios respecto de 'Mallplaza Valoracion Consolidada VF.xlsx'. Todas las cifras de esta hoja son vínculos vivos.
A4: Resultado
A5: Valor por acción DCF (CLP) | B5: =DCF!C49 -> 1858.6534
A6: Valor por acción por múltiplos — EV/EBITDA LTM (CLP) | B6: =Precio_Objetivo!D5 -> 2951.3855
A7: Precio objetivo 80% DCF / 20% múltiplos (CLP) | B7: =Precio_Objetivo!B15 -> 2077.1998
A8: Precio 30-09-2026 (CLP) | B8: =Supuestos!$B$8 -> 3555
A9: Upside / (downside) del precio objetivo | B9: =Precio_Objetivo!B17 -> -0.41569626
A10: Valor por acción APV — chequeo (CLP) | B10: =DCF!C63 -> 1894.9907
A11: WACC nominal: 2S26E → terminal | B11: =WACC!C43 -> 0.10536861 | C11: =WACC!I43 -> 0.10413887
A12: DFN/EBITDA: hoy → 2031 | B12: =Supuestos!$B$41 -> 2.3594374 | C12: =Deuda!H22 -> 3.5
A14: Comparación con el VF
A15: Valor por acción DCF VF (CLP) | B15: =Supuestos!$B$108 -> 1882.6524
A16: Diferencia DCF v2 − VF (CLP) | B16: =DCF!C62 -> -23.999011
A17: Precio objetivo VF (CLP) | B17: =Supuestos!$B$110 -> 2096.399
A20: Qué cambió en v2
A21: 1. Estructura de capital: parte en la DFN/EBITDA real de jun-26 (2,36x) y converge linealmente a 3,5x al cierre de 2031 (Supuestos C, editable). El valor terminal usa 3,5x.
A22: 2. Deuda: la caja sobrante se registra como distribución adicional a accionistas (recompra o dividendo extra), de modo que la DFN sigue la trayectoria objetivo. En el VF la DFN bajaba a ~1,0x mientras la WACC suponía 3,5x.
A23: 3. WACC por período: el D/E parte en la estructura actual del modelo original (19,98%) y converge a la objetivo (28,52%) en 2031; beta, Ke, Kd y WACC se recalculan cada año y el DCF descuenta con factores acumulados.
A24: 4. Costo de la deuda: +25 pb de Kd real por cada vuelta de DFN/EBITDA sobre 2,36x (supuesto del equipo). Afecta la WACC y el costo financiero.
A25: 5. Reajuste UF tratado como gasto deducible en la hoja Deuda (no cambia el EV).
A26: 6. Nuevas hojas: APV (chequeo de consistencia) y Sensibilidad (WACC vs g con fórmulas vivas; objetivo de deuda vs spread).
A27: 7. Todo el libro queda vinculado: betas y CRP → WACC; Capital_Trabajo → Supuestos; Expansion → DCF; Datos_BBG → Comparables → Precio_Objetivo.
A28: 8. Sin cambios de supuestos: forecast operativo, expansión, capital de trabajo, g terminal, múltiplos y puente a patrimonio.
A29: Control: Supuestos C, switch = 0 → reproduce exactamente el VF (WACC 10,37% constante; CLP 1.880; precio objetivo CLP 2.095).
A31: NUEVO · v3: hojas TIR_Implicita (TIR de la firma, tasa única, Buscar objetivo) y TIR_Accionista (TIR de la firma, del accionista y por escenario, nominal y real, fórmulas vivas).
A32: NUEVO · v3: sin cambios en las demás hojas (valores idénticos a v2). El 7,61% de TIR_Implicita es una tasa única; el 7,60% de la Figura 27 desplaza en paralelo la WACC de cada período.
A33: NUEVO · v4: pipeline completo con fecha (170.200 m², USD 613 MM): se activan los «Otros proyectos Chile» (46.500 m², apertura 2028, USD 134 MM) en el forecast (Exhibits v7) y Supuestos!B73 = 114.400 m²; cambian Forecast_Base (filas 5, 7 y 12), el mix de la expansión y, por fórmula, DCF, Deuda, TIR y Sensibilidad.

Sheet Supuestos
A1: Supuestos — modelo consolidado de valoración Mallplaza (Plaza S.A.) · v4
A2: Única hoja de inputs. Azul = dato ingresado · negro = fórmula · verde = vínculo a otra hoja · fondo amarillo = supuesto clave del equipo. MM CLP salvo indicación. Tags: [R] reportado · [P] consenso/forecast · [C] cálculo · [S] supuesto del equipo.
A4: Concepto | B4: Valor | C4: Unidad | D4: Tag | E4: Fuente / comentario
A6: A. General y puente a patrimonio
A7: Fecha de valorización | B7: 30-06-2026 | C7: fecha | D7: S | E7: Coincide con la última DFN y minoritarios reportados (Release 2Q26).
A8: Precio de referencia | B8: 3555 | C8: CLP | D8: R | E8: Bloomberg PX_LAST al 30-09-2026 (Datos_BBG).
A9: Acciones en circulación | B9: 2190 | C9: MM | D9: R | E9: Bloomberg: market cap / precio (Datos_BBG).
A10: Deuda financiera neta 30-06-2026 (definición compañía) | B10: 1285740 | C10: MM CLP | D10: R | E10: Release 2Q26 / Análisis Razonado 1S26.
A11: Participaciones no controladoras (libro) 30-06-2026 | B11: 50841 | C11: MM CLP | D11: R | E11: Release 2Q26. Libro como proxy del valor de mercado [S].
A12: Caja y equivalentes 30-06-2026 | B12: 347621 | C12: MM CLP | D12: R | E12: Release 2Q26. Se mantiene constante para pasar de DFN a deuda bruta.
A13: EBITDA LTM 2T26 (definición compañía) | B13: 544935 | C13: MM CLP | D13: R | E13: Release 2Q26, p. 29.
A14: Deuda neta Mallplaza para múltiplos (BBG NET_DEBT) | B14: 1311568.6 | C14: MM CLP | D14: R | E14: Misma definición que los pares (Bloomberg), solo para el método de múltiplos.
A16: B. WACC (fórmulas en hoja WACC)
A17: Rf — bono del Tesoro de EE.UU. | B17: 0.049778 | C17: % | D17: R | E17: Tasa_WACC.xlsm, FFCF!C11.
A18: Rf — tasa "Chile" del archivo original | B18: 0.0543 | C18: % | D18: R | E18: Tasa_WACC.xlsm, FFCF!E11. Si ya incluye riesgo Chile, el CRP se contaría dos veces.
A19: Rf usada en el Ke (1 = "Chile" · 2 = EE.UU.) | B19: 2 | C19: switch | D19: S | E19: Rf = bono de EE.UU.; el CRP se suma aparte (sin doble conteo).
A20: Inflación de largo plazo EE.UU. (breakeven 10Y, jun-26) | B20: 0.022431 | C20: % | D20: R | E20: Bloomberg USGG10YR − USGGT10Y al 30-06-2026.
A21: Convertir el Ke en USD a CLP con el diferencial de inflación (1 = sí) | B21: 1 | C21: switch | D21: S | E21: Ke CLP = (1 + Ke USD) × (1 + inflación Chile) / (1 + inflación EE.UU.) − 1.
A22: Prima por riesgo de mercado (ERP) | B22: 0.0414 | C22: % | D22: R | E22: Damodaran (Tasa_WACC.xlsm, FFCF!B73).
A23: CRP Chile | B23: 0.0104 | C23: % | D23: R | E23: Tasa_WACC.xlsm, FFCF!C79.
A24: CRP Perú | B24: 0.0155 | C24: % | D24: R | E24: Tasa_WACC.xlsm, FFCF!C80.
A25: CRP Colombia | B25: 0.037 | C25: % | D25: R | E25: Tasa_WACC.xlsm, FFCF!C81.
A26: Ingresos LTM consolidados (ponderador CRP) | B26: 677333 | C26: MM CLP | D26: R | E26: Tasa_WACC.xlsm, FFCF!C83.
A27: Ingresos LTM Chile | B27: 486084 | C27: MM CLP | D27: R | E27: Tasa_WACC.xlsm, FFCF!C86.
A28: Ingresos LTM Perú | B28: 463174 | C28: miles PEN | D28: R | E28: Tasa_WACC.xlsm, FFCF!C90.
... A37: Market cap Mallplaza (estructura de la WACC) | B37: 7905900 | C37: MM CLP | D37: R | E37: Tasa_WACC.xlsm, FFCF!G26.
A39: C. Política de deuda (v2: estructura actual → objetivo de largo plazo)
A40: Política de deuda (1 = convergencia al objetivo · 0 = WACC constante del VF) | B40: 1 | C40: switch | D40: S | E40: Con 0 se reproduce el DCF VF: 3,5x desde hoy, WACC 10,37% constante, CLP 1.880.
A41: DFN / EBITDA inicial (30-06-2026) | B41: =$B$10/$B$13 -> 2.3594374 | C41: x | D41: C | E41: DFN / EBITDA LTM.
A42: DFN / EBITDA objetivo de largo plazo | B42: 3.5 | C42: x | D42: S | E42: La compañía usa su capacidad de deuda para crecer. Referencias: 3,78x dic-24 (post Open Plaza Perú); Parque Arauco 5,7x; Cencosud Shopping 2,1x.
A43: Año en que se alcanza el objetivo (al 31-dic) | B43: 2031 | C43: año | D43: S | E43: Convergencia lineal desde el nivel inicial; el valor terminal usa el objetivo.
A44: Horizonte de convergencia | B44: =$B$43-2026+0.5 -> 5.5 | C44: años | D44: C | E44: Años entre el 30-06-2026 y el 31-dic del año objetivo.
A45: Aumento del Kd real por cada 1,0x de DFN/EBITDA sobre el nivel inicial | B45: 0.0025 | C45: % | D45: S | E45: Más deuda → menor clasificación y mayor spread. Calibrar con spreads de bonos corporativos UF por clasificación. Afecta la WACC y el costo financiero de la hoja Deuda.
A46: Costo financiero neto / DFN de apertura (sin reajuste UF), nivel inicial | B46: 0.0308 | C46: % | D46: C | E46: Exhibits v6: 1S26 anualizado.
A47: Deuda en UF / deuda total | B47: 0.79 | C47: % | D47: R | E47: Release 2Q26.
A48: Payout sobre utilidad distribuible | B48: 0.4 | C48: % | D48: R | E48: Política de dividendos (EEFF dic-25, Nota 20e).
A49: Dividendos 2026E totales | B49: 147724.8 | C49: MM CLP | D49: P | E49: Exhibits v6 (40% × distribuible 2025).
A50: Dividendos pagados 1S26 | B50: 87617 | C50: MM CLP | D50: R | E50: EEFF jun-26, flujos.
A51: Utilidad distribuible 2026E (año completo) | B51: 380038.82 | C51: MM CLP | D51: P | E51: Exhibits v6.
A53: D. Forecast base (motor operativo, Exhibits v6)
A54: Ingresos 1S26 real | B54: 339530 | C54: MM CLP | D54: R | E54: Release 2Q26, p. 31.
A55: EBITDA 1S26 real usado para aislar el 2S26 | B55: 270574 | C55: MM CLP | D55: R | E55: Release informa 270.573 (p. 8): diferencia de redondeo.
A56: Ingresos 2025A | B56: 653911 | C56: MM CLP | D56: R | E56: EEFF dic-25.
A57: D&A / ingresos | B57: 0.0070364208 | C57: % | D57: C | E57: D&A LTM / ingresos LTM (Exhibits v6).
A58: Capex de mantención + TI / ingresos | B58: 0.055 | C58: % | D58: S | E58: Entre 2024 (~4,8%) y UDM 2T26 (~6,6%).
A59: Tasa de impuesto operacional de largo plazo | B59: 0.27 | C59: % | D59: S | E59: Trayectoria 16,8% → 27%; 27% desde 2030.
A61: E. Expansión continua post-pipeline
A62: Incluir expansión continua (1 = sí) | B62: 1 | C62: switch | D62: S | E62: La compañía sigue expandiendo GLA después de 2028 a un ritmo parecido al histórico.
A63: GLA orgánico agregado 2022 | B63: 30458 | C63: m² | D63: R | E63: Release 2Q26, p. 29.
A64: GLA orgánico agregado 2023 | B64: 38618 | C64: m² | D64: R | E64: Release 2Q26, p. 29.
A65: GLA orgánico agregado 2025 | B65: 12150 | C65: m² | D65: R | E65: Release 2Q26, p. 29. Se excluye 2024 (413.628 m², incluye compra de Open Plaza Perú).
A66: GLA nuevo por año desde la primera apertura | B66: =AVERAGE($B$63,$B$64,$B$65) -> 27075.333 | C66: m² | D66: C | E66: Promedio 2022, 2023 y 2025. El pipeline 2026–2028 promedia ~41.000 m²/año.
A67: Primer año de apertura de la expansión genérica | B67: 2029 | C67: año | D67: S | E67: El pipeline informado termina en 2028 (Release 2Q26, p. 13).
A68: Capex desembolsado 2 años antes de abrir | B68: 0.5 | C68: % | D68: S | E68: 50% en t−2 y 50% en t−1. Ingresos desde el año de apertura.
A69: Inversión total pipeline en curso | B69: 613.2 | C69: MMUSD | D69: R | E69: Release 2Q26, p. 13.
A70: m² del pipeline en curso | B70: 170200 | C70: m² | D70: R | E70: Release 2Q26, p. 13.
A71: Costo por m² de expansión | B71: =$B$69*1000000/$B$70 -> 3602.8202 | C71: USD/m² | D71: C | E71: Inversión total / m² del pipeline.
A72: USDCLP para convertir el costo (2026) | B72: 921 | C72: CLP/USD | D72: P | E72: Forecast v6 (consenso ECFC).
A73: m² del pipeline en Chile (67.900 + 46.500 de «Otros proyectos Chile», v4) | B73: 114400 | C73: m² | D73: R | E73: Release 2Q26, p. 13: Trébol, Oeste, Norte, La Serena.
A74: m² del pipeline en Perú | B74: 55800 | C74: m² | D74: R | E74: Release 2Q26, p. 13: Trujillo, Piura, La Marina, Angamos.
A75: Mix de la expansión en Chile | B75: =$B$73/($B$73+$B$74) -> 0.67215041 | C75: % | D75: C | E75: Replica el mix país del pipeline actual; el resto va a Perú.
A76: Margen EBITDA Chile | B76: 0.8 | C76: % | D76: S | E76: Forecast v6.
A77: Margen EBITDA Perú | B77: 0.82 | C77: % | D77: S | E77: Forecast v6.
A78: Factor de ingreso: año de apertura | B78: 0.35 | C78: % | D78: S | E78: Apertura a mitad de año × 70% de productividad.
A79: Factor de ingreso: segundo año | B79: 0.9 | C79: % | D79: S | E79: Forecast v6.
A80: Factor de ingreso: tercer año en adelante | B80: 1 | C80: % | D80: S | E80: Forecast v6.
A81: Yield on cost (EBITDA maduro / inversión) — dejar vacío para usar el derivado | C81: % | D81: S | E81: Si el equipo tiene la guía de retorno de proyectos, ingresarla aquí.
A83: F. Capital de trabajo
A84: Incluir variación de capital de trabajo (1 = sí) | B84: 1 | C84: switch | D84: S | E84: Ver hoja Capital_Trabajo.
A85: Capital de trabajo neto / ingresos (dic-25, constante) | B85: =Capital_Trabajo!F20 -> 0.15604341 | C85: % | D85: C | E85: Hoja Capital_Trabajo.
A87: G. Valor terminal
A88: Crecimiento terminal nominal (g) | B88: 0.03 | C88: % | D88: S | E88: Igual a la inflación LP (0% real). Con RONIC < WACC real, crecer resta valor.
A89: Crecimiento terminal real implícito | B89: =(1+$B$88)/(1+$B$34)-1 -> 0 | C89: % | D89: C | E89: Solo el crecimiento real exige reinversión.
A91: H. Precio objetivo y múltiplos
A92: Peso del DCF en el precio objetivo | B92: 0.8 | C92: % | D92: S | E92: 80% DCF / 20% múltiplos.
A93: Peso de los comparables chilenos en el múltiplo | B93: 0.7 | C93: % | D93: S | E93: 70% mediana Chile + 30% mediana del set común.
A94: Umbral 'no significativo' (múltiplo mayor a → NM) | B94: 100 | C94: x | D94: S | E94: Archivo de comparables.
A96: I. Tipos de cambio para comparables (30-06-2026)
A97: USD por USD | B97: 1 | D97: R | E97: —
A98: BRL por USD | B98: 5.163 | C98: BRL | D98: R | E98: Cierre 30-jun-2026.
A99: MXN por USD | B99: 17.4986 | C99: MXN | D99: R | E99: Banxico, cierre 30-jun-2026.
A100: ARS por USD | B100: 1482 | C100: ARS | D100: R | E100: Oficial mayorista, cierre 30-jun-2026.
A101: CLP por CLP | B101: 1 | C101: CLP | D101: R | E101: —
A102: CLP por USD | B102: 922.34 | C102: CLP | D102: R | E102: Dólar observado BCCh 30-jun-2026.
A103: CLP por BRL | B103: =$B$102/$B$98 -> 178.6442 | C103: CLP | D103: C
A104: CLP por MXN | B104: =$B$102/$B$99 -> 52.70936 | C104: CLP | D104: C
A105: CLP por ARS | B105: =$B$102/$B$100 -> 0.62236167 | C105: CLP | D105: C
A107: J. Referencias de control (modelo VF)
A108: Valor por acción DCF VF | B108: 1882.6524 | C108: CLP | D108: C | E108: DCF VF. El switch de la sección C en 0 debe reproducirlo.
A109: WACC nominal VF (constante) | B109: 0.10366307 | C109: % | D109: C | E109: Hoja WACC del VF.
A110: Precio objetivo VF | B110: 2096.399 | C110: CLP | D110: C | E110: Hoja Precio_Objetivo del VF.

Sheet WACC
A1: WACC nominal en CLP por período — misma lógica que Tasa_WACC.xlsm (FFCF) con correcciones
A2: Correcciones del VF: (1) Kd real UF pasado a nominal; (2) escudo fiscal (1 − t); (3) set de pares = coincidencia betas–comparables. v2: la estructura de capital, la beta y el Kd cambian cada período según la hoja Deuda.
A4: A. Betas de los pares
A5: Empresa | B5: Ticker BBG | C5: País | D5: Beta apalancada | E5: Deuda | F5: Market cap | G5: Impuesto | H5: Beta desapalancada | I5: En set común (1/0) | J5: Beta incluida
A6: Parque Arauco | B6: PARAUCO CI | C6: Chile | D6: 1.25 | E6: 1700506.9 | F6: 3828031 | G6: 0.27 | H6: =D6/(1+(1-G6)*E6/F6) -> 0.94390614 | I6: =IF(COUNTIFS(Comparables!$B$5:$B$12,B6,Comparables!$D$5:$D$12,1)>0,1,0) -> 1 | J6: =IF(I6=1,H6,"") -> 0.94390614
A7: Cencosud Shopping | B7: CENCOMAL CI | C7: Chile | D7: 1.075 | E7: 762153.7 | F7: 3942858 | G7: 0.27 | H7: =D7/(1+(1-G7)*E7/F7) -> 0.94206612 | I7: =IF(COUNTIFS(Comparables!$B$5:$B$12,B7,Comparables!$D$5:$D$12,1)>0,1,0) -> 1 | J7: =IF(I7=1,H7,"") -> 0.94206612
A8: Allos | B8: ALOS3 BZ | C8: Brasil | D8: 1.164 | E8: 960191 | F8: 2712166.2 | G8: 0.34 | H8: =D8/(1+(1-G8)*E8/F8) -> 0.94353351 | I8: =IF(COUNTIFS(Comparables!$B$5:$B$12,B8,Comparables!$D$5:$D$12,1)>0,1,0) -> 1 | J8: =IF(I8=1,H8,"") -> 0.94353351
A9: Iguatemi | B9: IGTI11 BZ | C9: Brasil | D9: 0.908 | E9: 647396.6 | F9: 1421560.1 | G9: 0.34 | H9: =D9/(1+(1-G9)*E9/F9) -> 0.69815413 | I9: =IF(COUNTIFS(Comparables!$B$5:$B$12,B9,Comparables!$D$5:$D$12,1)>0,1,0) -> 1 | J9: =IF(I9=1,H9,"") -> 0.69815413
A10: Costa Verde | B10: n/d (no está en comparables) | C10: México | D10: 0.025 | E10: 203967.5 | F10: 489349.7 | G10: 0.3 | H10: =D10/(1+(1-G10)*E10/F10) -> 0.0193533 | I10: =IF(COUNTIFS(Comparables!$B$5:$B$12,B10,Comparables!$D$5:$D$12,1)>0,1,0) -> 0 | J10: =IF(I10=1,H10,"")
A11: IRSA | B11: IRSA AR | C11: Argentina | D11: 0.427 | E11: 625046.5 | F11: 1218777.1 | G11: 0.35 | H11: =D11/(1+(1-G11)*E11/F11) -> 0.32024582 | I11: =IF(COUNTIFS(Comparables!$B$5:$B$12,B11,Comparables!$D$5:$D$12,1)>0,1,0) -> 1 | J11: =IF(I11=1,H11,"") -> 0.32024582
A12: Multiplan | B12: MULT3 BZ | C12: Brasil | D12: 1.219 | E12: 191478.3 | F12: 2959844.9 | G12: 0.34 | H12: =D12/(1+(1-G12)*E12/F12) -> 1.1690839 | I12: =IF(COUNTIFS(Comparables!$B$5:$B$12,B12,Comparables!$D$5:$D$12,1)>0,1,0) -> 1 | J12: =IF(I12=1,H12,"") -> 1.1690839
A13: Beta desapalancada: mediana del set común | H13: =MEDIAN(J6:J12) -> 0.94279981 | I13: =COUNT(J6:J12) -> 6
A15: B. Riesgo país ponderado por ingresos
A16: Ponderación Chile (ingresos) | C16: =Supuestos!$B$27/Supuestos!$B$26 -> 0.71764405
A17: Ingresos Perú en MM CLP | C17: =Supuestos!$B$28/Supuestos!$B$31*Supuestos!$B$30/1000 -> 125262.08
A18: Ingresos Colombia en MM CLP | C18: =Supuestos!$B$29/Supuestos!$B$32*Supuestos!$B$30 -> 74355.805
A19: Ponderación Perú | C19: =(1-$C$16)*$C$17/($C$17+$C$18) -> 0.17718098
A20: Ponderación Colombia | C20: =(1-$C$16)*$C$18/($C$17+$C$18) -> 0.10517496
A21: CRP ponderado Mallplaza | C21: =$C$16*Supuestos!$B$23+$C$19*Supuestos!$B$24+$C$20*Supuestos!$B$25 -> 0.014101277
A22: Rf usada | C22: =IF(Supuestos!$B$19=1,Supuestos!$B$18,Supuestos!$B$17) -> 0.049778
A24: C. Estructura de capital original del modelo (extremos de la convergencia)
A25: Deuda bruta actual / market cap = D/E actual (punto de partida) | C25: =Supuestos!$B$36/Supuestos!$B$37 -> 0.19976413 | D25: Estructura actual calculada en el modelo original (Tasa_WACC.xlsm, FFCF!G23:G26): 1.579.315 / 7.905.900.
A26: Deuda objetivo = DFN/EBITDA objetivo × EBITDA LTM + caja | C26: =Supuestos!$B$42*Supuestos!$B$13+Supuestos!$B$12 -> 2254893.5
A27: D/E objetivo (punto de llegada, valor terminal) | C27: =C26/Supuestos!$B$37 -> 0.28521655 | D27: Estructura objetivo calculada en el modelo original (3,5x): 28,52%.
A28: Control: Ke del archivo original (Rf "Chile", estructura actual, sin conversión) | C28: =Supuestos!$B$18+$H$13*(1+(1-Supuestos!$B$35)*Supuestos!$B$36/Supuestos!$B$37)*Supuestos!$B$22+$C$21 -> 0.11312513 | D28: Debe dar 11,31% (Tasa_WACC.xlsm, FFCF!B112).
A30: D. WACC por período (D/E converge linealmente de la estructura actual a la objetivo)
A31: Concepto | C31: 2S26E | D31: 2027E | E31: 2028E | F31: 2029E | G31: 2030E | H31: 2031E | I31: Terminal
A32: DFN / EBITDA (cierre del período) | C32: =Deuda!C22 -> 2.4631249 | D32: =Deuda!D22 -> 2.6704999 | E32: =Deuda!E22 -> 2.8778749 | F32: =Deuda!F22 -> 3.08525 | G32: =Deuda!G22 -> 3.292625 | H32: =Deuda!H22 -> 3.5 | I32: =IF(Supuestos!$B$40=1,Supuestos!$B$42,Deuda!H22) -> 3.5
A33: Años desde 30-06-2026 al cierre del período | C33: =Deuda!C5 -> 0.5 | D33: =Deuda!D5 -> 1.5 | E33: =Deuda!E5 -> 2.5 | F33: =Deuda!F5 -> 3.5 | G33: =Deuda!G5 -> 4.5 | H33: =Deuda!H5 -> 5.5
A34: D/E usado | C34: =IF(Supuestos!$B$40=1,WACC!$C$25+(WACC!$C$27-WACC!$C$25)*MIN(1,C33/Supuestos!$B$44),WACC!$C$27) -> 0.20753253 | D34: =IF(Supuestos!$B$40=1,WACC!$C$25+(WACC!$C$27-WACC!$C$25)*MIN(1,D33/Supuestos!$B$44),WACC!$C$27) -> 0.22306933 | E34: =IF(Supuestos!$B$40=1,WACC!$C$25+(WACC!$C$27-WACC!$C$25)*MIN(1,E33/Supuestos!$B$44),WACC!$C$27) -> 0.23860614 | F34: =IF(Supuestos!$B$40=1,WACC!$C$25+(WACC!$C$27-WACC!$C$25)*MIN(1,F33/Supuestos!$B$44),WACC!$C$27) -> 0.25414294 | G34: =IF(Supuestos!$B$40=1,WACC!$C$25+(WACC!$C$27-WACC!$C$25)*MIN(1,G33/Supuestos!$B$44),WACC!$C$27) -> 0.26967974 | H34: =IF(Supuestos!$B$40=1,WACC!$C$25+(WACC!$C$27-WACC!$C$25)*MIN(1,H33/Supuestos!$B$44),WACC!$C$27) -> 0.28521655 | I34: =WACC!$C$27 -> 0.28521655 | J34: Convergencia lineal desde el D/E actual (19,98%) hasta el objetivo (28,52%) en el año objetivo de Supuestos C; el terminal usa el objetivo. Switch 0: objetivo desde hoy (VF).
A35: D/V | C35: =C34/(1+C34) -> 0.17186496 | D35: =D34/(1+D34) -> 0.18238486 | E35: =E34/(1+E34) -> 0.19264085 | F35: =F34/(1+F34) -> 0.20264272 | G35: =G34/(1+G34) -> 0.21239982 | H35: =H34/(1+H34) -> 0.221921 | I35: =I34/(1+I34) -> 0.221921
A36: E/V | C36: =1-C35 -> 0.82813504 | D36: =1-D35 -> 0.81761514 | E36: =1-E35 -> 0.80735915 | F36: =1-F35 -> 0.79735728 | G36: =1-G35 -> 0.78760018 | H36: =1-H35 -> 0.778079 | I36: =1-I35 -> 0.778079
A37: Beta re-apalancada | C37: =WACC!$H$13*(1+(1-Supuestos!$B$35)*C34) -> 1.0856328 | D37: =WACC!$H$13*(1+(1-Supuestos!$B$35)*D34) -> 1.0963259 | E37: =WACC!$H$13*(1+(1-Supuestos!$B$35)*E34) -> 1.107019 | F37: =WACC!$H$13*(1+(1-Supuestos!$B$35)*F34) -> 1.1177121 | G37: =WACC!$H$13*(1+(1-Supuestos!$B$35)*G34) -> 1.1284052 | H37: =WACC!$H$13*(1+(1-Supuestos!$B$35)*H34) -> 1.1390984 | I37: =WACC!$H$13*(1+(1-Supuestos!$B$35)*I34) -> 1.1390984
A38: Ke antes de conversión = Rf + β × ERP + CRP | C38: =WACC!$C$22+C37*Supuestos!$B$22+WACC!$C$21 -> 0.10882448 | D38: =WACC!$C$22+D37*Supuestos!$B$22+WACC!$C$21 -> 0.10926717 | E38: =WACC!$C$22+E37*Supuestos!$B$22+WACC!$C$21 -> 0.10970986 | F38: =WACC!$C$22+F37*Supuestos!$B$22+WACC!$C$21 -> 0.11015256 | G38: =WACC!$C$22+G37*Supuestos!$B$22+WACC!$C$21 -> 0.11059525 | H38: =WACC!$C$22+H37*Supuestos!$B$22+WACC!$C$21 -> 0.11103795 | I38: =WACC!$C$22+I37*Supuestos!$B$22+WACC!$C$21 -> 0.11103795
A39: Ke nominal CLP | C39: =IF(AND(Supuestos!$B$21=1,Supuestos!$B$19=2),(1+C38)*(1+Supuestos!$B$34)/(1+Supuestos!$B$20)-1,C38) -> 0.11703304 | D39: =IF(AND(Supuestos!$B$21=1,Supuestos!$B$19=2),(1+D38)*(1+Supuestos!$B$34)/(1+Supuestos!$B$20)-1,D38) -> 0.11747901 | E39: =IF(AND(Supuestos!$B$21=1,Supuestos!$B$19=2),(1+E38)*(1+Supuestos!$B$34)/(1+Supuestos!$B$20)-1,E38) -> 0.11792499 | F39: =IF(AND(Supuestos!$B$21=1,Supuestos!$B$19=2),(1+F38)*(1+Supuestos!$B$34)/(1+Supuestos!$B$20)-1,F38) -> 0.11837096 | G39: =IF(AND(Supuestos!$B$21=1,Supuestos!$B$19=2),(1+G38)*(1+Supuestos!$B$34)/(1+Supuestos!$B$20)-1,G38) -> 0.11881693 | H39: =IF(AND(Supuestos!$B$21=1,Supuestos!$B$19=2),(1+H38)*(1+Supuestos!$B$34)/(1+Supuestos!$B$20)-1,H38) -> 0.1192629 | I39: =IF(AND(Supuestos!$B$21=1,Supuestos!$B$19=2),(1+I38)*(1+Supuestos!$B$34)/(1+Supuestos!$B$20)-1,I38) -> 0.1192629 | J39: Con Rf de EE.UU. el Ke queda en USD y se pasa a CLP por diferencial de inflación.
A40: Kd real (UF) con spread por apalancamiento | C40: =Supuestos!$B$33+Supuestos!$B$40*Supuestos!$B$45*MAX(0,C32-Supuestos!$B$41) -> 0.036259219 | D40: =Supuestos!$B$33+Supuestos!$B$40*Supuestos!$B$45*MAX(0,D32-Supuestos!$B$41) -> 0.036777656 | E40: =Supuestos!$B$33+Supuestos!$B$40*Supuestos!$B$45*MAX(0,E32-Supuestos!$B$41) -> 0.037296094 | F40: =Supuestos!$B$33+Supuestos!$B$40*Supuestos!$B$45*MAX(0,F32-Supuestos!$B$41) -> 0.037814531 | G40: =Supuestos!$B$33+Supuestos!$B$40*Supuestos!$B$45*MAX(0,G32-Supuestos!$B$41) -> 0.038332969 | H40: =Supuestos!$B$33+Supuestos!$B$40*Supuestos!$B$45*MAX(0,H32-Supuestos!$B$41) -> 0.038851407 | I40: =Supuestos!$B$33+Supuestos!$B$40*Supuestos!$B$45*MAX(0,I32-Supuestos!$B$41) -> 0.038851407
A41: Kd nominal CLP = (1 + Kd real)(1 + inflación) − 1 | C41: =(1+C40)*(1+Supuestos!$B$34)-1 -> 0.067346995 | D41: =(1+D40)*(1+Supuestos!$B$34)-1 -> 0.067880986 | E41: =(1+E40)*(1+Supuestos!$B$34)-1 -> 0.068414977 | F41: =(1+F40)*(1+Supuestos!$B$34)-1 -> 0.068948967 | G41: =(1+G40)*(1+Supuestos!$B$34)-1 -> 0.069482958 | H41: =(1+H40)*(1+Supuestos!$B$34)-1 -> 0.070016949 | I41: =(1+I40)*(1+Supuestos!$B$34)-1 -> 0.070016949
A42: Kd nominal después de impuestos | C42: =C41*(1-Supuestos!$B$35) -> 0.049163307 | D42: =D41*(1-Supuestos!$B$35) -> 0.04955312 | E42: =E41*(1-Supuestos!$B$35) -> 0.049942933 | F42: =F41*(1-Supuestos!$B$35) -> 0.050332746 | G42: =G41*(1-Supuestos!$B$35) -> 0.050722559 | H42: =H41*(1-Supuestos!$B$35) -> 0.051112373 | I42: =I41*(1-Supuestos!$B$35) -> 0.051112373
A43: WACC nominal CLP | C43: =C36*C39+C35*C42 -> 0.10536861 | D43: =D36*D39+D35*D42 -> 0.10509036 | E43: =E36*E39+E35*E42 -> 0.10482887 | F43: =F36*F39+F35*F42 -> 0.10458351 | G43: =G36*G39+G35*G42 -> 0.1043537 | H43: =H36*H39+H35*H42 -> 0.10413887 | I43: =I36*I39+I35*I42 -> 0.10413887
A44: WACC real implícita | C44: =(1+C43)/(1+Supuestos!$B$34)-1 -> 0.07317341 | D44: =(1+D43)/(1+Supuestos!$B$34)-1 -> 0.072903261 | E44: =(1+E43)/(1+Supuestos!$B$34)-1 -> 0.072649384 | F44: =(1+F43)/(1+Supuestos!$B$34)-1 -> 0.072411174 | G44: =(1+G43)/(1+Supuestos!$B$34)-1 -> 0.072188056 | H44: =(1+H43)/(1+Supuestos!$B$34)-1 -> 0.071979483 | I44: =(1+I43)/(1+Supuestos!$B$34)-1 -> 0.071979483
A46: Referencia: WACC constante del VF | C46: =Supuestos!$B$109 -> 0.10366307 | D46: Con el switch de política de deuda en 0, todas las columnas deben dar este valor.
A47: Referencia: WACC real tasación Nota 11 Chile jun-26 | C47: 0.0555 | D47: Punto medio del rango de la Nota 11 (Exhibits v6, E7).

Sheet Forecast_Base
A1: Forecast base — motor operativo (Mallplaza_FA_Exhibits_v6.xlsx), 2S26E–2031E
A2: Cifras del forecast del equipo en azul (Exhibits v7), con el pipeline completo con fecha: 170.200 m² y USD 613 MM (incluye «Otros proyectos Chile», 46.500 m² que abren en 2028). Sin la expansión post-2028 (hoja Expansion).
A4: MM CLP | C4: 2S26E | D4: 2027E | E4: 2028E | F4: 2029E | G4: 2030E | H4: 2031E | I4: Fuente / supuesto
A5: Ingresos año calendario (2026E = año completo) | C5: 703998.94 | D5: 767179.42 | E5: 826661.82 | F5: 883482.45 | G5: 923321.86 | H5: 959373.85 | I5: Exhibits v7, Forecast fila «Ingresos ordinarios consolidados» (con Otros proyectos Chile).
A6: Ingresos del período (2S26E = 2026E − 1S26 real) | C6: =C5-Supuestos!$B$54 -> 364468.94 | D6: =D5 -> 767179.42 | E6: =E5 -> 826661.82 | F6: =F5 -> 883482.45 | G6: =G5 -> 923321.86 | H6: =H5 -> 959373.85
A7: EBITDA año calendario | C7: 561315.41 | D7: 611360.36 | E7: 659160.32 | F7: 704684.52 | G7: 736419.6 | H7: 765088.08 | I7: Exhibits v7, Forecast bloque E (con Otros proyectos Chile).
A8: EBITDA del período | C8: =C7-Supuestos!$B$55 -> 290741.41 | D8: =D7 -> 611360.36 | E8: =E7 -> 659160.32 | F8: =F7 -> 704684.52 | G8: =G7 -> 736419.6 | H8: =H7 -> 765088.08
A9: Margen EBITDA | C9: =C8/C6 -> 0.79771244 | D9: =D8/D6 -> 0.79689358 | E9: =E8/E6 -> 0.79737603 | F9: =F8/F6 -> 0.79762141 | G9: =G8/G6 -> 0.79757626 | H9: =H8/H6 -> 0.7974869
A10: D&A | C10: =Supuestos!$B$57*C6 -> 2564.5568 | D10: =Supuestos!$B$57*D6 -> 5398.1972 | E10: =Supuestos!$B$57*E6 -> 5816.7404 | F10: =Supuestos!$B$57*F6 -> 6216.5543 | G10: =Supuestos!$B$57*G6 -> 6496.8811 | H10: =Supuestos!$B$57*H6 -> 6750.5581 | I10: D&A / ingresos LTM × ingresos.
A11: Tasa de impuesto operacional en caja | C11: 0.168 | D11: 0.19 | E11: 0.215 | F11: 0.24 | G11: 0.27 | H11: 0.27 | I11: Exhibits v6: impuesto corriente / (EBITDA − costo financiero), 16,8% → 27%.
A12: Capex de proyectos en curso (MMUSD) | C12: 140.44 | D12: 268.68 | E12: 169.88 | F12: 0 | G12: 0 | H12: 0 | I12: Release 2Q26, pp. 12–14: remanente por proyecto repartido hasta su apertura.
A13: USDCLP promedio | C13: 929.55 | D13: 922.75 | E13: 914.75 | F13: 921 | G13: 921 | H13: 921 | I13: 2S26E promedio del semestre; 2027+ consenso ECFC; 2029+ constante.
A14: Capex de proyectos en curso (MM CLP) | C14: =C12*C13 -> 130546 | D14: =D12*D13 -> 247924.47 | E14: =E12*E13 -> 155397.73 | F14: =F12*F13 -> 0 | G14: =G12*G13 -> 0 | H14: =H12*H13 -> 0
A15: Capex de mantención + TI | C15: =Supuestos!$B$58*C5/2 -> 19359.971 | D15: =Supuestos!$B$58*D5 -> 42194.868 | E15: =Supuestos!$B$58*E5 -> 45466.4 | F15: =Supuestos!$B$58*F5 -> 48591.535 | G15: =Supuestos!$B$58*G5 -> 50782.702 | H15: =Supuestos!$B$58*H5 -> 52765.562 | I15: 5,5% de ingresos (2S26E: medio año de 2026E).
A16: Capex base total | C16: =C14+C15 -> 149905.97 | D16: =D14+D15 -> 290119.34 | E16: =E14+E15 -> 200864.13 | F16: =F14+F15 -> 48591.535 | G16: =G14+G15 -> 50782.702 | H16: =H14+H15 -> 52765.562 | I16: Sin la expansión post-pipeline (hoja Expansion).
A18: Ingreso anual por m² Chile (CLP) | C18: 341079.53 | D18: 360468.33 | E18: 378194.73 | F18: 395002.18 | G18: 411161.93 | H18: 426868.38 | I18: Exhibits v6, Forecast bloque D, Chile. Se aplica al GLA nuevo.
A19: Ingreso anual por m² Perú (PEN) | C19: 792.93865 | D19: 832.95944 | E19: 869.39102 | F19: 896.70772 | G19: 921.72945 | H19: 945.04514 | I19: Exhibits v6, Forecast bloque D, Perú.
A20: CLP por PEN (promedio) | C20: 267.99722 | D20: 275.85211 | E20: 279.34382 | F20: 284.77376 | G20: 287.56566 | H20: 290.38493 | I20: Exhibits v6, Forecast bloque A.

Sheet Expansion
A1: Expansión continua post-pipeline — capex con 2 años de construcción y rampa de ingresos
A2: Cada cohorte abre GLA nuevo al ritmo histórico. El capex se gasta en los 2 años previos a la apertura y los ingresos parten en el año de apertura con la rampa 35% / 90% / 100%. Se apaga con Supuestos E.
A4: Año del período | C4: 2S26E | D4: 2027E | E4: 2028E | F4: 2029E | G4: 2030E | H4: 2031E
A5: Año (número) | C5: 2026 | D5: 2027 | E5: 2028 | F5: 2029 | G5: 2030 | H5: 2031
A6: Índice de costo (IPC Chile, 2026 = 1) | C6: =(1+Supuestos!$B$34)^(C5-2026) -> 1 | D6: =(1+Supuestos!$B$34)^(D5-2026) -> 1.03 | E6: =(1+Supuestos!$B$34)^(E5-2026) -> 1.0609 | F6: =(1+Supuestos!$B$34)^(F5-2026) -> 1.092727 | G6: =(1+Supuestos!$B$34)^(G5-2026) -> 1.1255088 | H6: =(1+Supuestos!$B$34)^(H5-2026) -> 1.1592741
A7: Costo por m² (MM CLP) | C7: =Supuestos!$B$71*Supuestos!$B$72/1000000*C6 -> 3.3181974 | D7: =Supuestos!$B$71*Supuestos!$B$72/1000000*D6 -> 3.4177433 | E7: =Supuestos!$B$71*Supuestos!$B$72/1000000*E6 -> 3.5202756 | F7: =Supuestos!$B$71*Supuestos!$B$72/1000000*F6 -> 3.6258839 | G7: =Supuestos!$B$71*Supuestos!$B$72/1000000*G6 -> 3.7346604 | H7: =Supuestos!$B$71*Supuestos!$B$72/1000000*H6 -> 3.8467002 | J7: Costo del pipeline (USD/m²) × USDCLP 2026, indexado a IPC (obras en UF).
A8: Ingreso por m² de la expansión (CLP, mix Chile/Perú) | C8: =Supuestos!$B$75*Forecast_Base!C18+(1-Supuestos!$B$75)*Forecast_Base!C19*Forecast_Base!C20 -> 298926.54 | D8: =Supuestos!$B$75*Forecast_Base!D18+(1-Supuestos!$B$75)*Forecast_Base!D19*Forecast_Base!D20 -> 317620.12 | E8: =Supuestos!$B$75*Forecast_Base!E18+(1-Supuestos!$B$75)*Forecast_Base!E19*Forecast_Base!E20 -> 333824.97 | F8: =Supuestos!$B$75*Forecast_Base!F18+(1-Supuestos!$B$75)*Forecast_Base!F19*Forecast_Base!F20 -> 349220.16 | G8: =Supuestos!$B$75*Forecast_Base!G18+(1-Supuestos!$B$75)*Forecast_Base!G19*Forecast_Base!G20 -> 363261.73 | H8: =Supuestos!$B$75*Forecast_Base!H18+(1-Supuestos!$B$75)*Forecast_Base!H19*Forecast_Base!H20 -> 376890.49
A9: Margen EBITDA de la expansión | C9: =Supuestos!$B$75*Supuestos!$B$76+(1-Supuestos!$B$75)*Supuestos!$B$77 -> 0.80655699 | D9: =Supuestos!$B$75*Supuestos!$B$76+(1-Supuestos!$B$75)*Supuestos!$B$77 -> 0.80655699 | E9: =Supuestos!$B$75*Supuestos!$B$76+(1-Supuestos!$B$75)*Supuestos!$B$77 -> 0.80655699 | F9: =Supuestos!$B$75*Supuestos!$B$76+(1-Supuestos!$B$75)*Supuestos!$B$77 -> 0.80655699 | G9: =Supuestos!$B$75*Supuestos!$B$76+(1-Supuestos!$B$75)*Supuestos!$B$77 -> 0.80655699 | H9: =Supuestos!$B$75*Supuestos!$B$76+(1-Supuestos!$B$75)*Supuestos!$B$77 -> 0.80655699
A11: A. m² que abre cada cohorte | B11: m²
A12: =Supuestos!$B$67+0 -> 2029 | B12: =Supuestos!$B$66*Supuestos!$B$62 -> 27075.333 | J12: Las cohortes que abren después de 2031 tienen su capex dentro del horizonte: sostienen el valor terminal.
A13: =Supuestos!$B$67+1 -> 2030 | B13: =Supuestos!$B$66*Supuestos!$B$62 -> 27075.333
A14: =Supuestos!$B$67+2 -> 2031 | B14: =Supuestos!$B$66*Supuestos!$B$62 -> 27075.333
A15: =Supuestos!$B$67+3 -> 2032 | B15: =Supuestos!$B$66*Supuestos!$B$62 -> 27075.333
A16: =Supuestos!$B$67+4 -> 2033 | B16: =Supuestos!$B$66*Supuestos!$B$62 -> 27075.333
A18: B. Capex por cohorte (MM CLP)
A19: =A12 -> 2029 | C19: =IF(C$5=$A12-2,Supuestos!$B$68,IF(C$5=$A12-1,1-Supuestos!$B$68,0))*$B12*C$7 -> 0 | D19: =IF(D$5=$A12-2,Supuestos!$B$68,IF(D$5=$A12-1,1-Supuestos!$B$68,0))*$B12*D$7 -> 46268.27 | E19: =IF(E$5=$A12-2,Supuestos!$B$68,IF(E$5=$A12-1,1-Supuestos!$B$68,0))*$B12*E$7 -> 47656.318 | F19: =IF(F$5=$A12-2,Supuestos!$B$68,IF(F$5=$A12-1,1-Supuestos!$B$68,0))*$B12*F$7 -> 0 | G19: =IF(G$5=$A12-2,Supuestos!$B$68,IF(G$5=$A12-1,1-Supuestos!$B$68,0))*$B12*G$7 -> 0 | H19: =IF(H$5=$A12-2,Supuestos!$B$68,IF(H$5=$A12-1,1-Supuestos!$B$68,0))*$B12*H$7 -> 0
A20: =A13 -> 2030 | C20: =IF(C$5=$A13-2,Supuestos!$B$68,IF(C$5=$A13-1,1-Supuestos!$B$68,0))*$B13*C$7 -> 0 | D20: =IF(D$5=$A13-2,Supuestos!$B$68,IF(D$5=$A13-1,1-Supuestos!$B$68,0))*$B13*D$7 -> 0 | E20: =IF(E$5=$A13-2,Supuestos!$B$68,IF(E$5=$A13-1,1-Supuestos!$B$68,0))*$B13*E$7 -> 47656.318 | F20: =IF(F$5=$A13-2,Supuestos!$B$68,IF(F$5=$A13-1,1-Supuestos!$B$68,0))*$B13*F$7 -> 49086.008 | G20: =IF(G$5=$A13-2,Supuestos!$B$68,IF(G$5=$A13-1,1-Supuestos!$B$68,0))*$B13*G$7 -> 0 | H20: =IF(H$5=$A13-2,Supuestos!$B$68,IF(H$5=$A13-1,1-Supuestos!$B$68,0))*$B13*H$7 -> 0
A21: =A14 -> 2031 | C21: =IF(C$5=$A14-2,Supuestos!$B$68,IF(C$5=$A14-1,1-Supuestos!$B$68,0))*$B14*C$7 -> 0 | D21: =IF(D$5=$A14-2,Supuestos!$B$68,IF(D$5=$A14-1,1-Supuestos!$B$68,0))*$B14*D$7 -> 0 | E21: =IF(E$5=$A14-2,Supuestos!$B$68,IF(E$5=$A14-1,1-Supuestos!$B$68,0))*$B14*E$7 -> 0 | F21: =IF(F$5=$A14-2,Supuestos!$B$68,IF(F$5=$A14-1,1-Supuestos!$B$68,0))*$B14*F$7 -> 49086.008 | G21: =IF(G$5=$A14-2,Supuestos!$B$68,IF(G$5=$A14-1,1-Supuestos!$B$68,0))*$B14*G$7 -> 50558.588 | H21: =IF(H$5=$A14-2,Supuestos!$B$68,IF(H$5=$A14-1,1-Supuestos!$B$68,0))*$B14*H$7 -> 0
A22: =A15 -> 2032 | C22: =IF(C$5=$A15-2,Supuestos!$B$68,IF(C$5=$A15-1,1-Supuestos!$B$68,0))*$B15*C$7 -> 0 | D22: =IF(D$5=$A15-2,Supuestos!$B$68,IF(D$5=$A15-1,1-Supuestos!$B$68,0))*$B15*D$7 -> 0 | E22: =IF(E$5=$A15-2,Supuestos!$B$68,IF(E$5=$A15-1,1-Supuestos!$B$68,0))*$B15*E$7 -> 0 | F22: =IF(F$5=$A15-2,Supuestos!$B$68,IF(F$5=$A15-1,1-Supuestos!$B$68,0))*$B15*F$7 -> 0 | G22: =IF(G$5=$A15-2,Supuestos!$B$68,IF(G$5=$A15-1,1-Supuestos!$B$68,0))*$B15*G$7 -> 50558.588 | H22: =IF(H$5=$A15-2,Supuestos!$B$68,IF(H$5=$A15-1,1-Supuestos!$B$68,0))*$B15*H$7 -> 52075.346
A23: =A16 -> 2033 | C23: =IF(C$5=$A16-2,Supuestos!$B$68,IF(C$5=$A16-1,1-Supuestos!$B$68,0))*$B16*C$7 -> 0 | D23: =IF(D$5=$A16-2,Supuestos!$B$68,IF(D$5=$A16-1,1-Supuestos!$B$68,0))*$B16*D$7 -> 0 | E23: =IF(E$5=$A16-2,Supuestos!$B$68,IF(E$5=$A16-1,1-Supuestos!$B$68,0))*$B16*E$7 -> 0 | F23: =IF(F$5=$A16-2,Supuestos!$B$68,IF(F$5=$A16-1,1-Supuestos!$B$68,0))*$B16*F$7 -> 0 | G23: =IF(G$5=$A16-2,Supuestos!$B$68,IF(G$5=$A16-1,1-Supuestos!$B$68,0))*$B16*G$7 -> 0 | H23: =IF(H$5=$A16-2,Supuestos!$B$68,IF(H$5=$A16-1,1-Supuestos!$B$68,0))*$B16*H$7 -> 52075.346
A24: Total | C24: =SUM(C19:C23) -> 0 | D24: =SUM(D19:D23) -> 46268.27 | E24: =SUM(E19:E23) -> 95312.636 | F24: =SUM(F19:F23) -> 98172.015 | G24: =SUM(G19:G23) -> 101117.18 | H24: =SUM(H19:H23) -> 104150.69
A26: C. Ingresos por cohorte (MM CLP)
A27: =A12 -> 2029 | C27: =IF(C$5>=$A12,$B12*C$8/1000000*IF(C$5-$A12=0,Supuestos!$B$78,IF(C$5-$A12=1,Supuestos!$B$79,Supuestos!$B$80))*$C$39,0) -> 0 | D27: =IF(D$5>=$A12,$B12*D$8/1000000*IF(D$5-$A12=0,Supuestos!$B$78,IF(D$5-$A12=1,Supuestos!$B$79,Supuestos!$B$80))*$C$39,0) -> 0 | E27: =IF(E$5>=$A12,$B12*E$8/1000000*IF(E$5-$A12=0,Supuestos!$B$78,IF(E$5-$A12=1,Supuestos!$B$79,Supuestos!$B$80))*$C$39,0) -> 0 | F27: =IF(F$5>=$A12,$B12*F$8/1000000*IF(F$5-$A12=0,Supuestos!$B$78,IF(F$5-$A12=1,Supuestos!$B$79,Supuestos!$B$80))*$C$39,0) -> 3309.3383 | G27: =IF(G$5>=$A12,$B12*G$8/1000000*IF(G$5-$A12=0,Supuestos!$B$78,IF(G$5-$A12=1,Supuestos!$B$79,Supuestos!$B$80))*$C$39,0) -> 8851.8891 | H27: =IF(H$5>=$A12,$B12*H$8/1000000*IF(H$5-$A12=0,Supuestos!$B$78,IF(H$5-$A12=1,Supuestos!$B$79,Supuestos!$B$80))*$C$39,0) -> 10204.436
A28: =A13 -> 2030 | C28: =IF(C$5>=$A13,$B13*C$8/1000000*IF(C$5-$A13=0,Supuestos!$B$78,IF(C$5-$A13=1,Supuestos!$B$79,Supuestos!$B$80))*$C$39,0) -> 0 | D28: =IF(D$5>=$A13,$B13*D$8/1000000*IF(D$5-$A13=0,Supuestos!$B$78,IF(D$5-$A13=1,Supuestos!$B$79,Supuestos!$B$80))*$C$39,0) -> 0 | E28: =IF(E$5>=$A13,$B13*E$8/1000000*IF(E$5-$A13=0,Supuestos!$B$78,IF(E$5-$A13=1,Supuestos!$B$79,Supuestos!$B$80))*$C$39,0) -> 0 | F28: =IF(F$5>=$A13,$B13*F$8/1000000*IF(F$5-$A13=0,Supuestos!$B$78,IF(F$5-$A13=1,Supuestos!$B$79,Supuestos!$B$80))*$C$39,0) -> 0 | G28: =IF(G$5>=$A13,$B13*G$8/1000000*IF(G$5-$A13=0,Supuestos!$B$78,IF(G$5-$A13=1,Supuestos!$B$79,Supuestos!$B$80))*$C$39,0) -> 3442.4013 | H28: =IF(H$5>=$A13,$B13*H$8/1000000*IF(H$5-$A13=0,Supuestos!$B$78,IF(H$5-$A13=1,Supuestos!$B$79,Supuestos!$B$80))*$C$39,0) -> 9183.9922
A29: =A14 -> 2031 | C29: =IF(C$5>=$A14,$B14*C$8/1000000*IF(C$5-$A14=0,Supuestos!$B$78,IF(C$5-$A14=1,Supuestos!$B$79,Supuestos!$B$80))*$C$39,0) -> 0 | D29: =IF(D$5>=$A14,$B14*D$8/1000000*IF(D$5-$A14=0,Supuestos!$B$78,IF(D$5-$A14=1,Supuestos!$B$79,Supuestos!$B$80))*$C$39,0) -> 0 | E29: =IF(E$5>=$A14,$B14*E$8/1000000*IF(E$5-$A14=0,Supuestos!$B$78,IF(E$5-$A14=1,Supuestos!$B$79,Supuestos!$B$80))*$C$39,0) -> 0 | F29: =IF(F$5>=$A14,$B14*F$8/1000000*IF(F$5-$A14=0,Supuestos!$B$78,IF(F$5-$A14=1,Supuestos!$B$79,Supuestos!$B$80))*$C$39,0) -> 0 | G29: =IF(G$5>=$A14,$B14*G$8/1000000*IF(G$5-$A14=0,Supuestos!$B$78,IF(G$5-$A14=1,Supuestos!$B$79,Supuestos!$B$80))*$C$39,0) -> 0 | H29: =IF(H$5>=$A14,$B14*H$8/1000000*IF(H$5-$A14=0,Supuestos!$B$78,IF(H$5-$A14=1,Supuestos!$B$79,Supuestos!$B$80))*$C$39,0) -> 3571.5525
A30: =A15 -> 2032 | C30: =IF(C$5>=$A15,$B15*C$8/1000000*IF(C$5-$A15=0,Supuestos!$B$78,IF(C$5-$A15=1,Supuestos!$B$79,Supuestos!$B$80))*$C$39,0) -> 0 | D30: =IF(D$5>=$A15,$B15*D$8/1000000*IF(D$5-$A15=0,Supuestos!$B$78,IF(D$5-$A15=1,Supuestos!$B$79,Supuestos!$B$80))*$C$39,0) -> 0 | E30: =IF(E$5>=$A15,$B15*E$8/1000000*IF(E$5-$A15=0,Supuestos!$B$78,IF(E$5-$A15=1,Supuestos!$B$79,Supuestos!$B$80))*$C$39,0) -> 0 | F30: =IF(F$5>=$A15,$B15*F$8/1000000*IF(F$5-$A15=0,Supuestos!$B$78,IF(F$5-$A15=1,Supuestos!$B$79,Supuestos!$B$80))*$C$39,0) -> 0 | G30: =IF(G$5>=$A15,$B15*G$8/1000000*IF(G$5-$A15=0,Supuestos!$B$78,IF(G$5-$A15=1,Supuestos!$B$79,Supuestos!$B$80))*$C$39,0) -> 0 | H30: =IF(H$5>=$A15,$B15*H$8/1000000*IF(H$5-$A15=0,Supuestos!$B$78,IF(H$5-$A15=1,Supuestos!$B$79,Supuestos!$B$80))*$C$39,0) -> 0
A31: =A16 -> 2033 | C31: =IF(C$5>=$A16,$B16*C$8/1000000*IF(C$5-$A16=0,Supuestos!$B$78,IF(C$5-$A16=1,Supuestos!$B$79,Supuestos!$B$80))*$C$39,0) -> 0 | D31: =IF(D$5>=$A16,$B16*D$8/1000000*IF(D$5-$A16=0,Supuestos!$B$78,IF(D$5-$A16=1,Supuestos!$B$79,Supuestos!$B$80))*$C$39,0) -> 0 | E31: =IF(E$5>=$A16,$B16*E$8/1000000*IF(E$5-$A16=0,Supuestos!$B$78,IF(E$5-$A16=1,Supuestos!$B$79,Supuestos!$B$80))*$C$39,0) -> 0 | F31: =IF(F$5>=$A16,$B16*F$8/1000000*IF(F$5-$A16=0,Supuestos!$B$78,IF(F$5-$A16=1,Supuestos!$B$79,Supuestos!$B$80))*$C$39,0) -> 0 | G31: =IF(G$5>=$A16,$B16*G$8/1000000*IF(G$5-$A16=0,Supuestos!$B$78,IF(G$5-$A16=1,Supuestos!$B$79,Supuestos!$B$80))*$C$39,0) -> 0 | H31: =IF(H$5>=$A16,$B16*H$8/1000000*IF(H$5-$A16=0,Supuestos!$B$78,IF(H$5-$A16=1,Supuestos!$B$79,Supuestos!$B$80))*$C$39,0) -> 0
A32: Total | C32: =SUM(C27:C31) -> 0 | D32: =SUM(D27:D31) -> 0 | E32: =SUM(E27:E31) -> 0 | F32: =SUM(F27:F31) -> 3309.3383 | G32: =SUM(G27:G31) -> 12294.29 | H32: =SUM(H27:H31) -> 22959.98
A33: EBITDA de la expansión | C33: =C32*C9 -> 0 | D33: =D32*D9 -> 0 | E33: =E32*E9 -> 0 | F33: =F32*F9 -> 2669.17 | G33: =G32*G9 -> 9916.0459 | H33: =H32*H9 -> 18518.533
A35: D. Retorno de la expansión (alimenta el valor terminal)
A36: Yield on cost derivado (EBITDA maduro por m² / costo por m², 2026) | C36: =C8*C9/(C7*1000000) -> 0.072660321 | J36: Misma productividad que el forecast asume para el pipeline actual. El ingreso se indexa a inflación: es un yield real.
A37: Yield on cost usado | C37: =IF(Supuestos!$B$81="",C36,Supuestos!$B$81) -> 0.072660321
A38: RONIC real después de impuestos = yield × (1 − t) | C38: =C37*(1-Supuestos!$B$59) -> 0.053042034 | J38: Comparar con la WACC real (hoja WACC): si el RONIC es menor, crecer destruye valor.
A39: Ajuste de productividad de la expansión = yield usado / derivado | C39: =C37/C36 -> 1 | J39: Multiplica los ingresos de la expansión.

Sheet Capital_Trabajo
A1: Capital de trabajo — saldos de los EEFF y supuesto del modelo
A4: A. Saldos de balance operativos (MM CLP; EEFF consolidados Plaza S.A. y Filiales)
A5: Cuenta | C5: dic-23 | D5: dic-24 | E5: dic-25 | F5: mar-26 | G5: Fuente
A6: (+) Deudores comerciales y otras cuentas por cobrar corrientes | C6: 109044.23 | D6: 111058.3 | E6: 122369.81 | F6: 96333.76 | G6: dic-23: EEFF mar-24, p. 3 · dic-24: EEFF jun-25, p. 3 · dic-25 y mar-26: EEFF mar-26, p. 3 (M$ / 1.000).
A7: (+) Cuentas por cobrar a entidades relacionadas corrientes | C7: 45909.292 | D7: 19565.384 | E7: 13695.594 | F7: 9043.354 | G7: Arriendos por cobrar a tiendas del grupo controlador: operativo.
A8: Cuentas por pagar comerciales y otras cuentas por pagar (total) | C8: 115756.87 | D8: 95843.191 | E8: 122277.68 | F8: 169311.26 | G8: Incluye la provisión del dividendo mínimo (Nota 2.25), que es financiamiento y se excluye.
A9: menos: dividendo mínimo provisionado estimado (30% × utilidad distribuible) | C9: 59262 | D9: 71491.5 | E9: 110793.6 | G9: Nota 2.25. Supone sin dividendos provisorios.
A10: (−) Cuentas por pagar comerciales operativas (sin dividendos) | C10: =C8-C9 -> 56494.871 | D10: =D8-D9 -> 24351.691 | E10: =E8-E9 -> 11484.079
A11: (−) Cuentas por pagar a entidades relacionadas corrientes | C11: 34486.698 | D11: 2641.613 | E11: 2296.174 | F11: 2306.468
A12: (−) Otros pasivos no financieros corrientes | C12: 10367.061 | D12: 23176.757 | E12: 20246.646 | F12: 14591.09 | G12: Principalmente arriendos cobrados por anticipado y garantías: operativo.
A13: Ingresos del año | C13: 419904 | D13: 494605 | E13: 653911 | G13: Exhibits v6, Inputs.
A14: Excluidos: caja, deuda financiera y activos/pasivos por impuestos (los impuestos ya están en caja en el NOPAT).
A16: B. Capital de trabajo neto operativo
A17: Capital de trabajo neto operativo | C17: =C6+C7-C10-C11-C12 -> 53604.896 | D17: =D6+D7-D10-D11-D12 -> 80453.622 | E17: =E6+E7-E10-E11-E12 -> 102038.5
A18: Capital de trabajo neto / ingresos | C18: =C17/C13 -> 0.12765988 | D18: =D17/D13 -> 0.16266237 | E18: =E17/E13 -> 0.15604341
A19: Referencia: Δ capital de trabajo neto / Δ ingresos (dic-23 → dic-25) | E19: =(E17-C17)/(E13-C13) -> 0.20697503 | G19: Distorsionado: dic-24 ya consolida Perú pero los ingresos 2024 solo traen un mes.
A20: Supuesto del modelo: capital de trabajo neto / ingresos constante al nivel de dic-25 | F20: =E18 -> 0.15604341 | G20: Inversión anual = este % × Δ ingresos. Va a Supuestos (sección F).
A22: C. Lectura
A23: 1. Capital de trabajo neto operativo = deudores + cuentas por cobrar relacionadas − cuentas por pagar comerciales (sin dividendos) − cuentas por pagar relacionadas − otros pasivos no financieros.
A24: 2. La provisión del dividendo mínimo se resta de las cuentas por pagar porque es una obligación con accionistas, no de la operación.
A25: 3. Limitación: las cuentas por pagar comerciales también incluyen proveedores de obras (capex). Sin el desglose de la Nota 14/15 no se pueden separar.
A26: 4. Hay estacionalidad (mar-26: deudores bajan por recaudación, cuentas por pagar suben por el dividendo): se compara cierre contra cierre.
A27: 5. Se usa el nivel de dic-25 porque es el primer cierre con Perú completo tanto en balance como en ingresos.
A29: D. Referencia: brecha EBITDA − flujo operativo (MM CLP)
C30: FY2024 | D30: FY2025 | E30: 1S26
A31: EBITDA | C31: 380637 | D31: 526228 | E31: 270574
A32: Flujo operativo (EEFF) | C32: 300822 | D32: 441135 | E32: 258193
A33: Brecha = impuestos pagados + capital de trabajo + otros | C33: =C31-C32 -> 79815 | D33: =D31-D32 -> 85093 | E33: =E31-E32 -> 12381 | G33: Exhibits v6 (Inputs, E4_Cash). Mezcla impuestos y capital de trabajo: solo referencial.

Sheet DCF
A1: DCF de FCFF — Mallplaza · CLP nominales · valorización 30-06-2026 · WACC por período
A2: Flujos 2S26E–2031E con la expansión continua; valor terminal con reinversión explícita (solo el crecimiento real exige capex). Convención de mitad de período. Cada período se descuenta con su propia WACC (hoja WACC).
A4: MM CLP | C4: 2S26E | D4: 2027E | E4: 2028E | F4: 2029E | G4: 2030E | H4: 2031E | I4: Terminal (2032E)
A5: Ingresos base | C5: =Forecast_Base!C6 -> 364468.94 | D5: =Forecast_Base!D6 -> 767179.42 | E5: =Forecast_Base!E6 -> 826661.82 | F5: =Forecast_Base!F6 -> 883482.45 | G5: =Forecast_Base!G6 -> 923321.86 | H5: =Forecast_Base!H6 -> 959373.85
A6: Ingresos expansión | C6: =Expansion!C32 -> 0 | D6: =Expansion!D32 -> 0 | E6: =Expansion!E32 -> 0 | F6: =Expansion!F32 -> 3309.3383 | G6: =Expansion!G32 -> 12294.29 | H6: =Expansion!H32 -> 22959.98
A7: Ingresos totales | C7: =C5+C6 -> 364468.94 | D7: =D5+D6 -> 767179.42 | E7: =E5+E6 -> 826661.82 | F7: =F5+F6 -> 886791.79 | G7: =G5+G6 -> 935616.15 | H7: =H5+H6 -> 982333.83 | I7: =C34*(1+Supuestos!$B$88) -> 1030197.3
A8: Crecimiento ingresos (año calendario) | C8: =(Forecast_Base!C5+C6)/Supuestos!$B$56-1 -> 0.07659748 | D8: =D7/Forecast_Base!C5-1 -> 0.089745147 | E8: =E7/D7-1 -> 0.077533882 | F8: =F7/E7-1 -> 0.072738292 | G8: =G7/F7-1 -> 0.055057298 | H8: =H7/G7-1 -> 0.049932533
A9: EBITDA base | C9: =Forecast_Base!C8 -> 290741.41 | D9: =Forecast_Base!D8 -> 611360.36 | E9: =Forecast_Base!E8 -> 659160.32 | F9: =Forecast_Base!F8 -> 704684.52 | G9: =Forecast_Base!G8 -> 736419.6 | H9: =Forecast_Base!H8 -> 765088.08
A10: EBITDA expansión | C10: =Expansion!C33 -> 0 | D10: =Expansion!D33 -> 0 | E10: =Expansion!E33 -> 0 | F10: =Expansion!F33 -> 2669.17 | G10: =Expansion!G33 -> 9916.0459 | H10: =Expansion!H33 -> 18518.533
A11: EBITDA total | C11: =C9+C10 -> 290741.41 | D11: =D9+D10 -> 611360.36 | E11: =E9+E10 -> 659160.32 | F11: =F9+F10 -> 707353.69 | G11: =G9+G10 -> 746335.64 | H11: =H9+H10 -> 783606.62 | I11: =C35*(1+Supuestos!$B$88) -> 821950.22
A12: Margen EBITDA | C12: =C11/C7 -> 0.79771244 | D12: =D11/D7 -> 0.79689358 | E12: =E11/E7 -> 0.79737603 | F12: =F11/F7 -> 0.79765475 | G12: =G11/G7 -> 0.79769427 | H12: =H11/H7 -> 0.7976989 | I12: =I11/I7 -> 0.79785705
A13: (−) D&A | C13: =Supuestos!$B$57*C7 -> 2564.5568 | D13: =Supuestos!$B$57*D7 -> 5398.1972 | E13: =Supuestos!$B$57*E7 -> 5816.7404 | F13: =Supuestos!$B$57*F7 -> 6239.8402 | G13: =Supuestos!$B$57*G7 -> 6583.3889 | H13: =Supuestos!$B$57*H7 -> 6912.1142 | I13: =Supuestos!$B$57*I7 -> 7248.902
A14: EBIT | C14: =C11-C13 -> 288176.85 | D14: =D11-D13 -> 605962.16 | E14: =E11-E13 -> 653343.58 | F14: =F11-F13 -> 701113.85 | G14: =G11-G13 -> 739752.25 | H14: =H11-H13 -> 776694.5 | I14: =I11-I13 -> 814701.31
A15: Tasa de impuesto operacional | C15: =Forecast_Base!C11 -> 0.168 | D15: =Forecast_Base!D11 -> 0.19 | E15: =Forecast_Base!E11 -> 0.215 | F15: =Forecast_Base!F11 -> 0.24 | G15: =Forecast_Base!G11 -> 0.27 | H15: =Forecast_Base!H11 -> 0.27 | I15: =Supuestos!$B$59 -> 0.27
A16: (−) Impuestos operacionales | C16: =-C14*C15 -> -48413.711 | D16: =-D14*D15 -> -115132.81 | E16: =-E14*E15 -> -140468.87 | F16: =-F14*F15 -> -168267.32 | G16: =-G14*G15 -> -199733.11 | H16: =-H14*H15 -> -209707.52 | I16: =-I14*I15 -> -219969.35
A17: NOPAT | C17: =C14+C16 -> 239763.14 | D17: =D14+D16 -> 490829.35 | E17: =E14+E16 -> 512874.71 | F17: =F14+F16 -> 532846.52 | G17: =G14+G16 -> 540019.14 | H17: =H14+H16 -> 566986.99 | I17: =I14+I16 -> 594731.96
A18: (+) D&A | C18: =C13 -> 2564.5568 | D18: =D13 -> 5398.1972 | E18: =E13 -> 5816.7404 | F18: =F13 -> 6239.8402 | G18: =G13 -> 6583.3889 | H18: =H13 -> 6912.1142 | I18: =I13 -> 7248.902
A19: (−) Capex base (pipeline + mantención) | C19: =-Forecast_Base!C16 -> -149905.97 | D19: =-Forecast_Base!D16 -> -290119.34 | E19: =-Forecast_Base!E16 -> -200864.13 | F19: =-Forecast_Base!F16 -> -48591.535 | G19: =-Forecast_Base!G16 -> -50782.702 | H19: =-Forecast_Base!H16 -> -52765.562 | I19: =-Supuestos!$B$58*I7 -> -56660.854 | J19: Terminal: mantención 5,5% de ingresos.
A20: (−) Capex expansión / reinversión terminal | C20: =-Expansion!C24 -> 0 | D20: =-Expansion!D24 -> -46268.27 | E20: =-Expansion!E24 -> -95312.636 | F20: =-Expansion!F24 -> -98172.015 | G20: =-Expansion!G24 -> -101117.18 | H20: =-Expansion!H24 -> -104150.69 | I20: =-Supuestos!$B$89/Expansion!$C$38*I17 -> 0 | J20: Terminal: reinversión = g real / RONIC × NOPAT (value driver).
A21: (−) Inversión en capital de trabajo | C21: =-Supuestos!$B$84*Supuestos!$B$85*(Forecast_Base!C5-Supuestos!$B$56)/2 -> -3907.946 | D21: =-Supuestos!$B$84*Supuestos!$B$85*(D7-Forecast_Base!C5) -> -9858.8987 | E21: =-Supuestos!$B$84*Supuestos!$B$85*(E7-D7) -> -9281.8362 | F21: =-Supuestos!$B$84*Supuestos!$B$85*(F7-E7) -> -9382.8853 | G21: =-Supuestos!$B$84*Supuestos!$B$85*(G7-F7) -> -7618.7195 | H21: =-Supuestos!$B$84*Supuestos!$B$85*(H7-G7) -> -7289.9867 | I21: =-Supuestos!$B$84*Supuestos!$B$85*(I7-C34) -> -4682.1992 | J21: % del Δ ingresos (Supuestos F). 2S26E: medio año.
A22: FCFF | C22: =C17+C18+C19+C20+C21 -> 88513.776 | D22: =D17+D18+D19+D20+D21 -> 149981.04 | E22: =E17+E18+E19+E20+E21 -> 213232.85 | F22: =F17+F18+F19+F20+F21 -> 382939.93 | G22: =G17+G18+G19+G20+G21 -> 387083.94 | H22: =H17+H18+H19+H20+H21 -> 409692.86 | I22: =I17+I18+I19+I20+I21 -> 540637.81
A24: Descuento: WACC por período
A25: WACC nominal del período (hoja WACC) | C25: =WACC!C43 -> 0.10536861 | D25: =WACC!D43 -> 0.10509036 | E25: =WACC!E43 -> 0.10482887 | F25: =WACC!F43 -> 0.10458351 | G25: =WACC!G43 -> 0.1043537 | H25: =WACC!H43 -> 0.10413887 | I25: =WACC!I43 -> 0.10413887
A26: Fracción de año del período | C26: 0.5 | D26: 1 | E26: 1 | F26: 1 | G26: 1 | H26: 1
A27: Factor de descuento al cierre del período | C27: =(1+C25)^-C26 -> 0.95114436 | D27: =C27*(1+D25)^-D26 -> 0.86069374 | E27: =D27*(1+E25)^-E26 -> 0.77902902 | F27: =E27*(1+F25)^-F26 -> 0.70526946 | G27: =F27*(1+G25)^-G26 -> 0.63862643 | H27: =G27*(1+H25)^-H26 -> 0.57839322
A28: Factor de descuento a mitad del período | C28: =(1+C25)^-(C26/2) -> 0.9752663 | D28: =C27*(1+D25)^-(D26/2) -> 0.90478948 | E28: =D27*(1+E25)^-(E26/2) -> 0.81884394 | F28: =E27*(1+F25)^-(F26/2) -> 0.74123233 | G28: =F27*(1+G25)^-(G26/2) -> 0.67112124 | H28: =G27*(1+H25)^-(H26/2) -> 0.6077641 | J28: 2S26E a 0,25 años; luego la mitad de cada año desde el 30-06-2026.
A29: Valor presente del FCFF | C29: =C22*C28 -> 86324.503 | D29: =D22*D28 -> 135701.27 | E29: =E22*E28 -> 174604.43 | F29: =F22*F28 -> 283847.46 | G29: =G22*G28 -> 259780.25 | H29: =H22*H28 -> 248996.61
A31: Normalización 2031: base + expansión financiada (cohortes cuyo capex cae completo en el horizonte) a madurez
A32: Último año de apertura con capex completo dentro del horizonte | C32: =Expansion!H5+1 -> 2032 | J32: El capex de esas cohortes ya está en el FCFF explícito, pero sus ingresos maduran después de 2031: el año terminal los cuenta al 100%. La cohorte siguiente (solo parte del capex dentro) queda en la reinversión terminal.
A33: m² maduros que se suman al año terminal | C33: =SUMIF(Expansion!$A$12:$A$16,"<="&C32,Expansion!$B$12:$B$16) -> 108301.33
A34: Ingresos 2031 normalizados | C34: =Forecast_Base!H5+C33*Expansion!H8/1000000*Expansion!C39 -> 1000191.6
A35: EBITDA 2031 normalizado | C35: =Forecast_Base!H7+(C34-Forecast_Base!H5)*Expansion!H9 -> 798009.92
A37: Valor de la empresa → valor por acción
A38: WACC terminal (estructura objetivo) | C38: =I25 -> 0.10413887
A39: Crecimiento terminal nominal (g) | C39: =Supuestos!$B$88 -> 0.03
A40: Tasa de reinversión terminal (g real / RONIC) | C40: =Supuestos!$B$89/Expansion!$C$38 -> 0
A41: Valor terminal al 31-12-2031 = FCFF 2032E / (WACC terminal − g) | C41: =I22/(C38-C39) -> 7292231.8
A42: Valor presente del valor terminal | C42: =C41*H27 -> 4217777.4
A43: Suma VP del FCFF explícito | C43: =SUM(C29:H29) -> 1189254.5
A44: Enterprise value | C44: =C43+C42 -> 5407031.9
A45: (−) Deuda financiera neta 30-06-2026 | C45: =-Supuestos!$B$10 -> -1285740
A46: (−) Minoritarios (libro) | C46: =-Supuestos!$B$11 -> -50841
A47: Valor del patrimonio | C47: =C44+C45+C46 -> 4070450.9
A48: Acciones (MM) | C48: =Supuestos!$B$9 -> 2190
A49: Valor por acción DCF (CLP) | C49: =C47/C48 -> 1858.6534 | D49: Las distribuciones adicionales de la hoja Deuda no se restan: el patrimonio de hoy es EV − DFN de hoy.
A50: Precio 30-09-2026 (CLP) | C50: =Supuestos!$B$8 -> 3555
A51: Upside / (downside) | C51: =C49/C50-1 -> -0.47717204
A53: Chequeos
A54: VP del valor terminal / EV | C54: =C42/C44 -> 0.7800541 | D54: DCF anterior del equipo: 72%.
A55: EV / EBITDA LTM implícito | C55: =C44/Supuestos!$B$13 -> 9.9223429 | D55: Comparar con la hoja Comparables.
A56: Cap rate implícito sobre el EV (EBITDA LTM / EV) | C56: =Supuestos!$B$13/C44 -> 0.10078265 | D56: Mercado ~6,0%; pares Chile ~6,4%; libro (EBITDA LTM / PI) 7,5%; Gran Plaza 9,4%.
A57: Cap rate implícito del valor terminal (EBITDA 2032E / VT) | C57: =I11/C41 -> 0.11271586
A58: WACC real terminal | C58: =WACC!I44 -> 0.071979483 | D58: Nota 11 Chile jun-26: 5,55% real.
A59: RONIC real de la expansión | C59: =Expansion!$C$38 -> 0.053042034 | D59: Si es menor que la WACC real, la expansión resta valor.
A60: DFN / EBITDA al cierre de 2031 (hoja Deuda) | C60: =Deuda!H22 -> 3.5 | D60: Debe igualar el objetivo de Supuestos C.
A61: Valor por acción DCF VF (WACC constante 10,37%) | C61: =Supuestos!$B$108 -> 1882.6524
A62: Diferencia v2 vs VF (CLP) | C62: =C49-C61 -> -23.999011
A63: Valor por acción APV (hoja APV) | C63: =APV!C21 -> 1894.9907
A64: Diferencia DCF vs APV (% del APV) | C64: =C49/C63-1 -> -0.019175453 | D64: Chequeo de consistencia: deben quedar cerca.

Sheet Deuda
A1: Deuda — trayectoria desde la estructura actual hasta el objetivo de largo plazo
A2: DFN(t) = DFN(t−1) − FCFF + costo financiero y reajuste UF (después de impuestos) + dividendos ordinarios + distribución adicional. La distribución adicional (recompra o dividendo extra) cierra la brecha con el DFN/EBITDA objetivo. No entra en el EV (FCFF desapalancado): define la estructura de capital de la WACC.
A4: MM CLP | C4: 2S26E | D4: 2027E | E4: 2028E | F4: 2029E | G4: 2030E | H4: 2031E
A5: Años desde 30-06-2026 al cierre del período | C5: =DCF!C26 -> 0.5 | D5: =C5+DCF!D26 -> 1.5 | E5: =D5+DCF!E26 -> 2.5 | F5: =E5+DCF!F26 -> 3.5 | G5: =F5+DCF!G26 -> 4.5 | H5: =G5+DCF!H26 -> 5.5
A6: EBITDA año calendario (para el ratio) | C6: =Forecast_Base!C7+DCF!C10 -> 561315.41 | D6: =DCF!D11 -> 611360.36 | E6: =DCF!E11 -> 659160.32 | F6: =DCF!F11 -> 707353.69 | G6: =DCF!G11 -> 746335.64 | H6: =DCF!H11 -> 783606.62 | J6: 2S26E: EBITDA 2026E año completo (LTM al cierre).
A7: DFN de apertura | C7: =Supuestos!$B$10 -> 1285740 | D7: =C21 -> 1382589.9 | E7: =D21 -> 1632637.8 | F7: =E21 -> 1896981 | G7: =F21 -> 2182362.9 | H7: =G21 -> 2457403.4
A8: DFN / EBITDA de apertura | C8: =Supuestos!$B$41 -> 2.3594374 | D8: =C22 -> 2.4631249 | E8: =D22 -> 2.6704999 | F8: =E22 -> 2.8778749 | G8: =F22 -> 3.08525 | H8: =G22 -> 3.292625
A9: Costo financiero neto / DFN (con spread por apalancamiento) | C9: =Supuestos!$B$46+Supuestos!$B$40*Supuestos!$B$45*MAX(0,C8-Supuestos!$B$41) -> 0.0308 | D9: =Supuestos!$B$46+Supuestos!$B$40*Supuestos!$B$45*MAX(0,D8-Supuestos!$B$41) -> 0.031059219 | E9: =Supuestos!$B$46+Supuestos!$B$40*Supuestos!$B$45*MAX(0,E8-Supuestos!$B$41) -> 0.031577656 | F9: =Supuestos!$B$46+Supuestos!$B$40*Supuestos!$B$45*MAX(0,F8-Supuestos!$B$41) -> 0.032096094 | G9: =Supuestos!$B$46+Supuestos!$B$40*Supuestos!$B$45*MAX(0,G8-Supuestos!$B$41) -> 0.032614531 | H9: =Supuestos!$B$46+Supuestos!$B$40*Supuestos!$B$45*MAX(0,H8-Supuestos!$B$41) -> 0.033132969 | J9: 3,08% inicial + spread por cada vuelta sobre el nivel inicial.
A10: (−) FCFF | C10: =-DCF!C22 -> -88513.776 | D10: =-DCF!D22 -> -149981.04 | E10: =-DCF!E22 -> -213232.85 | F10: =-DCF!F22 -> -382939.93 | G10: =-DCF!G22 -> -387083.94 | H10: =-DCF!H22 -> -409692.86
A11: Costo financiero neto antes de impuestos | C11: =C7*C9*DCF!C26 -> 19800.396 | D11: =D7*D9*DCF!D26 -> 42942.163 | E11: =E7*E9*DCF!E26 -> 51554.875 | F11: =F7*F9*DCF!F26 -> 60885.679 | G11: =G7*G9*DCF!G26 -> 71176.744 | H11: =H7*H9*DCF!H26 -> 81421.07
A12: (+) Costo financiero neto después de impuestos | C12: =C11*(1-DCF!C15) -> 16473.929 | D12: =D11*(1-DCF!D15) -> 34783.152 | E12: =E11*(1-DCF!E15) -> 40470.577 | F12: =F11*(1-DCF!F15) -> 46273.116 | G12: =G11*(1-DCF!G15) -> 51959.023 | H12: =H11*(1-DCF!H15) -> 59437.381
A13: Reajuste UF de la deuda antes de impuestos | C13: =C7*Supuestos!$B$47*Supuestos!$B$34*DCF!C26 -> 15236.019 | D13: =D7*Supuestos!$B$47*Supuestos!$B$34*DCF!D26 -> 32767.382 | E13: =E7*Supuestos!$B$47*Supuestos!$B$34*DCF!E26 -> 38693.515 | F13: =F7*Supuestos!$B$47*Supuestos!$B$34*DCF!F26 -> 44958.449 | G13: =G7*Supuestos!$B$47*Supuestos!$B$34*DCF!G26 -> 51722.001 | H13: =H7*Supuestos!$B$47*Supuestos!$B$34*DCF!H26 -> 58240.46
A14: (+) Reajuste UF después de impuestos | C14: =C13*(1-DCF!C15) -> 12676.368 | D14: =D13*(1-DCF!D15) -> 26541.579 | E14: =E13*(1-DCF!E15) -> 30374.41 | F14: =F13*(1-DCF!F15) -> 34168.421 | G14: =G13*(1-DCF!G15) -> 37757.061 | H14: =H13*(1-DCF!H15) -> 42515.536 | J14: v2: el reajuste UF es gasto financiero deducible (el VF lo sumaba sin escudo). Consistente con Kd nominal × (1 − t) en la WACC.
A15: Utilidad distribuible proxy (FFO − reajuste UF) | C15: =Supuestos!$B$51 -> 380038.82 | D15: =D6-DCF!D15*(D6-D11)-D11-D13 -> 427651.36 | E15: =E6-DCF!E15*(E6-E11)-E11-E13 -> 438276.76 | F15: =F6-DCF!F15*(F6-F11)-F11-F13 -> 446357.24 | G15: =G6-DCF!G15*(G6-G11)-G11-G13 -> 441143.99 | H15: =H6-DCF!H15*(H6-H11)-H11-H13 -> 454354.99 | J15: 2S26E: distribuible 2026E de Exhibits v6. Proxy sin minoritarios.
A16: (+) Dividendos ordinarios | C16: =Supuestos!$B$49-Supuestos!$B$50 -> 60107.8 | D16: =Supuestos!$B$48*C15 -> 152015.53 | E16: =Supuestos!$B$48*D15 -> 171060.54 | F16: =Supuestos!$B$48*E15 -> 175310.7 | G16: =Supuestos!$B$48*F15 -> 178542.89 | H16: =Supuestos!$B$48*G15 -> 176457.6 | J16: 2S26E: dividendos 2026E − pagado 1S26. 2027E+: payout × distribuible del año anterior.
A17: DFN de cierre antes de distribución adicional | C17: =C7+C10+C12+C14+C16 -> 1286484.3 | D17: =D7+D10+D12+D14+D16 -> 1445949.2 | E17: =E7+E10+E12+E14+E16 -> 1661310.5 | F17: =F7+F10+F12+F14+F16 -> 1769793.3 | G17: =G7+G10+G12+G14+G16 -> 2063538 | H17: =H7+H10+H12+H14+H16 -> 2326121
A18: DFN / EBITDA objetivo del período | C18: =IF(Supuestos!$B$40=1,Supuestos!$B$41+(Supuestos!$B$42-Supuestos!$B$41)*MIN(1,C5/Supuestos!$B$44),C17/C6) -> 2.4631249 | D18: =IF(Supuestos!$B$40=1,Supuestos!$B$41+(Supuestos!$B$42-Supuestos!$B$41)*MIN(1,D5/Supuestos!$B$44),D17/D6) -> 2.6704999 | E18: =IF(Supuestos!$B$40=1,Supuestos!$B$41+(Supuestos!$B$42-Supuestos!$B$41)*MIN(1,E5/Supuestos!$B$44),E17/E6) -> 2.8778749 | F18: =IF(Supuestos!$B$40=1,Supuestos!$B$41+(Supuestos!$B$42-Supuestos!$B$41)*MIN(1,F5/Supuestos!$B$44),F17/F6) -> 3.08525 | G18: =IF(Supuestos!$B$40=1,Supuestos!$B$41+(Supuestos!$B$42-Supuestos!$B$41)*MIN(1,G5/Supuestos!$B$44),G17/G6) -> 3.292625 | H18: =IF(Supuestos!$B$40=1,Supuestos!$B$41+(Supuestos!$B$42-Supuestos!$B$41)*MIN(1,H5/Supuestos!$B$44),H17/H6) -> 3.5 | J18: Convergencia lineal hasta el año objetivo (Supuestos C).
A19: DFN objetivo | C19: =C18*C6 -> 1382589.9 | D19: =D18*D6 -> 1632637.8 | E19: =E18*E6 -> 1896981 | F19: =F18*F6 -> 2182362.9 | G19: =G18*G6 -> 2457403.4 | H19: =H18*H6 -> 2742623.2
A20: (+) Distribución adicional a accionistas (recompra / dividendo extra) | C20: =IF(Supuestos!$B$40=1,C19-C17,0) -> 96105.616 | D20: =IF(Supuestos!$B$40=1,D19-D17,0) -> 186688.63 | E20: =IF(Supuestos!$B$40=1,E19-E17,0) -> 235670.5 | F20: =IF(Supuestos!$B$40=1,F19-F17,0) -> 412569.65 | G20: =IF(Supuestos!$B$40=1,G19-G17,0) -> 393865.41 | H20: =IF(Supuestos!$B$40=1,H19-H17,0) -> 416502.13 | J20: Negativo = la compañía tendría que retener caja para no superar el objetivo.
A21: DFN de cierre | C21: =C17+C20 -> 1382589.9 | D21: =D17+D20 -> 1632637.8 | E21: =E17+E20 -> 1896981 | F21: =F17+F20 -> 2182362.9 | G21: =G17+G20 -> 2457403.4 | H21: =H17+H20 -> 2742623.2
A22: DFN / EBITDA de cierre | C22: =C21/C6 -> 2.4631249 | D22: =D21/D6 -> 2.6704999 | E22: =E21/E6 -> 2.8778749 | F22: =F21/F6 -> 3.08525 | G22: =G21/G6 -> 3.292625 | H22: =H21/H6 -> 3.5
A23: Deuda financiera bruta de cierre (DFN + caja) | C23: =C21+Supuestos!$B$12 -> 1730210.9 | D23: =D21+Supuestos!$B$12 -> 1980258.8 | E23: =E21+Supuestos!$B$12 -> 2244602 | F23: =F21+Supuestos!$B$12 -> 2529983.9 | G23: =G21+Supuestos!$B$12 -> 2805024.4 | H23: =H21+Supuestos!$B$12 -> 3090244.2 | J23: Caja constante al nivel de jun-26.
A24: Capacidad de deuda remanente al objetivo de LP (objetivo × EBITDA − DFN) | C24: =Supuestos!$B$42*C6-C21 -> 582013.98 | D24: =Supuestos!$B$42*D6-D21 -> 507123.48 | E24: =Supuestos!$B$42*E6-E21 -> 410080.16 | F24: =Supuestos!$B$42*F6-F21 -> 293374.98 | G24: =Supuestos!$B$42*G6-G21 -> 154771.37 | H24: =Supuestos!$B$42*H6-H21 -> 0
A25: Distribuciones adicionales acumuladas | C25: =C20 -> 96105.616 | D25: =C25+D20 -> 282794.24 | E25: =D25+E20 -> 518464.74 | F25: =E25+F20 -> 931034.39 | G25: =F25+G20 -> 1324899.8 | H25: =G25+H20 -> 1741401.9

Sheet APV
A1: APV — chequeo de consistencia: valor desapalancado + VP de los escudos fiscales de la deuda proyectada
A2: Los escudos se descuentan a Ku porque la deuda se reajusta con el tamaño de la empresa (objetivo como múltiplo del EBITDA), el mismo supuesto implícito en una WACC.
A4: Ku antes de conversión = Rf + βu × ERP + CRP | C4: =WACC!$C$22+WACC!$H$13*Supuestos!$B$22+WACC!$C$21 -> 0.10291119
A5: Ku nominal CLP | C5: =IF(AND(Supuestos!$B$21=1,Supuestos!$B$19=2),(1+C4)*(1+Supuestos!$B$34)/(1+Supuestos!$B$20)-1,C4) -> 0.11107598
A7: MM CLP | C7: 2S26E | D7: 2027E | E7: 2028E | F7: 2029E | G7: 2030E | H7: 2031E | I7: Terminal
A8: FCFF | C8: =DCF!C22 -> 88513.776 | D8: =DCF!D22 -> 149981.04 | E8: =DCF!E22 -> 213232.85 | F8: =DCF!F22 -> 382939.93 | G8: =DCF!G22 -> 387083.94 | H8: =DCF!H22 -> 409692.86 | I8: =DCF!I22 -> 540637.81
A9: Factor de descuento a Ku, cierre | C9: =(1+$C$5)^-DCF!C26 -> 0.9486983 | D9: =C9*(1+$C$5)^-DCF!D26 -> 0.85385546 | E9: =D9*(1+$C$5)^-DCF!E26 -> 0.76849422 | F9: =E9*(1+$C$5)^-DCF!F26 -> 0.69166666 | G9: =F9*(1+$C$5)^-DCF!G26 -> 0.62251968 | H9: =G9*(1+$C$5)^-DCF!H26 -> 0.56028543
A10: Factor de descuento a Ku, mitad | C10: =(1+$C$5)^-(DCF!C26/2) -> 0.97401145 | D10: =C9*(1+$C$5)^-(DCF!D26/2) -> 0.90002846 | E10: =D9*(1+$C$5)^-(DCF!E26/2) -> 0.81005122 | F10: =E9*(1+$C$5)^-(DCF!F26/2) -> 0.72906915 | G10: =F9*(1+$C$5)^-(DCF!G26/2) -> 0.65618299 | H10: =G9*(1+$C$5)^-(DCF!H26/2) -> 0.59058336
A11: VP del FCFF a Ku | C11: =C8*C10 -> 86213.431 | D11: =D8*D10 -> 134987.21 | E11: =E8*E10 -> 172729.53 | F11: =F8*F10 -> 279189.69 | G11: =G8*G10 -> 253997.89 | H11: =H8*H10 -> 241957.79 | I11: =I8/($C$5-Supuestos!$B$88)*H9 -> 3736143.4
A12: Deuda bruta de apertura | C12: =Supuestos!$B$10+Supuestos!$B$12 -> 1633361 | D12: =Deuda!C23 -> 1730210.9 | E12: =Deuda!D23 -> 1980258.8 | F12: =Deuda!E23 -> 2244602 | G12: =Deuda!F23 -> 2529983.9 | H12: =Deuda!G23 -> 2805024.4 | I12: =Deuda!H23 -> 3090244.2
A13: Kd nominal del período (hoja WACC) | C13: =WACC!C41 -> 0.067346995 | D13: =WACC!D41 -> 0.067880986 | E13: =WACC!E41 -> 0.068414977 | F13: =WACC!F41 -> 0.068948967 | G13: =WACC!G41 -> 0.069482958 | H13: =WACC!H41 -> 0.070016949 | I13: =WACC!I41 -> 0.070016949
A14: Escudo fiscal = t × Kd × D | C14: =Supuestos!$B$35*C13*C12*DCF!C26 -> 14850.264 | D14: =Supuestos!$B$35*D13*D12*DCF!D26 -> 31711.075 | E14: =Supuestos!$B$35*E13*E12*DCF!E26 -> 36579.427 | F14: =Supuestos!$B$35*F13*F12*DCF!F26 -> 41786.007 | G14: =Supuestos!$B$35*G13*G12*DCF!G26 -> 47463.507 | H14: =Supuestos!$B$35*H13*H12*DCF!H26 -> 53027.797 | I14: =Supuestos!$B$35*I13*I12*(1+Supuestos!$B$88) -> 60172.349 | J14: Terminal: escudo 2032E sobre la deuda de cierre 2031, creciendo con g.
A15: VP del escudo fiscal a Ku | C15: =C14*C10 -> 14464.327 | D15: =D14*D10 -> 28540.87 | E15: =E14*E10 -> 29631.209 | F15: =F14*F10 -> 30464.888 | G15: =G14*G10 -> 31144.746 | H15: =H14*H10 -> 31317.334 | I15: =I14/($C$5-Supuestos!$B$88)*H9 -> 415828.34
A17: Valor desapalancado (FCFF a Ku) | C17: =SUM(C11:I11) -> 4905218.9
A18: VP de los escudos fiscales | C18: =SUM(C15:I15) -> 581391.72
A19: Enterprise value APV | C19: =C17+C18 -> 5486610.6
A20: Valor del patrimonio | C20: =C19-Supuestos!$B$10-Supuestos!$B$11 -> 4150029.6
A21: Valor por acción APV (CLP) | C21: =C20/Supuestos!$B$9 -> 1894.9907
A22: de lo cual: valor sin deuda (CLP/acción) | C22: =(C17-Supuestos!$B$10-Supuestos!$B$11)/Supuestos!$B$9 -> 1629.515
A23: de lo cual: escudos fiscales (CLP/acción) | C23: =C18/Supuestos!$B$9 -> 265.47567

Sheet Sensibilidad
A1: Sensibilidad — valor por acción DCF (CLP)
A3: Tabla 1: desplazamiento paralelo de la WACC de todos los períodos (filas) vs g nominal terminal (columnas). Fórmulas vivas.
A5: Δ WACC \ g | B5: 0.025 | C5: 0.03 | D5: 0.035 | E5: 0.04
A6: -0.01 | B6: =(SUM($C$30:$H$30)+B$25/(DCF!$I$25+$A$6-B$5)*$H$28-Supuestos!$B$10-Supuestos!$B$11)/Supuestos!$B$9 -> 2329.2587 | C6: =(SUM($C$30:$H$30)+C$25/(DCF!$I$25+$A$6-C$5)*$H$28-Supuestos!$B$10-Supuestos!$B$11)/Supuestos!$B$9 -> 2288.4876 | D6: =(SUM($C$30:$H$30)+D$25/(DCF!$I$25+$A$6-D$5)*$H$28-Supuestos!$B$10-Supuestos!$B$11)/Supuestos!$B$9 -> 2238.3414 | E6: =(SUM($C$30:$H$30)+E$25/(DCF!$I$25+$A$6-E$5)*$H$28-Supuestos!$B$10-Supuestos!$B$11)/Supuestos!$B$9 -> 2176.2226
A7: -0.005 | B7: =(SUM($C$33:$H$33)+B$25/(DCF!$I$25+$A$7-B$5)*$H$31-Supuestos!$B$10-Supuestos!$B$11)/Supuestos!$B$9 -> 2105.9303 | C7: =(SUM($C$33:$H$33)+C$25/(DCF!$I$25+$A$7-C$5)*$H$31-Supuestos!$B$10-Supuestos!$B$11)/Supuestos!$B$9 -> 2057.7181 | D7: =(SUM($C$33:$H$33)+D$25/(DCF!$I$25+$A$7-D$5)*$H$31-Supuestos!$B$10-Supuestos!$B$11)/Supuestos!$B$9 -> 1999.758 | E7: =(SUM($C$33:$H$33)+E$25/(DCF!$I$25+$A$7-E$5)*$H$31-Supuestos!$B$10-Supuestos!$B$11)/Supuestos!$B$9 -> 1929.5777
A8: 0 | B8: =(SUM($C$36:$H$36)+B$25/(DCF!$I$25+$A$8-B$5)*$H$34-Supuestos!$B$10-Supuestos!$B$11)/Supuestos!$B$9 -> 1911.5063 | C8: =(SUM($C$36:$H$36)+C$25/(DCF!$I$25+$A$8-C$5)*$H$34-Supuestos!$B$10-Supuestos!$B$11)/Supuestos!$B$9 -> 1858.6534 | D8: =(SUM($C$36:$H$36)+D$25/(DCF!$I$25+$A$8-D$5)*$H$34-Supuestos!$B$10-Supuestos!$B$11)/Supuestos!$B$9 -> 1796.1374 | E8: =(SUM($C$36:$H$36)+E$25/(DCF!$I$25+$A$8-E$5)*$H$34-Supuestos!$B$10-Supuestos!$B$11)/Supuestos!$B$9 -> 1721.6985
A9: 0.005 | B9: =(SUM($C$39:$H$39)+B$25/(DCF!$I$25+$A$9-B$5)*$H$37-Supuestos!$B$10-Supuestos!$B$11)/Supuestos!$B$9 -> 1740.8117 | C9: =(SUM($C$39:$H$39)+C$25/(DCF!$I$25+$A$9-C$5)*$H$37-Supuestos!$B$10-Supuestos!$B$11)/Supuestos!$B$9 -> 1685.2657 | D9: =(SUM($C$39:$H$39)+D$25/(DCF!$I$25+$A$9-D$5)*$H$37-Supuestos!$B$10-Supuestos!$B$11)/Supuestos!$B$9 -> 1620.3911 | E9: =(SUM($C$39:$H$39)+E$25/(DCF!$I$25+$A$9-E$5)*$H$37-Supuestos!$B$10-Supuestos!$B$11)/Supuestos!$B$9 -> 1544.1643
A10: 0.01 | B10: =(SUM($C$42:$H$42)+B$25/(DCF!$I$25+$A$10-B$5)*$H$40-Supuestos!$B$10-Supuestos!$B$11)/Supuestos!$B$9 -> 1589.8337 | C10: =(SUM($C$42:$H$42)+C$25/(DCF!$I$25+$A$10-C$5)*$H$40-Supuestos!$B$10-Supuestos!$B$11)/Supuestos!$B$9 -> 1532.9605 | D10: =(SUM($C$42:$H$42)+D$25/(DCF!$I$25+$A$10-D$5)*$H$40-Supuestos!$B$10-Supuestos!$B$11)/Supuestos!$B$9 -> 1467.2226 | E10: =(SUM($C$42:$H$42)+E$25/(DCF!$I$25+$A$10-E$5)*$H$40-Supuestos!$B$10-Supuestos!$B$11)/Supuestos!$B$9 -> 1390.8264
A12: La celda resaltada debe igualar el valor por acción de la hoja DCF.
A14: Tabla 2 (estática): DFN/EBITDA objetivo (filas) vs spread por vuelta de apalancamiento (columnas). El D/E objetivo se recalcula con cada nivel. Generada cambiando Supuestos C; no se actualiza sola.
A15: DFN/EBITDA objetivo \ spread | B15: 0 | C15: 0.0025 | D15: 0.005
A16: Actual (2,36x, sin aumento) | B16: 1819.6 | C16: 1819.6 | D16: 1819.6
A17: 3,0x | B17: 1850.6 | C17: 1842.9 | D17: 1835.3
A18: 3,5x | B18: 1873.9 | C18: 1858.7 | D18: 1843.6
A19: 4,0x | B19: 1896.5 | C19: 1872.3 | D19: 1848.5
A20: Valores estáticos (no se recalculan). Resaltado = caso base.
A24: Auxiliar (no editar): FCFF 2032E según g
A25: FCFF 2032E | B25: =((DCF!$C$35*(1+B$5))-Supuestos!$B$57*(DCF!$C$34*(1+B$5)))*(1-Supuestos!$B$59)+Supuestos!$B$57*(DCF!$C$34*(1+B$5))-Supuestos!$B$58*(DCF!$C$34*(1+B$5))-Supuestos!$B$84*Supuestos!$B$85*((DCF!$C$34*(1+B$5))-DCF!$C$34)-((1+B$5)/(1+Supuestos!$B$34)-1)/Expansion!$C$38*((DCF!$C$35*(1+B$5))-Supuestos!$B$57*(DCF!$C$34*(1+B$5)))*(1-Supuestos!$B$59) -> 592936.21 | C25: =((DCF!$C$35*(1+C$5))-Supuestos!$B$57*(DCF!$C$34*(1+C$5)))*(1-Supuestos!$B$59)+Supuestos!$B$57*(DCF!$C$34*(1+C$5))-Supuestos!$B$58*(DCF!$C$34*(1+C$5))-Supuestos!$B$84*Supuestos!$B$85*((DCF!$C$34*(1+C$5))-DCF!$C$34)-((1+C$5)/(1+Supuestos!$B$34)-1)/Expansion!$C$38*((DCF!$C$35*(1+C$5))-Supuestos!$B$57*(DCF!$C$34*(1+C$5)))*(1-Supuestos!$B$59) -> 540637.81 | D25: =((DCF!$C$35*(1+D$5))-Supuestos!$B$57*(DCF!$C$34*(1+D$5)))*(1-Supuestos!$B$59)+Supuestos!$B$57*(DCF!$C$34*(1+D$5))-Supuestos!$B$58*(DCF!$C$34*(1+D$5))-Supuestos!$B$84*Supuestos!$B$85*((DCF!$C$34*(1+D$5))-DCF!$C$34)-((1+D$5)/(1+Supuestos!$B$34)-1)/Expansion!$C$38*((DCF!$C$35*(1+D$5))-Supuestos!$B$57*(DCF!$C$34*(1+D$5)))*(1-Supuestos!$B$59) -> 487810.96 | E25: =((DCF!$C$35*(1+E$5))-Supuestos!$B$57*(DCF!$C$34*(1+E$5)))*(1-Supuestos!$B$59)+Supuestos!$B$57*(DCF!$C$34*(1+E$5))-Supuestos!$B$58*(DCF!$C$34*(1+E$5))-Supuestos!$B$84*Supuestos!$B$85*((DCF!$C$34*(1+E$5))-DCF!$C$34)-((1+E$5)/(1+Supuestos!$B$34)-1)/Expansion!$C$38*((DCF!$C$35*(1+E$5))-Supuestos!$B$57*(DCF!$C$34*(1+E$5)))*(1-Supuestos!$B$59) -> 434455.68
A27: Auxiliar: factores de descuento por Δ (C–H = períodos)
A28: DF cierre (Δ -1.00%) | C28: =(1+(DCF!C$25+$A$6))^-DCF!C$26 -> 0.95547616 | D28: =C28*(1+(DCF!D$25+$A$6))^-DCF!D$26 -> 0.87250897 | E28: =D28*(1+(DCF!E$25+$A$6))^-DCF!E$26 -> 0.79693639 | F28: =E28*(1+(DCF!F$25+$A$6))^-DCF!F$26 -> 0.72807272 | G28: =F28*(1+(DCF!G$25+$A$6))^-DCF!G$26 -> 0.66529927 | H28: =G28*(1+(DCF!H$25+$A$6))^-DCF!H$26 -> 0.60805744
A29: DF mitad (Δ -1.00%) | C29: =(1+(DCF!C$25+$A$6))^-(DCF!C$26/2) -> 0.97748461 | D29: =C28*(1+(DCF!D$25+$A$6))^-(DCF!D$26/2) -> 0.91305066 | E29: =D28*(1+(DCF!E$25+$A$6))^-(DCF!E$26/2) -> 0.83386698 | F29: =E28*(1+(DCF!F$25+$A$6))^-(DCF!F$26/2) -> 0.76172675 | G29: =F28*(1+(DCF!G$25+$A$6))^-(DCF!G$26/2) -> 0.69597863 | H29: =G28*(1+(DCF!H$25+$A$6))^-(DCF!H$26/2) -> 0.63603472
A30: VP FCFF (Δ -1.00%) | C30: =DCF!C$22*C29 -> 86520.853 | D30: =DCF!D$22*D29 -> 136940.29 | E30: =DCF!E$22*E29 -> 177807.83 | F30: =DCF!F$22*F29 -> 291695.59 | G30: =DCF!G$22*G29 -> 269402.15 | H30: =DCF!H$22*H29 -> 260578.89
A31: DF cierre (Δ -0.50%) | C31: =(1+(DCF!C$25+$A$7))^-DCF!C$26 -> 0.95330288 | D31: =C31*(1+(DCF!D$25+$A$7))^-DCF!D$26 -> 0.86656779 | E31: =D31*(1+(DCF!E$25+$A$7))^-DCF!E$26 -> 0.78791149 | F31: =E31*(1+(DCF!F$25+$A$7))^-DCF!F$26 -> 0.71655448 | G31: =F31*(1+(DCF!G$25+$A$7))^-DCF!G$26 -> 0.65179612 | H31: =G31*(1+(DCF!H$25+$A$7))^-DCF!H$26 -> 0.59300616
A32: DF mitad (Δ -0.50%) | C32: =(1+(DCF!C$25+$A$7))^-(DCF!C$26/2) -> 0.9763723 | D32: =C31*(1+(DCF!D$25+$A$7))^-(DCF!D$26/2) -> 0.9089013 | E32: =D31*(1+(DCF!E$25+$A$7))^-(DCF!E$26/2) -> 0.82630425 | F32: =E31*(1+(DCF!F$25+$A$7))^-(DCF!F$26/2) -> 0.75138639 | G32: =F31*(1+(DCF!G$25+$A$7))^-(DCF!G$26/2) -> 0.68340868 | H32: =G31*(1+(DCF!H$25+$A$7))^-(DCF!H$26/2) -> 0.62170662
A33: VP FCFF (Δ -0.50%) | C33: =DCF!C$22*C32 -> 86422.399 | D33: =DCF!D$22*D32 -> 136317.96 | E33: =DCF!E$22*E32 -> 176195.21 | F33: =DCF!F$22*F32 -> 287735.85 | G33: =DCF!G$22*G32 -> 264536.52 | H33: =DCF!H$22*H32 -> 254708.76
A34: DF cierre (Δ +0.00%) | C34: =(1+(DCF!C$25+$A$8))^-DCF!C$26 -> 0.95114436 | D34: =C34*(1+(DCF!D$25+$A$8))^-DCF!D$26 -> 0.86069374 | E34: =D34*(1+(DCF!E$25+$A$8))^-DCF!E$26 -> 0.77902902 | F34: =E34*(1+(DCF!F$25+$A$8))^-DCF!F$26 -> 0.70526946 | G34: =F34*(1+(DCF!G$25+$A$8))^-DCF!G$26 -> 0.63862643 | H34: =G34*(1+(DCF!H$25+$A$8))^-DCF!H$26 -> 0.57839322
A35: DF mitad (Δ +0.00%) | C35: =(1+(DCF!C$25+$A$8))^-(DCF!C$26/2) -> 0.9752663 | D35: =C34*(1+(DCF!D$25+$A$8))^-(DCF!D$26/2) -> 0.90478948 | E35: =D34*(1+(DCF!E$25+$A$8))^-(DCF!E$26/2) -> 0.81884394 | F35: =E34*(1+(DCF!F$25+$A$8))^-(DCF!F$26/2) -> 0.74123233 | G35: =F34*(1+(DCF!G$25+$A$8))^-(DCF!G$26/2) -> 0.67112124 | H35: =G34*(1+(DCF!H$25+$A$8))^-(DCF!H$26/2) -> 0.6077641
A36: VP FCFF (Δ +0.00%) | C36: =DCF!C$22*C35 -> 86324.503 | D36: =DCF!D$22*D35 -> 135701.27 | E36: =DCF!E$22*E35 -> 174604.43 | F36: =DCF!F$22*F35 -> 283847.46 | G36: =DCF!G$22*G35 -> 259780.25 | H36: =DCF!H$22*H35 -> 248996.61
A37: DF cierre (Δ +0.50%) | C37: =(1+(DCF!C$25+$A$9))^-DCF!C$26 -> 0.94900044 | D37: =C37*(1+(DCF!D$25+$A$9))^-DCF!D$26 -> 0.85488576 | E37: =D37*(1+(DCF!E$25+$A$9))^-DCF!E$26 -> 0.77028611 | F37: =E37*(1+(DCF!F$25+$A$9))^-DCF!F$26 -> 0.69421193 | G37: =F37*(1+(DCF!G$25+$A$9))^-DCF!G$26 -> 0.62578051 | H37: =G37*(1+(DCF!H$25+$A$9))^-DCF!H$26 -> 0.56420394
A38: DF mitad (Δ +0.50%) | C38: =(1+(DCF!C$25+$A$9))^-(DCF!C$26/2) -> 0.97416653 | D38: =C37*(1+(DCF!D$25+$A$9))^-(DCF!D$26/2) -> 0.90071469 | E38: =D37*(1+(DCF!E$25+$A$9))^-(DCF!E$26/2) -> 0.81148421 | F38: =E37*(1+(DCF!F$25+$A$9))^-(DCF!F$26/2) -> 0.73126042 | G38: =F37*(1+(DCF!G$25+$A$9))^-(DCF!G$26/2) -> 0.65910871 | H38: =G37*(1+(DCF!H$25+$A$9))^-(DCF!H$26/2) -> 0.59419511
A39: VP FCFF (Δ +0.50%) | C39: =DCF!C$22*C38 -> 86227.158 | D39: =DCF!D$22*D38 -> 135090.13 | E39: =DCF!E$22*E38 -> 173035.09 | F39: =DCF!F$22*F38 -> 280028.81 | G39: =DCF!G$22*G38 -> 255130.4 | H39: =DCF!H$22*H38 -> 243437.49
A40: DF cierre (Δ +1.00%) | C40: =(1+(DCF!C$25+$A$10))^-DCF!C$26 -> 0.94687095 | D40: =C40*(1+(DCF!D$25+$A$10))^-DCF!D$26 -> 0.8491428 | E40: =D40*(1+(DCF!E$25+$A$10))^-DCF!E$26 -> 0.76167995 | F40: =E40*(1+(DCF!F$25+$A$10))^-DCF!F$26 -> 0.6833763 | G40: =F40*(1+(DCF!G$25+$A$10))^-DCF!G$26 -> 0.61324901 | H40: =G40*(1+(DCF!H$25+$A$10))^-DCF!H$26 -> 0.55042421
A41: DF mitad (Δ +1.00%) | C41: =(1+(DCF!C$25+$A$10))^-(DCF!C$26/2) -> 0.97307294 | D41: =C40*(1+(DCF!D$25+$A$10))^-(DCF!D$26/2) -> 0.89667644 | E41: =D40*(1+(DCF!E$25+$A$10))^-(DCF!E$26/2) -> 0.80422326 | F41: =E40*(1+(DCF!F$25+$A$10))^-(DCF!F$26/2) -> 0.72146658 | G41: =F40*(1+(DCF!G$25+$A$10))^-(DCF!G$26/2) -> 0.64736376 | H41: =G40*(1+(DCF!H$25+$A$10))^-(DCF!H$26/2) -> 0.58098804
A42: VP FCFF (Δ +1.00%) | C42: =DCF!C$22*C41 -> 86130.36 | D42: =DCF!D$22*D41 -> 134484.47 | E42: =DCF!E$22*E41 -> 171486.82 | F42: =DCF!F$22*F41 -> 276278.36 | G42: =DCF!G$22*G41 -> 250584.11 | H42: =DCF!H$22*H41 -> 238026.65

Sheet Comparables
A1: Comparables — múltiplos LTM y NTM con el mismo set de pares que la WACC
A2: Set común = empresas con beta en la WACC y con datos en Bloomberg. Estadístico principal: 70% mediana Chile + 30% mediana del set común (Supuestos H). MM CLP con TC del 30-06-2026; precio 30-09-2026.
W3: Columnas auxiliares para las medianas (no editar)
A4: Empresa | B4: Ticker | C4: País | D4: Set (1/0) | E4: Chile (1/0) | F4: Market cap | G4: Deuda neta | H4: Minoritarios | I4: EV | J4: Ingresos LTM | K4: EBITDA LTM | L4: EBIT LTM | M4: Utilidad LTM | N4: Patrimonio | O4: EBITDA NTM | P4: EV/EBITDA LTM | Q4: EV/EBITDA NTM | R4: EV/EBIT LTM | S4: P/E LTM | T4: P/BV | W4: EV/EBITDA LTM set | X4: EV/EBITDA NTM set | Y4: EV/EBIT LTM set | Z4: P/E LTM set | AA4: P/BV set | AB4: EV/EBITDA LTM Chile | AC4: EV/EBITDA NTM Chile | AD4: EV/EBIT LTM Chile | AE4: P/E LTM Chile | AF4: P/BV Chile
A5: Mallplaza | B5: =Datos_BBG!B9 -> MALLPLAZ CI | C5: =Datos_BBG!D9 -> Chile | D5: Target | E5: — | F5: =Datos_BBG!O9*Datos_BBG!S9 -> 7785450 | G5: =Datos_BBG!M9*Datos_BBG!S9 -> 1311568.6 | H5: =Datos_BBG!N9*Datos_BBG!S9 -> 50841.428 | I5: =F5+G5+H5 -> 9147860 | J5: =Datos_BBG!G9*Datos_BBG!S9 -> 677333.31 | K5: =Datos_BBG!H9*Datos_BBG!S9 -> 544935 | L5: =Datos_BBG!J9*Datos_BBG!S9 -> 540372.73 | M5: =Datos_BBG!K9*Datos_BBG!S9 -> 1258052.7 | N5: =Datos_BBG!L9*Datos_BBG!S9 -> 4820897.8 | O5: =Datos_BBG!H48*Datos_BBG!S48 -> 617130.34 | P5: =IF(OR(K5<=0,I5/K5>Supuestos!$B$94),"NM",I5/K5) -> 16.787066 | Q5: =IF(OR(O5<=0,I5/O5>Supuestos!$B$94),"NM",I5/O5) -> 14.823222 | R5: =IF(OR(L5<=0,I5/L5>Supuestos!$B$94),"NM",I5/L5) -> 16.928797 | S5: =IF(OR(M5<=0,Datos_BBG!Q9=1),"NM",IF(F5/M5>Supuestos!$B$94,"NM",F5/M5)) -> 6.1884925 | T5: =IF(OR(N5<=0,F5/N5>Supuestos!$B$94),"NM",F5/N5) -> 1.6149378
A6: Parque Arauco | B6: =Datos_BBG!B14 -> PARAUCO CI | C6: =Datos_BBG!D14 -> Chile | D6: 1 | E6: 1 | F6: =Datos_BBG!O14*Datos_BBG!S14 -> 3440408.4 | G6: =Datos_BBG!M14*Datos_BBG!S14 -> 1602287.6 | H6: =Datos_BBG!N14*Datos_BBG!S14 -> 386791.14 | I6: =F6+G6+H6 -> 5429487.2 | J6: =Datos_BBG!G14*Datos_BBG!S14 -> 416366.83 | K6: =Datos_BBG!H14*Datos_BBG!S14 -> 294411 | L6: =Datos_BBG!J14*Datos_BBG!S14 -> 289515.61 | M6: =Datos_BBG!K14*Datos_BBG!S14 -> 154352.78 | N6: =Datos_BBG!L14*Datos_BBG!S14 -> 1961393.2 | O6: =Datos_BBG!H49*Datos_BBG!S49 -> 342581.95 | P6: =IF(OR(K6<=0,I6/K6>Supuestos!$B$94),"NM",I6/K6) -> 18.441862 | Q6: =IF(OR(O6<=0,I6/O6>Supuestos!$B$94),"NM",I6/O6) -> 15.848725 | R6: =IF(OR(L6<=0,I6/L6>Supuestos!$B$94),"NM",I6/L6) -> 18.753694 | S6: =IF(OR(M6<=0,Datos_BBG!Q14=1),"NM",IF(F6/M6>Supuestos!$B$94,"NM",F6/M6)) -> 22.289255 | T6: =IF(OR(N6<=0,F6/N6>Supuestos!$B$94),"NM",F6/N6) -> 1.7540636 | W6: =IF(AND($D6=1,ISNUMBER(P6)),P6,"") -> 18.441862 | X6: =IF(AND($D6=1,ISNUMBER(Q6)),Q6,"") -> 15.848725 | Y6: =IF(AND($D6=1,ISNUMBER(R6)),R6,"") -> 18.753694 | Z6: =IF(AND($D6=1,ISNUMBER(S6)),S6,"") -> 22.289255 | AA6: =IF(AND($D6=1,ISNUMBER(T6)),T6,"") -> 1.7540636 | AB6: =IF(AND($D6=1,$E6=1,ISNUMBER(P6)),P6,"") -> 18.441862 | AC6: =IF(AND($D6=1,$E6=1,ISNUMBER(Q6)),Q6,"") -> 15.848725 | AD6: =IF(AND($D6=1,$E6=1,ISNUMBER(R6)),R6,"") -> 18.753694 | AE6: =IF(AND($D6=1,$E6=1,ISNUMBER(S6)),S6,"") -> 22.289255 | AF6: =IF(AND($D6=1,$E6=1,ISNUMBER(T6)),T6,"") -> 1.7540636
A7: Cencosud Shopping | B7: =Datos_BBG!B19 -> CENCOMAL CI | C7: =Datos_BBG!D19 -> Chile | D7: 1 | E7: 1 | F7: =Datos_BBG!O19*Datos_BBG!S19 -> 3710182.6 | G7: =Datos_BBG!M19*Datos_BBG!S19 -> 852533.94 | H7: =Datos_BBG!N19*Datos_BBG!S19 -> 6464.021 | I7: =F7+G7+H7 -> 4569180.6 | J7: =Datos_BBG!G19*Datos_BBG!S19 -> 390677.95 | K7: =Datos_BBG!H19*Datos_BBG!S19 -> 350561.25 | L7: =Datos_BBG!J19*Datos_BBG!S19 -> 349975.94 | M7: =Datos_BBG!K19*Datos_BBG!S19 -> 353938.28 | N7: =Datos_BBG!L19*Datos_BBG!S19 -> 3136456.8 | O7: =Datos_BBG!H50*Datos_BBG!S50 -> 392093.8 | P7: =IF(OR(K7<=0,I7/K7>Supuestos!$B$94),"NM",I7/K7) -> 13.033901 | Q7: =IF(OR(O7<=0,I7/O7>Supuestos!$B$94),"NM",I7/O7) -> 11.653284 | R7: =IF(OR(L7<=0,I7/L7>Supuestos!$B$94),"NM",I7/L7) -> 13.055699 | S7: =IF(OR(M7<=0,Datos_BBG!Q19=1),"NM",IF(F7/M7>Supuestos!$B$94,"NM",F7/M7)) -> 10.482569 | T7: =IF(OR(N7<=0,F7/N7>Supuestos!$B$94),"NM",F7/N7) -> 1.1829216 | W7: =IF(AND($D7=1,ISNUMBER(P7)),P7,"") -> 13.033901 | X7: =IF(AND($D7=1,ISNUMBER(Q7)),Q7,"") -> 11.653284 | Y7: =IF(AND($D7=1,ISNUMBER(R7)),R7,"") -> 13.055699 | Z7: =IF(AND($D7=1,ISNUMBER(S7)),S7,"") -> 10.482569 | AA7: =IF(AND($D7=1,ISNUMBER(T7)),T7,"") -> 1.1829216 | AB7: =IF(AND($D7=1,$E7=1,ISNUMBER(P7)),P7,"") -> 13.033901 | AC7: =IF(AND($D7=1,$E7=1,ISNUMBER(Q7)),Q7,"") -> 11.653284 | AD7: =IF(AND($D7=1,$E7=1,ISNUMBER(R7)),R7,"") -> 13.055699 | AE7: =IF(AND($D7=1,$E7=1,ISNUMBER(S7)),S7,"") -> 10.482569 | AF7: =IF(AND($D7=1,$E7=1,ISNUMBER(T7)),T7,"") -> 1.1829216
A8: Multiplan | B8: =Datos_BBG!B24 -> MULT3 BZ | C8: =Datos_BBG!D24 -> Brasil | D8: 1 | E8: 0 | F8: =Datos_BBG!O24*Datos_BBG!S24 -> 2907890.3 | G8: =Datos_BBG!M24*Datos_BBG!S24 -> 888983.2 | H8: =Datos_BBG!N24*Datos_BBG!S24 -> 33.049177 | I8: =F8+G8+H8 -> 3796906.6 | J8: =Datos_BBG!G24*Datos_BBG!S24 -> 570440.4 | K8: =Datos_BBG!H24*Datos_BBG!S24 -> 421296.08 | L8: =Datos_BBG!J24*Datos_BBG!S24 -> 397146.06 | M8: =Datos_BBG!K24*Datos_BBG!S24 -> 247648.38 | N8: =Datos_BBG!L24*Datos_BBG!S24 -> 1206875.9 | O8: =Datos_BBG!H51*Datos_BBG!S51 -> 376773.26 | P8: =IF(OR(K8<=0,I8/K8>Supuestos!$B$94),"NM",I8/K8) -> 9.0124423 | Q8: =IF(OR(O8<=0,I8/O8>Supuestos!$B$94),"NM",I8/O8) -> 10.077431 | R8: =IF(OR(L8<=0,I8/L8>Supuestos!$B$94),"NM",I8/L8) -> 9.560479 | S8: =IF(OR(M8<=0,Datos_BBG!Q24=1),"NM",IF(F8/M8>Supuestos!$B$94,"NM",F8/M8)) -> 11.742012 | T8: =IF(OR(N8<=0,F8/N8>Supuestos!$B$94),"NM",F8/N8) -> 2.4094361 | W8: =IF(AND($D8=1,ISNUMBER(P8)),P8,"") -> 9.0124423 | X8: =IF(AND($D8=1,ISNUMBER(Q8)),Q8,"") -> 10.077431 | Y8: =IF(AND($D8=1,ISNUMBER(R8)),R8,"") -> 9.560479 | Z8: =IF(AND($D8=1,ISNUMBER(S8)),S8,"") -> 11.742012 | AA8: =IF(AND($D8=1,ISNUMBER(T8)),T8,"") -> 2.4094361 | AB8: =IF(AND($D8=1,$E8=1,ISNUMBER(P8)),P8,"") | AC8: =IF(AND($D8=1,$E8=1,ISNUMBER(Q8)),Q8,"") | AD8: =IF(AND($D8=1,$E8=1,ISNUMBER(R8)),R8,"") | AE8: =IF(AND($D8=1,$E8=1,ISNUMBER(S8)),S8,"") | AF8: =IF(AND($D8=1,$E8=1,ISNUMBER(T8)),T8,"")
A9: Allos | B9: =Datos_BBG!B29 -> ALOS3 BZ | C9: =Datos_BBG!D29 -> Brasil | D9: 1 | E9: 0 | F9: =Datos_BBG!O29*Datos_BBG!S29 -> 2656187.5 | G9: =Datos_BBG!M29*Datos_BBG!S29 -> 1221640.7 | H9: =Datos_BBG!N29*Datos_BBG!S29 -> 17188.966 | I9: =F9+G9+H9 -> 3895017.2 | J9: =Datos_BBG!G29*Datos_BBG!S29 -> 524937.58 | K9: =Datos_BBG!H29*Datos_BBG!S29 -> 388838.75 | L9: =Datos_BBG!J29*Datos_BBG!S29 -> 276308.45 | M9: =Datos_BBG!K29*Datos_BBG!S29 -> 166950.15 | N9: =Datos_BBG!L29*Datos_BBG!S29 -> 2296067.8 | O9: =Datos_BBG!H52*Datos_BBG!S52 -> 413640.61 | P9: =IF(OR(K9<=0,I9/K9>Supuestos!$B$94),"NM",I9/K9) -> 10.01705 | Q9: =IF(OR(O9<=0,I9/O9>Supuestos!$B$94),"NM",I9/O9) -> 9.4164284 | R9: =IF(OR(L9<=0,I9/L9>Supuestos!$B$94),"NM",I9/L9) -> 14.096627 | S9: =IF(OR(M9<=0,Datos_BBG!Q29=1),"NM",IF(F9/M9>Supuestos!$B$94,"NM",F9/M9)) -> 15.910064 | T9: =IF(OR(N9<=0,F9/N9>Supuestos!$B$94),"NM",F9/N9) -> 1.1568419 | W9: =IF(AND($D9=1,ISNUMBER(P9)),P9,"") -> 10.01705 | X9: =IF(AND($D9=1,ISNUMBER(Q9)),Q9,"") -> 9.4164284 | Y9: =IF(AND($D9=1,ISNUMBER(R9)),R9,"") -> 14.096627 | Z9: =IF(AND($D9=1,ISNUMBER(S9)),S9,"") -> 15.910064 | AA9: =IF(AND($D9=1,ISNUMBER(T9)),T9,"") -> 1.1568419 | AB9: =IF(AND($D9=1,$E9=1,ISNUMBER(P9)),P9,"") | AC9: =IF(AND($D9=1,$E9=1,ISNUMBER(Q9)),Q9,"") | AD9: =IF(AND($D9=1,$E9=1,ISNUMBER(R9)),R9,"") | AE9: =IF(AND($D9=1,$E9=1,ISNUMBER(S9)),S9,"") | AF9: =IF(AND($D9=1,$E9=1,ISNUMBER(T9)),T9,"")
A10: Iguatemi | B10: =Datos_BBG!B34 -> IGTI11 BZ | C10: =Datos_BBG!D34 -> Brasil | D10: 1 | E10: 0 | F10: =Datos_BBG!O34*Datos_BBG!S34 -> 1381189.7 | G10: =Datos_BBG!M34*Datos_BBG!S34 -> 382047.95 | H10: =Datos_BBG!N34*Datos_BBG!S34 -> 38.944435 | I10: =F10+G10+H10 -> 1763276.6 | J10: =Datos_BBG!G34*Datos_BBG!S34 -> 272862.76 | K10: =Datos_BBG!H34*Datos_BBG!S34 -> 201422.94 | L10: =Datos_BBG!J34*Datos_BBG!S34 -> 178237.78 | M10: =Datos_BBG!K34*Datos_BBG!S34 -> 114077 | N10: =Datos_BBG!L34*Datos_BBG!S34 -> 881991.06 | O10: =Datos_BBG!H53*Datos_BBG!S53 -> 238273.43 | P10: =IF(OR(K10<=0,I10/K10>Supuestos!$B$94),"NM",I10/K10) -> 8.7541002 | Q10: =IF(OR(O10<=0,I10/O10>Supuestos!$B$94),"NM",I10/O10) -> 7.4002234 | R10: =IF(OR(L10<=0,I10/L10>Supuestos!$B$94),"NM",I10/L10) -> 9.892833 | S10: =IF(OR(M10<=0,Datos_BBG!Q34=1),"NM",IF(F10/M10>Supuestos!$B$94,"NM",F10/M10)) -> 12.107521 | T10: =IF(OR(N10<=0,F10/N10>Supuestos!$B$94),"NM",F10/N10) -> 1.5659906 | W10: =IF(AND($D10=1,ISNUMBER(P10)),P10,"") -> 8.7541002 | X10: =IF(AND($D10=1,ISNUMBER(Q10)),Q10,"") -> 7.4002234 | Y10: =IF(AND($D10=1,ISNUMBER(R10)),R10,"") -> 9.892833 | Z10: =IF(AND($D10=1,ISNUMBER(S10)),S10,"") -> 12.107521 | AA10: =IF(AND($D10=1,ISNUMBER(T10)),T10,"") -> 1.5659906 | AB10: =IF(AND($D10=1,$E10=1,ISNUMBER(P10)),P10,"") | AC10: =IF(AND($D10=1,$E10=1,ISNUMBER(Q10)),Q10,"") | AD10: =IF(AND($D10=1,$E10=1,ISNUMBER(R10)),R10,"") | AE10: =IF(AND($D10=1,$E10=1,ISNUMBER(S10)),S10,"") | AF10: =IF(AND($D10=1,$E10=1,ISNUMBER(T10)),T10,"")
A11: IRSA | B11: =Datos_BBG!B39 -> IRSA AR | C11: =Datos_BBG!D39 -> Argentina | D11: 1 | E11: 0 | F11: =Datos_BBG!O39*Datos_BBG!S39 -> 1140416.5 | G11: =Datos_BBG!M39*Datos_BBG!S39 -> 561235.18 | H11: =Datos_BBG!N39*Datos_BBG!S39 -> 87538.904 | I11: =F11+G11+H11 -> 1789190.5 | J11: =Datos_BBG!G39*Datos_BBG!S39 -> 409298.64 | K11: =Datos_BBG!H39*Datos_BBG!S39 -> 145686.2 | L11: =Datos_BBG!J39*Datos_BBG!S39 -> 135134.94 | M11: =Datos_BBG!K39*Datos_BBG!S39 -> 244905.54 | N11: =Datos_BBG!L39*Datos_BBG!S39 -> 1418831.5 | O11: =Datos_BBG!H54*Datos_BBG!S54 -> 286774.76 | P11: =IF(OR(K11<=0,I11/K11>Supuestos!$B$94),"NM",I11/K11) -> 12.281125 | Q11: =IF(OR(O11<=0,I11/O11>Supuestos!$B$94),"NM",I11/O11) -> 6.2390099 | R11: =IF(OR(L11<=0,I11/L11>Supuestos!$B$94),"NM",I11/L11) -> 13.240029 | S11: =IF(OR(M11<=0,Datos_BBG!Q39=1),"NM",IF(F11/M11>Supuestos!$B$94,"NM",F11/M11)) -> 4.6565564 | T11: =IF(OR(N11<=0,F11/N11>Supuestos!$B$94),"NM",F11/N11) -> 0.80377159 | W11: =IF(AND($D11=1,ISNUMBER(P11)),P11,"") -> 12.281125 | X11: =IF(AND($D11=1,ISNUMBER(Q11)),Q11,"") -> 6.2390099 | Y11: =IF(AND($D11=1,ISNUMBER(R11)),R11,"") -> 13.240029 | Z11: =IF(AND($D11=1,ISNUMBER(S11)),S11,"") -> 4.6565564 | AA11: =IF(AND($D11=1,ISNUMBER(T11)),T11,"") -> 0.80377159 | AB11: =IF(AND($D11=1,$E11=1,ISNUMBER(P11)),P11,"") | AC11: =IF(AND($D11=1,$E11=1,ISNUMBER(Q11)),Q11,"") | AD11: =IF(AND($D11=1,$E11=1,ISNUMBER(R11)),R11,"") | AE11: =IF(AND($D11=1,$E11=1,ISNUMBER(S11)),S11,"") | AF11: =IF(AND($D11=1,$E11=1,ISNUMBER(T11)),T11,"")
A12: Fibra Danhos | B12: =Datos_BBG!B44 -> DANHOS13 MM | C12: =Datos_BBG!D44 -> México | D12: 0 | E12: 0 | F12: =Datos_BBG!O44*Datos_BBG!S44 -> 2383999.4 | G12: =Datos_BBG!M44*Datos_BBG!S44 -> 618003.43 | H12: =Datos_BBG!N44*Datos_BBG!S44 -> 155940.9 | I12: =F12+G12+H12 -> 3157943.8 | J12: =Datos_BBG!G44*Datos_BBG!S44 -> 417411.61 | K12: =Datos_BBG!H44*Datos_BBG!S44 -> 277625.06 | L12: =Datos_BBG!J44*Datos_BBG!S44 -> 276925.52 | M12: =Datos_BBG!K44*Datos_BBG!S44 -> 301542.11 | N12: =Datos_BBG!L44*Datos_BBG!S44 -> 3445417.1 | O12: =Datos_BBG!H55*Datos_BBG!S55 -> 313368.82 | P12: =IF(OR(K12<=0,I12/K12>Supuestos!$B$94),"NM",I12/K12) -> 11.374851 | Q12: =IF(OR(O12<=0,I12/O12>Supuestos!$B$94),"NM",I12/O12) -> 10.077403 | R12: =IF(OR(L12<=0,I12/L12>Supuestos!$B$94),"NM",I12/L12) -> 11.403585 | S12: =IF(OR(M12<=0,Datos_BBG!Q44=1),"NM",IF(F12/M12>Supuestos!$B$94,"NM",F12/M12)) -> 7.9060247 | T12: =IF(OR(N12<=0,F12/N12>Supuestos!$B$94),"NM",F12/N12) -> 0.69193348 | W12: =IF(AND($D12=1,ISNUMBER(P12)),P12,"") | X12: =IF(AND($D12=1,ISNUMBER(Q12)),Q12,"") | Y12: =IF(AND($D12=1,ISNUMBER(R12)),R12,"") | Z12: =IF(AND($D12=1,ISNUMBER(S12)),S12,"") | AA12: =IF(AND($D12=1,ISNUMBER(T12)),T12,"") | AB12: =IF(AND($D12=1,$E12=1,ISNUMBER(P12)),P12,"") | AC12: =IF(AND($D12=1,$E12=1,ISNUMBER(Q12)),Q12,"") | AD12: =IF(AND($D12=1,$E12=1,ISNUMBER(R12)),R12,"") | AE12: =IF(AND($D12=1,$E12=1,ISNUMBER(S12)),S12,"") | AF12: =IF(AND($D12=1,$E12=1,ISNUMBER(T12)),T12,"")
A14: Estadísticos (excluyen a Mallplaza)
A15: Mediana set común | P15: =MEDIAN(W6:W12) -> 11.149088 | Q15: =MEDIAN(X6:X12) -> 9.7469298 | R15: =MEDIAN(Y6:Y12) -> 13.147864 | S15: =MEDIAN(Z6:Z12) -> 11.924767 | T15: =MEDIAN(AA6:AA12) -> 1.3744561
A16: Mediana Chile (set común) | P16: =MEDIAN(AB6:AB12) -> 15.737882 | Q16: =MEDIAN(AC6:AC12) -> 13.751005 | R16: =MEDIAN(AD6:AD12) -> 15.904696 | S16: =MEDIAN(AE6:AE12) -> 16.385912 | T16: =MEDIAN(AF6:AF12) -> 1.4684926
A17: Múltiplo ponderado (70% Chile / 30% set común) | P17: =Supuestos!$B$93*P16+(1-Supuestos!$B$93)*P15 -> 14.361243 | Q17: =Supuestos!$B$93*Q16+(1-Supuestos!$B$93)*Q15 -> 12.549782 | R17: =Supuestos!$B$93*R16+(1-Supuestos!$B$93)*R15 -> 15.077647 | S17: =Supuestos!$B$93*S16+(1-Supuestos!$B$93)*S15 -> 15.047569 | T17: =Supuestos!$B$93*T16+(1-Supuestos!$B$93)*T15 -> 1.4402817
A18: N° pares set común | P18: =COUNT(W6:W12) -> 6 | Q18: =COUNT(X6:X12) -> 6 | R18: =COUNT(Y6:Y12) -> 6 | S18: =COUNT(Z6:Z12) -> 6 | T18: =COUNT(AA6:AA12) -> 6
A19: Mallplaza vs ponderado (prima / (descuento)) | P19: =IF(ISNUMBER(P5),P5/P17-1,"NM") -> 0.16891455 | Q19: =IF(ISNUMBER(Q5),Q5/Q17-1,"NM") -> 0.18115372 | R19: =IF(ISNUMBER(R5),R5/R17-1,"NM") -> 0.12277446 | S19: =IF(ISNUMBER(S5),S5/S17-1,"NM") -> -0.58873804 | T19: =IF(ISNUMBER(T5),T5/T17-1,"NM") -> 0.12126524
A21: Notas: P/E y P/BV mezclan pares a valor razonable (Chile, IRSA) con pares a costo (Brasil); usar como referencia. EV/EBITDA es el método principal (neutral a la contabilidad de propiedades). IRSA: cifras NIC 29 y NTM de 1 analista. Fibra Danhos queda fuera del set (no tiene beta en la WACC).

Sheet Precio_Objetivo
A1: Precio objetivo — 80% DCF / 20% múltiplos (EV/EBITDA ponderado 70% Chile)
A3: A. Valor por múltiplos (Mallplaza)
A4: Múltiplo | B4: Múltiplo ponderado | C4: Métrica Mallplaza | D4: Valor por acción (CLP)
A5: EV/EBITDA LTM (método principal) | B5: =Comparables!P17 -> 14.361243 | C5: =Comparables!K5 -> 544935 | D5: =(B5*C5-Supuestos!$B$14-Comparables!H5)/Supuestos!$B$9 -> 2951.3855 | E5: EV implícito − deuda neta BBG − minoritarios, / acciones.
A6: EV/EBITDA NTM | B6: =Comparables!Q17 -> 12.549782 | C6: =Comparables!O5 -> 617130.34 | D6: =(B6*C6-Supuestos!$B$14-Comparables!H5)/Supuestos!$B$9 -> 2914.3568
A7: EV/EBIT LTM | B7: =Comparables!R17 -> 15.077647 | C7: =Comparables!L5 -> 540372.73 | D7: =(B7*C7-Supuestos!$B$14-Comparables!H5)/Supuestos!$B$9 -> 3098.237
A8: P/E LTM (referencia: incluye revalorización) | B8: =Comparables!S17 -> 15.047569 | C8: =Comparables!M5 -> 1258052.7 | D8: =B8*C8/Supuestos!$B$9 -> 8644.1255
A9: P/BV (referencia) | B9: =Comparables!T17 -> 1.4402817 | C9: =Comparables!N5 -> 4820897.8 | D9: =B9*C9/Supuestos!$B$9 -> 3170.5255
A11: B. Precio objetivo combinado
A12: Valor DCF (CLP) | B12: =DCF!C49 -> 1858.6534
A13: Valor por múltiplos: EV/EBITDA LTM ponderado (CLP) | B13: =D5 -> 2951.3855
A14: Peso DCF | B14: =Supuestos!$B$92 -> 0.8
A15: Precio objetivo (CLP) | B15: =B12*B14+B13*(1-B14) -> 2077.1998
A16: Precio 30-09-2026 (CLP) | B16: =Supuestos!$B$8 -> 3555
A17: Upside / (downside) | B17: =B15/B16-1 -> -0.41569626
A18: Referencia: precio objetivo VF (CLP) | B18: =Supuestos!$B$110 -> 2096.399
A20: C. Lectura rápida
A21: Cap rate implícito del DCF (EBITDA LTM / EV) | B21: =DCF!C56 -> 0.10078265
A22: Cap rate implícito del mercado (EBITDA LTM / EV de mercado) | B22: =1/Comparables!P5 -> 0.05956967
A23: Cap rate de los pares chilenos (1 / EV/EBITDA LTM mediana Chile) | B23: =1/Comparables!P16 -> 0.063540954
A24: WACC nominal terminal | B24: =DCF!C38 -> 0.10413887
A25: WACC real terminal | B25: =DCF!C58 -> 0.071979483

Sheet Datos_BBG
A1: Datos Bloomberg en moneda local (millones)
A2: EBITDA = IS_COMPARABLE_EBITDA (salvo nota) · EBIT = EBITDA − D&A (CF_DEPR_AMORT) · LTM = suma 3T25–2T26 · Balance LTM al 30-jun-2026
A4: Empresa | B4: Ticker BBG | C4: Grupo | D4: País | E4: Moneda | F4: Período | G4: Revenue | H4: EBITDA | I4: D&A | J4: EBIT | K4: Net Income (controladora) | L4: Book Value | M4: Net Debt (BBG) | N4: Minoritarios | O4: Market Cap | P4: Precio | Q4: Forzar P/E NM | R4: Nota | S4: Factor a CLP | T4: EV (local)
A5: Mallplaza | B5: MALLPLAZ CI | C5: Target | D5: Chile | E5: CLP | F5: FY2022 | G5: 370898.93 | H5: 282699 | I5: 2165.395 | J5: =H5-I5 -> 280533.6 | K5: 157666.76 | L5: 2263298.5 | M5: 1011613.3 | N5: 168378.48 | O5: 2073680 | P5: 1050.647 | Q5: 0 | S5: =Supuestos!$B$101 -> 1 | T5: =O5+M5+N5 -> 3253671.8
A6: Mallplaza | B6: MALLPLAZ CI | C6: Target | D6: Chile | E6: CLP | F6: FY2023 | G6: 419903.78 | H6: 322185 | I6: 2153.51 | J6: =H6-I6 -> 320031.49 | K6: 349758.85 | L6: 2601053.2 | M6: 1081082.3 | N6: 31634.353 | O6: 2439612 | P6: 1236.049 | Q6: 0 | S6: =Supuestos!$B$101 -> 1 | T6: =O6+M6+N6 -> 3552328.7
A7: Mallplaza | B7: MALLPLAZ CI | C7: Target | D7: Chile | E7: CLP | F7: FY2024 | G7: 494605.24 | H7: 380637 | I7: 2111.809 | J7: =H7-I7 -> 378525.19 | K7: 335933.78 | L7: 3157863.1 | M7: 1458589.1 | N7: 33186.747 | O7: 3569919 | P7: 1630.1 | Q7: 0 | S7: =Supuestos!$B$101 -> 1 | T7: =O7+M7+N7 -> 5061694.9
A8: Mallplaza | B8: MALLPLAZ CI | C8: Target | D8: Chile | E8: CLP | F8: FY2025 | G8: 653911.09 | H8: 526228 | I8: 3609.536 | J8: =H8-I8 -> 522618.46 | K8: 1431011.6 | L8: 4482903.9 | M8: 1327147.4 | N8: 41649.187 | O8: 6977559 | P8: 3186.1 | Q8: 0 | R8: Net Income incluye revalorización de propiedades (~1,0 bn). | S8: =Supuestos!$B$101 -> 1 | T8: =O8+M8+N8 -> 8346355.6
A9: Mallplaza | B9: MALLPLAZ CI | C9: Target | D9: Chile | E9: CLP | F9: LTM | G9: 677333.31 | H9: 544935 | I9: 4562.274 | J9: =H9-I9 -> 540372.73 | K9: 1258052.7 | L9: 4820897.8 | M9: 1311568.6 | N9: 50841.428 | O9: 7785450 | P9: 3555 | Q9: 0 | S9: =Supuestos!$B$101 -> 1 | T9: =O9+M9+N9 -> 9147860
A10: Parque Arauco | B10: PARAUCO CI | C10: Core | D10: Chile | E10: CLP | F10: FY2022 | G10: 243119.54 | H10: 170697 | I10: 5128.377 | J10: =H10-I10 -> 165568.62 | K10: 101031.63 | L10: 1144928.9 | M10: 989079.05 | N10: 211136.22 | O10: 979894.01 | P10: 1067.16 | Q10: 0 | S10: =Supuestos!$B$101 -> 1 | T10: =O10+M10+N10 -> 2180109.3
A11: Parque Arauco | B11: PARAUCO CI | C11: Core | D11: Chile | E11: CLP | F11: FY2023 | G11: 264312.61 | H11: 188159 | I11: 5280.937 | J11: =H11-I11 -> 182878.06 | K11: 112345.33 | L11: 1298911.3 | M11: 1113749.4 | N11: 332049.13 | O11: 1286116.6 | P11: 1400.66 | Q11: 0 | S11: =Supuestos!$B$101 -> 1 | T11: =O11+M11+N11 -> 2731915
A12: Parque Arauco | B12: PARAUCO CI | C12: Core | D12: Chile | E12: CLP | F12: FY2024 | G12: 316775.71 | H12: 227727 | I12: 6518.906 | J12: =H12-I12 -> 221208.09 | K12: 120571.31 | L12: 1464457.7 | M12: 1279923.4 | N12: 323589.52 | O12: 1439092 | P12: 1567.26 | Q12: 0 | S12: =Supuestos!$B$101 -> 1 | T12: =O12+M12+N12 -> 3042604.9
A13: Parque Arauco | B13: PARAUCO CI | C13: Core | D13: Chile | E13: CLP | F13: FY2025 | G13: 383792.58 | H13: 272233 | I13: 4739.59 | J13: =H13-I13 -> 267493.41 | K13: 149972.7 | L13: 1594521.9 | M13: 1631210.9 | N13: 362360.84 | O13: 2708090.5 | P13: 2949.27 | Q13: 0 | S13: =Supuestos!$B$101 -> 1 | T13: =O13+M13+N13 -> 4701662.2
A14: Parque Arauco | B14: PARAUCO CI | C14: Core | D14: Chile | E14: CLP | F14: LTM | G14: 416366.83 | H14: 294411 | I14: 4895.39 | J14: =H14-I14 -> 289515.61 | K14: 154352.78 | L14: 1961393.2 | M14: 1602287.6 | N14: 386791.14 | O14: 3440408.4 | P14: 3505 | Q14: 0 | S14: =Supuestos!$B$101 -> 1 | T14: =O14+M14+N14 -> 5429487.2
A15: Cencosud Shopping | B15: CENCOMAL CI | C15: Core | D15: Chile | E15: CLP | F15: FY2022 | G15: 286949.85 | H15: 258583.7 | I15: 178.837 | J15: =H15-I15 -> 258404.86 | K15: 181875.55 | L15: 2679608.6 | M15: 636796.49 | N15: 4966.978 | O15: 2283766.6 | P15: 1338.8 | Q15: 0 | R15: EBITDA = EBITDA_ADJUSTED (comparable BBG incluía revalorización). | S15: =Supuestos!$B$101 -> 1 | T15: =O15+M15+N15 -> 2925530.1
A16: Cencosud Shopping | B16: CENCOMAL CI | C16: Core | D16: Chile | E16: CLP | F16: FY2023 | G16: 314784.93 | H16: 272791.98 | I16: 213.006 | J16: =H16-I16 -> 272578.97 | K16: 187329.71 | L16: 2744754.9 | M16: 650170.98 | N16: 5991.871 | O16: 2405221.8 | P16: 1410 | Q16: 0 | S16: =Supuestos!$B$101 -> 1 | T16: =O16+M16+N16 -> 3061384.7
A17: Cencosud Shopping | B17: CENCOMAL CI | C17: Core | D17: Chile | E17: CLP | F17: FY2024 | G17: 353183.7 | H17: 320677 | I17: 409.897 | J17: =H17-I17 -> 320267.1 | K17: 266953.08 | L17: 2828031.7 | M17: 679855.78 | N17: 6467.54 | O17: 2654273.2 | P17: 1556 | Q17: 0 | S17: =Supuestos!$B$101 -> 1 | T17: =O17+M17+N17 -> 3340596.5
A18: Cencosud Shopping | B18: CENCOMAL CI | C18: Core | D18: Chile | E18: CLP | F18: FY2025 | G18: 377940.6 | H18: 340557 | I18: 540.654 | J18: =H18-I18 -> 340016.35 | K18: 303966.19 | L18: 2989170.6 | M18: 769416.4 | N18: 5505.4 | O18: 3974586.4 | P18: 2330 | Q18: 0 | S18: =Supuestos!$B$101 -> 1 | T18: =O18+M18+N18 -> 4749508.2
A19: Cencosud Shopping | B19: CENCOMAL CI | C19: Core | D19: Chile | E19: CLP | F19: LTM | G19: 390677.95 | H19: 350561.25 | I19: 585.311 | J19: =H19-I19 -> 349975.94 | K19: 353938.28 | L19: 3136456.8 | M19: 852533.94 | N19: 6464.021 | O19: 3710182.6 | P19: 2175 | Q19: 0 | R19: Q1-26 EBITDA = EBITDA_ADJUSTED (comparable incluía revalorización). | S19: =Supuestos!$B$101 -> 1 | T19: =O19+M19+N19 -> 4569180.6
A20: Multiplan | B20: MULT3 BZ | C20: Core | D20: Brasil | E20: BRL | F20: FY2022 | G20: 1797.605 | H20: 1275.254 | I20: 206.751 | J20: =H20-I20 -> 1068.503 | K20: 769.255 | L20: 6582.34 | M20: 3086.169 | N20: 0.203 | O20: 13156.663 | P20: 21.9 | Q20: 0 | S20: =Supuestos!$B$103 -> 178.6442 | T20: =O20+M20+N20 -> 16243.035
A21: Multiplan | B21: MULT3 BZ | C21: Core | D21: Brasil | E21: BRL | F21: FY2023 | G21: 2029.569 | H21: 1506.5 | I21: 170.144 | J21: =H21-I21 -> 1336.356 | K21: 1020.39 | L21: 6933.916 | M21: 3103.816 | N21: 0.082 | O21: 17073.624 | P21: 28.42 | Q21: 0 | S21: =Supuestos!$B$103 -> 178.6442 | T21: =O21+M21+N21 -> 20177.522
A22: Multiplan | B22: MULT3 BZ | C22: Core | D22: Brasil | E22: BRL | F22: FY2024 | G22: 2544.789 | H22: 1848.038 | I22: 138.508 | J22: =H22-I22 -> 1709.53 | K22: 1340.814 | L22: 5645.519 | M22: 5416.57 | N22: 0.25 | O22: 10943.971 | P22: 21.08 | Q22: 0 | S22: =Supuestos!$B$103 -> 178.6442 | T22: =O22+M22+N22 -> 16360.791
A23: Multiplan | B23: MULT3 BZ | C23: Core | D23: Brasil | E23: BRL | F23: FY2025 | G23: 2739.082 | H23: 2003.354 | I23: 137.757 | J23: =H23-I23 -> 1865.597 | K23: 1141.12 | L23: 6299.142 | M23: 5248.897 | N23: 0.237 | O23: 13983.711 | P23: 27.25 | Q23: 0 | S23: =Supuestos!$B$103 -> 178.6442 | T23: =O23+M23+N23 -> 19232.845
A24: Multiplan | B24: MULT3 BZ | C24: Core | D24: Brasil | E24: BRL | F24: LTM | G24: 3193.165 | H24: 2358.297 | I24: 135.185 | J24: =H24-I24 -> 2223.112 | K24: 1386.266 | L24: 6755.752 | M24: 4976.278 | N24: 0.185 | O24: 16277.553 | P24: 31.72 | Q24: 0 | S24: =Supuestos!$B$103 -> 178.6442 | T24: =O24+M24+N24 -> 21254.016
A25: Allos | B25: ALOS3 BZ | C25: Core | D25: Brasil | E25: BRL | F25: FY2022 | G25: 1111.321 | H25: 816.975 | I25: 202.11 | J25: =H25-I25 -> 614.865 | K25: 155.875 | L25: 6805.618 | M25: 2968.103 | N25: 1071.413 | O25: 10077.977 | P25: 17.01 | Q25: 0 | S25: =Supuestos!$B$103 -> 178.6442 | T25: =O25+M25+N25 -> 14117.493
A26: Allos | B26: ALOS3 BZ | C26: Core | D26: Brasil | E26: BRL | F26: FY2023 | G26: 2804 | H26: 1941.141 | I26: 684.466 | J26: =H26-I26 -> 1256.675 | K26: 3386.958 | L26: 13997.882 | M26: 5632.802 | N26: 1106.85 | O26: 15238.025 | P26: 26.55 | Q26: 1 | R26: Revenue BBG 7.481 incluye ítems no recurrentes de la combinación con brMalls; se usa 2.804 (S&P). P/E NM por ganancia no recurrente. | S26: =Supuestos!$B$103 -> 178.6442 | T26: =O26+M26+N26 -> 21977.677
A27: Allos | B27: ALOS3 BZ | C27: Core | D27: Brasil | E27: BRL | F27: FY2024 | G27: 2797.254 | H27: 1996.151 | I27: 618.831 | J27: =H27-I27 -> 1377.32 | K27: 698.511 | L27: 13364.892 | M27: 6586.625 | N27: 769.628 | O27: 9832.5874 | P27: 18.11 | Q27: 0 | S27: =Supuestos!$B$103 -> 178.6442 | T27: =O27+M27+N27 -> 17188.84
A28: Allos | B28: ALOS3 BZ | C28: Core | D28: Brasil | E28: BRL | F28: FY2025 | G28: 2899.583 | H28: 2067.985 | I28: 634.825 | J28: =H28-I28 -> 1433.16 | K28: 834.166 | L28: 13146.445 | M28: 5871.965 | N28: 752.561 | O28: 14303.897 | P28: 28.37 | Q28: 0 | S28: =Supuestos!$B$103 -> 178.6442 | T28: =O28+M28+N28 -> 20928.423
A29: Allos | B29: ALOS3 BZ | C29: Core | D29: Brasil | E29: BRL | F29: LTM | G29: 2938.453 | H29: 2176.61 | I29: 629.913 | J29: =H29-I29 -> 1546.697 | K29: 934.54 | L29: 12852.742 | M29: 6838.401 | N29: 96.219 | O29: 14868.591 | P29: 29.49 | Q29: 0 | S29: =Supuestos!$B$103 -> 178.6442 | T29: =O29+M29+N29 -> 21803.211
A30: Iguatemi | B30: IGTI11 BZ | C30: Core | D30: Brasil | E30: BRL | F30: FY2022 | G30: 1016.341 | H30: 653.8 | I30: 159.03 | J30: =H30-I30 -> 494.77 | K30: 7.568 | L30: 4093.329 | M30: 1193.596 | N30: 14.359 | O30: 5667.3061 | P30: 18.5 | Q30: 0 | S30: =Supuestos!$B$103 -> 178.6442 | T30: =O30+M30+N30 -> 6875.2611
A31: Iguatemi | B31: IGTI11 BZ | C31: Core | D31: Brasil | E31: BRL | F31: FY2023 | G31: 1157.163 | H31: 919.704 | I31: 174.376 | J31: =H31-I31 -> 745.328 | K31: 304.713 | L31: 4177.323 | M31: 1757.145 | N31: 0.195 | O31: 7059.6783 | P31: 24.38 | Q31: 0 | S31: =Supuestos!$B$103 -> 178.6442 | T31: =O31+M31+N31 -> 8817.0183
A32: Iguatemi | B32: IGTI11 BZ | C32: Core | D32: Brasil | E32: BRL | F32: FY2024 | G32: 1236.345 | H32: 914.762 | I32: 190.255 | J32: =H32-I32 -> 724.507 | K32: 399.771 | L32: 4309.804 | M32: 1614.844 | N32: 0.216 | O32: 5071.0437 | P32: 17.27 | Q32: 0 | S32: =Supuestos!$B$103 -> 178.6442 | T32: =O32+M32+N32 -> 6686.1037
A33: Iguatemi | B33: IGTI11 BZ | C33: Core | D33: Brasil | E33: BRL | F33: FY2025 | G33: 1486.833 | H33: 1029.691 | I33: 113.963 | J33: =H33-I33 -> 915.728 | K33: 582.46 | L33: 4651.644 | M33: 2210.196 | N33: 0.22 | O33: 7307.0208 | P33: 25.57 | Q33: 0 | R33: EBITDA = EBITDA_ADJUSTED (comparable incluía ganancia por venta de activos). | S33: =Supuestos!$B$103 -> 178.6442 | T33: =O33+M33+N33 -> 9517.4368
A34: Iguatemi | B34: IGTI11 BZ | C34: Core | D34: Brasil | E34: BRL | F34: LTM | G34: 1527.409 | H34: 1127.509 | I34: 129.784 | J34: =H34-I34 -> 997.725 | K34: 638.571 | L34: 4937.138 | M34: 2138.597 | N34: 0.218 | O34: 7731.5118 | P34: 27.02 | Q34: 0 | R34: Q1-26 EBITDA = EBITDA_ADJUSTED. | S34: =Supuestos!$B$103 -> 178.6442 | T34: =O34+M34+N34 -> 9870.3268
A35: IRSA | B35: IRSA AR | C35: Sensibilidad | D35: Argentina | E35: ARS | F35: FY2022 (jun) | G35: 69299 | H35: 28988 | I35: 2007 | J35: =H35-I35 -> 26981 | K35: 74487 | L35: 342457 | M35: 136044 | N35: 23443 | O35: 74930.179 | P35: 97.185 | Q35: 0 | S35: =Supuestos!$B$105 -> 0.62236167 | T35: =O35+M35+N35 -> 234417.18
A36: IRSA | B36: IRSA AR | C36: Sensibilidad | D36: Argentina | E36: ARS | F36: FY2023 (jun) | G36: 331721 | H36: 92531 | I36: 7056 | J36: =H36-I36 -> 85475 | K36: 213076 | L36: 1345130 | M36: 378401 | N36: 82965 | O36: 331336.46 | P36: 433.728 | Q36: 0 | S36: =Supuestos!$B$105 -> 0.62236167 | T36: =O36+M36+N36 -> 792702.46
A37: IRSA | B37: IRSA AR | C37: Sensibilidad | D37: Argentina | E37: ARS | F37: FY2024 (jun) | G37: 458059 | H37: 232057 | I37: 9130 | J37: =H37-I37 -> 222927 | K37: -25621 | L37: 1503846 | M37: 484504 | N37: 102883 | O37: 898977.28 | P37: 1178.315 | Q37: 0 | R37: Utilidad negativa → P/E NM. | S37: =Supuestos!$B$105 -> 0.62236167 | T37: =O37+M37+N37 -> 1486364.3
A38: IRSA | B38: IRSA AR | C38: Sensibilidad | D38: Argentina | E38: ARS | F38: FY2025 (jun) | G38: 626290 | H38: 252539 | I38: 14034 | J38: =H38-I38 -> 238505 | K38: 260661 | L38: 2107122 | M38: 632450 | N38: 125752 | O38: 1260882 | P38: 1685 | Q38: 0 | S38: =Supuestos!$B$105 -> 0.62236167 | T38: =O38+M38+N38 -> 2019084
A39: IRSA | B39: IRSA AR | C39: Sensibilidad | D39: Argentina | E39: ARS | F39: LTM | G39: 657654 | H39: 234086.08 | I39: 16953.583 | J39: =H39-I39 -> 217132.49 | K39: 393510 | L39: 2279754 | M39: 901783 | N39: 140656 | O39: 1832401.5 | P39: 2260 | Q39: 0 | R39: FY jun-2026. Revenue y NI anuales (TRAIL_12M); EBITDA = Revenue × margen ajustado de los 4 trimestres (cifras NIC 29). | S39: =Supuestos!$B$105 -> 0.62236167 | T39: =O39+M39+N39 -> 2874840.5
A40: Fibra Danhos | B40: DANHOS13 MM | C40: Sensibilidad | D40: México | E40: MXN | F40: FY2022 | G40: 5513.0751 | H40: 3548.488 | I40: 17.399054 | J40: =H40-I40 -> 3531.0889 | K40: 2839.2736 | L40: 58859.105 | M40: 5777.2148 | N40: 2514.0535 | O40: 35837.309 | P40: 23.4 | Q40: 0 | S40: =Supuestos!$B$104 -> 52.70936 | T40: =O40+M40+N40 -> 44128.577
A41: Fibra Danhos | B41: DANHOS13 MM | C41: Sensibilidad | D41: México | E41: MXN | F41: FY2023 | G41: 6188.9891 | H41: 3946.7937 | I41: 16.68704 | J41: =H41-I41 -> 3930.1067 | K41: 3309.204 | L41: 59273.71 | M41: 7103.915 | N41: 2779.6918 | O41: 32666.034 | P41: 20.96 | Q41: 0 | S41: =Supuestos!$B$104 -> 52.70936 | T41: =O41+M41+N41 -> 42549.641
A42: Fibra Danhos | B42: DANHOS13 MM | C42: Sensibilidad | D42: México | E42: MXN | F42: FY2024 | G42: 6774.6488 | H42: 4404.9799 | I42: 12.314015 | J42: =H42-I42 -> 4392.6659 | K42: 4201.2111 | L42: 61136.362 | M42: 8959.336 | N42: 2694.196 | O42: 31741.125 | P42: 20.06 | Q42: 0 | S42: =Supuestos!$B$104 -> 52.70936 | T42: =O42+M42+N42 -> 43394.657
A43: Fibra Danhos | B43: DANHOS13 MM | C43: Sensibilidad | D43: México | E43: MXN | F43: FY2025 | G43: 7576.4276 | H43: 5024.1114 | I43: 13.044624 | J43: =H43-I43 -> 5011.0668 | K43: 5033.0947 | L43: 63801.629 | M43: 10355.722 | N43: 2856.8299 | O43: 45010.308 | P43: 28.06 | Q43: 0 | S43: =Supuestos!$B$104 -> 52.70936 | T43: =O43+M43+N43 -> 58222.86
A44: Fibra Danhos | B44: DANHOS13 MM | C44: Sensibilidad | D44: México | E44: MXN | F44: LTM | G44: 7919.1174 | H44: 5267.0922 | I44: 13.271624 | J44: =H44-I44 -> 5253.8206 | K44: 5720.8457 | L44: 65366.324 | M44: 11724.738 | N44: 2958.505 | O44: 45229.148 | P44: 27.94 | Q44: 0 | S44: =Supuestos!$B$104 -> 52.70936 | T44: =O44+M44+N44 -> 59912.391
A46: NTM — consenso Bloomberg BEst, 12 meses forward mezclado (BEST_FPERIOD_OVERRIDE = BF), al 07-oct-2026
A47: Empresa | B47: Ticker BBG | C47: Grupo | D47: País | E47: Moneda | F47: Período | G47: Revenue NTM | H47: EBITDA NTM | I47: EBIT NTM | J47: Net Income NTM | K47: Nº analistas | R47: Nota | S47: Factor a CLP
A48: Mallplaza | B48: MALLPLAZ CI | C48: Target | D48: Chile | E48: CLP | F48: NTM | G48: 758569.53 | H48: 617130.34 | I48: 611889.82 | J48: 488981.25 | K48: 13 | S48: =Supuestos!$B$101 -> 1
A49: Parque Arauco | B49: PARAUCO CI | C49: Core | D49: Chile | E49: CLP | F49: NTM | G49: 475685.59 | H49: 342581.95 | I49: 347536.96 | J49: 166719.85 | K49: 13 | R49: Consenso EBIT > EBITDA (distintos sets de analistas). | S49: =Supuestos!$B$101 -> 1
A50: Cencosud Shopping | B50: CENCOMAL CI | C50: Core | D50: Chile | E50: CLP | F50: NTM | G50: 436396.65 | H50: 392093.8 | I50: 395608.2 | J50: 278140.73 | K50: 11 | R50: Consenso EBIT > EBITDA (distintos sets de analistas). | S50: =Supuestos!$B$101 -> 1
A51: Multiplan | B51: MULT3 BZ | C51: Core | D51: Brasil | E51: BRL | F51: NTM | G51: 2802.8045 | H51: 2109.0708 | I51: 1967.477 | J51: 1291.4975 | K51: 15 | S51: =Supuestos!$B$103 -> 178.6442
A52: Allos | B52: ALOS3 BZ | C52: Core | D52: Brasil | E52: BRL | F52: NTM | G52: 3116.1764 | H52: 2315.4438 | I52: 1723.1952 | J52: 949.76836 | K52: 14 | S52: =Supuestos!$B$103 -> 178.6442
A53: Iguatemi | B53: IGTI11 BZ | C53: Core | D53: Brasil | E53: BRL | F53: NTM | G53: 1781.4726 | H53: 1333.7877 | I53: 1112.7717 | J53: 649.87309 | K53: 13 | S53: =Supuestos!$B$103 -> 178.6442
A54: IRSA | B54: IRSA AR | C54: Sensibilidad | D54: Argentina | E54: ARS | F54: NTM | G54: 708864.62 | H54: 460784.73 | I54: 444193.92 | J54: 199514.54 | K54: 1 | R54: Solo 1 analista: consenso no representativo. | S54: =Supuestos!$B$105 -> 0.62236167
A55: Fibra Danhos | B55: DANHOS13 MM | C55: Sensibilidad | D55: México | E55: MXN | F55: NTM | G55: 8336.5205 | H55: 5945.2215 | I55: 5956.3452 | J55: 5316.659 | K55: 9 | R55: Consenso EBIT > EBITDA (distintos sets de analistas). | S55: =Supuestos!$B$104 -> 52.70936

Sheet Notas_Fuentes
A1: Metodología, advertencias y fuentes
A3: Fuente | B3: Bloomberg Terminal vía Excel Add-in (BDP/BDH), extraído el 07-oct-2026 desde el terminal del laboratorio. Tickers: MALLPLAZ CI, PARAUCO CI, CENCOMAL CI, MULT3 BZ, ALOS3 BZ, IGTI11 BZ, IRSA AR, DANHOS13 MM.
A4: Campos | B4: Revenue = SALES_REV_TURN · EBITDA = IS_COMPARABLE_EBITDA (excluye ítems no recurrentes) · D&A = CF_DEPR_AMORT · EBIT = EBITDA − D&A · Net Income = NET_INCOME (controladora) · Book Value = TOT_COMMON_EQY · Deuda neta = NET_DEBT · Minoritarios = MINORITY_NONCONTROLLING_INTEREST · Market Cap = CUR_MKT_CAP histórico (BDH) · Precio = PX_LAST.
A5: Por qué no el EBITDA 'normal' de Bloomberg | B5: El campo EBITDA estándar incluye la revalorización de propiedades para las empresas a valor razonable (ej. Mallplaza FY2025: 1,97 bn vs ingresos 0,65 bn). Por eso se usa el EBITDA comparable, y EBIT se reconstruye como EBITDA − D&A.
A6: Excepciones EBITDA | B6: Se usó EBITDA_ADJUSTED donde el comparable era inconsistente: Cencosud Shopping FY2022 y 1T26; Iguatemi FY2025 y 1T26; IRSA todos los períodos.
A7: LTM | B7: Suma de 3T25, 4T25, 1T26 y 2T26 (verificada contra TRAIL_12M de Bloomberg: Mallplaza revenue 677.333 = 677.334). Balance al 30-jun-2026. IRSA: FY2026 (jul-25 a jun-26).
A8: NTM | B8: Consenso BEst blended forward 12m. Cobertura: Mallplaza 13, Parque Arauco 13, Cencosud 11, Multiplan 15, Allos 14, Iguatemi 13, Fibra Danhos 9, IRSA 1 analista. La tabla principal es LTM.
A9: Moneda | B9: MM CLP con TC fijo del 30-jun-2026 (dólar observado 922,34) y cruces vía USD. Los múltiplos no cambian con el TC.
A10: Allos FY2023 | B10: Revenue de Bloomberg (7.481) incluye efectos de la combinación con brMalls; se reemplazó por 2.804 (S&P Global). P/E FY2023 NM.
A11: IRSA | B11: Ejercicio jul-jun; cifras bajo NIC 29: los múltiplos de cada columna son consistentes, los montos históricos en CLP no son comparables entre años.
A12: Valor razonable | B12: Mallplaza, Parque Arauco, Cencosud Shopping, IRSA y Danhos registran revalorizaciones en resultados → P/E bajo y volátil. Priorizar EV/EBITDA.
A13: v2 — Estructura de capital | B13: La WACC del VF suponía 3,5x DFN/EBITDA desde hoy y para siempre, mientras los flujos del propio modelo desapalancaban la compañía a ~1,0x en 2031. v2 parte en 2,36x, converge a 3,5x en 2031 y registra la caja sobrante como distribución adicional a accionistas, de modo que la deuda de la WACC existe en el plan.
A14: v2 — WACC por período | B14: El D/E converge linealmente desde la estructura actual del modelo original (deuda bruta / market cap = 19,98%) hasta la objetivo (28,52%, 3,5x) en 2031; beta, Ke, Kd y WACC se recalculan cada año. El DCF descuenta con factores acumulados.
... A17: v2 — Chequeos | B17: Switch de política de deuda = 0 reproduce el VF (CLP 1.880). La hoja APV (valor sin deuda + escudos fiscales) debe quedar cerca del DCF.

Sheet TIR_Implicita
A1: TIR implícita en el precio — Mallplaza | B1: NUEVO
A2: Tasa única (nominal CLP) que hace que el DCF dé el precio de mercado. Mismos flujos, valor terminal y puente que la hoja DCF.
A4: Tasa de descuento única (nominal CLP) | C4: 0.076113418 | D4: ← Celda que mueve Buscar objetivo
A5: Equivalente real (UF) | C5: =(1+C4)/(1+Supuestos!$B$34)-1 -> 0.044770308
A6: WACC real terminal del modelo | C6: =WACC!I44 -> 0.071979483
A7: Diferencia vs WACC real (pb) | C7: =(C5-C6)*10000 -> -272.09175
A9: MM CLP | C9: 2S26E | D9: 2027E | E9: 2028E | F9: 2029E | G9: 2030E | H9: 2031E
A10: FCFF (hoja DCF) | C10: =DCF!C22 -> 88513.776 | D10: =DCF!D22 -> 149981.04 | E10: =DCF!E22 -> 213232.85 | F10: =DCF!F22 -> 382939.93 | G10: =DCF!G22 -> 387083.94 | H10: =DCF!H22 -> 409692.86
A11: Fracción de año | C11: =DCF!C26 -> 0.5 | D11: =DCF!D26 -> 1 | E11: =DCF!E26 -> 1 | F11: =DCF!F26 -> 1 | G11: =DCF!G26 -> 1 | H11: =DCF!H26 -> 1
A12: Factor al cierre | C12: =1*(1+$C$4)^-C11 -> 0.96398656 | D12: =C12*(1+$C$4)^-D11 -> 0.89580386 | E12: =D12*(1+$C$4)^-E11 -> 0.83244372 | F12: =E12*(1+$C$4)^-F11 -> 0.77356505 | G12: =F12*(1+$C$4)^-G11 -> 0.71885085 | H12: =G12*(1+$C$4)^-H11 -> 0.66800659
A13: Factor a mitad de período | C13: =1*(1+$C$4)^-(C11/2) -> 0.98182817 | D13: =C12*(1+$C$4)^-(D11/2) -> 0.92927008 | E13: =D12*(1+$C$4)^-(E11/2) -> 0.86354288 | F13: =E12*(1+$C$4)^-(F11/2) -> 0.80246456 | G13: =F12*(1+$C$4)^-(G11/2) -> 0.7457063 | H13: =G12*(1+$C$4)^-(H11/2) -> 0.69296256
A14: VP del FCFF | C14: =C10*C13 -> 86905.318 | D14: =D10*D13 -> 139372.89 | E14: =E10*E13 -> 184135.71 | F14: =F10*F13 -> 307295.72 | G14: =G10*G13 -> 288650.93 | H14: =H10*H13 -> 283901.81
A16: Suma VP FCFF explícito | C16: =SUM(C14:H14) -> 1290262.4
A17: FCFF terminal 2032E (hoja DCF) | C17: =DCF!I22 -> 540637.81
A18: Crecimiento terminal g | C18: =DCF!C39 -> 0.03
A19: Valor terminal al 31-12-2031 | C19: =C17/(C4-C18) -> 11724089
A20: VP del valor terminal | C20: =C19*H12 -> 7831768.6
A21: Enterprise value | C21: =C16+C20 -> 9122031
A22: (−) DFN 30-06-2026 | C22: =DCF!C45 -> -1285740
A23: (−) Minoritarios | C23: =DCF!C46 -> -50841
A24: Valor del patrimonio | C24: =C21+C22+C23 -> 7785450
A25: Acciones (MM) | C25: =DCF!C48 -> 2190
A26: Valor por acción (CLP) | C26: =C24/C25 -> 3555
A27: Precio de mercado 30-09-2026 (CLP) | C27: =DCF!C50 -> 3555
A28: Diferencia (debe ser 0) | C28: =C26-C27 -> 8.1687449e-07
A31: Cómo recalcular (si cambian flujos o precio):
A32: Datos → Análisis de hipótesis → Buscar objetivo · Definir celda: C26 · Con el valor: precio (C27) · Cambiando la celda: C4.
A33: Chequeo: con C4 = WACC del modelo por período el valor da el valor DCF de la hoja DCF (CLP 1.859); aquí se usa una tasa única para todos los períodos y el terminal.
A34: Lectura: quien compra a CLP 3.555 obtiene esta rentabilidad si se cumplen nuestros flujos; es la "WACC implícita en el precio" de las Figuras 21 y 27 (7,61% tasa única; 7,60% con la curva de WACC desplazada).

Sheet TIR_Accionista
A1: TIR del accionista y de la firma · nominal CLP y real (UF) | B1: NUEVO
A2: TIR = retorno de quien compra al precio de mercado si se cumple el modelo (mismos FCFF, distribuciones de la hoja Deuda y valor de salida de la hoja DCF). Se compara con el costo de capital: firma vs WACC; accionista vs Ke.
A3: Convención: flujos a mitad de período desde el 30-06-26 (igual que la hoja DCF). Real (UF) = (1 + nominal)/(1 + π) − 1, con π = Supuestos!B34. Verde = vínculo a otra hoja · azul = dato pegado · negro = fórmula · amarillo = celda nueva.
A5: RESUMEN: qué rentabilidad obtiene quien compra y cómo se compara con su costo de capital
A6: Comprador (precio de compra) · costo de capital de referencia | C6: TIR nominal CLP | D6: TIR real (UF) | E6: Costo de capital nominal | F6: Costo de capital real | G6: Brecha nominal (pb) | H6: Brecha real (pb) | I6: Qué mide
A7: Firma: compra a CLP 3.555 (flujos FCFF) · vs WACC terminal | C7: =C72 -> 0.076113418 | D7: =C73 -> 0.044770308 | E7: =C27 -> 0.10413887 | F7: =D27 -> 0.071979483 | G7: =(C7-E7)*10000 -> -280.2545 | H7: =(D7-F7)*10000 -> -272.09175 | I7: Tasa que iguala el DCF al precio: la WACC que el mercado aplica hoy
A8: Accionista: compra a CLP 3.555, sale a nuestro valor 2031 · vs Ke terminal | C8: =F105 -> -0.018128543 | D8: =F106 -> -0.046726741 | E8: =C28 -> 0.1192629 | F8: =D28 -> 0.086663011 | G8: =(C8-E8)*10000 -> -1373.9144 | H8: =(D8-F8)*10000 -> -1333.8975 | I8: Retorno si el mercado converge a nuestro valor en 2031
A9: Accionista: compra a CLP 3.555, el mercado mantiene la tasa implícita · vs Ke | C9: =I105 -> 0.084849194 | D9: =I106 -> 0.053251645 | E9: =C28 -> 0.1192629 | F9: =D28 -> 0.086663011 | G9: =(C9-E9)*10000 -> -344.13707 | H9: =(D9-F9)*10000 -> -334.11366 | I9: Cota superior: no hay re-rating, la tasa del precio se sostiene
A10: Accionista: compra al precio objetivo (control) · vs Ke terminal | C10: =G105 -> 0.10612654 | D10: =G106 -> 0.073909261 | E10: =C28 -> 0.1192629 | F10: =D28 -> 0.086663011 | G10: =(C10-E10)*10000 -> -131.36363 | H10: =(D10-F10)*10000 -> -127.5375 | I10: Al precio objetivo el retorno queda cerca del Ke
A11: Accionista: compra al valor DCF (control de consistencia) · vs Ke terminal | C11: =H105 -> 0.13491834 | D11: =H106 -> 0.10186246 | E11: =C28 -> 0.1192629 | F11: =D28 -> 0.086663011 | G11: =(C11-E11)*10000 -> 156.55435 | H11: =(D11-F11)*10000 -> 151.99451 | I11: Debería ser ≈ Ke; la diferencia mide la inconsistencia WACC–Ke del modelo
A12: Lectura: brecha = TIR − costo de capital. Negativa = el precio paga menos que el riesgo que se asume (sin margen de seguridad). Firma vs WACC; accionista vs Ke (puntual: terminal).
A13: Nota: la TIR del accionista excluye los flujos de minoritarios y usa la salida con el valor terminal del DCF; la trayectoria de DFN incluye la distribución adicional (hoja Deuda).
A15: A. INSUMOS (vínculos vivos a Supuestos, WACC, DCF, Deuda y Precio_Objetivo)
C16: Nominal CLP | D16: Real (UF)
A17: Inflación de largo plazo Chile π (puente de Fisher nominal ↔ real) | C17: =Supuestos!B34 -> 0.03
A18: Precio de mercado 30-09-26 (CLP por acción) | C18: =Supuestos!B8 -> 3555
A19: Precio objetivo 80% DCF / 20% múltiplos (CLP por acción) | C19: =Precio_Objetivo!B15 -> 2077.1998
A20: Valor DCF por acción (CLP) | C20: =DCF!C49 -> 1858.6534
A21: Acciones en circulación (MM) | C21: =Supuestos!B9 -> 2190
A22: Capitalización bursátil a precio de mercado (MM CLP) | C22: =C18*C21 -> 7785450
A23: (+) Deuda financiera neta 30-06-26 (MM CLP) | C23: =Supuestos!B10 -> 1285740
A24: (+) Minoritarios (libro) (MM CLP) | C24: =Supuestos!B11 -> 50841
A25: Enterprise value de mercado (MM CLP) | C25: =C22+C23+C24 -> 9122031
A26: Crecimiento terminal g | C26: =DCF!C39 -> 0.03 | D26: =Supuestos!B89 -> 0
A27: WACC terminal (costo de capital de la firma) | C27: =WACC!I43 -> 0.10413887 | D27: =WACC!I44 -> 0.071979483
A28: Ke terminal (costo de capital del accionista) | C28: =WACC!I39 -> 0.1192629 | D28: =(1+C28)/(1+$C$17)-1 -> 0.086663011
A29: Kd después de impuestos terminal | C29: =WACC!I42 -> 0.051112373 | D29: =(1+C29)/(1+$C$17)-1 -> 0.020497449
A30: Ke del primer período (2S26E) | C30: =WACC!C39 -> 0.11703304 | D30: =(1+C30)/(1+$C$17)-1 -> 0.084498098
A32: B. FLUJOS POR PERÍODO (MM CLP nominales; vínculos a DCF y Deuda)
A33: MM CLP | C33: =DCF!C4 -> 2S26E | D33: =DCF!D4 -> 2027E | E33: =DCF!E4 -> 2028E | F33: =DCF!F4 -> 2029E | G33: =DCF!G4 -> 2030E | H33: =DCF!H4 -> 2031E | I33: Terminal 2032E | J33: Suma
A34: Fracción de año del período | C34: =DCF!C26 -> 0.5 | D34: =DCF!D26 -> 1 | E34: =DCF!E26 -> 1 | F34: =DCF!F26 -> 1 | G34: =DCF!G26 -> 1 | H34: =DCF!H26 -> 1
A35: Años desde el 30-06-26 al cierre del período | C35: =C34 -> 0.5 | D35: =C35+D34 -> 1.5 | E35: =D35+E34 -> 2.5 | F35: =E35+F34 -> 3.5 | G35: =F35+G34 -> 4.5 | H35: =G35+H34 -> 5.5
A36: Años desde el 30-06-26 a la mitad del período (momento del flujo) | C36: =C35-C34/2 -> 0.25 | D36: =D35-D34/2 -> 1 | E36: =E35-E34/2 -> 2 | F36: =F35-F34/2 -> 3 | G36: =G35-G34/2 -> 4 | H36: =H35-H34/2 -> 5
A37: FCFF (hoja DCF): flujo de la firma | C37: =DCF!C22 -> 88513.776 | D37: =DCF!D22 -> 149981.04 | E37: =DCF!E22 -> 213232.85 | F37: =DCF!F22 -> 382939.93 | G37: =DCF!G22 -> 387083.94 | H37: =DCF!H22 -> 409692.86 | I37: =DCF!I22 -> 540637.81
A38: Dividendos ordinarios al accionista (hoja Deuda) | C38: =Deuda!C16 -> 60107.8 | D38: =Deuda!D16 -> 152015.53 | E38: =Deuda!E16 -> 171060.54 | F38: =Deuda!F16 -> 175310.7 | G38: =Deuda!G16 -> 178542.89 | H38: =Deuda!H16 -> 176457.6
A39: Distribución adicional a accionistas, mantiene la DFN en la trayectoria objetivo (hoja Deuda) | C39: =Deuda!C20 -> 96105.616 | D39: =Deuda!D20 -> 186688.63 | E39: =Deuda!E20 -> 235670.5 | F39: =Deuda!F20 -> 412569.65 | G39: =Deuda!G20 -> 393865.41 | H39: =Deuda!H20 -> 416502.13
A40: Distribuciones totales al accionista (nominal CLP) | C40: =C38+C39 -> 156213.42 | D40: =D38+D39 -> 338704.15 | E40: =E38+E39 -> 406731.04 | F40: =F38+F39 -> 587880.35 | G40: =G38+G39 -> 572408.3 | H40: =H38+H39 -> 592959.73 | J40: =SUM(C40:H40) -> 2654897
A41: Distribuciones totales en CLP reales de jun-26 (deflactadas por π) | C41: =C40/(1+$C$17)^C36 -> 155063.3 | D41: =D40/(1+$C$17)^D36 -> 328838.99 | E41: =E40/(1+$C$17)^E36 -> 383383.01 | F41: =F40/(1+$C$17)^F36 -> 537993.8 | G41: =G40/(1+$C$17)^G36 -> 508577.36 | H41: =H40/(1+$C$17)^H36 -> 511492.27 | J41: =SUM(C41:H41) -> 2425348.7
A42: Distribución por acción (CLP nominales) | C42: =C40/$C$21 -> 71.330327 | D42: =D40/$C$21 -> 154.65943 | E42: =E40/$C$21 -> 185.72194 | F42: =F40/$C$21 -> 268.43852 | G42: =G40/$C$21 -> 261.37365 | H42: =H40/$C$21 -> 270.75787
A44: C. VALOR DE SALIDA DEL ACCIONISTA AL 31-12-2031 (nominal CLP)
A45: Valor terminal de la firma con la WACC terminal y g del modelo (hoja DCF) | C45: =DCF!C41 -> 7292231.8
A46: (−) DFN al cierre de 2031 (hoja Deuda, ya incluye 3,5x EBITDA) | C46: =-Deuda!H21 -> -2742623.2
A47: (−) Minoritarios (libro, igual que el DCF) | C47: =-Supuestos!B11 -> -50841
A48: Valor del patrimonio de salida: nuestro valor (MM CLP) | C48: =SUM(C45:C47) -> 4498767.7
A49: por acción de hoy (CLP, nominal de 2031) | C49: =C48/C21 -> 2054.2318
A50: Valor terminal de la firma si el mercado mantiene la tasa implícita (FCFF 2032E / (TIR firma − g)) | C50: =I37/(C72-C26) -> 11724089
A51: Valor del patrimonio de salida: tasa implícita en el precio (MM CLP) | C51: =C50+C46+C47 -> 8930624.8
A52: por acción de hoy (CLP, nominal de 2031) | C52: =C51/C21 -> 4077.9109
A54: D. TIR DE LA FIRMA AL PRECIO DE MERCADO (flujos FCFF; tasa única nominal CLP)
A55: r tal que VP(FCFF 2S26E–2031E, mitad de período) + VP(FCFF 2032E / (r − g)) = EV de mercado. Resuelta con iteraciones de Newton (sin Buscar objetivo): se recalcula sola.
A56: Iteración (parte de g + 1 punto) | C56: r (iteración) | D56: VP(r) | E56: VP(r) − EV | F56: dVP/dr | G56: r siguiente
A57: Iteración 0 | C57: =C26+0.01 -> 0.04 | D57: =SUMPRODUCT($C$37:$H$37,(1+C57)^(-$C$36:$H$36))+$I$37/(C57-$C$26)*(1+C57)^(-$H$35) -> 45010620 | E57: =D57-$C$25 -> 35888589 | F57: =-SUMPRODUCT($C$37:$H$37,$C$36:$H$36,(1+C57)^(-$C$36:$H$36-1))-$I$37*((1+C57)^(-$H$35)/(C57-$C$26)^2+$H$35*(1+C57)^(-$H$35-1)/(C57-$C$26)) -> -4.5922056e+09 | G57: =C57-E57/F57 -> 0.047815109
A58: Iteración 1 | C58: =G57 -> 0.047815109 | D58: =SUMPRODUCT($C$37:$H$37,(1+C58)^(-$C$36:$H$36))+$I$37/(C58-$C$26)*(1+C58)^(-$H$35) -> 24875315 | E58: =D58-$C$25 -> 15753284 | F58: =-SUMPRODUCT($C$37:$H$37,$C$36:$H$36,(1+C58)^(-$C$36:$H$36-1))-$I$37*((1+C58)^(-$H$35)/(C58-$C$26)^2+$H$35*(1+C58)^(-$H$35-1)/(C58-$C$26)) -> -1.4450005e+09 | G58: =C58-E58/F58 -> 0.058717032
A59: Iteración 2 | C59: =G58 -> 0.058717032 | D59: =SUMPRODUCT($C$37:$H$37,(1+C59)^(-$C$36:$H$36))+$I$37/(C59-$C$26)*(1+C59)^(-$H$35) -> 15113488 | E59: =D59-$C$25 -> 5991456.7 | F59: =-SUMPRODUCT($C$37:$H$37,$C$36:$H$36,(1+C59)^(-$C$36:$H$36-1))-$I$37*((1+C59)^(-$H$35)/(C59-$C$26)^2+$H$35*(1+C59)^(-$H$35-1)/(C59-$C$26)) -> -5.5450894e+08 | G59: =C59-E59/F59 -> 0.06952201
A60: Iteración 3 | C60: =G59 -> 0.06952201 | D60: =SUMPRODUCT($C$37:$H$37,(1+C60)^(-$C$36:$H$36))+$I$37/(C60-$C$26)*(1+C60)^(-$H$35) -> 10767291 | E60: =D60-$C$25 -> 1645259.7 | F60: =-SUMPRODUCT($C$37:$H$37,$C$36:$H$36,(1+C60)^(-$C$36:$H$36-1))-$I$37*((1+C60)^(-$H$35)/(C60-$C$26)^2+$H$35*(1+C60)^(-$H$35-1)/(C60-$C$26)) -> -2.9161786e+08 | G60: =C60-E60/F60 -> 0.075163845
A61: Iteración 4 | C61: =G60 -> 0.075163845 | D61: =SUMPRODUCT($C$37:$H$37,(1+C61)^(-$C$36:$H$36))+$I$37/(C61-$C$26)*(1+C61)^(-$H$35) -> 9329174.3 | E61: =D61-$C$25 -> 207143.25 | F61: =-SUMPRODUCT($C$37:$H$37,$C$36:$H$36,(1+C61)^(-$C$36:$H$36-1))-$I$37*((1+C61)^(-$H$35)/(C61-$C$26)^2+$H$35*(1+C61)^(-$H$35-1)/(C61-$C$26)) -> -2.2277703e+08 | G61: =C61-E61/F61 -> 0.076093668
A62: Iteración 5 | C62: =G61 -> 0.076093668 | D62: =SUMPRODUCT($C$37:$H$37,(1+C62)^(-$C$36:$H$36))+$I$37/(C62-$C$26)*(1+C62)^(-$H$35) -> 9126251.4 | E62: =D62-$C$25 -> 4220.4235 | F62: =-SUMPRODUCT($C$37:$H$37,$C$36:$H$36,(1+C62)^(-$C$36:$H$36-1))-$I$37*((1+C62)^(-$H$35)/(C62-$C$26)^2+$H$35*(1+C62)^(-$H$35-1)/(C62-$C$26)) -> -2.1379079e+08 | G62: =C62-E62/F62 -> 0.076113409
A63: Iteración 6 | C63: =G62 -> 0.076113409 | D63: =SUMPRODUCT($C$37:$H$37,(1+C63)^(-$C$36:$H$36))+$I$37/(C63-$C$26)*(1+C63)^(-$H$35) -> 9122032.8 | E63: =D63-$C$25 -> 1.8255039 | F63: =-SUMPRODUCT($C$37:$H$37,$C$36:$H$36,(1+C63)^(-$C$36:$H$36-1))-$I$37*((1+C63)^(-$H$35)/(C63-$C$26)^2+$H$35*(1+C63)^(-$H$35-1)/(C63-$C$26)) -> -2.1360588e+08 | G63: =C63-E63/F63 -> 0.076113418
A64: Iteración 7 | C64: =G63 -> 0.076113418 | D64: =SUMPRODUCT($C$37:$H$37,(1+C64)^(-$C$36:$H$36))+$I$37/(C64-$C$26)*(1+C64)^(-$H$35) -> 9122031 | E64: =D64-$C$25 -> 3.3713877e-07 | F64: =-SUMPRODUCT($C$37:$H$37,$C$36:$H$36,(1+C64)^(-$C$36:$H$36-1))-$I$37*((1+C64)^(-$H$35)/(C64-$C$26)^2+$H$35*(1+C64)^(-$H$35-1)/(C64-$C$26)) -> -2.136058e+08 | G64: =C64-E64/F64 -> 0.076113418
A65: Iteración 8 | C65: =G64 -> 0.076113418 | D65: =SUMPRODUCT($C$37:$H$37,(1+C65)^(-$C$36:$H$36))+$I$37/(C65-$C$26)*(1+C65)^(-$H$35) -> 9122031 | E65: =D65-$C$25 -> 0 | F65: =-SUMPRODUCT($C$37:$H$37,$C$36:$H$36,(1+C65)^(-$C$36:$H$36-1))-$I$37*((1+C65)^(-$H$35)/(C65-$C$26)^2+$H$35*(1+C65)^(-$H$35-1)/(C65-$C$26)) -> -2.136058e+08 | G65: =C65-E65/F65 -> 0.076113418
A66: Iteración 9 | C66: =G65 -> 0.076113418 | D66: =SUMPRODUCT($C$37:$H$37,(1+C66)^(-$C$36:$H$36))+$I$37/(C66-$C$26)*(1+C66)^(-$H$35) -> 9122031 | E66: =D66-$C$25 -> 0 | F66: =-SUMPRODUCT($C$37:$H$37,$C$36:$H$36,(1+C66)^(-$C$36:$H$36-1))-$I$37*((1+C66)^(-$H$35)/(C66-$C$26)^2+$H$35*(1+C66)^(-$H$35-1)/(C66-$C$26)) -> -2.136058e+08 | G66: =C66-E66/F66 -> 0.076113418
A67: Iteración 10 | C67: =G66 -> 0.076113418 | D67: =SUMPRODUCT($C$37:$H$37,(1+C67)^(-$C$36:$H$36))+$I$37/(C67-$C$26)*(1+C67)^(-$H$35) -> 9122031 | E67: =D67-$C$25 -> 0 | F67: =-SUMPRODUCT($C$37:$H$37,$C$36:$H$36,(1+C67)^(-$C$36:$H$36-1))-$I$37*((1+C67)^(-$H$35)/(C67-$C$26)^2+$H$35*(1+C67)^(-$H$35-1)/(C67-$C$26)) -> -2.136058e+08 | G67: =C67-E67/F67 -> 0.076113418
A68: Iteración 11 | C68: =G67 -> 0.076113418 | D68: =SUMPRODUCT($C$37:$H$37,(1+C68)^(-$C$36:$H$36))+$I$37/(C68-$C$26)*(1+C68)^(-$H$35) -> 9122031 | E68: =D68-$C$25 -> 0 | F68: =-SUMPRODUCT($C$37:$H$37,$C$36:$H$36,(1+C68)^(-$C$36:$H$36-1))-$I$37*((1+C68)^(-$H$35)/(C68-$C$26)^2+$H$35*(1+C68)^(-$H$35-1)/(C68-$C$26)) -> -2.136058e+08 | G68: =C68-E68/F68 -> 0.076113418
A69: Iteración 12 | C69: =G68 -> 0.076113418 | D69: =SUMPRODUCT($C$37:$H$37,(1+C69)^(-$C$36:$H$36))+$I$37/(C69-$C$26)*(1+C69)^(-$H$35) -> 9122031 | E69: =D69-$C$25 -> 0 | F69: =-SUMPRODUCT($C$37:$H$37,$C$36:$H$36,(1+C69)^(-$C$36:$H$36-1))-$I$37*((1+C69)^(-$H$35)/(C69-$C$26)^2+$H$35*(1+C69)^(-$H$35-1)/(C69-$C$26)) -> -2.136058e+08 | G69: =C69-E69/F69 -> 0.076113418
... A71: Iteración 14 | C71: =G70 -> 0.076113418 | D71: =SUMPRODUCT($C$37:$H$37,(1+C71)^(-$C$36:$H$36))+$I$37/(C71-$C$26)*(1+C71)^(-$H$35) -> 9122031 | E71: =D71-$C$25 -> 0 | F71: =-SUMPRODUCT($C$37:$H$37,$C$36:$H$36,(1+C71)^(-$C$36:$H$36-1))-$I$37*((1+C71)^(-$H$35)/(C71-$C$26)^2+$H$35*(1+C71)^(-$H$35-1)/(C71-$C$26)) -> -2.136058e+08 | G71: =C71-E71/F71 -> 0.076113418
A72: TIR de la firma, nominal CLP (tasa única) | C72: =G71 -> 0.076113418
A73: TIR de la firma, real (UF) | C73: =(1+C72)/(1+C17)-1 -> 0.044770308
A74: Chequeo: valor por acción del DCF con esa tasa (CLP); debe igualar el precio de mercado | C74: =(SUMPRODUCT($C$37:$H$37,(1+C72)^(-$C$36:$H$36))+$I$37/(C72-$C$26)*(1+C72)^(-$H$35)-C23-C24)/C21 -> 3555 | D74: =C74-C18 -> 0
A75: Chequeo: diferencia con la hoja TIR_Implicita!C4 (pb); la Figura 27 del informe desplaza toda la curva de WACC (7,60%), aquí es una tasa única (7,61%) | C75: =(C72-TIR_Implicita!C4)*10000 -> 8.375009e-08
A77: E. TIR DEL ACCIONISTA (distribuciones + valor de salida; TIR() trimestral anualizada)
A78: Línea de tiempo trimestral desde el 30-06-26 (t = 0): flujos a mitad de período (trimestres 1, 4, 8, 12, 16, 20) y salida el 31-12-31 (trimestre 22). TIR anual = (1 + TIR trimestral)^4 − 1.
A79: Precio de compra por acción (CLP) | F79: =C18 -> 3555 | G79: =C19 -> 2077.1998 | H79: =C20 -> 1858.6534 | I79: =C18 -> 3555
A80: Trimestre q (MM CLP nominales; compra = flujo negativo) | B80: Años | C80: Distribuciones | D80: Salida: nuestro valor | E80: Salida: tasa implícita | F80: Flujo: compra a precio de mercado | G80: Flujo: compra a precio objetivo | H80: Flujo: compra a valor DCF | I80: Flujo: mercado + salida a tasa implícita
A81: 0 | B81: =A81/4 -> 0 | C81: =SUMPRODUCT((ROUND($C$36:$H$36*4,0)=A81)*$C$40:$H$40) -> 0 | D81: =IF(A81=ROUND($H$35*4,0),$C$48,0) -> 0 | E81: =IF(A81=ROUND($H$35*4,0),$C$51,0) -> 0 | F81: =-F$79*$C$21 -> -7785450 | G81: =-G$79*$C$21 -> -4549067.6 | H81: =-H$79*$C$21 -> -4070450.9 | I81: =-I$79*$C$21 -> -7785450
A82: 1 | B82: =A82/4 -> 0.25 | C82: =SUMPRODUCT((ROUND($C$36:$H$36*4,0)=A82)*$C$40:$H$40) -> 156213.42 | D82: =IF(A82=ROUND($H$35*4,0),$C$48,0) -> 0 | E82: =IF(A82=ROUND($H$35*4,0),$C$51,0) -> 0 | F82: =C82+D82 -> 156213.42 | G82: =C82+D82 -> 156213.42 | H82: =C82+D82 -> 156213.42 | I82: =C82+E82 -> 156213.42
A83: 2 | B83: =A83/4 -> 0.5 | C83: =SUMPRODUCT((ROUND($C$36:$H$36*4,0)=A83)*$C$40:$H$40) -> 0 | D83: =IF(A83=ROUND($H$35*4,0),$C$48,0) -> 0 | E83: =IF(A83=ROUND($H$35*4,0),$C$51,0) -> 0 | F83: =C83+D83 -> 0 | G83: =C83+D83 -> 0 | H83: =C83+D83 -> 0 | I83: =C83+E83 -> 0
A84: 3 | B84: =A84/4 -> 0.75 | C84: =SUMPRODUCT((ROUND($C$36:$H$36*4,0)=A84)*$C$40:$H$40) -> 0 | D84: =IF(A84=ROUND($H$35*4,0),$C$48,0) -> 0 | E84: =IF(A84=ROUND($H$35*4,0),$C$51,0) -> 0 | F84: =C84+D84 -> 0 | G84: =C84+D84 -> 0 | H84: =C84+D84 -> 0 | I84: =C84+E84 -> 0
A85: 4 | B85: =A85/4 -> 1 | C85: =SUMPRODUCT((ROUND($C$36:$H$36*4,0)=A85)*$C$40:$H$40) -> 338704.15 | D85: =IF(A85=ROUND($H$35*4,0),$C$48,0) -> 0 | E85: =IF(A85=ROUND($H$35*4,0),$C$51,0) -> 0 | F85: =C85+D85 -> 338704.15 | G85: =C85+D85 -> 338704.15 | H85: =C85+D85 -> 338704.15 | I85: =C85+E85 -> 338704.15
A86: 5 | B86: =A86/4 -> 1.25 | C86: =SUMPRODUCT((ROUND($C$36:$H$36*4,0)=A86)*$C$40:$H$40) -> 0 | D86: =IF(A86=ROUND($H$35*4,0),$C$48,0) -> 0 | E86: =IF(A86=ROUND($H$35*4,0),$C$51,0) -> 0 | F86: =C86+D86 -> 0 | G86: =C86+D86 -> 0 | H86: =C86+D86 -> 0 | I86: =C86+E86 -> 0
A87: 6 | B87: =A87/4 -> 1.5 | C87: =SUMPRODUCT((ROUND($C$36:$H$36*4,0)=A87)*$C$40:$H$40) -> 0 | D87: =IF(A87=ROUND($H$35*4,0),$C$48,0) -> 0 | E87: =IF(A87=ROUND($H$35*4,0),$C$51,0) -> 0 | F87: =C87+D87 -> 0 | G87: =C87+D87 -> 0 | H87: =C87+D87 -> 0 | I87: =C87+E87 -> 0
A88: 7 | B88: =A88/4 -> 1.75 | C88: =SUMPRODUCT((ROUND($C$36:$H$36*4,0)=A88)*$C$40:$H$40) -> 0 | D88: =IF(A88=ROUND($H$35*4,0),$C$48,0) -> 0 | E88: =IF(A88=ROUND($H$35*4,0),$C$51,0) -> 0 | F88: =C88+D88 -> 0 | G88: =C88+D88 -> 0 | H88: =C88+D88 -> 0 | I88: =C88+E88 -> 0
A89: 8 | B89: =A89/4 -> 2 | C89: =SUMPRODUCT((ROUND($C$36:$H$36*4,0)=A89)*$C$40:$H$40) -> 406731.04 | D89: =IF(A89=ROUND($H$35*4,0),$C$48,0) -> 0 | E89: =IF(A89=ROUND($H$35*4,0),$C$51,0) -> 0 | F89: =C89+D89 -> 406731.04 | G89: =C89+D89 -> 406731.04 | H89: =C89+D89 -> 406731.04 | I89: =C89+E89 -> 406731.04
A90: 9 | B90: =A90/4 -> 2.25 | C90: =SUMPRODUCT((ROUND($C$36:$H$36*4,0)=A90)*$C$40:$H$40) -> 0 | D90: =IF(A90=ROUND($H$35*4,0),$C$48,0) -> 0 | E90: =IF(A90=ROUND($H$35*4,0),$C$51,0) -> 0 | F90: =C90+D90 -> 0 | G90: =C90+D90 -> 0 | H90: =C90+D90 -> 0 | I90: =C90+E90 -> 0
A91: 10 | B91: =A91/4 -> 2.5 | C91: =SUMPRODUCT((ROUND($C$36:$H$36*4,0)=A91)*$C$40:$H$40) -> 0 | D91: =IF(A91=ROUND($H$35*4,0),$C$48,0) -> 0 | E91: =IF(A91=ROUND($H$35*4,0),$C$51,0) -> 0 | F91: =C91+D91 -> 0 | G91: =C91+D91 -> 0 | H91: =C91+D91 -> 0 | I91: =C91+E91 -> 0
A92: 11 | B92: =A92/4 -> 2.75 | C92: =SUMPRODUCT((ROUND($C$36:$H$36*4,0)=A92)*$C$40:$H$40) -> 0 | D92: =IF(A92=ROUND($H$35*4,0),$C$48,0) -> 0 | E92: =IF(A92=ROUND($H$35*4,0),$C$51,0) -> 0 | F92: =C92+D92 -> 0 | G92: =C92+D92 -> 0 | H92: =C92+D92 -> 0 | I92: =C92+E92 -> 0
A93: 12 | B93: =A93/4 -> 3 | C93: =SUMPRODUCT((ROUND($C$36:$H$36*4,0)=A93)*$C$40:$H$40) -> 587880.35 | D93: =IF(A93=ROUND($H$35*4,0),$C$48,0) -> 0 | E93: =IF(A93=ROUND($H$35*4,0),$C$51,0) -> 0 | F93: =C93+D93 -> 587880.35 | G93: =C93+D93 -> 587880.35 | H93: =C93+D93 -> 587880.35 | I93: =C93+E93 -> 587880.35
... A103: 22 | B103: =A103/4 -> 5.5 | C103: =SUMPRODUCT((ROUND($C$36:$H$36*4,0)=A103)*$C$40:$H$40) -> 0 | D103: =IF(A103=ROUND($H$35*4,0),$C$48,0) -> 4498767.7 | E103: =IF(A103=ROUND($H$35*4,0),$C$51,0) -> 8930624.8 | F103: =C103+D103 -> 4498767.7 | G103: =C103+D103 -> 4498767.7 | H103: =C103+D103 -> 4498767.7 | I103: =C103+E103 -> 8930624.8
A104: TIR trimestral (función TIR de Excel) | F104: =IRR(F81:F103,0.01) -> -0.0045632761 | G104: =IRR(G81:G103,0.01) -> 0.025536691 | H104: =IRR(H81:H103,0.01) -> 0.032146046 | I104: =IRR(I81:I103,0.01) -> 0.02056893
A105: TIR del accionista, nominal CLP (anual) | F105: =(1+F104)^4-1 -> -0.018128543 | G105: =(1+G104)^4-1 -> 0.10612654 | H105: =(1+H104)^4-1 -> 0.13491834 | I105: =(1+I104)^4-1 -> 0.084849194
A106: TIR del accionista, real (UF) (anual) | F106: =(1+F105)/(1+$C$17)-1 -> -0.046726741 | G106: =(1+G105)/(1+$C$17)-1 -> 0.073909261 | H106: =(1+H105)/(1+$C$17)-1 -> 0.10186246 | I106: =(1+I105)/(1+$C$17)-1 -> 0.053251645
A107: Chequeo: VP de los flujos a la TIR trimestral (debe ser 0) | F107: =NPV(F104,F82:F103)+F81 -> 3.3192337e-06 | G107: =NPV(G104,G82:G103)+G81 -> 5.653128e-07 | H107: =NPV(H104,H82:H103)+H81 -> 0 | I107: =NPV(I104,I82:I103)+I81 -> 0
A110: F. TIR DE LA FIRMA POR ESCENARIO (mismo EV de mercado; FCFF de la réplica del DCF v2)
A111: Bear/bull: FCFF pegados desde la réplica del DCF (escenarios_dcf.py; azul; no son fórmulas, no hay hoja de escenarios en el modelo). Base: vínculo vivo a DCF. Cada escenario se compara con su propia WACC terminal.
A113: Escenario (TIR de la firma al precio de mercado) | C113: TIR nominal | D113: TIR real (UF) | E113: WACC terminal nominal | F113: WACC terminal real | G113: Brecha nominal (pb) | H113: Brecha real (pb) | I113: DCF de la réplica (CLP)
A114: Bear (réplica) | C114: =C126 -> 0.069535606 | D114: =(1+C114)/(1+$C$17)-1 -> 0.038384083 | E114: =C123 -> 0.11413887 | F114: =(1+E114)/(1+$C$17)-1 -> 0.081688221 | G114: =(C114-E114)*10000 -> -446.03262 | H114: =(D114-F114)*10000 -> -433.04138 | I114: 1189.9543
A115: Base (modelo v4) | C115: =C136 -> 0.076113418 | D115: =(1+C115)/(1+$C$17)-1 -> 0.044770308 | E115: =C133 -> 0.10413887 | F115: =(1+E115)/(1+$C$17)-1 -> 0.071979483 | G115: =(C115-E115)*10000 -> -280.2545 | H115: =(D115-F115)*10000 -> -272.09175 | I115: 1858.6534
A116: Bull (réplica) | C116: =C146 -> 0.085089881 | D116: =(1+C116)/(1+$C$17)-1 -> 0.053485322 | E116: =C143 -> 0.094138867 | F116: =(1+E116)/(1+$C$17)-1 -> 0.062270745 | G116: =(C116-E116)*10000 -> -90.489861 | H116: =(D116-F116)*10000 -> -87.854234 | I116: 2906.2099
A119: Escenario · Bear (todo sale mal): WACC +100 pb en todos los períodos y cada palanca operacional en su mínimo histórico (margen 75,8%, ocupación, arriendo y ventas en mismas tiendas, visitas, capex de mantención 6,6%)
A120: FCFF (MM CLP nominales) 2S26E–2031E y terminal 2032E | C120: 70086.35 | D120: 104682.48 | E120: 157141.05 | F120: 319372.78 | G120: 319181.23 | H120: 335774.25 | I120: 461950.84
A121: g terminal nominal | C121: 0.03
...

Sheet TIR_Proyecto
A1: TIR del proyecto nuevo (un m² de expansión) — NUEVO
A2: Flujo por m² de una cohorte (misma mecánica que la hoja Expansion y el valor terminal del DCF), en pesos reales de 2026. TIR nominal = (1 + real)(1 + π) − 1. Todo con fórmulas vivas sobre Supuestos, Expansion, WACC y DCF.
A4: Inflación de largo plazo π | B4: =Supuestos!B34 -> 0.03
A5: Tasa de impuesto de largo plazo | B5: =Supuestos!B59 -> 0.27
A6: D&A / ingresos | B6: =Supuestos!B57 -> 0.0070364208
A7: Mantención + TI / ingresos | B7: =Supuestos!B58 -> 0.055
A8: Capital de trabajo / ingresos | B8: =Supuestos!B85*Supuestos!B84 -> 0.15604341
A9: Margen EBITDA de la expansión | B9: =Expansion!C9 -> 0.80655699
A10: Costo por m² 2026 (CLP, real) | B10: =Expansion!C7*1000000 -> 3318197.4
A11: Capex pagado dos años antes de abrir | B11: =Supuestos!B68 -> 0.5
A12: Rampa de ingresos: año de apertura | B12: =Supuestos!B78 -> 0.35
A13: Rampa: segundo año | B13: =Supuestos!B79 -> 0.9
A14: Rampa: tercer año en adelante | B14: =Supuestos!B80 -> 1
A15: WACC nominal terminal | B15: =DCF!I25 -> 0.10413887
A16: WACC real terminal | B16: =WACC!I44 -> 0.071979483
A18: Resultado | B18: Real (UF) | C18: Nominal CLP | D18: Brecha vs WACC real / nominal (pb)
A19: TIR del proyecto (con mantención y capital de trabajo) | B19: =O84 -> 0.048361267 | C19: =(1+B19)*(1+B4)-1 -> 0.079812105 | D19: =(B19-B16)*10000 -> -236.18216 | E19: =(C19-B15)*10000 -> -243.26762
A20: Variante como el RONIC (sin mantención ni capital de trabajo) | B20: =T84 -> 0.054144076 | C20: =(1+B20)*(1+B4)-1 -> 0.085768398 | D20: =(B20-B16)*10000 -> -178.35407 | E20: =(C20-B15)*10000 -> -183.70469
A21: RONIC real de la hoja Expansion (yield × (1 − t)) | B21: =Expansion!C38 -> 0.053042034
A22: Yield on cost de la hoja Expansion (EBITDA maduro / costo) | B22: =Expansion!C37 -> 0.072660321
A24: Ingreso por m² de la expansión (hoja Expansion)
A25: Año | B25: Índice IPC (2026 = 1) | C25: Ingreso por m² nominal (CLP) | D25: Ingreso por m² real 2026 (CLP)
A26: 2026 | B26: =Expansion!C6 -> 1 | C26: =Expansion!C8 -> 298926.54 | D26: =C26/B26 -> 298926.54
A27: 2027 | B27: =Expansion!D6 -> 1.03 | C27: =Expansion!D8 -> 317620.12 | D27: =C27/B27 -> 308369.05
A28: 2028 | B28: =Expansion!E6 -> 1.0609 | C28: =Expansion!E8 -> 333824.97 | D28: =C28/B28 -> 314662.05
A29: 2029 | B29: =Expansion!F6 -> 1.092727 | C29: =Expansion!F8 -> 349220.16 | D29: =C29/B29 -> 319585.92
A30: 2030 | B30: =Expansion!G6 -> 1.1255088 | C30: =Expansion!G8 -> 363261.73 | D30: =C30/B30 -> 322753.34
A31: 2031 | B31: =Expansion!H6 -> 1.1592741 | C31: =Expansion!H8 -> 376890.49 | D31: =C31/B31 -> 325109.05
A34: Año | B34: Factor de rampa | C34: Ingreso real por m² | D34: EBITDA | E34: EBIT | F34: NOPAT | G34: Δ capital de trabajo | H34: Capex | I34: FCFF real (con mant. y CT) | J34: FCFF real (como RONIC) | L34: Iteración (con mant. y CT) | M34: Mínimo | N34: Máximo | O34: Punto medio | P34: VNA al punto medio | Q34: Iteración (como el RONIC) | R34: Mínimo | S34: Máximo | T34: Punto medio | U34: VNA al punto medio
A35: 2027 | B35: =IF(A35<2029,0,IF(A35=2029,$B$12,IF(A35=2030,$B$13,$B$14))) -> 0 | C35: =INDEX($D$26:$D$31,MIN(A35-2025,6))*B35 -> 0 | D35: =C35*$B$9 -> 0 | E35: =D35-C35*$B$6 -> 0 | F35: =E35*(1-$B$5) -> 0 | G35: =$B$8*(C35-0/(1+$B$4)) -> 0 | H35: =IF(A35=2027,$B$11,IF(A35=2028,1-$B$11,0))*$B$10 -> 1659098.7 | I35: =F35+C35*$B$6-C35*$B$7-G35-H35 -> -1659098.7 | J35: =F35+C35*$B$6-H35 -> -1659098.7 | L35: 1 | M35: 0 | N35: 0.2 | O35: =(M35+N35)/2 -> 0.1 | P35: =NPV(O35,I$35:I$194) -> -1584465.3 | Q35: 1 | R35: 0 | S35: 0.2 | T35: =(R35+S35)/2 -> 0.1 | U35: =NPV(T35,J$35:J$194) -> -1400953.2
A36: 2028 | B36: =IF(A36<2029,0,IF(A36=2029,$B$12,IF(A36=2030,$B$13,$B$14))) -> 0 | C36: =INDEX($D$26:$D$31,MIN(A36-2025,6))*B36 -> 0 | D36: =C36*$B$9 -> 0 | E36: =D36-C36*$B$6 -> 0 | F36: =E36*(1-$B$5) -> 0 | G36: =$B$8*(C36-C35/(1+$B$4)) -> 0 | H36: =IF(A36=2027,$B$11,IF(A36=2028,1-$B$11,0))*$B$10 -> 1659098.7 | I36: =F36+C36*$B$6-C36*$B$7-G36-H36 -> -1659098.7 | J36: =F36+C36*$B$6-H36 -> -1659098.7 | L36: 2 | M36: =IF(P35>0,O35,M35) -> 0 | N36: =IF(P35>0,N35,O35) -> 0.1 | O36: =(M36+N36)/2 -> 0.05 | P36: =NPV(O36,I$35:I$194) -> -107844.8 | Q36: 2 | R36: =IF(U35>0,T35,R35) -> 0 | S36: =IF(U35>0,S35,T35) -> 0.1 | T36: =(R36+S36)/2 -> 0.05 | U36: =NPV(T36,J$35:J$194) -> 271520.9
A37: 2029 | B37: =IF(A37<2029,0,IF(A37=2029,$B$12,IF(A37=2030,$B$13,$B$14))) -> 0.35 | C37: =INDEX($D$26:$D$31,MIN(A37-2025,6))*B37 -> 111855.07 | D37: =C37*$B$9 -> 90217.491 | E37: =D37-C37*$B$6 -> 89430.431 | F37: =E37*(1-$B$5) -> 65284.215 | G37: =$B$8*(C37-C36/(1+$B$4)) -> 17454.247 | H37: =IF(A37=2027,$B$11,IF(A37=2028,1-$B$11,0))*$B$10 -> 0 | I37: =F37+C37*$B$6-C37*$B$7-G37-H37 -> 42464.999 | J37: =F37+C37*$B$6-H37 -> 66071.274 | L37: 3 | M37: =IF(P36>0,O36,M36) -> 0 | N37: =IF(P36>0,N36,O36) -> 0.05 | O37: =(M37+N37)/2 -> 0.025 | P37: =NPV(O37,I$35:I$194) -> 3076923.4 | Q37: 3 | R37: =IF(U36>0,T36,R36) -> 0.05 | S37: =IF(U36>0,S36,T36) -> 0.1 | T37: =(R37+S37)/2 -> 0.075 | U37: =NPV(T37,J$35:J$194) -> -880075.15
A38: 2030 | B38: =IF(A38<2029,0,IF(A38=2029,$B$12,IF(A38=2030,$B$13,$B$14))) -> 0.9 | C38: =INDEX($D$26:$D$31,MIN(A38-2025,6))*B38 -> 290478.01 | D38: =C38*$B$9 -> 234287.07 | E38: =D38-C38*$B$6 -> 232243.14 | F38: =E38*(1-$B$5) -> 169537.49 | G38: =$B$8*(C38-C37/(1+$B$4)) -> 28381.307 | H38: =IF(A38=2027,$B$11,IF(A38=2028,1-$B$11,0))*$B$10 -> 0 | I38: =F38+C38*$B$6-C38*$B$7-G38-H38 -> 127223.82 | J38: =F38+C38*$B$6-H38 -> 171581.42 | L38: 4 | M38: =IF(P37>0,O37,M37) -> 0.025 | N38: =IF(P37>0,N37,O37) -> 0.05 | O38: =(M38+N38)/2 -> 0.0375 | P38: =NPV(O38,I$35:I$194) -> 964516.58 | Q38: 4 | R38: =IF(U37>0,T37,R37) -> 0.05 | S38: =IF(U37>0,S37,T37) -> 0.075 | T38: =(R38+S38)/2 -> 0.0625 | U38: =NPV(T38,J$35:J$194) -> -430664.89
A39: 2031 | B39: =IF(A39<2029,0,IF(A39=2029,$B$12,IF(A39=2030,$B$13,$B$14))) -> 1 | C39: =INDEX($D$26:$D$31,MIN(A39-2025,6))*B39 -> 325109.05 | D39: =C39*$B$9 -> 262218.98 | E39: =D39-C39*$B$6 -> 259931.37 | F39: =E39*(1-$B$5) -> 189749.9 | G39: =$B$8*(C39-C38/(1+$B$4)) -> 6724.1552 | H39: =IF(A39=2027,$B$11,IF(A39=2028,1-$B$11,0))*$B$10 -> 0 | I39: =F39+C39*$B$6-C39*$B$7-G39-H39 -> 167432.35 | J39: =F39+C39*$B$6-H39 -> 192037.51 | L39: 5 | M39: =IF(P38>0,O38,M38) -> 0.0375 | N39: =IF(P38>0,N38,O38) -> 0.05 | O39: =(M39+N39)/2 -> 0.04375 | P39: =NPV(O39,I$35:I$194) -> 349287.84 | Q39: 5 | R39: =IF(U38>0,T38,R38) -> 0.05 | S39: =IF(U38>0,S38,T38) -> 0.0625 | T39: =(R39+S39)/2 -> 0.05625 | U39: =NPV(T39,J$35:J$194) -> -121644.93
A40: 2032 | B40: =IF(A40<2029,0,IF(A40=2029,$B$12,IF(A40=2030,$B$13,$B$14))) -> 1 | C40: =INDEX($D$26:$D$31,MIN(A40-2025,6))*B40 -> 325109.05 | D40: =C40*$B$9 -> 262218.98 | E40: =D40-C40*$B$6 -> 259931.37 | F40: =E40*(1-$B$5) -> 189749.9 | G40: =$B$8*(C40-C39/(1+$B$4)) -> 1477.6056 | H40: =IF(A40=2027,$B$11,IF(A40=2028,1-$B$11,0))*$B$10 -> 0 | I40: =F40+C40*$B$6-C40*$B$7-G40-H40 -> 172678.9 | J40: =F40+C40*$B$6-H40 -> 192037.51 | L40: 6 | M40: =IF(P39>0,O39,M39) -> 0.04375 | N40: =IF(P39>0,N39,O39) -> 0.05 | O40: =(M40+N40)/2 -> 0.046875 | P40: =NPV(O40,I$35:I$194) -> 104721.32 | Q40: 6 | R40: =IF(U39>0,T39,R39) -> 0.05 | S40: =IF(U39>0,S39,T39) -> 0.05625 | T40: =(R40+S40)/2 -> 0.053125 | U40: =NPV(T40,J$35:J$194) -> 62589.187
A41: 2033 | B41: =IF(A41<2029,0,IF(A41=2029,$B$12,IF(A41=2030,$B$13,$B$14))) -> 1 | C41: =INDEX($D$26:$D$31,MIN(A41-2025,6))*B41 -> 325109.05 | D41: =C41*$B$9 -> 262218.98 | E41: =D41-C41*$B$6 -> 259931.37 | F41: =E41*(1-$B$5) -> 189749.9 | G41: =$B$8*(C41-C40/(1+$B$4)) -> 1477.6056 | H41: =IF(A41=2027,$B$11,IF(A41=2028,1-$B$11,0))*$B$10 -> 0 | I41: =F41+C41*$B$6-C41*$B$7-G41-H41 -> 172678.9 | J41: =F41+C41*$B$6-H41 -> 192037.51 | L41: 7 | M41: =IF(P40>0,O40,M40) -> 0.046875 | N41: =IF(P40>0,N40,O40) -> 0.05 | O41: =(M41+N41)/2 -> 0.0484375 | P41: =NPV(O41,I$35:I$194) -> -5188.5614 | Q41: 7 | R41: =IF(U40>0,T40,R40) -> 0.053125 | S41: =IF(U40>0,S40,T40) -> 0.05625 | T41: =(R41+S41)/2 -> 0.0546875 | U41: =NPV(T41,J$35:J$194) -> -32354.895
A42: 2034 | B42: =IF(A42<2029,0,IF(A42=2029,$B$12,IF(A42=2030,$B$13,$B$14))) -> 1 | C42: =INDEX($D$26:$D$31,MIN(A42-2025,6))*B42 -> 325109.05 | D42: =C42*$B$9 -> 262218.98 | E42: =D42-C42*$B$6 -> 259931.37 | F42: =E42*(1-$B$5) -> 189749.9 | G42: =$B$8*(C42-C41/(1+$B$4)) -> 1477.6056 | H42: =IF(A42=2027,$B$11,IF(A42=2028,1-$B$11,0))*$B$10 -> 0 | I42: =F42+C42*$B$6-C42*$B$7-G42-H42 -> 172678.9 | J42: =F42+C42*$B$6-H42 -> 192037.51 | L42: 8 | M42: =IF(P41>0,O41,M41) -> 0.046875 | N42: =IF(P41>0,N41,O41) -> 0.0484375 | O42: =(M42+N42)/2 -> 0.04765625 | P42: =NPV(O42,I$35:I$194) -> 48816.551 | Q42: 8 | R42: =IF(U41>0,T41,R41) -> 0.053125 | S42: =IF(U41>0,S41,T41) -> 0.0546875 | T42: =(R42+S42)/2 -> 0.05390625 | U42: =NPV(T42,J$35:J$194) -> 14380.117
A43: 2035 | B43: =IF(A43<2029,0,IF(A43=2029,$B$12,IF(A43=2030,$B$13,$B$14))) -> 1 | C43: =INDEX($D$26:$D$31,MIN(A43-2025,6))*B43 -> 325109.05 | D43: =C43*$B$9 -> 262218.98 | E43: =D43-C43*$B$6 -> 259931.37 | F43: =E43*(1-$B$5) -> 189749.9 | G43: =$B$8*(C43-C42/(1+$B$4)) -> 1477.6056 | H43: =IF(A43=2027,$B$11,IF(A43=2028,1-$B$11,0))*$B$10 -> 0 | I43: =F43+C43*$B$6-C43*$B$7-G43-H43 -> 172678.9 | J43: =F43+C43*$B$6-H43 -> 192037.51 | L43: 9 | M43: =IF(P42>0,O42,M42) -> 0.04765625 | N43: =IF(P42>0,N42,O42) -> 0.0484375 | O43: =(M43+N43)/2 -> 0.048046875 | P43: =NPV(O43,I$35:I$194) -> 21582.131 | Q43: 9 | R43: =IF(U42>0,T42,R42) -> 0.05390625 | S43: =IF(U42>0,S42,T42) -> 0.0546875 | T43: =(R43+S43)/2 -> 0.054296875 | U43: =NPV(T43,J$35:J$194) -> -9167.732
A44: 2036 | B44: =IF(A44<2029,0,IF(A44=2029,$B$12,IF(A44=2030,$B$13,$B$14))) -> 1 | C44: =INDEX($D$26:$D$31,MIN(A44-2025,6))*B44 -> 325109.05 | D44: =C44*$B$9 -> 262218.98 | E44: =D44-C44*$B$6 -> 259931.37 | F44: =E44*(1-$B$5) -> 189749.9 | G44: =$B$8*(C44-C43/(1+$B$4)) -> 1477.6056 | H44: =IF(A44=2027,$B$11,IF(A44=2028,1-$B$11,0))*$B$10 -> 0 | I44: =F44+C44*$B$6-C44*$B$7-G44-H44 -> 172678.9 | J44: =F44+C44*$B$6-H44 -> 192037.51 | L44: 10 | M44: =IF(P43>0,O43,M43) -> 0.048046875 | N44: =IF(P43>0,N43,O43) -> 0.0484375 | O44: =(M44+N44)/2 -> 0.048242187 | P44: =NPV(O44,I$35:I$194) -> 8139.5 | Q44: 10 | R44: =IF(U43>0,T43,R43) -> 0.05390625 | S44: =IF(U43>0,S43,T43) -> 0.054296875 | T44: =(R44+S44)/2 -> 0.054101562 | U44: =NPV(T44,J$35:J$194) -> 2560.6257
A45: 2037 | B45: =IF(A45<2029,0,IF(A45=2029,$B$12,IF(A45=2030,$B$13,$B$14))) -> 1 | C45: =INDEX($D$26:$D$31,MIN(A45-2025,6))*B45 -> 325109.05 | D45: =C45*$B$9 -> 262218.98 | E45: =D45-C45*$B$6 -> 259931.37 | F45: =E45*(1-$B$5) -> 189749.9 | G45: =$B$8*(C45-C44/(1+$B$4)) -> 1477.6056 | H45: =IF(A45=2027,$B$11,IF(A45=2028,1-$B$11,0))*$B$10 -> 0 | I45: =F45+C45*$B$6-C45*$B$7-G45-H45 -> 172678.9 | J45: =F45+C45*$B$6-H45 -> 192037.51 | L45: 11 | M45: =IF(P44>0,O44,M44) -> 0.048242187 | N45: =IF(P44>0,N44,O44) -> 0.0484375 | O45: =(M45+N45)/2 -> 0.048339844 | P45: =NPV(O45,I$35:I$194) -> 1461.2321 | Q45: 11 | R45: =IF(U44>0,T44,R44) -> 0.054101562 | S45: =IF(U44>0,S44,T44) -> 0.054296875 | T45: =(R45+S45)/2 -> 0.054199219 | U45: =NPV(T45,J$35:J$194) -> -3314.8842
A46: 2038 | B46: =IF(A46<2029,0,IF(A46=2029,$B$12,IF(A46=2030,$B$13,$B$14))) -> 1 | C46: =INDEX($D$26:$D$31,MIN(A46-2025,6))*B46 -> 325109.05 | D46: =C46*$B$9 -> 262218.98 | E46: =D46-C46*$B$6 -> 259931.37 | F46: =E46*(1-$B$5) -> 189749.9 | G46: =$B$8*(C46-C45/(1+$B$4)) -> 1477.6056 | H46: =IF(A46=2027,$B$11,IF(A46=2028,1-$B$11,0))*$B$10 -> 0 | I46: =F46+C46*$B$6-C46*$B$7-G46-H46 -> 172678.9 | J46: =F46+C46*$B$6-H46 -> 192037.51 | L46: 12 | M46: =IF(P45>0,O45,M45) -> 0.048339844 | N46: =IF(P45>0,N45,O45) -> 0.0484375 | O46: =(M46+N46)/2 -> 0.048388672 | P46: =NPV(O46,I$35:I$194) -> -1867.2135 | Q46: 12 | R46: =IF(U45>0,T45,R45) -> 0.054101562 | S46: =IF(U45>0,S45,T45) -> 0.054199219 | T46: =(R46+S46)/2 -> 0.054150391 | U46: =NPV(T46,J$35:J$194) -> -379.96954
A47: 2039 | B47: =IF(A47<2029,0,IF(A47=2029,$B$12,IF(A47=2030,$B$13,$B$14))) -> 1 | C47: =INDEX($D$26:$D$31,MIN(A47-2025,6))*B47 -> 325109.05 | D47: =C47*$B$9 -> 262218.98 | E47: =D47-C47*$B$6 -> 259931.37 | F47: =E47*(1-$B$5) -> 189749.9 | G47: =$B$8*(C47-C46/(1+$B$4)) -> 1477.6056 | H47: =IF(A47=2027,$B$11,IF(A47=2028,1-$B$11,0))*$B$10 -> 0 | I47: =F47+C47*$B$6-C47*$B$7-G47-H47 -> 172678.9 | J47: =F47+C47*$B$6-H47 -> 192037.51 | L47: 13 | M47: =IF(P46>0,O46,M46) -> 0.048339844 | N47: =IF(P46>0,N46,O46) -> 0.048388672 | O47: =(M47+N47)/2 -> 0.048364258 | P47: =NPV(O47,I$35:I$194) -> -203.87924 | Q47: 13 | R47: =IF(U46>0,T46,R46) -> 0.054101562 | S47: =IF(U46>0,S46,T46) -> 0.054150391 | T47: =(R47+S47)/2 -> 0.054125977 | U47: =NPV(T47,J$35:J$194) -> 1089.6171
... A84: 2076 | B84: =IF(A84<2029,0,IF(A84=2029,$B$12,IF(A84=2030,$B$13,$B$14))) -> 1 | C84: =INDEX($D$26:$D$31,MIN(A84-2025,6))*B84 -> 325109.05 | D84: =C84*$B$9 -> 262218.98 | E84: =D84-C84*$B$6 -> 259931.37 | F84: =E84*(1-$B$5) -> 189749.9 | G84: =$B$8*(C84-C83/(1+$B$4)) -> 1477.6056 | H84: =IF(A84=2027,$B$11,IF(A84=2028,1-$B$11,0))*$B$10 -> 0 | I84: =F84+C84*$B$6-C84*$B$7-G84-H84 -> 172678.9 | J84: =F84+C84*$B$6-H84 -> 192037.51 | L84: 50 | M84: =IF(P83>0,O83,M83) -> 0.048361267 | N84: =IF(P83>0,N83,O83) -> 0.048361267 | O84: =(M84+N84)/2 -> 0.048361267 | P84: =NPV(O84,I$35:I$194) -> -1.4418859e-08 | Q84: 50 | R84: =IF(U83>0,T83,R83) -> 0.054144076 | S84: =IF(U83>0,S83,T83) -> 0.054144076 | T84: =(R84+S84)/2 -> 0.054144076 | U84: =NPV(T84,J$35:J$194) -> -2.3579645e-09
A85: 2077 | B85: =IF(A85<2029,0,IF(A85=2029,$B$12,IF(A85=2030,$B$13,$B$14))) -> 1 | C85: =INDEX($D$26:$D$31,MIN(A85-2025,6))*B85 -> 325109.05 | D85: =C85*$B$9 -> 262218.98 | E85: =D85-C85*$B$6 -> 259931.37 | F85: =E85*(1-$B$5) -> 189749.9 | G85: =$B$8*(C85-C84/(1+$B$4)) -> 1477.6056 | H85: =IF(A85=2027,$B$11,IF(A85=2028,1-$B$11,0))*$B$10 -> 0 | I85: =F85+C85*$B$6-C85*$B$7-G85-H85 -> 172678.9 | J85: =F85+C85*$B$6-H85 -> 192037.51
A86: 2078 | B86: =IF(A86<2029,0,IF(A86=2029,$B$12,IF(A86=2030,$B$13,$B$14))) -> 1 | C86: =INDEX($D$26:$D$31,MIN(A86-2025,6))*B86 -> 325109.05 | D86: =C86*$B$9 -> 262218.98 | E86: =D86-C86*$B$6 -> 259931.37 | F86: =E86*(1-$B$5) -> 189749.9 | G86: =$B$8*(C86-C85/(1+$B$4)) -> 1477.6056 | H86: =IF(A86=2027,$B$11,IF(A86=2028,1-$B$11,0))*$B$10 -> 0 | I86: =F86+C86*$B$6-C86*$B$7-G86-H86 -> 172678.9 | J86: =F86+C86*$B$6-H86 -> 192037.51
A87: 2079 | B87: =IF(A87<2029,0,IF(A87=2029,$B$12,IF(A87=2030,$B$13,$B$14))) -> 1 | C87: =INDEX($D$26:$D$31,MIN(A87-2025,6))*B87 -> 325109.05 | D87: =C87*$B$9 -> 262218.98 | E87: =D87-C87*$B$6 -> 259931.37 | F87: =E87*(1-$B$5) -> 189749.9 | G87: =$B$8*(C87-C86/(1+$B$4)) -> 1477.6056 | H87: =IF(A87=2027,$B$11,IF(A87=2028,1-$B$11,0))*$B$10 -> 0 | I87: =F87+C87*$B$6-C87*$B$7-G87-H87 -> 172678.9 | J87: =F87+C87*$B$6-H87 -> 192037.51
A88: 2080 | B88: =IF(A88<2029,0,IF(A88=2029,$B$12,IF(A88=2030,$B$13,$B$14))) -> 1 | C88: =INDEX($D$26:$D$31,MIN(A88-2025,6))*B88 -> 325109.05 | D88: =C88*$B$9 -> 262218.98 | E88: =D88-C88*$B$6 -> 259931.37 | F88: =E88*(1-$B$5) -> 189749.9 | G88: =$B$8*(C88-C87/(1+$B$4)) -> 1477.6056 | H88: =IF(A88=2027,$B$11,IF(A88=2028,1-$B$11,0))*$B$10 -> 0 | I88: =F88+C88*$B$6-C88*$B$7-G88-H88 -> 172678.9 | J88: =F88+C88*$B$6-H88 -> 192037.51
A89: 2081 | B89: =IF(A89<2029,0,IF(A89=2029,$B$12,IF(A89=2030,$B$13,$B$14))) -> 1 | C89: =INDEX($D$26:$D$31,MIN(A89-2025,6))*B89 -> 325109.05 | D89: =C89*$B$9 -> 262218.98 | E89: =D89-C89*$B$6 -> 259931.37 | F89: =E89*(1-$B$5) -> 189749.9 | G89: =$B$8*(C89-C88/(1+$B$4)) -> 1477.6056 | H89: =IF(A89=2027,$B$11,IF(A89=2028,1-$B$11,0))*$B$10 -> 0 | I89: =F89+C89*$B$6-C89*$B$7-G89-H89 -> 172678.9 | J89: =F89+C89*$B$6-H89 -> 192037.51
A90: 2082 | B90: =IF(A90<2029,0,IF(A90=2029,$B$12,IF(A90=2030,$B$13,$B$14))) -> 1 | C90: =INDEX($D$26:$D$31,MIN(A90-2025,6))*B90 -> 325109.05 | D90: =C90*$B$9 -> 262218.98 | E90: =D90-C90*$B$6 -> 259931.37 | F90: =E90*(1-$B$5) -> 189749.9 | G90: =$B$8*(C90-C89/(1+$B$4)) -> 1477.6056 | H90: =IF(A90=2027,$B$11,IF(A90=2028,1-$B$11,0))*$B$10 -> 0 | I90: =F90+C90*$B$6-C90*$B$7-G90-H90 -> 172678.9 | J90: =F90+C90*$B$6-H90 -> 192037.51
A91: 2083 | B91: =IF(A91<2029,0,IF(A91=2029,$B$12,IF(A91=2030,$B$13,$B$14))) -> 1 | C91: =INDEX($D$26:$D$31,MIN(A91-2025,6))*B91 -> 325109.05 | D91: =C91*$B$9 -> 262218.98 | E91: =D91-C91*$B$6 -> 259931.37 | F91: =E91*(1-$B$5) -> 189749.9 | G91: =$B$8*(C91-C90/(1+$B$4)) -> 1477.6056 | H91: =IF(A91=2027,$B$11,IF(A91=2028,1-$B$11,0))*$B$10 -> 0 | I91: =F91+C91*$B$6-C91*$B$7-G91-H91 -> 172678.9 | J91: =F91+C91*$B$6-H91 -> 192037.51
A92: 2084 | B92: =IF(A92<2029,0,IF(A92=2029,$B$12,IF(A92=2030,$B$13,$B$14))) -> 1 | C92: =INDEX($D$26:$D$31,MIN(A92-2025,6))*B92 -> 325109.05 | D92: =C92*$B$9 -> 262218.98 | E92: =D92-C92*$B$6 -> 259931.37 | F92: =E92*(1-$B$5) -> 189749.9 | G92: =$B$8*(C92-C91/(1+$B$4)) -> 1477.6056 | H92: =IF(A92=2027,$B$11,IF(A92=2028,1-$B$11,0))*$B$10 -> 0 | I92: =F92+C92*$B$6-C92*$B$7-G92-H92 -> 172678.9 | J92: =F92+C92*$B$6-H92 -> 192037.51
A93: 2085 | B93: =IF(A93<2029,0,IF(A93=2029,$B$12,IF(A93=2030,$B$13,$B$14))) -> 1 | C93: =INDEX($D$26:$D$31,MIN(A93-2025,6))*B93 -> 325109.05 | D93: =C93*$B$9 -> 262218.98 | E93: =D93-C93*$B$6 -> 259931.37 | F93: =E93*(1-$B$5) -> 189749.9 | G93: =$B$8*(C93-C92/(1+$B$4)) -> 1477.6056 | H93: =IF(A93=2027,$B$11,IF(A93=2028,1-$B$11,0))*$B$10 -> 0 | I93: =F93+C93*$B$6-C93*$B$7-G93-H93 -> 172678.9 | J93: =F93+C93*$B$6-H93 -> 192037.51
A94: 2086 | B94: =IF(A94<2029,0,IF(A94=2029,$B$12,IF(A94=2030,$B$13,$B$14))) -> 1 | C94: =INDEX($D$26:$D$31,MIN(A94-2025,6))*B94 -> 325109.05 | D94: =C94*$B$9 -> 262218.98 | E94: =D94-C94*$B$6 -> 259931.37 | F94: =E94*(1-$B$5) -> 189749.9 | G94: =$B$8*(C94-C93/(1+$B$4)) -> 1477.6056 | H94: =IF(A94=2027,$B$11,IF(A94=2028,1-$B$11,0))*$B$10 -> 0 | I94: =F94+C94*$B$6-C94*$B$7-G94-H94 -> 172678.9 | J94: =F94+C94*$B$6-H94 -> 192037.51
A95: 2087 | B95: =IF(A95<2029,0,IF(A95=2029,$B$12,IF(A95=2030,$B$13,$B$14))) -> 1 | C95: =INDEX($D$26:$D$31,MIN(A95-2025,6))*B95 -> 325109.05 | D95: =C95*$B$9 -> 262218.98 | E95: =D95-C95*$B$6 -> 259931.37 | F95: =E95*(1-$B$5) -> 189749.9 | G95: =$B$8*(C95-C94/(1+$B$4)) -> 1477.6056 | H95: =IF(A95=2027,$B$11,IF(A95=2028,1-$B$11,0))*$B$10 -> 0 | I95: =F95+C95*$B$6-C95*$B$7-G95-H95 -> 172678.9 | J95: =F95+C95*$B$6-H95 -> 192037.51
A96: 2088 | B96: =IF(A96<2029,0,IF(A96=2029,$B$12,IF(A96=2030,$B$13,$B$14))) -> 1 | C96: =INDEX($D$26:$D$31,MIN(A96-2025,6))*B96 -> 325109.05 | D96: =C96*$B$9 -> 262218.98 | E96: =D96-C96*$B$6 -> 259931.37 | F96: =E96*(1-$B$5) -> 189749.9 | G96: =$B$8*(C96-C95/(1+$B$4)) -> 1477.6056 | H96: =IF(A96=2027,$B$11,IF(A96=2028,1-$B$11,0))*$B$10 -> 0 | I96: =F96+C96*$B$6-C96*$B$7-G96-H96 -> 172678.9 | J96: =F96+C96*$B$6-H96 -> 192037.51
... A194: 2186 | B194: =IF(A194<2029,0,IF(A194=2029,$B$12,IF(A194=2030,$B$13,$B$14))) -> 1 | C194: =INDEX($D$26:$D$31,MIN(A194-2025,6))*B194 -> 325109.05 | D194: =C194*$B$9 -> 262218.98 | E194: =D194-C194*$B$6 -> 259931.37 | F194: =E194*(1-$B$5) -> 189749.9 | G194: =$B$8*(C194-C193/(1+$B$4)) -> 1477.6056 | H194: =IF(A194=2027,$B$11,IF(A194=2028,1-$B$11,0))*$B$10 -> 0 | I194: =F194+C194*$B$6-C194*$B$7-G194-H194 -> 172678.9 | J194: =F194+C194*$B$6-H194 -> 192037.51
