Workbook

Sheet Sensibilidad
A1: Sensibilidad del valor por acción a tasas largas e inflación (NUEVO)
A2: Valor DCF por acción (CLP) y variación frente a la base (CLP 1.857). Δ tasa real y Δ inflación esperada en puntos base; todo se recalcula desde Calculo.
A4: A. Valor DCF por acción (CLP): filas = Δ inflación esperada (pb), columnas = Δ tasa real (pb)
B5: -150 | C5: -100 | D5: -50 | E5: 0 | F5: 50 | G5: 100 | H5: 150
A6: -100 | B6: =Calculo!AI6 | C6: =Calculo!AI7 | D6: =Calculo!AI8 | E6: =Calculo!AI9 | F6: =Calculo!AI10 | G6: =Calculo!AI11 | H6: =Calculo!AI12
A7: -50 | B7: =Calculo!AI13 | C7: =Calculo!AI14 | D7: =Calculo!AI15 | E7: =Calculo!AI16 | F7: =Calculo!AI17 | G7: =Calculo!AI18 | H7: =Calculo!AI19
A8: 0 | B8: =Calculo!AI20 | C8: =Calculo!AI21 | D8: =Calculo!AI22 | E8: =Calculo!AI23 | F8: =Calculo!AI24 | G8: =Calculo!AI25 | H8: =Calculo!AI26
A9: 50 | B9: =Calculo!AI27 | C9: =Calculo!AI28 | D9: =Calculo!AI29 | E9: =Calculo!AI30 | F9: =Calculo!AI31 | G9: =Calculo!AI32 | H9: =Calculo!AI33
A10: 100 | B10: =Calculo!AI34 | C10: =Calculo!AI35 | D10: =Calculo!AI36 | E10: =Calculo!AI37 | F10: =Calculo!AI38 | G10: =Calculo!AI39 | H10: =Calculo!AI40
A12: B. Variación frente a la base
B13: -150 | C13: -100 | D13: -50 | E13: 0 | F13: 50 | G13: 100 | H13: 150
A14: -100 | B14: =Calculo!AJ6 | C14: =Calculo!AJ7 | D14: =Calculo!AJ8 | E14: =Calculo!AJ9 | F14: =Calculo!AJ10 | G14: =Calculo!AJ11 | H14: =Calculo!AJ12
A15: -50 | B15: =Calculo!AJ13 | C15: =Calculo!AJ14 | D15: =Calculo!AJ15 | E15: =Calculo!AJ16 | F15: =Calculo!AJ17 | G15: =Calculo!AJ18 | H15: =Calculo!AJ19
A16: 0 | B16: =Calculo!AJ20 | C16: =Calculo!AJ21 | D16: =Calculo!AJ22 | E16: =Calculo!AJ23 | F16: =Calculo!AJ24 | G16: =Calculo!AJ25 | H16: =Calculo!AJ26
A17: 50 | B17: =Calculo!AJ27 | C17: =Calculo!AJ28 | D17: =Calculo!AJ29 | E17: =Calculo!AJ30 | F17: =Calculo!AJ31 | G17: =Calculo!AJ32 | H17: =Calculo!AJ33
A18: 100 | B18: =Calculo!AJ34 | C18: =Calculo!AJ35 | D18: =Calculo!AJ36 | E18: =Calculo!AJ37 | F18: =Calculo!AJ38 | G18: =Calculo!AJ39 | H18: =Calculo!AJ40
A20: C. Mix: efecto de una misma alza (+100 pb) o baja (−100 pb) de la tasa larga NOMINAL según cuánto venga de inflación (Δi ≈ Δr + Δπ)
A21: % de la variación que viene de inflación | B21: 0 | C21: 0.1 | D21: 0.2 | E21: 0.3 | F21: 0.4 | G21: 0.5 | H21: 0.6 | I21: 0.7 | J21: 0.8 | K21: 0.9 | L21: 1
A22: Δi = +100 pb, θ = 1.0 | B22: =Calculo!AJ41 | C22: =Calculo!AJ42 | D22: =Calculo!AJ43 | E22: =Calculo!AJ44 | F22: =Calculo!AJ45 | G22: =Calculo!AJ46 | H22: =Calculo!AJ47 | I22: =Calculo!AJ48 | J22: =Calculo!AJ49 | K22: =Calculo!AJ50 | L22: =Calculo!AJ51
A23: Δi = +100 pb, θ = 0.85 | B23: =Calculo!AJ52 | C23: =Calculo!AJ53 | D23: =Calculo!AJ54 | E23: =Calculo!AJ55 | F23: =Calculo!AJ56 | G23: =Calculo!AJ57 | H23: =Calculo!AJ58 | I23: =Calculo!AJ59 | J23: =Calculo!AJ60 | K23: =Calculo!AJ61 | L23: =Calculo!AJ62
A24: Δi = +100 pb, θ = 0.7 | B24: =Calculo!AJ63 | C24: =Calculo!AJ64 | D24: =Calculo!AJ65 | E24: =Calculo!AJ66 | F24: =Calculo!AJ67 | G24: =Calculo!AJ68 | H24: =Calculo!AJ69 | I24: =Calculo!AJ70 | J24: =Calculo!AJ71 | K24: =Calculo!AJ72 | L24: =Calculo!AJ73
A25: Δi = -100 pb, θ = 1.0 | B25: =Calculo!AJ74 | C25: =Calculo!AJ75 | D25: =Calculo!AJ76 | E25: =Calculo!AJ77 | F25: =Calculo!AJ78 | G25: =Calculo!AJ79 | H25: =Calculo!AJ80 | I25: =Calculo!AJ81 | J25: =Calculo!AJ82 | K25: =Calculo!AJ83 | L25: =Calculo!AJ84
A26: Δi = -100 pb, θ = 0.85 | B26: =Calculo!AJ85 | C26: =Calculo!AJ86 | D26: =Calculo!AJ87 | E26: =Calculo!AJ88 | F26: =Calculo!AJ89 | G26: =Calculo!AJ90 | H26: =Calculo!AJ91 | I26: =Calculo!AJ92 | J26: =Calculo!AJ93 | K26: =Calculo!AJ94 | L26: =Calculo!AJ95
A27: Δi = -100 pb, θ = 0.7 | B27: =Calculo!AJ96 | C27: =Calculo!AJ97 | D27: =Calculo!AJ98 | E27: =Calculo!AJ99 | F27: =Calculo!AJ100 | G27: =Calculo!AJ101 | H27: =Calculo!AJ102 | I27: =Calculo!AJ103 | J27: =Calculo!AJ104 | K27: =Calculo!AJ105 | L27: =Calculo!AJ106
A29: D. Control empírico (regresión semanal; ver hoja Empirico)
A30: Variable | B30: Coef. por +1 pp | C30: Estadístico t
A31: Δ tasa real 10 años (BCU10) | B31: =INDEX(LINEST(Empirico!$G$6:$G$118,Empirico!$H$6:$J$118,TRUE,TRUE),1,3) | C31: =INDEX(LINEST(Empirico!$G$6:$G$118,Empirico!$H$6:$J$118,TRUE,TRUE),1,3)/INDEX(LINEST(Empirico!$G$6:$G$118,Empirico!$H$6:$J$118,TRUE,TRUE),2,3)
A32: Δ inflación implícita (BCP10 − BCU10) | B32: =INDEX(LINEST(Empirico!$G$6:$G$118,Empirico!$H$6:$J$118,TRUE,TRUE),1,2) | C32: =INDEX(LINEST(Empirico!$G$6:$G$118,Empirico!$H$6:$J$118,TRUE,TRUE),1,2)/INDEX(LINEST(Empirico!$G$6:$G$118,Empirico!$H$6:$J$118,TRUE,TRUE),2,2)
A33: Δ ln IPSA (control) | B33: =INDEX(LINEST(Empirico!$G$6:$G$118,Empirico!$H$6:$J$118,TRUE,TRUE),1,1) | C33: =INDEX(LINEST(Empirico!$G$6:$G$118,Empirico!$H$6:$J$118,TRUE,TRUE),1,1)/INDEX(LINEST(Empirico!$G$6:$G$118,Empirico!$H$6:$J$118,TRUE,TRUE),2,1)
A34: R² | B34: =INDEX(LINEST(Empirico!$G$6:$G$118,Empirico!$H$6:$J$118,TRUE,TRUE),3,1)
A35: N.º de semanas | B35: =COUNT(Empirico!$G$6:$G$118)
A37: Lectura: el DCF dice que una alza de 100 pb de tasa real baja el valor ~17%, mientras que la inflación casi no lo mueve; en el dato histórico la sensibilidad es mucho menor y poco significativa porque la acción se re-valorizó con tasas casi planas.
A40: E. Precio objetivo (80% DCF + 20% múltiplos, múltiplos fijos): filas = inflación esperada, columnas = tasa real a 10 años (BCU10, base 30-09-26)
A41: Tasa real / inflación | B41: =2.82/100+-100/10000 | C41: =2.82/100+-50/10000 | D41: =2.82/100+0/10000 | E41: =2.82/100+50/10000 | F41: =2.82/100+100/10000
A42: =Supuestos!$B$4+100/10000 | B42: =Supuestos!$B$12*Calculo!AI35+(1-Supuestos!$B$12)*Supuestos!$B$11 | C42: =Supuestos!$B$12*Calculo!AI36+(1-Supuestos!$B$12)*Supuestos!$B$11 | D42: =Supuestos!$B$12*Calculo!AI37+(1-Supuestos!$B$12)*Supuestos!$B$11 | E42: =Supuestos!$B$12*Calculo!AI38+(1-Supuestos!$B$12)*Supuestos!$B$11 | F42: =Supuestos!$B$12*Calculo!AI39+(1-Supuestos!$B$12)*Supuestos!$B$11
A43: =Supuestos!$B$4+50/10000 | B43: =Supuestos!$B$12*Calculo!AI28+(1-Supuestos!$B$12)*Supuestos!$B$11 | C43: =Supuestos!$B$12*Calculo!AI29+(1-Supuestos!$B$12)*Supuestos!$B$11 | D43: =Supuestos!$B$12*Calculo!AI30+(1-Supuestos!$B$12)*Supuestos!$B$11 | E43: =Supuestos!$B$12*Calculo!AI31+(1-Supuestos!$B$12)*Supuestos!$B$11 | F43: =Supuestos!$B$12*Calculo!AI32+(1-Supuestos!$B$12)*Supuestos!$B$11
A44: =Supuestos!$B$4+0/10000 | B44: =Supuestos!$B$12*Calculo!AI21+(1-Supuestos!$B$12)*Supuestos!$B$11 | C44: =Supuestos!$B$12*Calculo!AI22+(1-Supuestos!$B$12)*Supuestos!$B$11 | D44: =Supuestos!$B$12*Calculo!AI23+(1-Supuestos!$B$12)*Supuestos!$B$11 | E44: =Supuestos!$B$12*Calculo!AI24+(1-Supuestos!$B$12)*Supuestos!$B$11 | F44: =Supuestos!$B$12*Calculo!AI25+(1-Supuestos!$B$12)*Supuestos!$B$11
A45: =Supuestos!$B$4+-50/10000 | B45: =Supuestos!$B$12*Calculo!AI14+(1-Supuestos!$B$12)*Supuestos!$B$11 | C45: =Supuestos!$B$12*Calculo!AI15+(1-Supuestos!$B$12)*Supuestos!$B$11 | D45: =Supuestos!$B$12*Calculo!AI16+(1-Supuestos!$B$12)*Supuestos!$B$11 | E45: =Supuestos!$B$12*Calculo!AI17+(1-Supuestos!$B$12)*Supuestos!$B$11 | F45: =Supuestos!$B$12*Calculo!AI18+(1-Supuestos!$B$12)*Supuestos!$B$11
A46: =Supuestos!$B$4+-100/10000 | B46: =Supuestos!$B$12*Calculo!AI7+(1-Supuestos!$B$12)*Supuestos!$B$11 | C46: =Supuestos!$B$12*Calculo!AI8+(1-Supuestos!$B$12)*Supuestos!$B$11 | D46: =Supuestos!$B$12*Calculo!AI9+(1-Supuestos!$B$12)*Supuestos!$B$11 | E46: =Supuestos!$B$12*Calculo!AI10+(1-Supuestos!$B$12)*Supuestos!$B$11 | F46: =Supuestos!$B$12*Calculo!AI11+(1-Supuestos!$B$12)*Supuestos!$B$11

Sheet Supuestos
A1: Sensibilidad a tasas largas e inflación — insumos
A2: Azul = dato pegado del modelo v3 (fuente en col. K); negro = fórmula. Los supuestos de traspaso (B13, B14) son del equipo y se pueden mover.
A4: Inflación esperada de largo plazo π (Chile) | B4: 0.03 | K4: Mallplaza_Valoracion_Consolidada_v3 · Supuestos!B34
A5: Crecimiento terminal nominal g | B5: 0.03 | K5: v3 · DCF!C39 (real = 0%)
A6: Tasa de impuesto t | B6: 0.27 | K6: v3 · Supuestos!B35
A7: DFN al 30-06-2026 (MM CLP) | B7: 1285740 | K7: v3 · DCF!C45
A8: Minoritarios a libro (MM CLP) | B8: 50841 | K8: v3 · DCF!C46
A9: Acciones (MM) | B9: 2190 | K9: v3 · DCF!C48
A10: Precio 30-09-2026 (CLP) | B10: 3555 | K10: v3 · DCF!C50
A11: Valor por múltiplos EV/EBITDA LTM (CLP) | B11: 2951.3855 | K11: v3 · Precio_Objetivo!D5
A12: Peso del DCF en el precio objetivo | B12: 0.8 | K12: v3 · Precio_Objetivo!B14
A13: θ: parte del flujo que se reajusta con la inflación | B13: 0.85 | K13: SUPUESTO del equipo: rentas UF/reajustables y valor terminal; <1 por contratos fijos en CLP y rezago
A14: λ: traspaso de la tasa real al Ke (Kd traspasa 1:1) | B14: 1 | K14: SUPUESTO del equipo: la tasa libre de riesgo mueve el Ke 1:1
A15: Escenario único: Δ tasa real (pb) | B15: 100 | K15: Cambiar para ver un caso puntual (resultado en B19)
A16: Escenario único: Δ inflación esperada (pb) | B16: 0 | K16: Cambiar para ver un caso puntual
A19: Valor por acción del escenario único (CLP) | B19: =Calculo!AI107
A20: Variación frente a la base | B20: =B19/Calculo!AI5-1
A22: Período | C22: 2S26E | D22: 2027E | E22: 2028E | F22: 2029E | G22: 2030E | H22: 2031E | I22: Terminal
A23: FCFF (MM CLP nominales) | C23: 113425.72 | D23: 199440.44 | E23: 259687.72 | F23: 375320.62 | G23: 377068.22 | H23: 398715.5 | I23: 528835.31 | K23: v3 · DCF!C22:I22
A24: Fracción de año | C24: 0.5 | D24: 1 | E24: 1 | F24: 1 | G24: 1 | H24: 1 | K24: v3 · DCF!C26:H26
A25: τ: años a mitad de período desde 30-06-26 | C25: 0.25 | D25: 1 | E25: 2 | F25: 3 | G25: 4 | H25: 5 | I25: 6 | K25: Convención de mitad de período del DCF
A26: Ke nominal CLP | C26: 0.11703304 | D26: 0.11747901 | E26: 0.11792499 | F26: 0.11837096 | G26: 0.11881693 | H26: 0.1192629 | I26: 0.1192629 | K26: v3 · WACC!C39:I39
A27: Kd real (UF) | C27: 0.036259219 | D27: 0.036777656 | E27: 0.037296094 | F27: 0.037814531 | G27: 0.038332969 | H27: 0.038851407 | I27: 0.038851407 | K27: v3 · WACC!C40:I40
A28: D/V | C28: 0.17186496 | D28: 0.18238486 | E28: 0.19264085 | F28: 0.20264272 | G28: 0.21239982 | H28: 0.221921 | I28: 0.221921 | K28: v3 · WACC!C35:I35

Sheet Calculo
A1: Cálculo por escenario (réplica del DCF v3 con Δ tasa real y Δ inflación)
A2: Cada fila es un escenario completo: WACC por período, factores de descuento, flujos ajustados, valor terminal y valor por acción.
A4: Δ tasa real (pb) | B4: Δ inflación (pb) | C4: θ | D4: Escenario | E4: WACC 2S26E | F4: WACC 2027E | G4: WACC 2028E | H4: WACC 2029E | I4: WACC 2030E | J4: WACC 2031E | K4: WACC Terminal | L4: Factor cierre 1 | M4: Factor cierre 2 | N4: Factor cierre 3 | O4: Factor cierre 4 | P4: Factor cierre 5 | Q4: Factor cierre 6 | R4: Factor medio 1 | S4: Factor medio 2 | T4: Factor medio 3 | U4: Factor medio 4 | V4: Factor medio 5 | W4: Factor medio 6 | X4: FCFF aj. 2S26E | Y4: FCFF aj. 2027E | Z4: FCFF aj. 2028E | AA4: FCFF aj. 2029E | AB4: FCFF aj. 2030E | AC4: FCFF aj. 2031E | AD4: FCFF aj. Terminal | AE4: VP explícito | AF4: g terminal | AG4: Valor terminal | AH4: VP valor terminal | AI4: Valor por acción (CLP) | AJ4: Variación vs base
A5: 0 | B5: 0 | C5: =Supuestos!$B$13 | D5: Base | E5: =(1-Supuestos!C$28)*((1+((1+Supuestos!C$26)/(1+Supuestos!$B$4)-1+Supuestos!$B$14*$A5/10000))*(1+Supuestos!$B$4+$B5/10000)-1)+Supuestos!C$28*((1+Supuestos!C$27+$A5/10000)*(1+Supuestos!$B$4+$B5/10000)-1)*(1-Supuestos!$B$6) | F5: =(1-Supuestos!D$28)*((1+((1+Supuestos!D$26)/(1+Supuestos!$B$4)-1+Supuestos!$B$14*$A5/10000))*(1+Supuestos!$B$4+$B5/10000)-1)+Supuestos!D$28*((1+Supuestos!D$27+$A5/10000)*(1+Supuestos!$B$4+$B5/10000)-1)*(1-Supuestos!$B$6) | G5: =(1-Supuestos!E$28)*((1+((1+Supuestos!E$26)/(1+Supuestos!$B$4)-1+Supuestos!$B$14*$A5/10000))*(1+Supuestos!$B$4+$B5/10000)-1)+Supuestos!E$28*((1+Supuestos!E$27+$A5/10000)*(1+Supuestos!$B$4+$B5/10000)-1)*(1-Supuestos!$B$6) | H5: =(1-Supuestos!F$28)*((1+((1+Supuestos!F$26)/(1+Supuestos!$B$4)-1+Supuestos!$B$14*$A5/10000))*(1+Supuestos!$B$4+$B5/10000)-1)+Supuestos!F$28*((1+Supuestos!F$27+$A5/10000)*(1+Supuestos!$B$4+$B5/10000)-1)*(1-Supuestos!$B$6) | I5: =(1-Supuestos!G$28)*((1+((1+Supuestos!G$26)/(1+Supuestos!$B$4)-1+Supuestos!$B$14*$A5/10000))*(1+Supuestos!$B$4+$B5/10000)-1)+Supuestos!G$28*((1+Supuestos!G$27+$A5/10000)*(1+Supuestos!$B$4+$B5/10000)-1)*(1-Supuestos!$B$6) | J5: =(1-Supuestos!H$28)*((1+((1+Supuestos!H$26)/(1+Supuestos!$B$4)-1+Supuestos!$B$14*$A5/10000))*(1+Supuestos!$B$4+$B5/10000)-1)+Supuestos!H$28*((1+Supuestos!H$27+$A5/10000)*(1+Supuestos!$B$4+$B5/10000)-1)*(1-Supuestos!$B$6) | K5: =(1-Supuestos!I$28)*((1+((1+Supuestos!I$26)/(1+Supuestos!$B$4)-1+Supuestos!$B$14*$A5/10000))*(1+Supuestos!$B$4+$B5/10000)-1)+Supuestos!I$28*((1+Supuestos!I$27+$A5/10000)*(1+Supuestos!$B$4+$B5/10000)-1)*(1-Supuestos!$B$6) | L5: =(1+E5)^-Supuestos!C$24 | M5: =L5*(1+F5)^-Supuestos!D$24 | N5: =M5*(1+G5)^-Supuestos!E$24 | O5: =N5*(1+H5)^-Supuestos!F$24 | P5: =O5*(1+I5)^-Supuestos!G$24 | Q5: =P5*(1+J5)^-Supuestos!H$24 | R5: =(1+E5)^-(Supuestos!C$24/2) | S5: =L5*(1+F5)^-(Supuestos!D$24/2) | T5: =M5*(1+G5)^-(Supuestos!E$24/2) | U5: =N5*(1+H5)^-(Supuestos!F$24/2) | V5: =O5*(1+I5)^-(Supuestos!G$24/2) | W5: =P5*(1+J5)^-(Supuestos!H$24/2) | X5: =Supuestos!C$23*(1-$C5+$C5*((1+Supuestos!$B$4+$B5/10000)/(1+Supuestos!$B$4))^Supuestos!C$25) | Y5: =Supuestos!D$23*(1-$C5+$C5*((1+Supuestos!$B$4+$B5/10000)/(1+Supuestos!$B$4))^Supuestos!D$25) | Z5: =Supuestos!E$23*(1-$C5+$C5*((1+Supuestos!$B$4+$B5/10000)/(1+Supuestos!$B$4))^Supuestos!E$25) | AA5: =Supuestos!F$23*(1-$C5+$C5*((1+Supuestos!$B$4+$B5/10000)/(1+Supuestos!$B$4))^Supuestos!F$25) | AB5: =Supuestos!G$23*(1-$C5+$C5*((1+Supuestos!$B$4+$B5/10000)/(1+Supuestos!$B$4))^Supuestos!G$25) | AC5: =Supuestos!H$23*(1-$C5+$C5*((1+Supuestos!$B$4+$B5/10000)/(1+Supuestos!$B$4))^Supuestos!H$25) | AD5: =Supuestos!I$23*(1-$C5+$C5*((1+Supuestos!$B$4+$B5/10000)/(1+Supuestos!$B$4))^Supuestos!I$25) | AE5: =SUMPRODUCT(X5:AC5,R5:W5) | AF5: =(1+Supuestos!$B$5)/(1+Supuestos!$B$4)*(1+Supuestos!$B$4+$B5/10000)-1 | AG5: =AD5/(K5-AF5) | AH5: =AG5*Q5 | AI5: =(AE5+AH5-Supuestos!$B$7-Supuestos!$B$8)/Supuestos!$B$9 | AJ5: =AI5/AI$5-1
A6: -150 | B6: -100 | C6: =Supuestos!$B$13 | D6: Grilla | E6: =(1-Supuestos!C$28)*((1+((1+Supuestos!C$26)/(1+Supuestos!$B$4)-1+Supuestos!$B$14*$A6/10000))*(1+Supuestos!$B$4+$B6/10000)-1)+Supuestos!C$28*((1+Supuestos!C$27+$A6/10000)*(1+Supuestos!$B$4+$B6/10000)-1)*(1-Supuestos!$B$6) | F6: =(1-Supuestos!D$28)*((1+((1+Supuestos!D$26)/(1+Supuestos!$B$4)-1+Supuestos!$B$14*$A6/10000))*(1+Supuestos!$B$4+$B6/10000)-1)+Supuestos!D$28*((1+Supuestos!D$27+$A6/10000)*(1+Supuestos!$B$4+$B6/10000)-1)*(1-Supuestos!$B$6) | G6: =(1-Supuestos!E$28)*((1+((1+Supuestos!E$26)/(1+Supuestos!$B$4)-1+Supuestos!$B$14*$A6/10000))*(1+Supuestos!$B$4+$B6/10000)-1)+Supuestos!E$28*((1+Supuestos!E$27+$A6/10000)*(1+Supuestos!$B$4+$B6/10000)-1)*(1-Supuestos!$B$6) | H6: =(1-Supuestos!F$28)*((1+((1+Supuestos!F$26)/(1+Supuestos!$B$4)-1+Supuestos!$B$14*$A6/10000))*(1+Supuestos!$B$4+$B6/10000)-1)+Supuestos!F$28*((1+Supuestos!F$27+$A6/10000)*(1+Supuestos!$B$4+$B6/10000)-1)*(1-Supuestos!$B$6) | I6: =(1-Supuestos!G$28)*((1+((1+Supuestos!G$26)/(1+Supuestos!$B$4)-1+Supuestos!$B$14*$A6/10000))*(1+Supuestos!$B$4+$B6/10000)-1)+Supuestos!G$28*((1+Supuestos!G$27+$A6/10000)*(1+Supuestos!$B$4+$B6/10000)-1)*(1-Supuestos!$B$6) | J6: =(1-Supuestos!H$28)*((1+((1+Supuestos!H$26)/(1+Supuestos!$B$4)-1+Supuestos!$B$14*$A6/10000))*(1+Supuestos!$B$4+$B6/10000)-1)+Supuestos!H$28*((1+Supuestos!H$27+$A6/10000)*(1+Supuestos!$B$4+$B6/10000)-1)*(1-Supuestos!$B$6) | K6: =(1-Supuestos!I$28)*((1+((1+Supuestos!I$26)/(1+Supuestos!$B$4)-1+Supuestos!$B$14*$A6/10000))*(1+Supuestos!$B$4+$B6/10000)-1)+Supuestos!I$28*((1+Supuestos!I$27+$A6/10000)*(1+Supuestos!$B$4+$B6/10000)-1)*(1-Supuestos!$B$6) | L6: =(1+E6)^-Supuestos!C$24 | M6: =L6*(1+F6)^-Supuestos!D$24 | N6: =M6*(1+G6)^-Supuestos!E$24 | O6: =N6*(1+H6)^-Supuestos!F$24 | P6: =O6*(1+I6)^-Supuestos!G$24 | Q6: =P6*(1+J6)^-Supuestos!H$24 | R6: =(1+E6)^-(Supuestos!C$24/2) | S6: =L6*(1+F6)^-(Supuestos!D$24/2) | T6: =M6*(1+G6)^-(Supuestos!E$24/2) | U6: =N6*(1+H6)^-(Supuestos!F$24/2) | V6: =O6*(1+I6)^-(Supuestos!G$24/2) | W6: =P6*(1+J6)^-(Supuestos!H$24/2) | X6: =Supuestos!C$23*(1-$C6+$C6*((1+Supuestos!$B$4+$B6/10000)/(1+Supuestos!$B$4))^Supuestos!C$25) | Y6: =Supuestos!D$23*(1-$C6+$C6*((1+Supuestos!$B$4+$B6/10000)/(1+Supuestos!$B$4))^Supuestos!D$25) | Z6: =Supuestos!E$23*(1-$C6+$C6*((1+Supuestos!$B$4+$B6/10000)/(1+Supuestos!$B$4))^Supuestos!E$25) | AA6: =Supuestos!F$23*(1-$C6+$C6*((1+Supuestos!$B$4+$B6/10000)/(1+Supuestos!$B$4))^Supuestos!F$25) | AB6: =Supuestos!G$23*(1-$C6+$C6*((1+Supuestos!$B$4+$B6/10000)/(1+Supuestos!$B$4))^Supuestos!G$25) | AC6: =Supuestos!H$23*(1-$C6+$C6*((1+Supuestos!$B$4+$B6/10000)/(1+Supuestos!$B$4))^Supuestos!H$25) | AD6: =Supuestos!I$23*(1-$C6+$C6*((1+Supuestos!$B$4+$B6/10000)/(1+Supuestos!$B$4))^Supuestos!I$25) | AE6: =SUMPRODUCT(X6:AC6,R6:W6) | AF6: =(1+Supuestos!$B$5)/(1+Supuestos!$B$4)*(1+Supuestos!$B$4+$B6/10000)-1 | AG6: =AD6/(K6-AF6) | AH6: =AG6*Q6 | AI6: =(AE6+AH6-Supuestos!$B$7-Supuestos!$B$8)/Supuestos!$B$9 | AJ6: =AI6/AI$5-1
A7: -100 | B7: -100 | C7: =Supuestos!$B$13 | D7: Grilla | E7: =(1-Supuestos!C$28)*((1+((1+Supuestos!C$26)/(1+Supuestos!$B$4)-1+Supuestos!$B$14*$A7/10000))*(1+Supuestos!$B$4+$B7/10000)-1)+Supuestos!C$28*((1+Supuestos!C$27+$A7/10000)*(1+Supuestos!$B$4+$B7/10000)-1)*(1-Supuestos!$B$6) | F7: =(1-Supuestos!D$28)*((1+((1+Supuestos!D$26)/(1+Supuestos!$B$4)-1+Supuestos!$B$14*$A7/10000))*(1+Supuestos!$B$4+$B7/10000)-1)+Supuestos!D$28*((1+Supuestos!D$27+$A7/10000)*(1+Supuestos!$B$4+$B7/10000)-1)*(1-Supuestos!$B$6) | G7: =(1-Supuestos!E$28)*((1+((1+Supuestos!E$26)/(1+Supuestos!$B$4)-1+Supuestos!$B$14*$A7/10000))*(1+Supuestos!$B$4+$B7/10000)-1)+Supuestos!E$28*((1+Supuestos!E$27+$A7/10000)*(1+Supuestos!$B$4+$B7/10000)-1)*(1-Supuestos!$B$6) | H7: =(1-Supuestos!F$28)*((1+((1+Supuestos!F$26)/(1+Supuestos!$B$4)-1+Supuestos!$B$14*$A7/10000))*(1+Supuestos!$B$4+$B7/10000)-1)+Supuestos!F$28*((1+Supuestos!F$27+$A7/10000)*(1+Supuestos!$B$4+$B7/10000)-1)*(1-Supuestos!$B$6) | I7: =(1-Supuestos!G$28)*((1+((1+Supuestos!G$26)/(1+Supuestos!$B$4)-1+Supuestos!$B$14*$A7/10000))*(1+Supuestos!$B$4+$B7/10000)-1)+Supuestos!G$28*((1+Supuestos!G$27+$A7/10000)*(1+Supuestos!$B$4+$B7/10000)-1)*(1-Supuestos!$B$6) | J7: =(1-Supuestos!H$28)*((1+((1+Supuestos!H$26)/(1+Supuestos!$B$4)-1+Supuestos!$B$14*$A7/10000))*(1+Supuestos!$B$4+$B7/10000)-1)+Supuestos!H$28*((1+Supuestos!H$27+$A7/10000)*(1+Supuestos!$B$4+$B7/10000)-1)*(1-Supuestos!$B$6) | K7: =(1-Supuestos!I$28)*((1+((1+Supuestos!I$26)/(1+Supuestos!$B$4)-1+Supuestos!$B$14*$A7/10000))*(1+Supuestos!$B$4+$B7/10000)-1)+Supuestos!I$28*((1+Supuestos!I$27+$A7/10000)*(1+Supuestos!$B$4+$B7/10000)-1)*(1-Supuestos!$B$6) | L7: =(1+E7)^-Supuestos!C$24 | M7: =L7*(1+F7)^-Supuestos!D$24 | N7: =M7*(1+G7)^-Supuestos!E$24 | O7: =N7*(1+H7)^-Supuestos!F$24 | P7: =O7*(1+I7)^-Supuestos!G$24 | Q7: =P7*(1+J7)^-Supuestos!H$24 | R7: =(1+E7)^-(Supuestos!C$24/2) | S7: =L7*(1+F7)^-(Supuestos!D$24/2) | T7: =M7*(1+G7)^-(Supuestos!E$24/2) | U7: =N7*(1+H7)^-(Supuestos!F$24/2) | V7: =O7*(1+I7)^-(Supuestos!G$24/2) | W7: =P7*(1+J7)^-(Supuestos!H$24/2) | X7: =Supuestos!C$23*(1-$C7+$C7*((1+Supuestos!$B$4+$B7/10000)/(1+Supuestos!$B$4))^Supuestos!C$25) | Y7: =Supuestos!D$23*(1-$C7+$C7*((1+Supuestos!$B$4+$B7/10000)/(1+Supuestos!$B$4))^Supuestos!D$25) | Z7: =Supuestos!E$23*(1-$C7+$C7*((1+Supuestos!$B$4+$B7/10000)/(1+Supuestos!$B$4))^Supuestos!E$25) | AA7: =Supuestos!F$23*(1-$C7+$C7*((1+Supuestos!$B$4+$B7/10000)/(1+Supuestos!$B$4))^Supuestos!F$25) | AB7: =Supuestos!G$23*(1-$C7+$C7*((1+Supuestos!$B$4+$B7/10000)/(1+Supuestos!$B$4))^Supuestos!G$25) | AC7: =Supuestos!H$23*(1-$C7+$C7*((1+Supuestos!$B$4+$B7/10000)/(1+Supuestos!$B$4))^Supuestos!H$25) | AD7: =Supuestos!I$23*(1-$C7+$C7*((1+Supuestos!$B$4+$B7/10000)/(1+Supuestos!$B$4))^Supuestos!I$25) | AE7: =SUMPRODUCT(X7:AC7,R7:W7) | AF7: =(1+Supuestos!$B$5)/(1+Supuestos!$B$4)*(1+Supuestos!$B$4+$B7/10000)-1 | AG7: =AD7/(K7-AF7) | AH7: =AG7*Q7 | AI7: =(AE7+AH7-Supuestos!$B$7-Supuestos!$B$8)/Supuestos!$B$9 | AJ7: =AI7/AI$5-1
A8: -50 | B8: -100 | C8: =Supuestos!$B$13 | D8: Grilla | E8: =(1-Supuestos!C$28)*((1+((1+Supuestos!C$26)/(1+Supuestos!$B$4)-1+Supuestos!$B$14*$A8/10000))*(1+Supuestos!$B$4+$B8/10000)-1)+Supuestos!C$28*((1+Supuestos!C$27+$A8/10000)*(1+Supuestos!$B$4+$B8/10000)-1)*(1-Supuestos!$B$6) | F8: =(1-Supuestos!D$28)*((1+((1+Supuestos!D$26)/(1+Supuestos!$B$4)-1+Supuestos!$B$14*$A8/10000))*(1+Supuestos!$B$4+$B8/10000)-1)+Supuestos!D$28*((1+Supuestos!D$27+$A8/10000)*(1+Supuestos!$B$4+$B8/10000)-1)*(1-Supuestos!$B$6) | G8: =(1-Supuestos!E$28)*((1+((1+Supuestos!E$26)/(1+Supuestos!$B$4)-1+Supuestos!$B$14*$A8/10000))*(1+Supuestos!$B$4+$B8/10000)-1)+Supuestos!E$28*((1+Supuestos!E$27+$A8/10000)*(1+Supuestos!$B$4+$B8/10000)-1)*(1-Supuestos!$B$6) | H8: =(1-Supuestos!F$28)*((1+((1+Supuestos!F$26)/(1+Supuestos!$B$4)-1+Supuestos!$B$14*$A8/10000))*(1+Supuestos!$B$4+$B8/10000)-1)+Supuestos!F$28*((1+Supuestos!F$27+$A8/10000)*(1+Supuestos!$B$4+$B8/10000)-1)*(1-Supuestos!$B$6) | I8: =(1-Supuestos!G$28)*((1+((1+Supuestos!G$26)/(1+Supuestos!$B$4)-1+Supuestos!$B$14*$A8/10000))*(1+Supuestos!$B$4+$B8/10000)-1)+Supuestos!G$28*((1+Supuestos!G$27+$A8/10000)*(1+Supuestos!$B$4+$B8/10000)-1)*(1-Supuestos!$B$6) | J8: =(1-Supuestos!H$28)*((1+((1+Supuestos!H$26)/(1+Supuestos!$B$4)-1+Supuestos!$B$14*$A8/10000))*(1+Supuestos!$B$4+$B8/10000)-1)+Supuestos!H$28*((1+Supuestos!H$27+$A8/10000)*(1+Supuestos!$B$4+$B8/10000)-1)*(1-Supuestos!$B$6) | K8: =(1-Supuestos!I$28)*((1+((1+Supuestos!I$26)/(1+Supuestos!$B$4)-1+Supuestos!$B$14*$A8/10000))*(1+Supuestos!$B$4+$B8/10000)-1)+Supuestos!I$28*((1+Supuestos!I$27+$A8/10000)*(1+Supuestos!$B$4+$B8/10000)-1)*(1-Supuestos!$B$6) | L8: =(1+E8)^-Supuestos!C$24 | M8: =L8*(1+F8)^-Supuestos!D$24 | N8: =M8*(1+G8)^-Supuestos!E$24 | O8: =N8*(1+H8)^-Supuestos!F$24 | P8: =O8*(1+I8)^-Supuestos!G$24 | Q8: =P8*(1+J8)^-Supuestos!H$24 | R8: =(1+E8)^-(Supuestos!C$24/2) | S8: =L8*(1+F8)^-(Supuestos!D$24/2) | T8: =M8*(1+G8)^-(Supuestos!E$24/2) | U8: =N8*(1+H8)^-(Supuestos!F$24/2) | V8: =O8*(1+I8)^-(Supuestos!G$24/2) | W8: =P8*(1+J8)^-(Supuestos!H$24/2) | X8: =Supuestos!C$23*(1-$C8+$C8*((1+Supuestos!$B$4+$B8/10000)/(1+Supuestos!$B$4))^Supuestos!C$25) | Y8: =Supuestos!D$23*(1-$C8+$C8*((1+Supuestos!$B$4+$B8/10000)/(1+Supuestos!$B$4))^Supuestos!D$25) | Z8: =Supuestos!E$23*(1-$C8+$C8*((1+Supuestos!$B$4+$B8/10000)/(1+Supuestos!$B$4))^Supuestos!E$25) | AA8: =Supuestos!F$23*(1-$C8+$C8*((1+Supuestos!$B$4+$B8/10000)/(1+Supuestos!$B$4))^Supuestos!F$25) | AB8: =Supuestos!G$23*(1-$C8+$C8*((1+Supuestos!$B$4+$B8/10000)/(1+Supuestos!$B$4))^Supuestos!G$25) | AC8: =Supuestos!H$23*(1-$C8+$C8*((1+Supuestos!$B$4+$B8/10000)/(1+Supuestos!$B$4))^Supuestos!H$25) | AD8: =Supuestos!I$23*(1-$C8+$C8*((1+Supuestos!$B$4+$B8/10000)/(1+Supuestos!$B$4))^Supuestos!I$25) | AE8: =SUMPRODUCT(X8:AC8,R8:W8) | AF8: =(1+Supuestos!$B$5)/(1+Supuestos!$B$4)*(1+Supuestos!$B$4+$B8/10000)-1 | AG8: =AD8/(K8-AF8) | AH8: =AG8*Q8 | AI8: =(AE8+AH8-Supuestos!$B$7-Supuestos!$B$8)/Supuestos!$B$9 | AJ8: =AI8/AI$5-1
A9: 0 | B9: -100 | C9: =Supuestos!$B$13 | D9: Grilla | E9: =(1-Supuestos!C$28)*((1+((1+Supuestos!C$26)/(1+Supuestos!$B$4)-1+Supuestos!$B$14*$A9/10000))*(1+Supuestos!$B$4+$B9/10000)-1)+Supuestos!C$28*((1+Supuestos!C$27+$A9/10000)*(1+Supuestos!$B$4+$B9/10000)-1)*(1-Supuestos!$B$6) | F9: =(1-Supuestos!D$28)*((1+((1+Supuestos!D$26)/(1+Supuestos!$B$4)-1+Supuestos!$B$14*$A9/10000))*(1+Supuestos!$B$4+$B9/10000)-1)+Supuestos!D$28*((1+Supuestos!D$27+$A9/10000)*(1+Supuestos!$B$4+$B9/10000)-1)*(1-Supuestos!$B$6) | G9: =(1-Supuestos!E$28)*((1+((1+Supuestos!E$26)/(1+Supuestos!$B$4)-1+Supuestos!$B$14*$A9/10000))*(1+Supuestos!$B$4+$B9/10000)-1)+Supuestos!E$28*((1+Supuestos!E$27+$A9/10000)*(1+Supuestos!$B$4+$B9/10000)-1)*(1-Supuestos!$B$6) | H9: =(1-Supuestos!F$28)*((1+((1+Supuestos!F$26)/(1+Supuestos!$B$4)-1+Supuestos!$B$14*$A9/10000))*(1+Supuestos!$B$4+$B9/10000)-1)+Supuestos!F$28*((1+Supuestos!F$27+$A9/10000)*(1+Supuestos!$B$4+$B9/10000)-1)*(1-Supuestos!$B$6) | I9: =(1-Supuestos!G$28)*((1+((1+Supuestos!G$26)/(1+Supuestos!$B$4)-1+Supuestos!$B$14*$A9/10000))*(1+Supuestos!$B$4+$B9/10000)-1)+Supuestos!G$28*((1+Supuestos!G$27+$A9/10000)*(1+Supuestos!$B$4+$B9/10000)-1)*(1-Supuestos!$B$6) | J9: =(1-Supuestos!H$28)*((1+((1+Supuestos!H$26)/(1+Supuestos!$B$4)-1+Supuestos!$B$14*$A9/10000))*(1+Supuestos!$B$4+$B9/10000)-1)+Supuestos!H$28*((1+Supuestos!H$27+$A9/10000)*(1+Supuestos!$B$4+$B9/10000)-1)*(1-Supuestos!$B$6) | K9: =(1-Supuestos!I$28)*((1+((1+Supuestos!I$26)/(1+Supuestos!$B$4)-1+Supuestos!$B$14*$A9/10000))*(1+Supuestos!$B$4+$B9/10000)-1)+Supuestos!I$28*((1+Supuestos!I$27+$A9/10000)*(1+Supuestos!$B$4+$B9/10000)-1)*(1-Supuestos!$B$6) | L9: =(1+E9)^-Supuestos!C$24 | M9: =L9*(1+F9)^-Supuestos!D$24 | N9: =M9*(1+G9)^-Supuestos!E$24 | O9: =N9*(1+H9)^-Supuestos!F$24 | P9: =O9*(1+I9)^-Supuestos!G$24 | Q9: =P9*(1+J9)^-Supuestos!H$24 | R9: =(1+E9)^-(Supuestos!C$24/2) | S9: =L9*(1+F9)^-(Supuestos!D$24/2) | T9: =M9*(1+G9)^-(Supuestos!E$24/2) | U9: =N9*(1+H9)^-(Supuestos!F$24/2) | V9: =O9*(1+I9)^-(Supuestos!G$24/2) | W9: =P9*(1+J9)^-(Supuestos!H$24/2) | X9: =Supuestos!C$23*(1-$C9+$C9*((1+Supuestos!$B$4+$B9/10000)/(1+Supuestos!$B$4))^Supuestos!C$25) | Y9: =Supuestos!D$23*(1-$C9+$C9*((1+Supuestos!$B$4+$B9/10000)/(1+Supuestos!$B$4))^Supuestos!D$25) | Z9: =Supuestos!E$23*(1-$C9+$C9*((1+Supuestos!$B$4+$B9/10000)/(1+Supuestos!$B$4))^Supuestos!E$25) | AA9: =Supuestos!F$23*(1-$C9+$C9*((1+Supuestos!$B$4+$B9/10000)/(1+Supuestos!$B$4))^Supuestos!F$25) | AB9: =Supuestos!G$23*(1-$C9+$C9*((1+Supuestos!$B$4+$B9/10000)/(1+Supuestos!$B$4))^Supuestos!G$25) | AC9: =Supuestos!H$23*(1-$C9+$C9*((1+Supuestos!$B$4+$B9/10000)/(1+Supuestos!$B$4))^Supuestos!H$25) | AD9: =Supuestos!I$23*(1-$C9+$C9*((1+Supuestos!$B$4+$B9/10000)/(1+Supuestos!$B$4))^Supuestos!I$25) | AE9: =SUMPRODUCT(X9:AC9,R9:W9) | AF9: =(1+Supuestos!$B$5)/(1+Supuestos!$B$4)*(1+Supuestos!$B$4+$B9/10000)-1 | AG9: =AD9/(K9-AF9) | AH9: =AG9*Q9 | AI9: =(AE9+AH9-Supuestos!$B$7-Supuestos!$B$8)/Supuestos!$B$9 | AJ9: =AI9/AI$5-1
A10: 50 | B10: -100 | C10: =Supuestos!$B$13 | D10: Grilla | E10: =(1-Supuestos!C$28)*((1+((1+Supuestos!C$26)/(1+Supuestos!$B$4)-1+Supuestos!$B$14*$A10/10000))*(1+Supuestos!$B$4+$B10/10000)-1)+Supuestos!C$28*((1+Supuestos!C$27+$A10/10000)*(1+Supuestos!$B$4+$B10/10000)-1)*(1-Supuestos!$B$6) | F10: =(1-Supuestos!D$28)*((1+((1+Supuestos!D$26)/(1+Supuestos!$B$4)-1+Supuestos!$B$14*$A10/10000))*(1+Supuestos!$B$4+$B10/10000)-1)+Supuestos!D$28*((1+Supuestos!D$27+$A10/10000)*(1+Supuestos!$B$4+$B10/10000)-1)*(1-Supuestos!$B$6) | G10: =(1-Supuestos!E$28)*((1+((1+Supuestos!E$26)/(1+Supuestos!$B$4)-1+Supuestos!$B$14*$A10/10000))*(1+Supuestos!$B$4+$B10/10000)-1)+Supuestos!E$28*((1+Supuestos!E$27+$A10/10000)*(1+Supuestos!$B$4+$B10/10000)-1)*(1-Supuestos!$B$6) | H10: =(1-Supuestos!F$28)*((1+((1+Supuestos!F$26)/(1+Supuestos!$B$4)-1+Supuestos!$B$14*$A10/10000))*(1+Supuestos!$B$4+$B10/10000)-1)+Supuestos!F$28*((1+Supuestos!F$27+$A10/10000)*(1+Supuestos!$B$4+$B10/10000)-1)*(1-Supuestos!$B$6) | I10: =(1-Supuestos!G$28)*((1+((1+Supuestos!G$26)/(1+Supuestos!$B$4)-1+Supuestos!$B$14*$A10/10000))*(1+Supuestos!$B$4+$B10/10000)-1)+Supuestos!G$28*((1+Supuestos!G$27+$A10/10000)*(1+Supuestos!$B$4+$B10/10000)-1)*(1-Supuestos!$B$6) | J10: =(1-Supuestos!H$28)*((1+((1+Supuestos!H$26)/(1+Supuestos!$B$4)-1+Supuestos!$B$14*$A10/10000))*(1+Supuestos!$B$4+$B10/10000)-1)+Supuestos!H$28*((1+Supuestos!H$27+$A10/10000)*(1+Supuestos!$B$4+$B10/10000)-1)*(1-Supuestos!$B$6) | K10: =(1-Supuestos!I$28)*((1+((1+Supuestos!I$26)/(1+Supuestos!$B$4)-1+Supuestos!$B$14*$A10/10000))*(1+Supuestos!$B$4+$B10/10000)-1)+Supuestos!I$28*((1+Supuestos!I$27+$A10/10000)*(1+Supuestos!$B$4+$B10/10000)-1)*(1-Supuestos!$B$6) | L10: =(1+E10)^-Supuestos!C$24 | M10: =L10*(1+F10)^-Supuestos!D$24 | N10: =M10*(1+G10)^-Supuestos!E$24 | O10: =N10*(1+H10)^-Supuestos!F$24 | P10: =O10*(1+I10)^-Supuestos!G$24 | Q10: =P10*(1+J10)^-Supuestos!H$24 | R10: =(1+E10)^-(Supuestos!C$24/2) | S10: =L10*(1+F10)^-(Supuestos!D$24/2) | T10: =M10*(1+G10)^-(Supuestos!E$24/2) | U10: =N10*(1+H10)^-(Supuestos!F$24/2) | V10: =O10*(1+I10)^-(Supuestos!G$24/2) | W10: =P10*(1+J10)^-(Supuestos!H$24/2) | X10: =Supuestos!C$23*(1-$C10+$C10*((1+Supuestos!$B$4+$B10/10000)/(1+Supuestos!$B$4))^Supuestos!C$25) | Y10: =Supuestos!D$23*(1-$C10+$C10*((1+Supuestos!$B$4+$B10/10000)/(1+Supuestos!$B$4))^Supuestos!D$25) | Z10: =Supuestos!E$23*(1-$C10+$C10*((1+Supuestos!$B$4+$B10/10000)/(1+Supuestos!$B$4))^Supuestos!E$25) | AA10: =Supuestos!F$23*(1-$C10+$C10*((1+Supuestos!$B$4+$B10/10000)/(1+Supuestos!$B$4))^Supuestos!F$25) | AB10: =Supuestos!G$23*(1-$C10+$C10*((1+Supuestos!$B$4+$B10/10000)/(1+Supuestos!$B$4))^Supuestos!G$25) | AC10: =Supuestos!H$23*(1-$C10+$C10*((1+Supuestos!$B$4+$B10/10000)/(1+Supuestos!$B$4))^Supuestos!H$25) | AD10: =Supuestos!I$23*(1-$C10+$C10*((1+Supuestos!$B$4+$B10/10000)/(1+Supuestos!$B$4))^Supuestos!I$25) | AE10: =SUMPRODUCT(X10:AC10,R10:W10) | AF10: =(1+Supuestos!$B$5)/(1+Supuestos!$B$4)*(1+Supuestos!$B$4+$B10/10000)-1 | AG10: =AD10/(K10-AF10) | AH10: =AG10*Q10 | AI10: =(AE10+AH10-Supuestos!$B$7-Supuestos!$B$8)/Supuestos!$B$9 | AJ10: =AI10/AI$5-1
A11: 100 | B11: -100 | C11: =Supuestos!$B$13 | D11: Grilla | E11: =(1-Supuestos!C$28)*((1+((1+Supuestos!C$26)/(1+Supuestos!$B$4)-1+Supuestos!$B$14*$A11/10000))*(1+Supuestos!$B$4+$B11/10000)-1)+Supuestos!C$28*((1+Supuestos!C$27+$A11/10000)*(1+Supuestos!$B$4+$B11/10000)-1)*(1-Supuestos!$B$6) | F11: =(1-Supuestos!D$28)*((1+((1+Supuestos!D$26)/(1+Supuestos!$B$4)-1+Supuestos!$B$14*$A11/10000))*(1+Supuestos!$B$4+$B11/10000)-1)+Supuestos!D$28*((1+Supuestos!D$27+$A11/10000)*(1+Supuestos!$B$4+$B11/10000)-1)*(1-Supuestos!$B$6) | G11: =(1-Supuestos!E$28)*((1+((1+Supuestos!E$26)/(1+Supuestos!$B$4)-1+Supuestos!$B$14*$A11/10000))*(1+Supuestos!$B$4+$B11/10000)-1)+Supuestos!E$28*((1+Supuestos!E$27+$A11/10000)*(1+Supuestos!$B$4+$B11/10000)-1)*(1-Supuestos!$B$6) | H11: =(1-Supuestos!F$28)*((1+((1+Supuestos!F$26)/(1+Supuestos!$B$4)-1+Supuestos!$B$14*$A11/10000))*(1+Supuestos!$B$4+$B11/10000)-1)+Supuestos!F$28*((1+Supuestos!F$27+$A11/10000)*(1+Supuestos!$B$4+$B11/10000)-1)*(1-Supuestos!$B$6) | I11: =(1-Supuestos!G$28)*((1+((1+Supuestos!G$26)/(1+Supuestos!$B$4)-1+Supuestos!$B$14*$A11/10000))*(1+Supuestos!$B$4+$B11/10000)-1)+Supuestos!G$28*((1+Supuestos!G$27+$A11/10000)*(1+Supuestos!$B$4+$B11/10000)-1)*(1-Supuestos!$B$6) | J11: =(1-Supuestos!H$28)*((1+((1+Supuestos!H$26)/(1+Supuestos!$B$4)-1+Supuestos!$B$14*$A11/10000))*(1+Supuestos!$B$4+$B11/10000)-1)+Supuestos!H$28*((1+Supuestos!H$27+$A11/10000)*(1+Supuestos!$B$4+$B11/10000)-1)*(1-Supuestos!$B$6) | K11: =(1-Supuestos!I$28)*((1+((1+Supuestos!I$26)/(1+Supuestos!$B$4)-1+Supuestos!$B$14*$A11/10000))*(1+Supuestos!$B$4+$B11/10000)-1)+Supuestos!I$28*((1+Supuestos!I$27+$A11/10000)*(1+Supuestos!$B$4+$B11/10000)-1)*(1-Supuestos!$B$6) | L11: =(1+E11)^-Supuestos!C$24 | M11: =L11*(1+F11)^-Supuestos!D$24 | N11: =M11*(1+G11)^-Supuestos!E$24 | O11: =N11*(1+H11)^-Supuestos!F$24 | P11: =O11*(1+I11)^-Supuestos!G$24 | Q11: =P11*(1+J11)^-Supuestos!H$24 | R11: =(1+E11)^-(Supuestos!C$24/2) | S11: =L11*(1+F11)^-(Supuestos!D$24/2) | T11: =M11*(1+G11)^-(Supuestos!E$24/2) | U11: =N11*(1+H11)^-(Supuestos!F$24/2) | V11: =O11*(1+I11)^-(Supuestos!G$24/2) | W11: =P11*(1+J11)^-(Supuestos!H$24/2) | X11: =Supuestos!C$23*(1-$C11+$C11*((1+Supuestos!$B$4+$B11/10000)/(1+Supuestos!$B$4))^Supuestos!C$25) | Y11: =Supuestos!D$23*(1-$C11+$C11*((1+Supuestos!$B$4+$B11/10000)/(1+Supuestos!$B$4))^Supuestos!D$25) | Z11: =Supuestos!E$23*(1-$C11+$C11*((1+Supuestos!$B$4+$B11/10000)/(1+Supuestos!$B$4))^Supuestos!E$25) | AA11: =Supuestos!F$23*(1-$C11+$C11*((1+Supuestos!$B$4+$B11/10000)/(1+Supuestos!$B$4))^Supuestos!F$25) | AB11: =Supuestos!G$23*(1-$C11+$C11*((1+Supuestos!$B$4+$B11/10000)/(1+Supuestos!$B$4))^Supuestos!G$25) | AC11: =Supuestos!H$23*(1-$C11+$C11*((1+Supuestos!$B$4+$B11/10000)/(1+Supuestos!$B$4))^Supuestos!H$25) | AD11: =Supuestos!I$23*(1-$C11+$C11*((1+Supuestos!$B$4+$B11/10000)/(1+Supuestos!$B$4))^Supuestos!I$25) | AE11: =SUMPRODUCT(X11:AC11,R11:W11) | AF11: =(1+Supuestos!$B$5)/(1+Supuestos!$B$4)*(1+Supuestos!$B$4+$B11/10000)-1 | AG11: =AD11/(K11-AF11) | AH11: =AG11*Q11 | AI11: =(AE11+AH11-Supuestos!$B$7-Supuestos!$B$8)/Supuestos!$B$9 | AJ11: =AI11/AI$5-1
A12: 150 | B12: -100 | C12: =Supuestos!$B$13 | D12: Grilla | E12: =(1-Supuestos!C$28)*((1+((1+Supuestos!C$26)/(1+Supuestos!$B$4)-1+Supuestos!$B$14*$A12/10000))*(1+Supuestos!$B$4+$B12/10000)-1)+Supuestos!C$28*((1+Supuestos!C$27+$A12/10000)*(1+Supuestos!$B$4+$B12/10000)-1)*(1-Supuestos!$B$6) | F12: =(1-Supuestos!D$28)*((1+((1+Supuestos!D$26)/(1+Supuestos!$B$4)-1+Supuestos!$B$14*$A12/10000))*(1+Supuestos!$B$4+$B12/10000)-1)+Supuestos!D$28*((1+Supuestos!D$27+$A12/10000)*(1+Supuestos!$B$4+$B12/10000)-1)*(1-Supuestos!$B$6) | G12: =(1-Supuestos!E$28)*((1+((1+Supuestos!E$26)/(1+Supuestos!$B$4)-1+Supuestos!$B$14*$A12/10000))*(1+Supuestos!$B$4+$B12/10000)-1)+Supuestos!E$28*((1+Supuestos!E$27+$A12/10000)*(1+Supuestos!$B$4+$B12/10000)-1)*(1-Supuestos!$B$6) | H12: =(1-Supuestos!F$28)*((1+((1+Supuestos!F$26)/(1+Supuestos!$B$4)-1+Supuestos!$B$14*$A12/10000))*(1+Supuestos!$B$4+$B12/10000)-1)+Supuestos!F$28*((1+Supuestos!F$27+$A12/10000)*(1+Supuestos!$B$4+$B12/10000)-1)*(1-Supuestos!$B$6) | I12: =(1-Supuestos!G$28)*((1+((1+Supuestos!G$26)/(1+Supuestos!$B$4)-1+Supuestos!$B$14*$A12/10000))*(1+Supuestos!$B$4+$B12/10000)-1)+Supuestos!G$28*((1+Supuestos!G$27+$A12/10000)*(1+Supuestos!$B$4+$B12/10000)-1)*(1-Supuestos!$B$6) | J12: =(1-Supuestos!H$28)*((1+((1+Supuestos!H$26)/(1+Supuestos!$B$4)-1+Supuestos!$B$14*$A12/10000))*(1+Supuestos!$B$4+$B12/10000)-1)+Supuestos!H$28*((1+Supuestos!H$27+$A12/10000)*(1+Supuestos!$B$4+$B12/10000)-1)*(1-Supuestos!$B$6) | K12: =(1-Supuestos!I$28)*((1+((1+Supuestos!I$26)/(1+Supuestos!$B$4)-1+Supuestos!$B$14*$A12/10000))*(1+Supuestos!$B$4+$B12/10000)-1)+Supuestos!I$28*((1+Supuestos!I$27+$A12/10000)*(1+Supuestos!$B$4+$B12/10000)-1)*(1-Supuestos!$B$6) | L12: =(1+E12)^-Supuestos!C$24 | M12: =L12*(1+F12)^-Supuestos!D$24 | N12: =M12*(1+G12)^-Supuestos!E$24 | O12: =N12*(1+H12)^-Supuestos!F$24 | P12: =O12*(1+I12)^-Supuestos!G$24 | Q12: =P12*(1+J12)^-Supuestos!H$24 | R12: =(1+E12)^-(Supuestos!C$24/2) | S12: =L12*(1+F12)^-(Supuestos!D$24/2) | T12: =M12*(1+G12)^-(Supuestos!E$24/2) | U12: =N12*(1+H12)^-(Supuestos!F$24/2) | V12: =O12*(1+I12)^-(Supuestos!G$24/2) | W12: =P12*(1+J12)^-(Supuestos!H$24/2) | X12: =Supuestos!C$23*(1-$C12+$C12*((1+Supuestos!$B$4+$B12/10000)/(1+Supuestos!$B$4))^Supuestos!C$25) | Y12: =Supuestos!D$23*(1-$C12+$C12*((1+Supuestos!$B$4+$B12/10000)/(1+Supuestos!$B$4))^Supuestos!D$25) | Z12: =Supuestos!E$23*(1-$C12+$C12*((1+Supuestos!$B$4+$B12/10000)/(1+Supuestos!$B$4))^Supuestos!E$25) | AA12: =Supuestos!F$23*(1-$C12+$C12*((1+Supuestos!$B$4+$B12/10000)/(1+Supuestos!$B$4))^Supuestos!F$25) | AB12: =Supuestos!G$23*(1-$C12+$C12*((1+Supuestos!$B$4+$B12/10000)/(1+Supuestos!$B$4))^Supuestos!G$25) | AC12: =Supuestos!H$23*(1-$C12+$C12*((1+Supuestos!$B$4+$B12/10000)/(1+Supuestos!$B$4))^Supuestos!H$25) | AD12: =Supuestos!I$23*(1-$C12+$C12*((1+Supuestos!$B$4+$B12/10000)/(1+Supuestos!$B$4))^Supuestos!I$25) | AE12: =SUMPRODUCT(X12:AC12,R12:W12) | AF12: =(1+Supuestos!$B$5)/(1+Supuestos!$B$4)*(1+Supuestos!$B$4+$B12/10000)-1 | AG12: =AD12/(K12-AF12) | AH12: =AG12*Q12 | AI12: =(AE12+AH12-Supuestos!$B$7-Supuestos!$B$8)/Supuestos!$B$9 | AJ12: =AI12/AI$5-1
A13: -150 | B13: -50 | C13: =Supuestos!$B$13 | D13: Grilla | E13: =(1-Supuestos!C$28)*((1+((1+Supuestos!C$26)/(1+Supuestos!$B$4)-1+Supuestos!$B$14*$A13/10000))*(1+Supuestos!$B$4+$B13/10000)-1)+Supuestos!C$28*((1+Supuestos!C$27+$A13/10000)*(1+Supuestos!$B$4+$B13/10000)-1)*(1-Supuestos!$B$6) | F13: =(1-Supuestos!D$28)*((1+((1+Supuestos!D$26)/(1+Supuestos!$B$4)-1+Supuestos!$B$14*$A13/10000))*(1+Supuestos!$B$4+$B13/10000)-1)+Supuestos!D$28*((1+Supuestos!D$27+$A13/10000)*(1+Supuestos!$B$4+$B13/10000)-1)*(1-Supuestos!$B$6) | G13: =(1-Supuestos!E$28)*((1+((1+Supuestos!E$26)/(1+Supuestos!$B$4)-1+Supuestos!$B$14*$A13/10000))*(1+Supuestos!$B$4+$B13/10000)-1)+Supuestos!E$28*((1+Supuestos!E$27+$A13/10000)*(1+Supuestos!$B$4+$B13/10000)-1)*(1-Supuestos!$B$6) | H13: =(1-Supuestos!F$28)*((1+((1+Supuestos!F$26)/(1+Supuestos!$B$4)-1+Supuestos!$B$14*$A13/10000))*(1+Supuestos!$B$4+$B13/10000)-1)+Supuestos!F$28*((1+Supuestos!F$27+$A13/10000)*(1+Supuestos!$B$4+$B13/10000)-1)*(1-Supuestos!$B$6) | I13: =(1-Supuestos!G$28)*((1+((1+Supuestos!G$26)/(1+Supuestos!$B$4)-1+Supuestos!$B$14*$A13/10000))*(1+Supuestos!$B$4+$B13/10000)-1)+Supuestos!G$28*((1+Supuestos!G$27+$A13/10000)*(1+Supuestos!$B$4+$B13/10000)-1)*(1-Supuestos!$B$6) | J13: =(1-Supuestos!H$28)*((1+((1+Supuestos!H$26)/(1+Supuestos!$B$4)-1+Supuestos!$B$14*$A13/10000))*(1+Supuestos!$B$4+$B13/10000)-1)+Supuestos!H$28*((1+Supuestos!H$27+$A13/10000)*(1+Supuestos!$B$4+$B13/10000)-1)*(1-Supuestos!$B$6) | K13: =(1-Supuestos!I$28)*((1+((1+Supuestos!I$26)/(1+Supuestos!$B$4)-1+Supuestos!$B$14*$A13/10000))*(1+Supuestos!$B$4+$B13/10000)-1)+Supuestos!I$28*((1+Supuestos!I$27+$A13/10000)*(1+Supuestos!$B$4+$B13/10000)-1)*(1-Supuestos!$B$6) | L13: =(1+E13)^-Supuestos!C$24 | M13: =L13*(1+F13)^-Supuestos!D$24 | N13: =M13*(1+G13)^-Supuestos!E$24 | O13: =N13*(1+H13)^-Supuestos!F$24 | P13: =O13*(1+I13)^-Supuestos!G$24 | Q13: =P13*(1+J13)^-Supuestos!H$24 | R13: =(1+E13)^-(Supuestos!C$24/2) | S13: =L13*(1+F13)^-(Supuestos!D$24/2) | T13: =M13*(1+G13)^-(Supuestos!E$24/2) | U13: =N13*(1+H13)^-(Supuestos!F$24/2) | V13: =O13*(1+I13)^-(Supuestos!G$24/2) | W13: =P13*(1+J13)^-(Supuestos!H$24/2) | X13: =Supuestos!C$23*(1-$C13+$C13*((1+Supuestos!$B$4+$B13/10000)/(1+Supuestos!$B$4))^Supuestos!C$25) | Y13: =Supuestos!D$23*(1-$C13+$C13*((1+Supuestos!$B$4+$B13/10000)/(1+Supuestos!$B$4))^Supuestos!D$25) | Z13: =Supuestos!E$23*(1-$C13+$C13*((1+Supuestos!$B$4+$B13/10000)/(1+Supuestos!$B$4))^Supuestos!E$25) | AA13: =Supuestos!F$23*(1-$C13+$C13*((1+Supuestos!$B$4+$B13/10000)/(1+Supuestos!$B$4))^Supuestos!F$25) | AB13: =Supuestos!G$23*(1-$C13+$C13*((1+Supuestos!$B$4+$B13/10000)/(1+Supuestos!$B$4))^Supuestos!G$25) | AC13: =Supuestos!H$23*(1-$C13+$C13*((1+Supuestos!$B$4+$B13/10000)/(1+Supuestos!$B$4))^Supuestos!H$25) | AD13: =Supuestos!I$23*(1-$C13+$C13*((1+Supuestos!$B$4+$B13/10000)/(1+Supuestos!$B$4))^Supuestos!I$25) | AE13: =SUMPRODUCT(X13:AC13,R13:W13) | AF13: =(1+Supuestos!$B$5)/(1+Supuestos!$B$4)*(1+Supuestos!$B$4+$B13/10000)-1 | AG13: =AD13/(K13-AF13) | AH13: =AG13*Q13 | AI13: =(AE13+AH13-Supuestos!$B$7-Supuestos!$B$8)/Supuestos!$B$9 | AJ13: =AI13/AI$5-1
A14: -100 | B14: -50 | C14: =Supuestos!$B$13 | D14: Grilla | E14: =(1-Supuestos!C$28)*((1+((1+Supuestos!C$26)/(1+Supuestos!$B$4)-1+Supuestos!$B$14*$A14/10000))*(1+Supuestos!$B$4+$B14/10000)-1)+Supuestos!C$28*((1+Supuestos!C$27+$A14/10000)*(1+Supuestos!$B$4+$B14/10000)-1)*(1-Supuestos!$B$6) | F14: =(1-Supuestos!D$28)*((1+((1+Supuestos!D$26)/(1+Supuestos!$B$4)-1+Supuestos!$B$14*$A14/10000))*(1+Supuestos!$B$4+$B14/10000)-1)+Supuestos!D$28*((1+Supuestos!D$27+$A14/10000)*(1+Supuestos!$B$4+$B14/10000)-1)*(1-Supuestos!$B$6) | G14: =(1-Supuestos!E$28)*((1+((1+Supuestos!E$26)/(1+Supuestos!$B$4)-1+Supuestos!$B$14*$A14/10000))*(1+Supuestos!$B$4+$B14/10000)-1)+Supuestos!E$28*((1+Supuestos!E$27+$A14/10000)*(1+Supuestos!$B$4+$B14/10000)-1)*(1-Supuestos!$B$6) | H14: =(1-Supuestos!F$28)*((1+((1+Supuestos!F$26)/(1+Supuestos!$B$4)-1+Supuestos!$B$14*$A14/10000))*(1+Supuestos!$B$4+$B14/10000)-1)+Supuestos!F$28*((1+Supuestos!F$27+$A14/10000)*(1+Supuestos!$B$4+$B14/10000)-1)*(1-Supuestos!$B$6) | I14: =(1-Supuestos!G$28)*((1+((1+Supuestos!G$26)/(1+Supuestos!$B$4)-1+Supuestos!$B$14*$A14/10000))*(1+Supuestos!$B$4+$B14/10000)-1)+Supuestos!G$28*((1+Supuestos!G$27+$A14/10000)*(1+Supuestos!$B$4+$B14/10000)-1)*(1-Supuestos!$B$6) | J14: =(1-Supuestos!H$28)*((1+((1+Supuestos!H$26)/(1+Supuestos!$B$4)-1+Supuestos!$B$14*$A14/10000))*(1+Supuestos!$B$4+$B14/10000)-1)+Supuestos!H$28*((1+Supuestos!H$27+$A14/10000)*(1+Supuestos!$B$4+$B14/10000)-1)*(1-Supuestos!$B$6) | K14: =(1-Supuestos!I$28)*((1+((1+Supuestos!I$26)/(1+Supuestos!$B$4)-1+Supuestos!$B$14*$A14/10000))*(1+Supuestos!$B$4+$B14/10000)-1)+Supuestos!I$28*((1+Supuestos!I$27+$A14/10000)*(1+Supuestos!$B$4+$B14/10000)-1)*(1-Supuestos!$B$6) | L14: =(1+E14)^-Supuestos!C$24 | M14: =L14*(1+F14)^-Supuestos!D$24 | N14: =M14*(1+G14)^-Supuestos!E$24 | O14: =N14*(1+H14)^-Supuestos!F$24 | P14: =O14*(1+I14)^-Supuestos!G$24 | Q14: =P14*(1+J14)^-Supuestos!H$24 | R14: =(1+E14)^-(Supuestos!C$24/2) | S14: =L14*(1+F14)^-(Supuestos!D$24/2) | T14: =M14*(1+G14)^-(Supuestos!E$24/2) | U14: =N14*(1+H14)^-(Supuestos!F$24/2) | V14: =O14*(1+I14)^-(Supuestos!G$24/2) | W14: =P14*(1+J14)^-(Supuestos!H$24/2) | X14: =Supuestos!C$23*(1-$C14+$C14*((1+Supuestos!$B$4+$B14/10000)/(1+Supuestos!$B$4))^Supuestos!C$25) | Y14: =Supuestos!D$23*(1-$C14+$C14*((1+Supuestos!$B$4+$B14/10000)/(1+Supuestos!$B$4))^Supuestos!D$25) | Z14: =Supuestos!E$23*(1-$C14+$C14*((1+Supuestos!$B$4+$B14/10000)/(1+Supuestos!$B$4))^Supuestos!E$25) | AA14: =Supuestos!F$23*(1-$C14+$C14*((1+Supuestos!$B$4+$B14/10000)/(1+Supuestos!$B$4))^Supuestos!F$25) | AB14: =Supuestos!G$23*(1-$C14+$C14*((1+Supuestos!$B$4+$B14/10000)/(1+Supuestos!$B$4))^Supuestos!G$25) | AC14: =Supuestos!H$23*(1-$C14+$C14*((1+Supuestos!$B$4+$B14/10000)/(1+Supuestos!$B$4))^Supuestos!H$25) | AD14: =Supuestos!I$23*(1-$C14+$C14*((1+Supuestos!$B$4+$B14/10000)/(1+Supuestos!$B$4))^Supuestos!I$25) | AE14: =SUMPRODUCT(X14:AC14,R14:W14) | AF14: =(1+Supuestos!$B$5)/(1+Supuestos!$B$4)*(1+Supuestos!$B$4+$B14/10000)-1 | AG14: =AD14/(K14-AF14) | AH14: =AG14*Q14 | AI14: =(AE14+AH14-Supuestos!$B$7-Supuestos!$B$8)/Supuestos!$B$9 | AJ14: =AI14/AI$5-1
A15: -50 | B15: -50 | C15: =Supuestos!$B$13 | D15: Grilla | E15: =(1-Supuestos!C$28)*((1+((1+Supuestos!C$26)/(1+Supuestos!$B$4)-1+Supuestos!$B$14*$A15/10000))*(1+Supuestos!$B$4+$B15/10000)-1)+Supuestos!C$28*((1+Supuestos!C$27+$A15/10000)*(1+Supuestos!$B$4+$B15/10000)-1)*(1-Supuestos!$B$6) | F15: =(1-Supuestos!D$28)*((1+((1+Supuestos!D$26)/(1+Supuestos!$B$4)-1+Supuestos!$B$14*$A15/10000))*(1+Supuestos!$B$4+$B15/10000)-1)+Supuestos!D$28*((1+Supuestos!D$27+$A15/10000)*(1+Supuestos!$B$4+$B15/10000)-1)*(1-Supuestos!$B$6) | G15: =(1-Supuestos!E$28)*((1+((1+Supuestos!E$26)/(1+Supuestos!$B$4)-1+Supuestos!$B$14*$A15/10000))*(1+Supuestos!$B$4+$B15/10000)-1)+Supuestos!E$28*((1+Supuestos!E$27+$A15/10000)*(1+Supuestos!$B$4+$B15/10000)-1)*(1-Supuestos!$B$6) | H15: =(1-Supuestos!F$28)*((1+((1+Supuestos!F$26)/(1+Supuestos!$B$4)-1+Supuestos!$B$14*$A15/10000))*(1+Supuestos!$B$4+$B15/10000)-1)+Supuestos!F$28*((1+Supuestos!F$27+$A15/10000)*(1+Supuestos!$B$4+$B15/10000)-1)*(1-Supuestos!$B$6) | I15: =(1-Supuestos!G$28)*((1+((1+Supuestos!G$26)/(1+Supuestos!$B$4)-1+Supuestos!$B$14*$A15/10000))*(1+Supuestos!$B$4+$B15/10000)-1)+Supuestos!G$28*((1+Supuestos!G$27+$A15/10000)*(1+Supuestos!$B$4+$B15/10000)-1)*(1-Supuestos!$B$6) | J15: =(1-Supuestos!H$28)*((1+((1+Supuestos!H$26)/(1+Supuestos!$B$4)-1+Supuestos!$B$14*$A15/10000))*(1+Supuestos!$B$4+$B15/10000)-1)+Supuestos!H$28*((1+Supuestos!H$27+$A15/10000)*(1+Supuestos!$B$4+$B15/10000)-1)*(1-Supuestos!$B$6) | K15: =(1-Supuestos!I$28)*((1+((1+Supuestos!I$26)/(1+Supuestos!$B$4)-1+Supuestos!$B$14*$A15/10000))*(1+Supuestos!$B$4+$B15/10000)-1)+Supuestos!I$28*((1+Supuestos!I$27+$A15/10000)*(1+Supuestos!$B$4+$B15/10000)-1)*(1-Supuestos!$B$6) | L15: =(1+E15)^-Supuestos!C$24 | M15: =L15*(1+F15)^-Supuestos!D$24 | N15: =M15*(1+G15)^-Supuestos!E$24 | O15: =N15*(1+H15)^-Supuestos!F$24 | P15: =O15*(1+I15)^-Supuestos!G$24 | Q15: =P15*(1+J15)^-Supuestos!H$24 | R15: =(1+E15)^-(Supuestos!C$24/2) | S15: =L15*(1+F15)^-(Supuestos!D$24/2) | T15: =M15*(1+G15)^-(Supuestos!E$24/2) | U15: =N15*(1+H15)^-(Supuestos!F$24/2) | V15: =O15*(1+I15)^-(Supuestos!G$24/2) | W15: =P15*(1+J15)^-(Supuestos!H$24/2) | X15: =Supuestos!C$23*(1-$C15+$C15*((1+Supuestos!$B$4+$B15/10000)/(1+Supuestos!$B$4))^Supuestos!C$25) | Y15: =Supuestos!D$23*(1-$C15+$C15*((1+Supuestos!$B$4+$B15/10000)/(1+Supuestos!$B$4))^Supuestos!D$25) | Z15: =Supuestos!E$23*(1-$C15+$C15*((1+Supuestos!$B$4+$B15/10000)/(1+Supuestos!$B$4))^Supuestos!E$25) | AA15: =Supuestos!F$23*(1-$C15+$C15*((1+Supuestos!$B$4+$B15/10000)/(1+Supuestos!$B$4))^Supuestos!F$25) | AB15: =Supuestos!G$23*(1-$C15+$C15*((1+Supuestos!$B$4+$B15/10000)/(1+Supuestos!$B$4))^Supuestos!G$25) | AC15: =Supuestos!H$23*(1-$C15+$C15*((1+Supuestos!$B$4+$B15/10000)/(1+Supuestos!$B$4))^Supuestos!H$25) | AD15: =Supuestos!I$23*(1-$C15+$C15*((1+Supuestos!$B$4+$B15/10000)/(1+Supuestos!$B$4))^Supuestos!I$25) | AE15: =SUMPRODUCT(X15:AC15,R15:W15) | AF15: =(1+Supuestos!$B$5)/(1+Supuestos!$B$4)*(1+Supuestos!$B$4+$B15/10000)-1 | AG15: =AD15/(K15-AF15) | AH15: =AG15*Q15 | AI15: =(AE15+AH15-Supuestos!$B$7-Supuestos!$B$8)/Supuestos!$B$9 | AJ15: =AI15/AI$5-1
A16: 0 | B16: -50 | C16: =Supuestos!$B$13 | D16: Grilla | E16: =(1-Supuestos!C$28)*((1+((1+Supuestos!C$26)/(1+Supuestos!$B$4)-1+Supuestos!$B$14*$A16/10000))*(1+Supuestos!$B$4+$B16/10000)-1)+Supuestos!C$28*((1+Supuestos!C$27+$A16/10000)*(1+Supuestos!$B$4+$B16/10000)-1)*(1-Supuestos!$B$6) | F16: =(1-Supuestos!D$28)*((1+((1+Supuestos!D$26)/(1+Supuestos!$B$4)-1+Supuestos!$B$14*$A16/10000))*(1+Supuestos!$B$4+$B16/10000)-1)+Supuestos!D$28*((1+Supuestos!D$27+$A16/10000)*(1+Supuestos!$B$4+$B16/10000)-1)*(1-Supuestos!$B$6) | G16: =(1-Supuestos!E$28)*((1+((1+Supuestos!E$26)/(1+Supuestos!$B$4)-1+Supuestos!$B$14*$A16/10000))*(1+Supuestos!$B$4+$B16/10000)-1)+Supuestos!E$28*((1+Supuestos!E$27+$A16/10000)*(1+Supuestos!$B$4+$B16/10000)-1)*(1-Supuestos!$B$6) | H16: =(1-Supuestos!F$28)*((1+((1+Supuestos!F$26)/(1+Supuestos!$B$4)-1+Supuestos!$B$14*$A16/10000))*(1+Supuestos!$B$4+$B16/10000)-1)+Supuestos!F$28*((1+Supuestos!F$27+$A16/10000)*(1+Supuestos!$B$4+$B16/10000)-1)*(1-Supuestos!$B$6) | I16: =(1-Supuestos!G$28)*((1+((1+Supuestos!G$26)/(1+Supuestos!$B$4)-1+Supuestos!$B$14*$A16/10000))*(1+Supuestos!$B$4+$B16/10000)-1)+Supuestos!G$28*((1+Supuestos!G$27+$A16/10000)*(1+Supuestos!$B$4+$B16/10000)-1)*(1-Supuestos!$B$6) | J16: =(1-Supuestos!H$28)*((1+((1+Supuestos!H$26)/(1+Supuestos!$B$4)-1+Supuestos!$B$14*$A16/10000))*(1+Supuestos!$B$4+$B16/10000)-1)+Supuestos!H$28*((1+Supuestos!H$27+$A16/10000)*(1+Supuestos!$B$4+$B16/10000)-1)*(1-Supuestos!$B$6) | K16: =(1-Supuestos!I$28)*((1+((1+Supuestos!I$26)/(1+Supuestos!$B$4)-1+Supuestos!$B$14*$A16/10000))*(1+Supuestos!$B$4+$B16/10000)-1)+Supuestos!I$28*((1+Supuestos!I$27+$A16/10000)*(1+Supuestos!$B$4+$B16/10000)-1)*(1-Supuestos!$B$6) | L16: =(1+E16)^-Supuestos!C$24 | M16: =L16*(1+F16)^-Supuestos!D$24 | N16: =M16*(1+G16)^-Supuestos!E$24 | O16: =N16*(1+H16)^-Supuestos!F$24 | P16: =O16*(1+I16)^-Supuestos!G$24 | Q16: =P16*(1+J16)^-Supuestos!H$24 | R16: =(1+E16)^-(Supuestos!C$24/2) | S16: =L16*(1+F16)^-(Supuestos!D$24/2) | T16: =M16*(1+G16)^-(Supuestos!E$24/2) | U16: =N16*(1+H16)^-(Supuestos!F$24/2) | V16: =O16*(1+I16)^-(Supuestos!G$24/2) | W16: =P16*(1+J16)^-(Supuestos!H$24/2) | X16: =Supuestos!C$23*(1-$C16+$C16*((1+Supuestos!$B$4+$B16/10000)/(1+Supuestos!$B$4))^Supuestos!C$25) | Y16: =Supuestos!D$23*(1-$C16+$C16*((1+Supuestos!$B$4+$B16/10000)/(1+Supuestos!$B$4))^Supuestos!D$25) | Z16: =Supuestos!E$23*(1-$C16+$C16*((1+Supuestos!$B$4+$B16/10000)/(1+Supuestos!$B$4))^Supuestos!E$25) | AA16: =Supuestos!F$23*(1-$C16+$C16*((1+Supuestos!$B$4+$B16/10000)/(1+Supuestos!$B$4))^Supuestos!F$25) | AB16: =Supuestos!G$23*(1-$C16+$C16*((1+Supuestos!$B$4+$B16/10000)/(1+Supuestos!$B$4))^Supuestos!G$25) | AC16: =Supuestos!H$23*(1-$C16+$C16*((1+Supuestos!$B$4+$B16/10000)/(1+Supuestos!$B$4))^Supuestos!H$25) | AD16: =Supuestos!I$23*(1-$C16+$C16*((1+Supuestos!$B$4+$B16/10000)/(1+Supuestos!$B$4))^Supuestos!I$25) | AE16: =SUMPRODUCT(X16:AC16,R16:W16) | AF16: =(1+Supuestos!$B$5)/(1+Supuestos!$B$4)*(1+Supuestos!$B$4+$B16/10000)-1 | AG16: =AD16/(K16-AF16) | AH16: =AG16*Q16 | AI16: =(AE16+AH16-Supuestos!$B$7-Supuestos!$B$8)/Supuestos!$B$9 | AJ16: =AI16/AI$5-1
... A40: 150 | B40: 100 | C40: =Supuestos!$B$13 | D40: Grilla | E40: =(1-Supuestos!C$28)*((1+((1+Supuestos!C$26)/(1+Supuestos!$B$4)-1+Supuestos!$B$14*$A40/10000))*(1+Supuestos!$B$4+$B40/10000)-1)+Supuestos!C$28*((1+Supuestos!C$27+$A40/10000)*(1+Supuestos!$B$4+$B40/10000)-1)*(1-Supuestos!$B$6) | F40: =(1-Supuestos!D$28)*((1+((1+Supuestos!D$26)/(1+Supuestos!$B$4)-1+Supuestos!$B$14*$A40/10000))*(1+Supuestos!$B$4+$B40/10000)-1)+Supuestos!D$28*((1+Supuestos!D$27+$A40/10000)*(1+Supuestos!$B$4+$B40/10000)-1)*(1-Supuestos!$B$6) | G40: =(1-Supuestos!E$28)*((1+((1+Supuestos!E$26)/(1+Supuestos!$B$4)-1+Supuestos!$B$14*$A40/10000))*(1+Supuestos!$B$4+$B40/10000)-1)+Supuestos!E$28*((1+Supuestos!E$27+$A40/10000)*(1+Supuestos!$B$4+$B40/10000)-1)*(1-Supuestos!$B$6) | H40: =(1-Supuestos!F$28)*((1+((1+Supuestos!F$26)/(1+Supuestos!$B$4)-1+Supuestos!$B$14*$A40/10000))*(1+Supuestos!$B$4+$B40/10000)-1)+Supuestos!F$28*((1+Supuestos!F$27+$A40/10000)*(1+Supuestos!$B$4+$B40/10000)-1)*(1-Supuestos!$B$6) | I40: =(1-Supuestos!G$28)*((1+((1+Supuestos!G$26)/(1+Supuestos!$B$4)-1+Supuestos!$B$14*$A40/10000))*(1+Supuestos!$B$4+$B40/10000)-1)+Supuestos!G$28*((1+Supuestos!G$27+$A40/10000)*(1+Supuestos!$B$4+$B40/10000)-1)*(1-Supuestos!$B$6) | J40: =(1-Supuestos!H$28)*((1+((1+Supuestos!H$26)/(1+Supuestos!$B$4)-1+Supuestos!$B$14*$A40/10000))*(1+Supuestos!$B$4+$B40/10000)-1)+Supuestos!H$28*((1+Supuestos!H$27+$A40/10000)*(1+Supuestos!$B$4+$B40/10000)-1)*(1-Supuestos!$B$6) | K40: =(1-Supuestos!I$28)*((1+((1+Supuestos!I$26)/(1+Supuestos!$B$4)-1+Supuestos!$B$14*$A40/10000))*(1+Supuestos!$B$4+$B40/10000)-1)+Supuestos!I$28*((1+Supuestos!I$27+$A40/10000)*(1+Supuestos!$B$4+$B40/10000)-1)*(1-Supuestos!$B$6) | L40: =(1+E40)^-Supuestos!C$24 | M40: =L40*(1+F40)^-Supuestos!D$24 | N40: =M40*(1+G40)^-Supuestos!E$24 | O40: =N40*(1+H40)^-Supuestos!F$24 | P40: =O40*(1+I40)^-Supuestos!G$24 | Q40: =P40*(1+J40)^-Supuestos!H$24 | R40: =(1+E40)^-(Supuestos!C$24/2) | S40: =L40*(1+F40)^-(Supuestos!D$24/2) | T40: =M40*(1+G40)^-(Supuestos!E$24/2) | U40: =N40*(1+H40)^-(Supuestos!F$24/2) | V40: =O40*(1+I40)^-(Supuestos!G$24/2) | W40: =P40*(1+J40)^-(Supuestos!H$24/2) | X40: =Supuestos!C$23*(1-$C40+$C40*((1+Supuestos!$B$4+$B40/10000)/(1+Supuestos!$B$4))^Supuestos!C$25) | Y40: =Supuestos!D$23*(1-$C40+$C40*((1+Supuestos!$B$4+$B40/10000)/(1+Supuestos!$B$4))^Supuestos!D$25) | Z40: =Supuestos!E$23*(1-$C40+$C40*((1+Supuestos!$B$4+$B40/10000)/(1+Supuestos!$B$4))^Supuestos!E$25) | AA40: =Supuestos!F$23*(1-$C40+$C40*((1+Supuestos!$B$4+$B40/10000)/(1+Supuestos!$B$4))^Supuestos!F$25) | AB40: =Supuestos!G$23*(1-$C40+$C40*((1+Supuestos!$B$4+$B40/10000)/(1+Supuestos!$B$4))^Supuestos!G$25) | AC40: =Supuestos!H$23*(1-$C40+$C40*((1+Supuestos!$B$4+$B40/10000)/(1+Supuestos!$B$4))^Supuestos!H$25) | AD40: =Supuestos!I$23*(1-$C40+$C40*((1+Supuestos!$B$4+$B40/10000)/(1+Supuestos!$B$4))^Supuestos!I$25) | AE40: =SUMPRODUCT(X40:AC40,R40:W40) | AF40: =(1+Supuestos!$B$5)/(1+Supuestos!$B$4)*(1+Supuestos!$B$4+$B40/10000)-1 | AG40: =AD40/(K40-AF40) | AH40: =AG40*Q40 | AI40: =(AE40+AH40-Supuestos!$B$7-Supuestos!$B$8)/Supuestos!$B$9 | AJ40: =AI40/AI$5-1
A41: 100 | B41: 0 | C41: 1 | D41: Mix Δi=+100 θ=1.0 | E41: =(1-Supuestos!C$28)*((1+((1+Supuestos!C$26)/(1+Supuestos!$B$4)-1+Supuestos!$B$14*$A41/10000))*(1+Supuestos!$B$4+$B41/10000)-1)+Supuestos!C$28*((1+Supuestos!C$27+$A41/10000)*(1+Supuestos!$B$4+$B41/10000)-1)*(1-Supuestos!$B$6) | F41: =(1-Supuestos!D$28)*((1+((1+Supuestos!D$26)/(1+Supuestos!$B$4)-1+Supuestos!$B$14*$A41/10000))*(1+Supuestos!$B$4+$B41/10000)-1)+Supuestos!D$28*((1+Supuestos!D$27+$A41/10000)*(1+Supuestos!$B$4+$B41/10000)-1)*(1-Supuestos!$B$6) | G41: =(1-Supuestos!E$28)*((1+((1+Supuestos!E$26)/(1+Supuestos!$B$4)-1+Supuestos!$B$14*$A41/10000))*(1+Supuestos!$B$4+$B41/10000)-1)+Supuestos!E$28*((1+Supuestos!E$27+$A41/10000)*(1+Supuestos!$B$4+$B41/10000)-1)*(1-Supuestos!$B$6) | H41: =(1-Supuestos!F$28)*((1+((1+Supuestos!F$26)/(1+Supuestos!$B$4)-1+Supuestos!$B$14*$A41/10000))*(1+Supuestos!$B$4+$B41/10000)-1)+Supuestos!F$28*((1+Supuestos!F$27+$A41/10000)*(1+Supuestos!$B$4+$B41/10000)-1)*(1-Supuestos!$B$6) | I41: =(1-Supuestos!G$28)*((1+((1+Supuestos!G$26)/(1+Supuestos!$B$4)-1+Supuestos!$B$14*$A41/10000))*(1+Supuestos!$B$4+$B41/10000)-1)+Supuestos!G$28*((1+Supuestos!G$27+$A41/10000)*(1+Supuestos!$B$4+$B41/10000)-1)*(1-Supuestos!$B$6) | J41: =(1-Supuestos!H$28)*((1+((1+Supuestos!H$26)/(1+Supuestos!$B$4)-1+Supuestos!$B$14*$A41/10000))*(1+Supuestos!$B$4+$B41/10000)-1)+Supuestos!H$28*((1+Supuestos!H$27+$A41/10000)*(1+Supuestos!$B$4+$B41/10000)-1)*(1-Supuestos!$B$6) | K41: =(1-Supuestos!I$28)*((1+((1+Supuestos!I$26)/(1+Supuestos!$B$4)-1+Supuestos!$B$14*$A41/10000))*(1+Supuestos!$B$4+$B41/10000)-1)+Supuestos!I$28*((1+Supuestos!I$27+$A41/10000)*(1+Supuestos!$B$4+$B41/10000)-1)*(1-Supuestos!$B$6) | L41: =(1+E41)^-Supuestos!C$24 | M41: =L41*(1+F41)^-Supuestos!D$24 | N41: =M41*(1+G41)^-Supuestos!E$24 | O41: =N41*(1+H41)^-Supuestos!F$24 | P41: =O41*(1+I41)^-Supuestos!G$24 | Q41: =P41*(1+J41)^-Supuestos!H$24 | R41: =(1+E41)^-(Supuestos!C$24/2) | S41: =L41*(1+F41)^-(Supuestos!D$24/2) | T41: =M41*(1+G41)^-(Supuestos!E$24/2) | U41: =N41*(1+H41)^-(Supuestos!F$24/2) | V41: =O41*(1+I41)^-(Supuestos!G$24/2) | W41: =P41*(1+J41)^-(Supuestos!H$24/2) | X41: =Supuestos!C$23*(1-$C41+$C41*((1+Supuestos!$B$4+$B41/10000)/(1+Supuestos!$B$4))^Supuestos!C$25) | Y41: =Supuestos!D$23*(1-$C41+$C41*((1+Supuestos!$B$4+$B41/10000)/(1+Supuestos!$B$4))^Supuestos!D$25) | Z41: =Supuestos!E$23*(1-$C41+$C41*((1+Supuestos!$B$4+$B41/10000)/(1+Supuestos!$B$4))^Supuestos!E$25) | AA41: =Supuestos!F$23*(1-$C41+$C41*((1+Supuestos!$B$4+$B41/10000)/(1+Supuestos!$B$4))^Supuestos!F$25) | AB41: =Supuestos!G$23*(1-$C41+$C41*((1+Supuestos!$B$4+$B41/10000)/(1+Supuestos!$B$4))^Supuestos!G$25) | AC41: =Supuestos!H$23*(1-$C41+$C41*((1+Supuestos!$B$4+$B41/10000)/(1+Supuestos!$B$4))^Supuestos!H$25) | AD41: =Supuestos!I$23*(1-$C41+$C41*((1+Supuestos!$B$4+$B41/10000)/(1+Supuestos!$B$4))^Supuestos!I$25) | AE41: =SUMPRODUCT(X41:AC41,R41:W41) | AF41: =(1+Supuestos!$B$5)/(1+Supuestos!$B$4)*(1+Supuestos!$B$4+$B41/10000)-1 | AG41: =AD41/(K41-AF41) | AH41: =AG41*Q41 | AI41: =(AE41+AH41-Supuestos!$B$7-Supuestos!$B$8)/Supuestos!$B$9 | AJ41: =AI41/AI$5-1
A42: 90 | B42: 10 | C42: 1 | D42: Mix Δi=+100 θ=1.0 | E42: =(1-Supuestos!C$28)*((1+((1+Supuestos!C$26)/(1+Supuestos!$B$4)-1+Supuestos!$B$14*$A42/10000))*(1+Supuestos!$B$4+$B42/10000)-1)+Supuestos!C$28*((1+Supuestos!C$27+$A42/10000)*(1+Supuestos!$B$4+$B42/10000)-1)*(1-Supuestos!$B$6) | F42: =(1-Supuestos!D$28)*((1+((1+Supuestos!D$26)/(1+Supuestos!$B$4)-1+Supuestos!$B$14*$A42/10000))*(1+Supuestos!$B$4+$B42/10000)-1)+Supuestos!D$28*((1+Supuestos!D$27+$A42/10000)*(1+Supuestos!$B$4+$B42/10000)-1)*(1-Supuestos!$B$6) | G42: =(1-Supuestos!E$28)*((1+((1+Supuestos!E$26)/(1+Supuestos!$B$4)-1+Supuestos!$B$14*$A42/10000))*(1+Supuestos!$B$4+$B42/10000)-1)+Supuestos!E$28*((1+Supuestos!E$27+$A42/10000)*(1+Supuestos!$B$4+$B42/10000)-1)*(1-Supuestos!$B$6) | H42: =(1-Supuestos!F$28)*((1+((1+Supuestos!F$26)/(1+Supuestos!$B$4)-1+Supuestos!$B$14*$A42/10000))*(1+Supuestos!$B$4+$B42/10000)-1)+Supuestos!F$28*((1+Supuestos!F$27+$A42/10000)*(1+Supuestos!$B$4+$B42/10000)-1)*(1-Supuestos!$B$6) | I42: =(1-Supuestos!G$28)*((1+((1+Supuestos!G$26)/(1+Supuestos!$B$4)-1+Supuestos!$B$14*$A42/10000))*(1+Supuestos!$B$4+$B42/10000)-1)+Supuestos!G$28*((1+Supuestos!G$27+$A42/10000)*(1+Supuestos!$B$4+$B42/10000)-1)*(1-Supuestos!$B$6) | J42: =(1-Supuestos!H$28)*((1+((1+Supuestos!H$26)/(1+Supuestos!$B$4)-1+Supuestos!$B$14*$A42/10000))*(1+Supuestos!$B$4+$B42/10000)-1)+Supuestos!H$28*((1+Supuestos!H$27+$A42/10000)*(1+Supuestos!$B$4+$B42/10000)-1)*(1-Supuestos!$B$6) | K42: =(1-Supuestos!I$28)*((1+((1+Supuestos!I$26)/(1+Supuestos!$B$4)-1+Supuestos!$B$14*$A42/10000))*(1+Supuestos!$B$4+$B42/10000)-1)+Supuestos!I$28*((1+Supuestos!I$27+$A42/10000)*(1+Supuestos!$B$4+$B42/10000)-1)*(1-Supuestos!$B$6) | L42: =(1+E42)^-Supuestos!C$24 | M42: =L42*(1+F42)^-Supuestos!D$24 | N42: =M42*(1+G42)^-Supuestos!E$24 | O42: =N42*(1+H42)^-Supuestos!F$24 | P42: =O42*(1+I42)^-Supuestos!G$24 | Q42: =P42*(1+J42)^-Supuestos!H$24 | R42: =(1+E42)^-(Supuestos!C$24/2) | S42: =L42*(1+F42)^-(Supuestos!D$24/2) | T42: =M42*(1+G42)^-(Supuestos!E$24/2) | U42: =N42*(1+H42)^-(Supuestos!F$24/2) | V42: =O42*(1+I42)^-(Supuestos!G$24/2) | W42: =P42*(1+J42)^-(Supuestos!H$24/2) | X42: =Supuestos!C$23*(1-$C42+$C42*((1+Supuestos!$B$4+$B42/10000)/(1+Supuestos!$B$4))^Supuestos!C$25) | Y42: =Supuestos!D$23*(1-$C42+$C42*((1+Supuestos!$B$4+$B42/10000)/(1+Supuestos!$B$4))^Supuestos!D$25) | Z42: =Supuestos!E$23*(1-$C42+$C42*((1+Supuestos!$B$4+$B42/10000)/(1+Supuestos!$B$4))^Supuestos!E$25) | AA42: =Supuestos!F$23*(1-$C42+$C42*((1+Supuestos!$B$4+$B42/10000)/(1+Supuestos!$B$4))^Supuestos!F$25) | AB42: =Supuestos!G$23*(1-$C42+$C42*((1+Supuestos!$B$4+$B42/10000)/(1+Supuestos!$B$4))^Supuestos!G$25) | AC42: =Supuestos!H$23*(1-$C42+$C42*((1+Supuestos!$B$4+$B42/10000)/(1+Supuestos!$B$4))^Supuestos!H$25) | AD42: =Supuestos!I$23*(1-$C42+$C42*((1+Supuestos!$B$4+$B42/10000)/(1+Supuestos!$B$4))^Supuestos!I$25) | AE42: =SUMPRODUCT(X42:AC42,R42:W42) | AF42: =(1+Supuestos!$B$5)/(1+Supuestos!$B$4)*(1+Supuestos!$B$4+$B42/10000)-1 | AG42: =AD42/(K42-AF42) | AH42: =AG42*Q42 | AI42: =(AE42+AH42-Supuestos!$B$7-Supuestos!$B$8)/Supuestos!$B$9 | AJ42: =AI42/AI$5-1
A43: 80 | B43: 20 | C43: 1 | D43: Mix Δi=+100 θ=1.0 | E43: =(1-Supuestos!C$28)*((1+((1+Supuestos!C$26)/(1+Supuestos!$B$4)-1+Supuestos!$B$14*$A43/10000))*(1+Supuestos!$B$4+$B43/10000)-1)+Supuestos!C$28*((1+Supuestos!C$27+$A43/10000)*(1+Supuestos!$B$4+$B43/10000)-1)*(1-Supuestos!$B$6) | F43: =(1-Supuestos!D$28)*((1+((1+Supuestos!D$26)/(1+Supuestos!$B$4)-1+Supuestos!$B$14*$A43/10000))*(1+Supuestos!$B$4+$B43/10000)-1)+Supuestos!D$28*((1+Supuestos!D$27+$A43/10000)*(1+Supuestos!$B$4+$B43/10000)-1)*(1-Supuestos!$B$6) | G43: =(1-Supuestos!E$28)*((1+((1+Supuestos!E$26)/(1+Supuestos!$B$4)-1+Supuestos!$B$14*$A43/10000))*(1+Supuestos!$B$4+$B43/10000)-1)+Supuestos!E$28*((1+Supuestos!E$27+$A43/10000)*(1+Supuestos!$B$4+$B43/10000)-1)*(1-Supuestos!$B$6) | H43: =(1-Supuestos!F$28)*((1+((1+Supuestos!F$26)/(1+Supuestos!$B$4)-1+Supuestos!$B$14*$A43/10000))*(1+Supuestos!$B$4+$B43/10000)-1)+Supuestos!F$28*((1+Supuestos!F$27+$A43/10000)*(1+Supuestos!$B$4+$B43/10000)-1)*(1-Supuestos!$B$6) | I43: =(1-Supuestos!G$28)*((1+((1+Supuestos!G$26)/(1+Supuestos!$B$4)-1+Supuestos!$B$14*$A43/10000))*(1+Supuestos!$B$4+$B43/10000)-1)+Supuestos!G$28*((1+Supuestos!G$27+$A43/10000)*(1+Supuestos!$B$4+$B43/10000)-1)*(1-Supuestos!$B$6) | J43: =(1-Supuestos!H$28)*((1+((1+Supuestos!H$26)/(1+Supuestos!$B$4)-1+Supuestos!$B$14*$A43/10000))*(1+Supuestos!$B$4+$B43/10000)-1)+Supuestos!H$28*((1+Supuestos!H$27+$A43/10000)*(1+Supuestos!$B$4+$B43/10000)-1)*(1-Supuestos!$B$6) | K43: =(1-Supuestos!I$28)*((1+((1+Supuestos!I$26)/(1+Supuestos!$B$4)-1+Supuestos!$B$14*$A43/10000))*(1+Supuestos!$B$4+$B43/10000)-1)+Supuestos!I$28*((1+Supuestos!I$27+$A43/10000)*(1+Supuestos!$B$4+$B43/10000)-1)*(1-Supuestos!$B$6) | L43: =(1+E43)^-Supuestos!C$24 | M43: =L43*(1+F43)^-Supuestos!D$24 | N43: =M43*(1+G43)^-Supuestos!E$24 | O43: =N43*(1+H43)^-Supuestos!F$24 | P43: =O43*(1+I43)^-Supuestos!G$24 | Q43: =P43*(1+J43)^-Supuestos!H$24 | R43: =(1+E43)^-(Supuestos!C$24/2) | S43: =L43*(1+F43)^-(Supuestos!D$24/2) | T43: =M43*(1+G43)^-(Supuestos!E$24/2) | U43: =N43*(1+H43)^-(Supuestos!F$24/2) | V43: =O43*(1+I43)^-(Supuestos!G$24/2) | W43: =P43*(1+J43)^-(Supuestos!H$24/2) | X43: =Supuestos!C$23*(1-$C43+$C43*((1+Supuestos!$B$4+$B43/10000)/(1+Supuestos!$B$4))^Supuestos!C$25) | Y43: =Supuestos!D$23*(1-$C43+$C43*((1+Supuestos!$B$4+$B43/10000)/(1+Supuestos!$B$4))^Supuestos!D$25) | Z43: =Supuestos!E$23*(1-$C43+$C43*((1+Supuestos!$B$4+$B43/10000)/(1+Supuestos!$B$4))^Supuestos!E$25) | AA43: =Supuestos!F$23*(1-$C43+$C43*((1+Supuestos!$B$4+$B43/10000)/(1+Supuestos!$B$4))^Supuestos!F$25) | AB43: =Supuestos!G$23*(1-$C43+$C43*((1+Supuestos!$B$4+$B43/10000)/(1+Supuestos!$B$4))^Supuestos!G$25) | AC43: =Supuestos!H$23*(1-$C43+$C43*((1+Supuestos!$B$4+$B43/10000)/(1+Supuestos!$B$4))^Supuestos!H$25) | AD43: =Supuestos!I$23*(1-$C43+$C43*((1+Supuestos!$B$4+$B43/10000)/(1+Supuestos!$B$4))^Supuestos!I$25) | AE43: =SUMPRODUCT(X43:AC43,R43:W43) | AF43: =(1+Supuestos!$B$5)/(1+Supuestos!$B$4)*(1+Supuestos!$B$4+$B43/10000)-1 | AG43: =AD43/(K43-AF43) | AH43: =AG43*Q43 | AI43: =(AE43+AH43-Supuestos!$B$7-Supuestos!$B$8)/Supuestos!$B$9 | AJ43: =AI43/AI$5-1
A44: 70 | B44: 30 | C44: 1 | D44: Mix Δi=+100 θ=1.0 | E44: =(1-Supuestos!C$28)*((1+((1+Supuestos!C$26)/(1+Supuestos!$B$4)-1+Supuestos!$B$14*$A44/10000))*(1+Supuestos!$B$4+$B44/10000)-1)+Supuestos!C$28*((1+Supuestos!C$27+$A44/10000)*(1+Supuestos!$B$4+$B44/10000)-1)*(1-Supuestos!$B$6) | F44: =(1-Supuestos!D$28)*((1+((1+Supuestos!D$26)/(1+Supuestos!$B$4)-1+Supuestos!$B$14*$A44/10000))*(1+Supuestos!$B$4+$B44/10000)-1)+Supuestos!D$28*((1+Supuestos!D$27+$A44/10000)*(1+Supuestos!$B$4+$B44/10000)-1)*(1-Supuestos!$B$6) | G44: =(1-Supuestos!E$28)*((1+((1+Supuestos!E$26)/(1+Supuestos!$B$4)-1+Supuestos!$B$14*$A44/10000))*(1+Supuestos!$B$4+$B44/10000)-1)+Supuestos!E$28*((1+Supuestos!E$27+$A44/10000)*(1+Supuestos!$B$4+$B44/10000)-1)*(1-Supuestos!$B$6) | H44: =(1-Supuestos!F$28)*((1+((1+Supuestos!F$26)/(1+Supuestos!$B$4)-1+Supuestos!$B$14*$A44/10000))*(1+Supuestos!$B$4+$B44/10000)-1)+Supuestos!F$28*((1+Supuestos!F$27+$A44/10000)*(1+Supuestos!$B$4+$B44/10000)-1)*(1-Supuestos!$B$6) | I44: =(1-Supuestos!G$28)*((1+((1+Supuestos!G$26)/(1+Supuestos!$B$4)-1+Supuestos!$B$14*$A44/10000))*(1+Supuestos!$B$4+$B44/10000)-1)+Supuestos!G$28*((1+Supuestos!G$27+$A44/10000)*(1+Supuestos!$B$4+$B44/10000)-1)*(1-Supuestos!$B$6) | J44: =(1-Supuestos!H$28)*((1+((1+Supuestos!H$26)/(1+Supuestos!$B$4)-1+Supuestos!$B$14*$A44/10000))*(1+Supuestos!$B$4+$B44/10000)-1)+Supuestos!H$28*((1+Supuestos!H$27+$A44/10000)*(1+Supuestos!$B$4+$B44/10000)-1)*(1-Supuestos!$B$6) | K44: =(1-Supuestos!I$28)*((1+((1+Supuestos!I$26)/(1+Supuestos!$B$4)-1+Supuestos!$B$14*$A44/10000))*(1+Supuestos!$B$4+$B44/10000)-1)+Supuestos!I$28*((1+Supuestos!I$27+$A44/10000)*(1+Supuestos!$B$4+$B44/10000)-1)*(1-Supuestos!$B$6) | L44: =(1+E44)^-Supuestos!C$24 | M44: =L44*(1+F44)^-Supuestos!D$24 | N44: =M44*(1+G44)^-Supuestos!E$24 | O44: =N44*(1+H44)^-Supuestos!F$24 | P44: =O44*(1+I44)^-Supuestos!G$24 | Q44: =P44*(1+J44)^-Supuestos!H$24 | R44: =(1+E44)^-(Supuestos!C$24/2) | S44: =L44*(1+F44)^-(Supuestos!D$24/2) | T44: =M44*(1+G44)^-(Supuestos!E$24/2) | U44: =N44*(1+H44)^-(Supuestos!F$24/2) | V44: =O44*(1+I44)^-(Supuestos!G$24/2) | W44: =P44*(1+J44)^-(Supuestos!H$24/2) | X44: =Supuestos!C$23*(1-$C44+$C44*((1+Supuestos!$B$4+$B44/10000)/(1+Supuestos!$B$4))^Supuestos!C$25) | Y44: =Supuestos!D$23*(1-$C44+$C44*((1+Supuestos!$B$4+$B44/10000)/(1+Supuestos!$B$4))^Supuestos!D$25) | Z44: =Supuestos!E$23*(1-$C44+$C44*((1+Supuestos!$B$4+$B44/10000)/(1+Supuestos!$B$4))^Supuestos!E$25) | AA44: =Supuestos!F$23*(1-$C44+$C44*((1+Supuestos!$B$4+$B44/10000)/(1+Supuestos!$B$4))^Supuestos!F$25) | AB44: =Supuestos!G$23*(1-$C44+$C44*((1+Supuestos!$B$4+$B44/10000)/(1+Supuestos!$B$4))^Supuestos!G$25) | AC44: =Supuestos!H$23*(1-$C44+$C44*((1+Supuestos!$B$4+$B44/10000)/(1+Supuestos!$B$4))^Supuestos!H$25) | AD44: =Supuestos!I$23*(1-$C44+$C44*((1+Supuestos!$B$4+$B44/10000)/(1+Supuestos!$B$4))^Supuestos!I$25) | AE44: =SUMPRODUCT(X44:AC44,R44:W44) | AF44: =(1+Supuestos!$B$5)/(1+Supuestos!$B$4)*(1+Supuestos!$B$4+$B44/10000)-1 | AG44: =AD44/(K44-AF44) | AH44: =AG44*Q44 | AI44: =(AE44+AH44-Supuestos!$B$7-Supuestos!$B$8)/Supuestos!$B$9 | AJ44: =AI44/AI$5-1
A45: 60 | B45: 40 | C45: 1 | D45: Mix Δi=+100 θ=1.0 | E45: =(1-Supuestos!C$28)*((1+((1+Supuestos!C$26)/(1+Supuestos!$B$4)-1+Supuestos!$B$14*$A45/10000))*(1+Supuestos!$B$4+$B45/10000)-1)+Supuestos!C$28*((1+Supuestos!C$27+$A45/10000)*(1+Supuestos!$B$4+$B45/10000)-1)*(1-Supuestos!$B$6) | F45: =(1-Supuestos!D$28)*((1+((1+Supuestos!D$26)/(1+Supuestos!$B$4)-1+Supuestos!$B$14*$A45/10000))*(1+Supuestos!$B$4+$B45/10000)-1)+Supuestos!D$28*((1+Supuestos!D$27+$A45/10000)*(1+Supuestos!$B$4+$B45/10000)-1)*(1-Supuestos!$B$6) | G45: =(1-Supuestos!E$28)*((1+((1+Supuestos!E$26)/(1+Supuestos!$B$4)-1+Supuestos!$B$14*$A45/10000))*(1+Supuestos!$B$4+$B45/10000)-1)+Supuestos!E$28*((1+Supuestos!E$27+$A45/10000)*(1+Supuestos!$B$4+$B45/10000)-1)*(1-Supuestos!$B$6) | H45: =(1-Supuestos!F$28)*((1+((1+Supuestos!F$26)/(1+Supuestos!$B$4)-1+Supuestos!$B$14*$A45/10000))*(1+Supuestos!$B$4+$B45/10000)-1)+Supuestos!F$28*((1+Supuestos!F$27+$A45/10000)*(1+Supuestos!$B$4+$B45/10000)-1)*(1-Supuestos!$B$6) | I45: =(1-Supuestos!G$28)*((1+((1+Supuestos!G$26)/(1+Supuestos!$B$4)-1+Supuestos!$B$14*$A45/10000))*(1+Supuestos!$B$4+$B45/10000)-1)+Supuestos!G$28*((1+Supuestos!G$27+$A45/10000)*(1+Supuestos!$B$4+$B45/10000)-1)*(1-Supuestos!$B$6) | J45: =(1-Supuestos!H$28)*((1+((1+Supuestos!H$26)/(1+Supuestos!$B$4)-1+Supuestos!$B$14*$A45/10000))*(1+Supuestos!$B$4+$B45/10000)-1)+Supuestos!H$28*((1+Supuestos!H$27+$A45/10000)*(1+Supuestos!$B$4+$B45/10000)-1)*(1-Supuestos!$B$6) | K45: =(1-Supuestos!I$28)*((1+((1+Supuestos!I$26)/(1+Supuestos!$B$4)-1+Supuestos!$B$14*$A45/10000))*(1+Supuestos!$B$4+$B45/10000)-1)+Supuestos!I$28*((1+Supuestos!I$27+$A45/10000)*(1+Supuestos!$B$4+$B45/10000)-1)*(1-Supuestos!$B$6) | L45: =(1+E45)^-Supuestos!C$24 | M45: =L45*(1+F45)^-Supuestos!D$24 | N45: =M45*(1+G45)^-Supuestos!E$24 | O45: =N45*(1+H45)^-Supuestos!F$24 | P45: =O45*(1+I45)^-Supuestos!G$24 | Q45: =P45*(1+J45)^-Supuestos!H$24 | R45: =(1+E45)^-(Supuestos!C$24/2) | S45: =L45*(1+F45)^-(Supuestos!D$24/2) | T45: =M45*(1+G45)^-(Supuestos!E$24/2) | U45: =N45*(1+H45)^-(Supuestos!F$24/2) | V45: =O45*(1+I45)^-(Supuestos!G$24/2) | W45: =P45*(1+J45)^-(Supuestos!H$24/2) | X45: =Supuestos!C$23*(1-$C45+$C45*((1+Supuestos!$B$4+$B45/10000)/(1+Supuestos!$B$4))^Supuestos!C$25) | Y45: =Supuestos!D$23*(1-$C45+$C45*((1+Supuestos!$B$4+$B45/10000)/(1+Supuestos!$B$4))^Supuestos!D$25) | Z45: =Supuestos!E$23*(1-$C45+$C45*((1+Supuestos!$B$4+$B45/10000)/(1+Supuestos!$B$4))^Supuestos!E$25) | AA45: =Supuestos!F$23*(1-$C45+$C45*((1+Supuestos!$B$4+$B45/10000)/(1+Supuestos!$B$4))^Supuestos!F$25) | AB45: =Supuestos!G$23*(1-$C45+$C45*((1+Supuestos!$B$4+$B45/10000)/(1+Supuestos!$B$4))^Supuestos!G$25) | AC45: =Supuestos!H$23*(1-$C45+$C45*((1+Supuestos!$B$4+$B45/10000)/(1+Supuestos!$B$4))^Supuestos!H$25) | AD45: =Supuestos!I$23*(1-$C45+$C45*((1+Supuestos!$B$4+$B45/10000)/(1+Supuestos!$B$4))^Supuestos!I$25) | AE45: =SUMPRODUCT(X45:AC45,R45:W45) | AF45: =(1+Supuestos!$B$5)/(1+Supuestos!$B$4)*(1+Supuestos!$B$4+$B45/10000)-1 | AG45: =AD45/(K45-AF45) | AH45: =AG45*Q45 | AI45: =(AE45+AH45-Supuestos!$B$7-Supuestos!$B$8)/Supuestos!$B$9 | AJ45: =AI45/AI$5-1
A46: 50 | B46: 50 | C46: 1 | D46: Mix Δi=+100 θ=1.0 | E46: =(1-Supuestos!C$28)*((1+((1+Supuestos!C$26)/(1+Supuestos!$B$4)-1+Supuestos!$B$14*$A46/10000))*(1+Supuestos!$B$4+$B46/10000)-1)+Supuestos!C$28*((1+Supuestos!C$27+$A46/10000)*(1+Supuestos!$B$4+$B46/10000)-1)*(1-Supuestos!$B$6) | F46: =(1-Supuestos!D$28)*((1+((1+Supuestos!D$26)/(1+Supuestos!$B$4)-1+Supuestos!$B$14*$A46/10000))*(1+Supuestos!$B$4+$B46/10000)-1)+Supuestos!D$28*((1+Supuestos!D$27+$A46/10000)*(1+Supuestos!$B$4+$B46/10000)-1)*(1-Supuestos!$B$6) | G46: =(1-Supuestos!E$28)*((1+((1+Supuestos!E$26)/(1+Supuestos!$B$4)-1+Supuestos!$B$14*$A46/10000))*(1+Supuestos!$B$4+$B46/10000)-1)+Supuestos!E$28*((1+Supuestos!E$27+$A46/10000)*(1+Supuestos!$B$4+$B46/10000)-1)*(1-Supuestos!$B$6) | H46: =(1-Supuestos!F$28)*((1+((1+Supuestos!F$26)/(1+Supuestos!$B$4)-1+Supuestos!$B$14*$A46/10000))*(1+Supuestos!$B$4+$B46/10000)-1)+Supuestos!F$28*((1+Supuestos!F$27+$A46/10000)*(1+Supuestos!$B$4+$B46/10000)-1)*(1-Supuestos!$B$6) | I46: =(1-Supuestos!G$28)*((1+((1+Supuestos!G$26)/(1+Supuestos!$B$4)-1+Supuestos!$B$14*$A46/10000))*(1+Supuestos!$B$4+$B46/10000)-1)+Supuestos!G$28*((1+Supuestos!G$27+$A46/10000)*(1+Supuestos!$B$4+$B46/10000)-1)*(1-Supuestos!$B$6) | J46: =(1-Supuestos!H$28)*((1+((1+Supuestos!H$26)/(1+Supuestos!$B$4)-1+Supuestos!$B$14*$A46/10000))*(1+Supuestos!$B$4+$B46/10000)-1)+Supuestos!H$28*((1+Supuestos!H$27+$A46/10000)*(1+Supuestos!$B$4+$B46/10000)-1)*(1-Supuestos!$B$6) | K46: =(1-Supuestos!I$28)*((1+((1+Supuestos!I$26)/(1+Supuestos!$B$4)-1+Supuestos!$B$14*$A46/10000))*(1+Supuestos!$B$4+$B46/10000)-1)+Supuestos!I$28*((1+Supuestos!I$27+$A46/10000)*(1+Supuestos!$B$4+$B46/10000)-1)*(1-Supuestos!$B$6) | L46: =(1+E46)^-Supuestos!C$24 | M46: =L46*(1+F46)^-Supuestos!D$24 | N46: =M46*(1+G46)^-Supuestos!E$24 | O46: =N46*(1+H46)^-Supuestos!F$24 | P46: =O46*(1+I46)^-Supuestos!G$24 | Q46: =P46*(1+J46)^-Supuestos!H$24 | R46: =(1+E46)^-(Supuestos!C$24/2) | S46: =L46*(1+F46)^-(Supuestos!D$24/2) | T46: =M46*(1+G46)^-(Supuestos!E$24/2) | U46: =N46*(1+H46)^-(Supuestos!F$24/2) | V46: =O46*(1+I46)^-(Supuestos!G$24/2) | W46: =P46*(1+J46)^-(Supuestos!H$24/2) | X46: =Supuestos!C$23*(1-$C46+$C46*((1+Supuestos!$B$4+$B46/10000)/(1+Supuestos!$B$4))^Supuestos!C$25) | Y46: =Supuestos!D$23*(1-$C46+$C46*((1+Supuestos!$B$4+$B46/10000)/(1+Supuestos!$B$4))^Supuestos!D$25) | Z46: =Supuestos!E$23*(1-$C46+$C46*((1+Supuestos!$B$4+$B46/10000)/(1+Supuestos!$B$4))^Supuestos!E$25) | AA46: =Supuestos!F$23*(1-$C46+$C46*((1+Supuestos!$B$4+$B46/10000)/(1+Supuestos!$B$4))^Supuestos!F$25) | AB46: =Supuestos!G$23*(1-$C46+$C46*((1+Supuestos!$B$4+$B46/10000)/(1+Supuestos!$B$4))^Supuestos!G$25) | AC46: =Supuestos!H$23*(1-$C46+$C46*((1+Supuestos!$B$4+$B46/10000)/(1+Supuestos!$B$4))^Supuestos!H$25) | AD46: =Supuestos!I$23*(1-$C46+$C46*((1+Supuestos!$B$4+$B46/10000)/(1+Supuestos!$B$4))^Supuestos!I$25) | AE46: =SUMPRODUCT(X46:AC46,R46:W46) | AF46: =(1+Supuestos!$B$5)/(1+Supuestos!$B$4)*(1+Supuestos!$B$4+$B46/10000)-1 | AG46: =AD46/(K46-AF46) | AH46: =AG46*Q46 | AI46: =(AE46+AH46-Supuestos!$B$7-Supuestos!$B$8)/Supuestos!$B$9 | AJ46: =AI46/AI$5-1
A47: 40 | B47: 60 | C47: 1 | D47: Mix Δi=+100 θ=1.0 | E47: =(1-Supuestos!C$28)*((1+((1+Supuestos!C$26)/(1+Supuestos!$B$4)-1+Supuestos!$B$14*$A47/10000))*(1+Supuestos!$B$4+$B47/10000)-1)+Supuestos!C$28*((1+Supuestos!C$27+$A47/10000)*(1+Supuestos!$B$4+$B47/10000)-1)*(1-Supuestos!$B$6) | F47: =(1-Supuestos!D$28)*((1+((1+Supuestos!D$26)/(1+Supuestos!$B$4)-1+Supuestos!$B$14*$A47/10000))*(1+Supuestos!$B$4+$B47/10000)-1)+Supuestos!D$28*((1+Supuestos!D$27+$A47/10000)*(1+Supuestos!$B$4+$B47/10000)-1)*(1-Supuestos!$B$6) | G47: =(1-Supuestos!E$28)*((1+((1+Supuestos!E$26)/(1+Supuestos!$B$4)-1+Supuestos!$B$14*$A47/10000))*(1+Supuestos!$B$4+$B47/10000)-1)+Supuestos!E$28*((1+Supuestos!E$27+$A47/10000)*(1+Supuestos!$B$4+$B47/10000)-1)*(1-Supuestos!$B$6) | H47: =(1-Supuestos!F$28)*((1+((1+Supuestos!F$26)/(1+Supuestos!$B$4)-1+Supuestos!$B$14*$A47/10000))*(1+Supuestos!$B$4+$B47/10000)-1)+Supuestos!F$28*((1+Supuestos!F$27+$A47/10000)*(1+Supuestos!$B$4+$B47/10000)-1)*(1-Supuestos!$B$6) | I47: =(1-Supuestos!G$28)*((1+((1+Supuestos!G$26)/(1+Supuestos!$B$4)-1+Supuestos!$B$14*$A47/10000))*(1+Supuestos!$B$4+$B47/10000)-1)+Supuestos!G$28*((1+Supuestos!G$27+$A47/10000)*(1+Supuestos!$B$4+$B47/10000)-1)*(1-Supuestos!$B$6) | J47: =(1-Supuestos!H$28)*((1+((1+Supuestos!H$26)/(1+Supuestos!$B$4)-1+Supuestos!$B$14*$A47/10000))*(1+Supuestos!$B$4+$B47/10000)-1)+Supuestos!H$28*((1+Supuestos!H$27+$A47/10000)*(1+Supuestos!$B$4+$B47/10000)-1)*(1-Supuestos!$B$6) | K47: =(1-Supuestos!I$28)*((1+((1+Supuestos!I$26)/(1+Supuestos!$B$4)-1+Supuestos!$B$14*$A47/10000))*(1+Supuestos!$B$4+$B47/10000)-1)+Supuestos!I$28*((1+Supuestos!I$27+$A47/10000)*(1+Supuestos!$B$4+$B47/10000)-1)*(1-Supuestos!$B$6) | L47: =(1+E47)^-Supuestos!C$24 | M47: =L47*(1+F47)^-Supuestos!D$24 | N47: =M47*(1+G47)^-Supuestos!E$24 | O47: =N47*(1+H47)^-Supuestos!F$24 | P47: =O47*(1+I47)^-Supuestos!G$24 | Q47: =P47*(1+J47)^-Supuestos!H$24 | R47: =(1+E47)^-(Supuestos!C$24/2) | S47: =L47*(1+F47)^-(Supuestos!D$24/2) | T47: =M47*(1+G47)^-(Supuestos!E$24/2) | U47: =N47*(1+H47)^-(Supuestos!F$24/2) | V47: =O47*(1+I47)^-(Supuestos!G$24/2) | W47: =P47*(1+J47)^-(Supuestos!H$24/2) | X47: =Supuestos!C$23*(1-$C47+$C47*((1+Supuestos!$B$4+$B47/10000)/(1+Supuestos!$B$4))^Supuestos!C$25) | Y47: =Supuestos!D$23*(1-$C47+$C47*((1+Supuestos!$B$4+$B47/10000)/(1+Supuestos!$B$4))^Supuestos!D$25) | Z47: =Supuestos!E$23*(1-$C47+$C47*((1+Supuestos!$B$4+$B47/10000)/(1+Supuestos!$B$4))^Supuestos!E$25) | AA47: =Supuestos!F$23*(1-$C47+$C47*((1+Supuestos!$B$4+$B47/10000)/(1+Supuestos!$B$4))^Supuestos!F$25) | AB47: =Supuestos!G$23*(1-$C47+$C47*((1+Supuestos!$B$4+$B47/10000)/(1+Supuestos!$B$4))^Supuestos!G$25) | AC47: =Supuestos!H$23*(1-$C47+$C47*((1+Supuestos!$B$4+$B47/10000)/(1+Supuestos!$B$4))^Supuestos!H$25) | AD47: =Supuestos!I$23*(1-$C47+$C47*((1+Supuestos!$B$4+$B47/10000)/(1+Supuestos!$B$4))^Supuestos!I$25) | AE47: =SUMPRODUCT(X47:AC47,R47:W47) | AF47: =(1+Supuestos!$B$5)/(1+Supuestos!$B$4)*(1+Supuestos!$B$4+$B47/10000)-1 | AG47: =AD47/(K47-AF47) | AH47: =AG47*Q47 | AI47: =(AE47+AH47-Supuestos!$B$7-Supuestos!$B$8)/Supuestos!$B$9 | AJ47: =AI47/AI$5-1
A48: 30 | B48: 70 | C48: 1 | D48: Mix Δi=+100 θ=1.0 | E48: =(1-Supuestos!C$28)*((1+((1+Supuestos!C$26)/(1+Supuestos!$B$4)-1+Supuestos!$B$14*$A48/10000))*(1+Supuestos!$B$4+$B48/10000)-1)+Supuestos!C$28*((1+Supuestos!C$27+$A48/10000)*(1+Supuestos!$B$4+$B48/10000)-1)*(1-Supuestos!$B$6) | F48: =(1-Supuestos!D$28)*((1+((1+Supuestos!D$26)/(1+Supuestos!$B$4)-1+Supuestos!$B$14*$A48/10000))*(1+Supuestos!$B$4+$B48/10000)-1)+Supuestos!D$28*((1+Supuestos!D$27+$A48/10000)*(1+Supuestos!$B$4+$B48/10000)-1)*(1-Supuestos!$B$6) | G48: =(1-Supuestos!E$28)*((1+((1+Supuestos!E$26)/(1+Supuestos!$B$4)-1+Supuestos!$B$14*$A48/10000))*(1+Supuestos!$B$4+$B48/10000)-1)+Supuestos!E$28*((1+Supuestos!E$27+$A48/10000)*(1+Supuestos!$B$4+$B48/10000)-1)*(1-Supuestos!$B$6) | H48: =(1-Supuestos!F$28)*((1+((1+Supuestos!F$26)/(1+Supuestos!$B$4)-1+Supuestos!$B$14*$A48/10000))*(1+Supuestos!$B$4+$B48/10000)-1)+Supuestos!F$28*((1+Supuestos!F$27+$A48/10000)*(1+Supuestos!$B$4+$B48/10000)-1)*(1-Supuestos!$B$6) | I48: =(1-Supuestos!G$28)*((1+((1+Supuestos!G$26)/(1+Supuestos!$B$4)-1+Supuestos!$B$14*$A48/10000))*(1+Supuestos!$B$4+$B48/10000)-1)+Supuestos!G$28*((1+Supuestos!G$27+$A48/10000)*(1+Supuestos!$B$4+$B48/10000)-1)*(1-Supuestos!$B$6) | J48: =(1-Supuestos!H$28)*((1+((1+Supuestos!H$26)/(1+Supuestos!$B$4)-1+Supuestos!$B$14*$A48/10000))*(1+Supuestos!$B$4+$B48/10000)-1)+Supuestos!H$28*((1+Supuestos!H$27+$A48/10000)*(1+Supuestos!$B$4+$B48/10000)-1)*(1-Supuestos!$B$6) | K48: =(1-Supuestos!I$28)*((1+((1+Supuestos!I$26)/(1+Supuestos!$B$4)-1+Supuestos!$B$14*$A48/10000))*(1+Supuestos!$B$4+$B48/10000)-1)+Supuestos!I$28*((1+Supuestos!I$27+$A48/10000)*(1+Supuestos!$B$4+$B48/10000)-1)*(1-Supuestos!$B$6) | L48: =(1+E48)^-Supuestos!C$24 | M48: =L48*(1+F48)^-Supuestos!D$24 | N48: =M48*(1+G48)^-Supuestos!E$24 | O48: =N48*(1+H48)^-Supuestos!F$24 | P48: =O48*(1+I48)^-Supuestos!G$24 | Q48: =P48*(1+J48)^-Supuestos!H$24 | R48: =(1+E48)^-(Supuestos!C$24/2) | S48: =L48*(1+F48)^-(Supuestos!D$24/2) | T48: =M48*(1+G48)^-(Supuestos!E$24/2) | U48: =N48*(1+H48)^-(Supuestos!F$24/2) | V48: =O48*(1+I48)^-(Supuestos!G$24/2) | W48: =P48*(1+J48)^-(Supuestos!H$24/2) | X48: =Supuestos!C$23*(1-$C48+$C48*((1+Supuestos!$B$4+$B48/10000)/(1+Supuestos!$B$4))^Supuestos!C$25) | Y48: =Supuestos!D$23*(1-$C48+$C48*((1+Supuestos!$B$4+$B48/10000)/(1+Supuestos!$B$4))^Supuestos!D$25) | Z48: =Supuestos!E$23*(1-$C48+$C48*((1+Supuestos!$B$4+$B48/10000)/(1+Supuestos!$B$4))^Supuestos!E$25) | AA48: =Supuestos!F$23*(1-$C48+$C48*((1+Supuestos!$B$4+$B48/10000)/(1+Supuestos!$B$4))^Supuestos!F$25) | AB48: =Supuestos!G$23*(1-$C48+$C48*((1+Supuestos!$B$4+$B48/10000)/(1+Supuestos!$B$4))^Supuestos!G$25) | AC48: =Supuestos!H$23*(1-$C48+$C48*((1+Supuestos!$B$4+$B48/10000)/(1+Supuestos!$B$4))^Supuestos!H$25) | AD48: =Supuestos!I$23*(1-$C48+$C48*((1+Supuestos!$B$4+$B48/10000)/(1+Supuestos!$B$4))^Supuestos!I$25) | AE48: =SUMPRODUCT(X48:AC48,R48:W48) | AF48: =(1+Supuestos!$B$5)/(1+Supuestos!$B$4)*(1+Supuestos!$B$4+$B48/10000)-1 | AG48: =AD48/(K48-AF48) | AH48: =AG48*Q48 | AI48: =(AE48+AH48-Supuestos!$B$7-Supuestos!$B$8)/Supuestos!$B$9 | AJ48: =AI48/AI$5-1
A49: 20 | B49: 80 | C49: 1 | D49: Mix Δi=+100 θ=1.0 | E49: =(1-Supuestos!C$28)*((1+((1+Supuestos!C$26)/(1+Supuestos!$B$4)-1+Supuestos!$B$14*$A49/10000))*(1+Supuestos!$B$4+$B49/10000)-1)+Supuestos!C$28*((1+Supuestos!C$27+$A49/10000)*(1+Supuestos!$B$4+$B49/10000)-1)*(1-Supuestos!$B$6) | F49: =(1-Supuestos!D$28)*((1+((1+Supuestos!D$26)/(1+Supuestos!$B$4)-1+Supuestos!$B$14*$A49/10000))*(1+Supuestos!$B$4+$B49/10000)-1)+Supuestos!D$28*((1+Supuestos!D$27+$A49/10000)*(1+Supuestos!$B$4+$B49/10000)-1)*(1-Supuestos!$B$6) | G49: =(1-Supuestos!E$28)*((1+((1+Supuestos!E$26)/(1+Supuestos!$B$4)-1+Supuestos!$B$14*$A49/10000))*(1+Supuestos!$B$4+$B49/10000)-1)+Supuestos!E$28*((1+Supuestos!E$27+$A49/10000)*(1+Supuestos!$B$4+$B49/10000)-1)*(1-Supuestos!$B$6) | H49: =(1-Supuestos!F$28)*((1+((1+Supuestos!F$26)/(1+Supuestos!$B$4)-1+Supuestos!$B$14*$A49/10000))*(1+Supuestos!$B$4+$B49/10000)-1)+Supuestos!F$28*((1+Supuestos!F$27+$A49/10000)*(1+Supuestos!$B$4+$B49/10000)-1)*(1-Supuestos!$B$6) | I49: =(1-Supuestos!G$28)*((1+((1+Supuestos!G$26)/(1+Supuestos!$B$4)-1+Supuestos!$B$14*$A49/10000))*(1+Supuestos!$B$4+$B49/10000)-1)+Supuestos!G$28*((1+Supuestos!G$27+$A49/10000)*(1+Supuestos!$B$4+$B49/10000)-1)*(1-Supuestos!$B$6) | J49: =(1-Supuestos!H$28)*((1+((1+Supuestos!H$26)/(1+Supuestos!$B$4)-1+Supuestos!$B$14*$A49/10000))*(1+Supuestos!$B$4+$B49/10000)-1)+Supuestos!H$28*((1+Supuestos!H$27+$A49/10000)*(1+Supuestos!$B$4+$B49/10000)-1)*(1-Supuestos!$B$6) | K49: =(1-Supuestos!I$28)*((1+((1+Supuestos!I$26)/(1+Supuestos!$B$4)-1+Supuestos!$B$14*$A49/10000))*(1+Supuestos!$B$4+$B49/10000)-1)+Supuestos!I$28*((1+Supuestos!I$27+$A49/10000)*(1+Supuestos!$B$4+$B49/10000)-1)*(1-Supuestos!$B$6) | L49: =(1+E49)^-Supuestos!C$24 | M49: =L49*(1+F49)^-Supuestos!D$24 | N49: =M49*(1+G49)^-Supuestos!E$24 | O49: =N49*(1+H49)^-Supuestos!F$24 | P49: =O49*(1+I49)^-Supuestos!G$24 | Q49: =P49*(1+J49)^-Supuestos!H$24 | R49: =(1+E49)^-(Supuestos!C$24/2) | S49: =L49*(1+F49)^-(Supuestos!D$24/2) | T49: =M49*(1+G49)^-(Supuestos!E$24/2) | U49: =N49*(1+H49)^-(Supuestos!F$24/2) | V49: =O49*(1+I49)^-(Supuestos!G$24/2) | W49: =P49*(1+J49)^-(Supuestos!H$24/2) | X49: =Supuestos!C$23*(1-$C49+$C49*((1+Supuestos!$B$4+$B49/10000)/(1+Supuestos!$B$4))^Supuestos!C$25) | Y49: =Supuestos!D$23*(1-$C49+$C49*((1+Supuestos!$B$4+$B49/10000)/(1+Supuestos!$B$4))^Supuestos!D$25) | Z49: =Supuestos!E$23*(1-$C49+$C49*((1+Supuestos!$B$4+$B49/10000)/(1+Supuestos!$B$4))^Supuestos!E$25) | AA49: =Supuestos!F$23*(1-$C49+$C49*((1+Supuestos!$B$4+$B49/10000)/(1+Supuestos!$B$4))^Supuestos!F$25) | AB49: =Supuestos!G$23*(1-$C49+$C49*((1+Supuestos!$B$4+$B49/10000)/(1+Supuestos!$B$4))^Supuestos!G$25) | AC49: =Supuestos!H$23*(1-$C49+$C49*((1+Supuestos!$B$4+$B49/10000)/(1+Supuestos!$B$4))^Supuestos!H$25) | AD49: =Supuestos!I$23*(1-$C49+$C49*((1+Supuestos!$B$4+$B49/10000)/(1+Supuestos!$B$4))^Supuestos!I$25) | AE49: =SUMPRODUCT(X49:AC49,R49:W49) | AF49: =(1+Supuestos!$B$5)/(1+Supuestos!$B$4)*(1+Supuestos!$B$4+$B49/10000)-1 | AG49: =AD49/(K49-AF49) | AH49: =AG49*Q49 | AI49: =(AE49+AH49-Supuestos!$B$7-Supuestos!$B$8)/Supuestos!$B$9 | AJ49: =AI49/AI$5-1
A50: 10 | B50: 90 | C50: 1 | D50: Mix Δi=+100 θ=1.0 | E50: =(1-Supuestos!C$28)*((1+((1+Supuestos!C$26)/(1+Supuestos!$B$4)-1+Supuestos!$B$14*$A50/10000))*(1+Supuestos!$B$4+$B50/10000)-1)+Supuestos!C$28*((1+Supuestos!C$27+$A50/10000)*(1+Supuestos!$B$4+$B50/10000)-1)*(1-Supuestos!$B$6) | F50: =(1-Supuestos!D$28)*((1+((1+Supuestos!D$26)/(1+Supuestos!$B$4)-1+Supuestos!$B$14*$A50/10000))*(1+Supuestos!$B$4+$B50/10000)-1)+Supuestos!D$28*((1+Supuestos!D$27+$A50/10000)*(1+Supuestos!$B$4+$B50/10000)-1)*(1-Supuestos!$B$6) | G50: =(1-Supuestos!E$28)*((1+((1+Supuestos!E$26)/(1+Supuestos!$B$4)-1+Supuestos!$B$14*$A50/10000))*(1+Supuestos!$B$4+$B50/10000)-1)+Supuestos!E$28*((1+Supuestos!E$27+$A50/10000)*(1+Supuestos!$B$4+$B50/10000)-1)*(1-Supuestos!$B$6) | H50: =(1-Supuestos!F$28)*((1+((1+Supuestos!F$26)/(1+Supuestos!$B$4)-1+Supuestos!$B$14*$A50/10000))*(1+Supuestos!$B$4+$B50/10000)-1)+Supuestos!F$28*((1+Supuestos!F$27+$A50/10000)*(1+Supuestos!$B$4+$B50/10000)-1)*(1-Supuestos!$B$6) | I50: =(1-Supuestos!G$28)*((1+((1+Supuestos!G$26)/(1+Supuestos!$B$4)-1+Supuestos!$B$14*$A50/10000))*(1+Supuestos!$B$4+$B50/10000)-1)+Supuestos!G$28*((1+Supuestos!G$27+$A50/10000)*(1+Supuestos!$B$4+$B50/10000)-1)*(1-Supuestos!$B$6) | J50: =(1-Supuestos!H$28)*((1+((1+Supuestos!H$26)/(1+Supuestos!$B$4)-1+Supuestos!$B$14*$A50/10000))*(1+Supuestos!$B$4+$B50/10000)-1)+Supuestos!H$28*((1+Supuestos!H$27+$A50/10000)*(1+Supuestos!$B$4+$B50/10000)-1)*(1-Supuestos!$B$6) | K50: =(1-Supuestos!I$28)*((1+((1+Supuestos!I$26)/(1+Supuestos!$B$4)-1+Supuestos!$B$14*$A50/10000))*(1+Supuestos!$B$4+$B50/10000)-1)+Supuestos!I$28*((1+Supuestos!I$27+$A50/10000)*(1+Supuestos!$B$4+$B50/10000)-1)*(1-Supuestos!$B$6) | L50: =(1+E50)^-Supuestos!C$24 | M50: =L50*(1+F50)^-Supuestos!D$24 | N50: =M50*(1+G50)^-Supuestos!E$24 | O50: =N50*(1+H50)^-Supuestos!F$24 | P50: =O50*(1+I50)^-Supuestos!G$24 | Q50: =P50*(1+J50)^-Supuestos!H$24 | R50: =(1+E50)^-(Supuestos!C$24/2) | S50: =L50*(1+F50)^-(Supuestos!D$24/2) | T50: =M50*(1+G50)^-(Supuestos!E$24/2) | U50: =N50*(1+H50)^-(Supuestos!F$24/2) | V50: =O50*(1+I50)^-(Supuestos!G$24/2) | W50: =P50*(1+J50)^-(Supuestos!H$24/2) | X50: =Supuestos!C$23*(1-$C50+$C50*((1+Supuestos!$B$4+$B50/10000)/(1+Supuestos!$B$4))^Supuestos!C$25) | Y50: =Supuestos!D$23*(1-$C50+$C50*((1+Supuestos!$B$4+$B50/10000)/(1+Supuestos!$B$4))^Supuestos!D$25) | Z50: =Supuestos!E$23*(1-$C50+$C50*((1+Supuestos!$B$4+$B50/10000)/(1+Supuestos!$B$4))^Supuestos!E$25) | AA50: =Supuestos!F$23*(1-$C50+$C50*((1+Supuestos!$B$4+$B50/10000)/(1+Supuestos!$B$4))^Supuestos!F$25) | AB50: =Supuestos!G$23*(1-$C50+$C50*((1+Supuestos!$B$4+$B50/10000)/(1+Supuestos!$B$4))^Supuestos!G$25) | AC50: =Supuestos!H$23*(1-$C50+$C50*((1+Supuestos!$B$4+$B50/10000)/(1+Supuestos!$B$4))^Supuestos!H$25) | AD50: =Supuestos!I$23*(1-$C50+$C50*((1+Supuestos!$B$4+$B50/10000)/(1+Supuestos!$B$4))^Supuestos!I$25) | AE50: =SUMPRODUCT(X50:AC50,R50:W50) | AF50: =(1+Supuestos!$B$5)/(1+Supuestos!$B$4)*(1+Supuestos!$B$4+$B50/10000)-1 | AG50: =AD50/(K50-AF50) | AH50: =AG50*Q50 | AI50: =(AE50+AH50-Supuestos!$B$7-Supuestos!$B$8)/Supuestos!$B$9 | AJ50: =AI50/AI$5-1
A51: 0 | B51: 100 | C51: 1 | D51: Mix Δi=+100 θ=1.0 | E51: =(1-Supuestos!C$28)*((1+((1+Supuestos!C$26)/(1+Supuestos!$B$4)-1+Supuestos!$B$14*$A51/10000))*(1+Supuestos!$B$4+$B51/10000)-1)+Supuestos!C$28*((1+Supuestos!C$27+$A51/10000)*(1+Supuestos!$B$4+$B51/10000)-1)*(1-Supuestos!$B$6) | F51: =(1-Supuestos!D$28)*((1+((1+Supuestos!D$26)/(1+Supuestos!$B$4)-1+Supuestos!$B$14*$A51/10000))*(1+Supuestos!$B$4+$B51/10000)-1)+Supuestos!D$28*((1+Supuestos!D$27+$A51/10000)*(1+Supuestos!$B$4+$B51/10000)-1)*(1-Supuestos!$B$6) | G51: =(1-Supuestos!E$28)*((1+((1+Supuestos!E$26)/(1+Supuestos!$B$4)-1+Supuestos!$B$14*$A51/10000))*(1+Supuestos!$B$4+$B51/10000)-1)+Supuestos!E$28*((1+Supuestos!E$27+$A51/10000)*(1+Supuestos!$B$4+$B51/10000)-1)*(1-Supuestos!$B$6) | H51: =(1-Supuestos!F$28)*((1+((1+Supuestos!F$26)/(1+Supuestos!$B$4)-1+Supuestos!$B$14*$A51/10000))*(1+Supuestos!$B$4+$B51/10000)-1)+Supuestos!F$28*((1+Supuestos!F$27+$A51/10000)*(1+Supuestos!$B$4+$B51/10000)-1)*(1-Supuestos!$B$6) | I51: =(1-Supuestos!G$28)*((1+((1+Supuestos!G$26)/(1+Supuestos!$B$4)-1+Supuestos!$B$14*$A51/10000))*(1+Supuestos!$B$4+$B51/10000)-1)+Supuestos!G$28*((1+Supuestos!G$27+$A51/10000)*(1+Supuestos!$B$4+$B51/10000)-1)*(1-Supuestos!$B$6) | J51: =(1-Supuestos!H$28)*((1+((1+Supuestos!H$26)/(1+Supuestos!$B$4)-1+Supuestos!$B$14*$A51/10000))*(1+Supuestos!$B$4+$B51/10000)-1)+Supuestos!H$28*((1+Supuestos!H$27+$A51/10000)*(1+Supuestos!$B$4+$B51/10000)-1)*(1-Supuestos!$B$6) | K51: =(1-Supuestos!I$28)*((1+((1+Supuestos!I$26)/(1+Supuestos!$B$4)-1+Supuestos!$B$14*$A51/10000))*(1+Supuestos!$B$4+$B51/10000)-1)+Supuestos!I$28*((1+Supuestos!I$27+$A51/10000)*(1+Supuestos!$B$4+$B51/10000)-1)*(1-Supuestos!$B$6) | L51: =(1+E51)^-Supuestos!C$24 | M51: =L51*(1+F51)^-Supuestos!D$24 | N51: =M51*(1+G51)^-Supuestos!E$24 | O51: =N51*(1+H51)^-Supuestos!F$24 | P51: =O51*(1+I51)^-Supuestos!G$24 | Q51: =P51*(1+J51)^-Supuestos!H$24 | R51: =(1+E51)^-(Supuestos!C$24/2) | S51: =L51*(1+F51)^-(Supuestos!D$24/2) | T51: =M51*(1+G51)^-(Supuestos!E$24/2) | U51: =N51*(1+H51)^-(Supuestos!F$24/2) | V51: =O51*(1+I51)^-(Supuestos!G$24/2) | W51: =P51*(1+J51)^-(Supuestos!H$24/2) | X51: =Supuestos!C$23*(1-$C51+$C51*((1+Supuestos!$B$4+$B51/10000)/(1+Supuestos!$B$4))^Supuestos!C$25) | Y51: =Supuestos!D$23*(1-$C51+$C51*((1+Supuestos!$B$4+$B51/10000)/(1+Supuestos!$B$4))^Supuestos!D$25) | Z51: =Supuestos!E$23*(1-$C51+$C51*((1+Supuestos!$B$4+$B51/10000)/(1+Supuestos!$B$4))^Supuestos!E$25) | AA51: =Supuestos!F$23*(1-$C51+$C51*((1+Supuestos!$B$4+$B51/10000)/(1+Supuestos!$B$4))^Supuestos!F$25) | AB51: =Supuestos!G$23*(1-$C51+$C51*((1+Supuestos!$B$4+$B51/10000)/(1+Supuestos!$B$4))^Supuestos!G$25) | AC51: =Supuestos!H$23*(1-$C51+$C51*((1+Supuestos!$B$4+$B51/10000)/(1+Supuestos!$B$4))^Supuestos!H$25) | AD51: =Supuestos!I$23*(1-$C51+$C51*((1+Supuestos!$B$4+$B51/10000)/(1+Supuestos!$B$4))^Supuestos!I$25) | AE51: =SUMPRODUCT(X51:AC51,R51:W51) | AF51: =(1+Supuestos!$B$5)/(1+Supuestos!$B$4)*(1+Supuestos!$B$4+$B51/10000)-1 | AG51: =AD51/(K51-AF51) | AH51: =AG51*Q51 | AI51: =(AE51+AH51-Supuestos!$B$7-Supuestos!$B$8)/Supuestos!$B$9 | AJ51: =AI51/AI$5-1
A52: 100 | B52: 0 | C52: 0.85 | D52: Mix Δi=+100 θ=0.85 | E52: =(1-Supuestos!C$28)*((1+((1+Supuestos!C$26)/(1+Supuestos!$B$4)-1+Supuestos!$B$14*$A52/10000))*(1+Supuestos!$B$4+$B52/10000)-1)+Supuestos!C$28*((1+Supuestos!C$27+$A52/10000)*(1+Supuestos!$B$4+$B52/10000)-1)*(1-Supuestos!$B$6) | F52: =(1-Supuestos!D$28)*((1+((1+Supuestos!D$26)/(1+Supuestos!$B$4)-1+Supuestos!$B$14*$A52/10000))*(1+Supuestos!$B$4+$B52/10000)-1)+Supuestos!D$28*((1+Supuestos!D$27+$A52/10000)*(1+Supuestos!$B$4+$B52/10000)-1)*(1-Supuestos!$B$6) | G52: =(1-Supuestos!E$28)*((1+((1+Supuestos!E$26)/(1+Supuestos!$B$4)-1+Supuestos!$B$14*$A52/10000))*(1+Supuestos!$B$4+$B52/10000)-1)+Supuestos!E$28*((1+Supuestos!E$27+$A52/10000)*(1+Supuestos!$B$4+$B52/10000)-1)*(1-Supuestos!$B$6) | H52: =(1-Supuestos!F$28)*((1+((1+Supuestos!F$26)/(1+Supuestos!$B$4)-1+Supuestos!$B$14*$A52/10000))*(1+Supuestos!$B$4+$B52/10000)-1)+Supuestos!F$28*((1+Supuestos!F$27+$A52/10000)*(1+Supuestos!$B$4+$B52/10000)-1)*(1-Supuestos!$B$6) | I52: =(1-Supuestos!G$28)*((1+((1+Supuestos!G$26)/(1+Supuestos!$B$4)-1+Supuestos!$B$14*$A52/10000))*(1+Supuestos!$B$4+$B52/10000)-1)+Supuestos!G$28*((1+Supuestos!G$27+$A52/10000)*(1+Supuestos!$B$4+$B52/10000)-1)*(1-Supuestos!$B$6) | J52: =(1-Supuestos!H$28)*((1+((1+Supuestos!H$26)/(1+Supuestos!$B$4)-1+Supuestos!$B$14*$A52/10000))*(1+Supuestos!$B$4+$B52/10000)-1)+Supuestos!H$28*((1+Supuestos!H$27+$A52/10000)*(1+Supuestos!$B$4+$B52/10000)-1)*(1-Supuestos!$B$6) | K52: =(1-Supuestos!I$28)*((1+((1+Supuestos!I$26)/(1+Supuestos!$B$4)-1+Supuestos!$B$14*$A52/10000))*(1+Supuestos!$B$4+$B52/10000)-1)+Supuestos!I$28*((1+Supuestos!I$27+$A52/10000)*(1+Supuestos!$B$4+$B52/10000)-1)*(1-Supuestos!$B$6) | L52: =(1+E52)^-Supuestos!C$24 | M52: =L52*(1+F52)^-Supuestos!D$24 | N52: =M52*(1+G52)^-Supuestos!E$24 | O52: =N52*(1+H52)^-Supuestos!F$24 | P52: =O52*(1+I52)^-Supuestos!G$24 | Q52: =P52*(1+J52)^-Supuestos!H$24 | R52: =(1+E52)^-(Supuestos!C$24/2) | S52: =L52*(1+F52)^-(Supuestos!D$24/2) | T52: =M52*(1+G52)^-(Supuestos!E$24/2) | U52: =N52*(1+H52)^-(Supuestos!F$24/2) | V52: =O52*(1+I52)^-(Supuestos!G$24/2) | W52: =P52*(1+J52)^-(Supuestos!H$24/2) | X52: =Supuestos!C$23*(1-$C52+$C52*((1+Supuestos!$B$4+$B52/10000)/(1+Supuestos!$B$4))^Supuestos!C$25) | Y52: =Supuestos!D$23*(1-$C52+$C52*((1+Supuestos!$B$4+$B52/10000)/(1+Supuestos!$B$4))^Supuestos!D$25) | Z52: =Supuestos!E$23*(1-$C52+$C52*((1+Supuestos!$B$4+$B52/10000)/(1+Supuestos!$B$4))^Supuestos!E$25) | AA52: =Supuestos!F$23*(1-$C52+$C52*((1+Supuestos!$B$4+$B52/10000)/(1+Supuestos!$B$4))^Supuestos!F$25) | AB52: =Supuestos!G$23*(1-$C52+$C52*((1+Supuestos!$B$4+$B52/10000)/(1+Supuestos!$B$4))^Supuestos!G$25) | AC52: =Supuestos!H$23*(1-$C52+$C52*((1+Supuestos!$B$4+$B52/10000)/(1+Supuestos!$B$4))^Supuestos!H$25) | AD52: =Supuestos!I$23*(1-$C52+$C52*((1+Supuestos!$B$4+$B52/10000)/(1+Supuestos!$B$4))^Supuestos!I$25) | AE52: =SUMPRODUCT(X52:AC52,R52:W52) | AF52: =(1+Supuestos!$B$5)/(1+Supuestos!$B$4)*(1+Supuestos!$B$4+$B52/10000)-1 | AG52: =AD52/(K52-AF52) | AH52: =AG52*Q52 | AI52: =(AE52+AH52-Supuestos!$B$7-Supuestos!$B$8)/Supuestos!$B$9 | AJ52: =AI52/AI$5-1
... A106: 0 | B106: -100 | C106: 0.7 | D106: Mix Δi=-100 θ=0.7 | E106: =(1-Supuestos!C$28)*((1+((1+Supuestos!C$26)/(1+Supuestos!$B$4)-1+Supuestos!$B$14*$A106/10000))*(1+Supuestos!$B$4+$B106/10000)-1)+Supuestos!C$28*((1+Supuestos!C$27+$A106/10000)*(1+Supuestos!$B$4+$B106/10000)-1)*(1-Supuestos!$B$6) | F106: =(1-Supuestos!D$28)*((1+((1+Supuestos!D$26)/(1+Supuestos!$B$4)-1+Supuestos!$B$14*$A106/10000))*(1+Supuestos!$B$4+$B106/10000)-1)+Supuestos!D$28*((1+Supuestos!D$27+$A106/10000)*(1+Supuestos!$B$4+$B106/10000)-1)*(1-Supuestos!$B$6) | G106: =(1-Supuestos!E$28)*((1+((1+Supuestos!E$26)/(1+Supuestos!$B$4)-1+Supuestos!$B$14*$A106/10000))*(1+Supuestos!$B$4+$B106/10000)-1)+Supuestos!E$28*((1+Supuestos!E$27+$A106/10000)*(1+Supuestos!$B$4+$B106/10000)-1)*(1-Supuestos!$B$6) | H106: =(1-Supuestos!F$28)*((1+((1+Supuestos!F$26)/(1+Supuestos!$B$4)-1+Supuestos!$B$14*$A106/10000))*(1+Supuestos!$B$4+$B106/10000)-1)+Supuestos!F$28*((1+Supuestos!F$27+$A106/10000)*(1+Supuestos!$B$4+$B106/10000)-1)*(1-Supuestos!$B$6) | I106: =(1-Supuestos!G$28)*((1+((1+Supuestos!G$26)/(1+Supuestos!$B$4)-1+Supuestos!$B$14*$A106/10000))*(1+Supuestos!$B$4+$B106/10000)-1)+Supuestos!G$28*((1+Supuestos!G$27+$A106/10000)*(1+Supuestos!$B$4+$B106/10000)-1)*(1-Supuestos!$B$6) | J106: =(1-Supuestos!H$28)*((1+((1+Supuestos!H$26)/(1+Supuestos!$B$4)-1+Supuestos!$B$14*$A106/10000))*(1+Supuestos!$B$4+$B106/10000)-1)+Supuestos!H$28*((1+Supuestos!H$27+$A106/10000)*(1+Supuestos!$B$4+$B106/10000)-1)*(1-Supuestos!$B$6) | K106: =(1-Supuestos!I$28)*((1+((1+Supuestos!I$26)/(1+Supuestos!$B$4)-1+Supuestos!$B$14*$A106/10000))*(1+Supuestos!$B$4+$B106/10000)-1)+Supuestos!I$28*((1+Supuestos!I$27+$A106/10000)*(1+Supuestos!$B$4+$B106/10000)-1)*(1-Supuestos!$B$6) | L106: =(1+E106)^-Supuestos!C$24 | M106: =L106*(1+F106)^-Supuestos!D$24 | N106: =M106*(1+G106)^-Supuestos!E$24 | O106: =N106*(1+H106)^-Supuestos!F$24 | P106: =O106*(1+I106)^-Supuestos!G$24 | Q106: =P106*(1+J106)^-Supuestos!H$24 | R106: =(1+E106)^-(Supuestos!C$24/2) | S106: =L106*(1+F106)^-(Supuestos!D$24/2) | T106: =M106*(1+G106)^-(Supuestos!E$24/2) | U106: =N106*(1+H106)^-(Supuestos!F$24/2) | V106: =O106*(1+I106)^-(Supuestos!G$24/2) | W106: =P106*(1+J106)^-(Supuestos!H$24/2) | X106: =Supuestos!C$23*(1-$C106+$C106*((1+Supuestos!$B$4+$B106/10000)/(1+Supuestos!$B$4))^Supuestos!C$25) | Y106: =Supuestos!D$23*(1-$C106+$C106*((1+Supuestos!$B$4+$B106/10000)/(1+Supuestos!$B$4))^Supuestos!D$25) | Z106: =Supuestos!E$23*(1-$C106+$C106*((1+Supuestos!$B$4+$B106/10000)/(1+Supuestos!$B$4))^Supuestos!E$25) | AA106: =Supuestos!F$23*(1-$C106+$C106*((1+Supuestos!$B$4+$B106/10000)/(1+Supuestos!$B$4))^Supuestos!F$25) | AB106: =Supuestos!G$23*(1-$C106+$C106*((1+Supuestos!$B$4+$B106/10000)/(1+Supuestos!$B$4))^Supuestos!G$25) | AC106: =Supuestos!H$23*(1-$C106+$C106*((1+Supuestos!$B$4+$B106/10000)/(1+Supuestos!$B$4))^Supuestos!H$25) | AD106: =Supuestos!I$23*(1-$C106+$C106*((1+Supuestos!$B$4+$B106/10000)/(1+Supuestos!$B$4))^Supuestos!I$25) | AE106: =SUMPRODUCT(X106:AC106,R106:W106) | AF106: =(1+Supuestos!$B$5)/(1+Supuestos!$B$4)*(1+Supuestos!$B$4+$B106/10000)-1 | AG106: =AD106/(K106-AF106) | AH106: =AG106*Q106 | AI106: =(AE106+AH106-Supuestos!$B$7-Supuestos!$B$8)/Supuestos!$B$9 | AJ106: =AI106/AI$5-1
A107: =Supuestos!B15 | B107: =Supuestos!B16 | C107: =Supuestos!$B$13 | D107: Escenario único | E107: =(1-Supuestos!C$28)*((1+((1+Supuestos!C$26)/(1+Supuestos!$B$4)-1+Supuestos!$B$14*$A107/10000))*(1+Supuestos!$B$4+$B107/10000)-1)+Supuestos!C$28*((1+Supuestos!C$27+$A107/10000)*(1+Supuestos!$B$4+$B107/10000)-1)*(1-Supuestos!$B$6) | F107: =(1-Supuestos!D$28)*((1+((1+Supuestos!D$26)/(1+Supuestos!$B$4)-1+Supuestos!$B$14*$A107/10000))*(1+Supuestos!$B$4+$B107/10000)-1)+Supuestos!D$28*((1+Supuestos!D$27+$A107/10000)*(1+Supuestos!$B$4+$B107/10000)-1)*(1-Supuestos!$B$6) | G107: =(1-Supuestos!E$28)*((1+((1+Supuestos!E$26)/(1+Supuestos!$B$4)-1+Supuestos!$B$14*$A107/10000))*(1+Supuestos!$B$4+$B107/10000)-1)+Supuestos!E$28*((1+Supuestos!E$27+$A107/10000)*(1+Supuestos!$B$4+$B107/10000)-1)*(1-Supuestos!$B$6) | H107: =(1-Supuestos!F$28)*((1+((1+Supuestos!F$26)/(1+Supuestos!$B$4)-1+Supuestos!$B$14*$A107/10000))*(1+Supuestos!$B$4+$B107/10000)-1)+Supuestos!F$28*((1+Supuestos!F$27+$A107/10000)*(1+Supuestos!$B$4+$B107/10000)-1)*(1-Supuestos!$B$6) | I107: =(1-Supuestos!G$28)*((1+((1+Supuestos!G$26)/(1+Supuestos!$B$4)-1+Supuestos!$B$14*$A107/10000))*(1+Supuestos!$B$4+$B107/10000)-1)+Supuestos!G$28*((1+Supuestos!G$27+$A107/10000)*(1+Supuestos!$B$4+$B107/10000)-1)*(1-Supuestos!$B$6) | J107: =(1-Supuestos!H$28)*((1+((1+Supuestos!H$26)/(1+Supuestos!$B$4)-1+Supuestos!$B$14*$A107/10000))*(1+Supuestos!$B$4+$B107/10000)-1)+Supuestos!H$28*((1+Supuestos!H$27+$A107/10000)*(1+Supuestos!$B$4+$B107/10000)-1)*(1-Supuestos!$B$6) | K107: =(1-Supuestos!I$28)*((1+((1+Supuestos!I$26)/(1+Supuestos!$B$4)-1+Supuestos!$B$14*$A107/10000))*(1+Supuestos!$B$4+$B107/10000)-1)+Supuestos!I$28*((1+Supuestos!I$27+$A107/10000)*(1+Supuestos!$B$4+$B107/10000)-1)*(1-Supuestos!$B$6) | L107: =(1+E107)^-Supuestos!C$24 | M107: =L107*(1+F107)^-Supuestos!D$24 | N107: =M107*(1+G107)^-Supuestos!E$24 | O107: =N107*(1+H107)^-Supuestos!F$24 | P107: =O107*(1+I107)^-Supuestos!G$24 | Q107: =P107*(1+J107)^-Supuestos!H$24 | R107: =(1+E107)^-(Supuestos!C$24/2) | S107: =L107*(1+F107)^-(Supuestos!D$24/2) | T107: =M107*(1+G107)^-(Supuestos!E$24/2) | U107: =N107*(1+H107)^-(Supuestos!F$24/2) | V107: =O107*(1+I107)^-(Supuestos!G$24/2) | W107: =P107*(1+J107)^-(Supuestos!H$24/2) | X107: =Supuestos!C$23*(1-$C107+$C107*((1+Supuestos!$B$4+$B107/10000)/(1+Supuestos!$B$4))^Supuestos!C$25) | Y107: =Supuestos!D$23*(1-$C107+$C107*((1+Supuestos!$B$4+$B107/10000)/(1+Supuestos!$B$4))^Supuestos!D$25) | Z107: =Supuestos!E$23*(1-$C107+$C107*((1+Supuestos!$B$4+$B107/10000)/(1+Supuestos!$B$4))^Supuestos!E$25) | AA107: =Supuestos!F$23*(1-$C107+$C107*((1+Supuestos!$B$4+$B107/10000)/(1+Supuestos!$B$4))^Supuestos!F$25) | AB107: =Supuestos!G$23*(1-$C107+$C107*((1+Supuestos!$B$4+$B107/10000)/(1+Supuestos!$B$4))^Supuestos!G$25) | AC107: =Supuestos!H$23*(1-$C107+$C107*((1+Supuestos!$B$4+$B107/10000)/(1+Supuestos!$B$4))^Supuestos!H$25) | AD107: =Supuestos!I$23*(1-$C107+$C107*((1+Supuestos!$B$4+$B107/10000)/(1+Supuestos!$B$4))^Supuestos!I$25) | AE107: =SUMPRODUCT(X107:AC107,R107:W107) | AF107: =(1+Supuestos!$B$5)/(1+Supuestos!$B$4)*(1+Supuestos!$B$4+$B107/10000)-1 | AG107: =AD107/(K107-AF107) | AH107: =AG107*Q107 | AI107: =(AE107+AH107-Supuestos!$B$7-Supuestos!$B$8)/Supuestos!$B$9 | AJ107: =AI107/AI$5-1

Sheet Empirico
A1: Semanal: precio de Mallplaza, tasas a 10 años (BCCh) e IPSA
A2: Fuente: Mallplaza_Tasas_Historico.xlsx, hoja Datos (último dato de cada semana). Azul = dato; negro = fórmula.
A4: Semana (último día) | B4: Mallplaza (CLP) | C4: BCP10 (%) | D4: BCU10 (%) | E4: IPSA | F4: Inflación implícita (%) | G4: Δ ln precio | H4: Δ BCU10 (pp) | I4: Δ infl. implícita (pp) | J4: Δ ln IPSA
A5: 45478 | B5: 1381.56 | C5: 6.22 | D5: 3.1 | E5: 6483.67 | F5: =C5-D5
A6: 45485 | B6: 1362.81 | C6: 6.11 | D6: 2.9 | E6: 6550.01 | F6: =C6-D6 | G6: =LN(B6/B5) | H6: =D6-D5 | I6: =F6-F5 | J6: =LN(E6/E5)
A7: 45492 | B7: 1421.03 | C7: 6.1 | D7: 2.87 | E7: 6558.68 | F7: =C7-D7 | G7: =LN(B7/B6) | H7: =D7-D6 | I7: =F7-F6 | J7: =LN(E7/E6)
A8: 45499 | B8: 1440.77 | C8: 6.08 | D8: 2.77 | E8: 6432.16 | F8: =C8-D8 | G8: =LN(B8/B7) | H8: =D8-D7 | I8: =F8-F7 | J8: =LN(E8/E7)
A9: 45506 | B9: 1423.4 | C9: 5.99 | D9: 2.6 | E9: 6315.46 | F9: =C9-D9 | G9: =LN(B9/B8) | H9: =D9-D8 | I9: =F9-F8 | J9: =LN(E9/E8)
A10: 45513 | B10: 1460.5 | C10: 5.91 | D10: 2.53 | E10: 6320.96 | F10: =C10-D10 | G10: =LN(B10/B9) | H10: =D10-D9 | I10: =F10-F9 | J10: =LN(E10/E9)
A11: 45520 | B11: 1512.11 | C11: 5.8 | D11: 2.49 | E11: 6457.74 | F11: =C11-D11 | G11: =LN(B11/B10) | H11: =D11-D10 | I11: =F11-F10 | J11: =LN(E11/E10)
A12: 45527 | B12: 1519.71 | C12: 5.73 | D12: 2.4 | E12: 6463.24 | F12: =C12-D12 | G12: =LN(B12/B11) | H12: =D12-D11 | I12: =F12-F11 | J12: =LN(E12/E11)
A13: 45534 | B13: 1490.21 | C13: 5.64 | D13: 2.37 | E13: 6459.96 | F13: =C13-D13 | G13: =LN(B13/B12) | H13: =D13-D12 | I13: =F13-F12 | J13: =LN(E13/E12)
A14: 45541 | B14: 1506.29 | C14: 5.5 | D14: 2.26 | E14: 6245.42 | F14: =C14-D14 | G14: =LN(B14/B13) | H14: =D14-D13 | I14: =F14-F13 | J14: =LN(E14/E13)
A15: 45547 | B15: 1509.05 | C15: 5.37 | D15: 2.1 | E15: 6343.16 | F15: =C15-D15 | G15: =LN(B15/B14) | H15: =D15-D14 | I15: =F15-F14 | J15: =LN(E15/E14)
A16: 45562 | B16: 1580.6 | C16: 5.16 | D16: 1.82 | E16: 6530.73 | F16: =C16-D16 | G16: =LN(B16/B15) | H16: =D16-D15 | I16: =F16-F15 | J16: =LN(E16/E15)
A17: 45568 | B17: 1524.65 | C17: 5.3 | D17: 2 | E17: 6389.82 | F17: =C17-D17 | G17: =LN(B17/B16) | H17: =D17-D16 | I17: =F17-F16 | J17: =LN(E17/E16)
... A118: 46295 | B118: 3555 | C118: 6.25 | D118: 2.82 | E118: 10969.49 | F118: =C118-D118 | G118: =LN(B118/B117) | H118: =D118-D117 | I118: =F118-F117 | J118: =LN(E118/E117)
