Workbook

Sheet README
A1: Mallplaza (Plaza S.A.) — Financial Analysis exhibits v5 · 05-10-2026 (v4 + hoja FCFF_DCF: interfaz forecast ↔ valuation)
A2: Borrador de trabajo del equipo. Todo número debe verificarse contra la fuente citada en Inputs antes de entrar al informe.
A4: Convención de colores: azul = dato ingresado [R]/[C]; negro = fórmula; verde = vínculo a la hoja Inputs; amarillo = alerta.
A5: Hojas: Inputs · Forecast · Forecast_link · FCFF_DCF · Peers_inputs · E1_DuPont · E2_FFO_bridge · E3_Growth · E4_Cash · E5_Leverage · E6_Debt · E7_WACC
A6: Para actualizar: cambiar solo valores azules en Inputs, Peers_inputs, E6 (tabla de bonos) o E7 (tabla de tasas).
A7: Pendientes: covenant (E5); tasas de descuento de los pares (CMF); GLA de Colombia por año (E3); IPC mensual Colombia (E3); ticker Colombia USD 10Y (E7); ingresos 2019–2020 y EBITDA 2019 (E1); fecha de cierre de Gran Plaza (Forecast); dueño del motor operativo con valuation.
A8: v3 (28-09): Inputs +26 filas (tipo de cambio, inflación, PI por país, Chile segmento); nueva hoja Peers_inputs; E1 bloque C (pares); E3 bloque B (moneda local y real) + gráfico; E5 bloque de pares; nueva hoja E7_WACC con gráfico. E2, E4 y E6 sin cambios.
A9: v4 (05-10): nueva hoja Forecast (motor operativo); Forecast_link vinculado; Inputs: utilidad 2022 reformulada 157.667, distribuible 2023 = 197.540 [R] y 2022 [C], balances 2022; E7: WACC jun-25 y residuos semestrales 2025.
A11: v6+ (16-10): nueva hoja E8_ROIC_RONIC (ROIC 2025 = NOPAT / capital promedio a valor razonable; RONIC de la expansión).

Sheet Inputs
A1: Inputs — datos reportados [R] y supuestos [S] (MM CLP salvo indicación)
A3: Clave | B3: Concepto | C3: Valor | D3: Unidad | E3: Período | F3: Tag | G3: Fuente
A4: rev23 | B4: Ingresos ordinarios | C4: 419904 | D4: MM CLP | E4: FY2023 | F4: R | G4: EEFF dic-24, EERR (comparativo)
A5: rev24 | B5: Ingresos ordinarios | C5: 494605 | D5: MM CLP | E5: FY2024 | F5: R | G5: EEFF dic-25, EERR (reformulado)
A6: rev25 | B6: Ingresos ordinarios | C6: 653911 | D6: MM CLP | E6: FY2025 | F6: R | G6: EEFF dic-25, EERR
A7: rev1s25 | B7: Ingresos ordinarios | C7: 316108 | D7: MM CLP | E7: 1S25 | F7: R | G7: EEFF jun-26, EERR (comparativo)
A8: rev1s26 | B8: Ingresos ordinarios | C8: 339530 | D8: MM CLP | E8: 1S26 | F8: R | G8: EEFF jun-26, EERR
A9: ebitda24 | B9: EBITDA (definición compañía) | C9: 380637 | D9: MM CLP | E9: FY2024 | F9: R | G9: Análisis Razonado 2025
A10: ebitda25 | B10: EBITDA (definición compañía) | C10: 526228 | D10: MM CLP | E10: FY2025 | F10: R | G10: Análisis Razonado 2025; reconciliado WP §2.1
A11: ni_cons25 | B11: Ganancia consolidada | C11: 1440978 | D11: MM CLP | E11: FY2025 | F11: R | G11: EEFF dic-25, EERR
A12: ni24 | B12: Utilidad atribuible a la controladora | C12: 335934 | D12: MM CLP | E12: FY2024 | F12: R | G12: EEFF dic-25, EERR
A13: ni25 | B13: Utilidad atribuible a la controladora | C13: 1431012 | D13: MM CLP | E13: FY2025 | F13: R | G13: EEFF dic-25, EERR
A14: nci25 | B14: Utilidad atribuible a no controladores | C14: 9967 | D14: MM CLP | E14: FY2025 | F14: R | G14: EEFF dic-25, EERR
A15: oif25 | B15: Otros ingresos por función (incl. valor razonable 1.447.136) | C15: 1448943 | D15: MM CLP | E15: FY2025 | F15: R | G15: EEFF dic-25, Nota 23.2
... A89: dist23 | B89: Utilidad líquida distribuible | C89: 197540 | D89: MM CLP | E89: FY2023 | F89: R | G89: EEFF dic-23, Nota 21e (utilidad líquida y distribuible). Reemplaza la inferida 148.155
A90: rev19 | B90: Ingresos ordinarios | D90: MM CLP | E90: FY2019 | F90: P | G90: PENDIENTE: Bloomberg FA (export existente)
A91: rev20 | B91: Ingresos ordinarios | D91: MM CLP | E91: FY2020 | F91: P | G91: PENDIENTE: Bloomberg FA (export existente)
A92: ebitda19 | B92: EBITDA (definición compañía) | D92: MM CLP | E92: FY2019 | F92: P | G92: PENDIENTE: Bloomberg ARD_REF_EBITDA_IS
A93: ta21r | B93: Total activos REFORMULADO al 01-01-2022 | C93: 4094996 | D93: MM CLP | E93: 01-01-22 | F93: R | G93: EEFF dic-23, balance reformulado al 01-01-2022
A94: ta22 | B94: Total activos | C94: 4513943 | D94: MM CLP | E94: dic-22 | F94: R | G94: EEFF dic-23, balance reformulado al 31-12-2022
A95: eq21r | B95: Patrimonio atribuible REFORMULADO al 01-01-2022 | C95: 2167172 | D95: MM CLP | E95: 01-01-22 | F95: R | G95: EEFF dic-23, patrimonio atribuible reformulado al 01-01-2022
A96: eq22 | B96: Patrimonio atribuible | C96: 2263298 | D96: MM CLP | E96: dic-22 | F96: R | G96: EEFF dic-23, patrimonio atribuible reformulado al 31-12-2022
A97: dist22 | B97: Utilidad líquida distribuible | C97: 95856 | D97: MM CLP | E97: FY2022 | F97: C | G97: Proxy: 157.667 − valor razonable 79.489 × (1 − 22,24%); 22,24% = impuesto diferido / valor razonable de la Nota 21e 2023 (43.537 / 195.756). EEFF dic-23, Notas 24.2 y 21e. La compañía no publica la cifra 2022 bajo NIC 40
A98: payout | B98: Payout sobre utilidad distribuible (política) | C98: 0.4 | D98: % | E98: Política | F98: R | G98: Acuerdo de directorio 25-01-2017; EEFF dic-25 Nota 20e
A99: bank25 | B99: Obligaciones con bancos | C99: 301600 | D99: MM CLP | E99: dic-25 | F99: R | G99: EEFF dic-25, Nota 14
A100: co23 | B100: Ingresos segmento Colombia | C100: 36360 | D100: MM CLP | E100: FY2023 | F100: R | G100: Bloomberg FA GEO (WP §55)
A101: fx_cop23 | B101: CLP por COP, promedio del período | C101: 0.197936 | D101: CLP/COP | E101: FY2023 (feb–dic) | F101: C | G101: Bloomberg USDCLP/USDCOP REGN Curncy, PX_LAST diario, cruces día a día y promediados; export 28-09-2026 (WP §82). USDCLP parte 31-01-2023
A102: fx_cop24 | B102: CLP por COP, promedio del período | C102: 0.232018 | D102: CLP/COP | E102: FY2024 | F102: C | G102: Ídem (WP §82)
A103: fx_cop25 | B103: CLP por COP, promedio del período | C103: 0.235126 | D103: CLP/COP | E103: FY2025 | F103: C | G103: Ídem (WP §82)
A104: fx_cop1s25 | B104: CLP por COP, promedio del período | C104: 0.22793 | D104: CLP/COP | E104: 1S25 | F104: C | G104: Ídem (WP §82)
... A125: shares | B125: Acciones en circulación | C125: 2190 | D125: MM acciones | E125: sep-26 | F125: R | G125: Bloomberg DES 27-09-2026

Sheet Forecast
A1: Forecast — motor operativo 2026E–2031E (CLP nominales; drivers en real por país, nominalizados con IPC y tipo de cambio de consenso)
A2: Borrador de trabajo [S] para el equipo. Azul = input; amarillo = supuesto clave a discutir; negro = fórmula; verde = vínculo a otra hoja. Alimenta Forecast_link → E1. Caso base: sin Gran Plaza y sin "Otros proyectos Chile" (46.500 m² sin fecha); ambos con interruptor.
A3: Tags: [R] reportado · [P] consenso de mercado (Bloomberg ECFC, composite de contribuidores, privado, 05-10-2026) · [C] cálculo · [S] supuesto propio.
A5: A. Macro (fin de año salvo IPC, que es promedio anual) | B5: Tag | C5: 2025A | D5: 2026E | E5: 2027E | F5: 2028E | G5: 2029E | H5: 2030E | I5: 2031E | J5: Fuente / supuesto
A6: IPC Chile (YoY%) | B6: P / S | C6: 0.042 | D6: 0.037 | E6: 0.032 | F6: 0.03 | G6: 0.03 | H6: 0.03 | I6: 0.03 | J6: ECFC Chile 2025–2028 [P]; 2029–2031 = meta BCCh 3% [S]
A7: IPC Perú (YoY%) | B7: P / S | C7: 0.015 | D7: 0.038 | E7: 0.026 | F7: 0.024 | G7: 0.02 | H7: 0.02 | I7: 0.02 | J7: ECFC Perú 2025–2028 [P]; 2029–2031 = centro del rango meta BCRP (1%–3%) [S]
A8: IPC Colombia (promedio, YoY%) | B8: P / S | C8: 0.051 | D8: 0.06 | E8: 0.054 | F8: 0.041 | G8: 0.035 | H8: 0.03 | I8: 0.03 | J8: ECFC Colombia 2025–2028 [P]; 2029 convergencia; 2030–2031 = meta BanRep 3% [S]
A9: Tasa de política BCCh (fin de año) | B9: P / S | C9: 0.045 | D9: 0.0452 | E9: 0.0456 | F9: 0.0433 | G9: 0.0433 | H9: 0.0433 | I9: 0.0433 | J9: ECFC Chile [P]; 2029+ se mantiene [S]. Referencia, no se usa en fórmulas
A10: USDCLP (fin de año) | B10: P / S | C10: 900.58 | D10: 937 | E10: 908.5 | F10: 921 | G10: =F10 -> 921 | H10: =G10 -> 921 | I10: =H10 -> 921 | J10: ECFC [P]; 2029+ se mantiene [S] (solo afecta capex en USD de "Otros proyectos Chile" si se activa)
A11: USDPEN (fin de año) | B11: P | C11: 3.36 | D11: 3.39 | E11: 3.3 | F11: 3.25 | J11: ECFC Perú [P]
A12: USDCOP (fin de año) | B12: P | C12: 3775 | D12: 3213 | E12: 3288 | F12: 3500 | J12: ECFC Colombia [P]
A13: CLP por PEN (fin de año) | B13: C | C13: =C10/C11 -> 268.02976 | D13: =D10/D11 -> 276.40118 | E13: =E10/E11 -> 275.30303 | F13: =F10/F11 -> 283.38462 | G13: =F13*(1+G6)/(1+G7) -> 286.1629 | H13: =G13*(1+H6)/(1+H7) -> 288.96841 | I13: =H13*(1+I6)/(1+I7) -> 291.80144 | J13: Cruce de consenso 2025–2028; 2029+ paridad de poder de compra relativa con IPC de cada país [S]
A14: CLP por COP (fin de año) | B14: C | C14: =C10/C12 -> 0.23856424 | D14: =D10/D12 -> 0.29162776 | E14: =E10/E12 -> 0.27630779 | F14: =F10/F12 -> 0.26314286 | G14: =F14*(1+G6)/(1+G8) -> 0.26187164 | H14: =G14*(1+H6)/(1+H8) -> 0.26187164 | I14: =H14*(1+I6)/(1+I8) -> 0.26187164 | J14: Cruce de consenso 2025–2028; 2029+ paridad de poder de compra relativa con IPC de cada país [S]
A15: CLP por PEN (promedio) | B15: C | C15: =Inputs!C107 -> 266.84002 | D15: =G34/G31 -> 267.99722 | E15: =(D13+E13)/2 -> 275.85211 | F15: =(E13+F13)/2 -> 279.34382 | G15: =(F13+G13)/2 -> 284.77376 | H15: =(G13+H13)/2 -> 287.56566 | I15: =(H13+I13)/2 -> 290.38493 | J15: 2025A promedio real (Inputs); 2026E desde el puente semestral (bloque B); 2027+ promedio de fin de año t−1 y t [S]
A16: CLP por COP (promedio) | B16: C | C16: =Inputs!C103 -> 0.235126 | D16: =G35/G32 -> 0.26340869 | E16: =(D14+E14)/2 -> 0.28396777 | F16: =(E14+F14)/2 -> 0.26972532 | G16: =(F14+G14)/2 -> 0.26250725 | H16: =(G14+H14)/2 -> 0.26187164 | I16: =(H14+I14)/2 -> 0.26187164 | J16: 2025A promedio real (Inputs); 2026E desde el puente semestral (bloque B); 2027+ promedio de fin de año t−1 y t [S]
A17: USDCLP (promedio) | B17: C | D17: =(C10+D10)/2 -> 918.79 | E17: =(D10+E10)/2 -> 922.75 | F17: =(E10+F10)/2 -> 914.75 | G17: =(F10+G10)/2 -> 921 | H17: =(G10+H10)/2 -> 921 | I17: =(H10+I10)/2 -> 921 | J17: 2025A promedio real (Inputs); 2026E desde el puente semestral (bloque B); 2027+ promedio de fin de año t−1 y t [S]
A19: B. Puente 2026E = 1S26 real + 2S26E (moneda local) | C19: 1S25 | D19: 2S25 | E19: 1S26 | F19: 2S26E | G19: 2026E | J19: Fuente / supuesto
A20: Cierre jun-26: USDCLP | B20: R | E20: 922.1 | J20: Release 2T26, nota de tipo de cambio de la tabla de proyectos
A21: Cierre jun-26: USDPEN | B21: R | E21: 3.41 | J21: Ídem
A22: Cierre jun-26: USDCOP | B22: R | E22: 3416.45 | J22: Ídem
A23: CLP por PEN (promedio del semestre) | B23: C | C23: =Inputs!C108 -> 259.72007 | D23: =2*Inputs!C107-Inputs!C108 -> 273.95997 | E23: =Inputs!C109 -> 262.11386 | F23: =(E20/E21+D13)/2 -> 273.40587 | J23: 2S25 = 2 × promedio anual − 1S25 (aproxima pesos iguales por semestre); 2S26E = promedio entre cierre jun-26 y fin de 2026 de consenso [S]
A24: CLP por COP (promedio del semestre) | B24: C | C24: =Inputs!C104 -> 0.22793 | D24: =2*Inputs!C103-Inputs!C104 -> 0.242322 | E24: =Inputs!C105 -> 0.244951 | F24: =(E20/E22+D14)/2 -> 0.2807639 | J24: Ídem
A25: USDCLP (promedio 2S26E) | B25: C | F25: =(E20+D10)/2 -> 929.55 | J25: Para convertir el capex en USD del 2S26
A26: Ingresos segmento Chile (MM CLP) | B26: R | C26: =Inputs!C29 -> 230626 | D26: =Inputs!C36-Inputs!C29 -> 239338 | E26: =Inputs!C30 -> 244588 | J26: EEFF Notas de segmentos (Inputs)
A27: Ingresos segmento Perú (MM CLP) | B27: R | C27: =Inputs!C33 -> 56496 | D27: =Inputs!C40-Inputs!C33 -> 64824 | E27: =Inputs!C34 -> 61532 | J27: Ídem
A28: Ingresos segmento Colombia (MM CLP) | B28: R | C28: =Inputs!C31 -> 29393 | D28: =Inputs!C38-Inputs!C31 -> 33234 | E28: =Inputs!C32 -> 33899 | J28: Ídem
A29: Crecimiento local 1S26 vs 1S25 (Chile / Perú / Colombia) → se aplica al 2S26E | B29: S | C29: =E30/C30-1 -> 0.060539575 | D29: =E31/C31-1 -> 0.079192337 | E29: =E32/C32-1 -> 0.073161901 | J29: Columnas C/D/E de esta fila = Chile / Perú / Colombia (no semestres). Supuesto clave [S]: el 2S26 repite el crecimiento local del 1S26; las aperturas de 2026 (8.900 m²) quedan dentro
A30: Chile (MM CLP) | B30: C | C30: =C26 -> 230626 | D30: =D26 -> 239338 | E30: =E26 -> 244588 | F30: =D26*(1+E26/C26-1) -> 253827.42 | G30: =E30+F30 -> 498415.42
A31: Perú (MM PEN) | B31: C | C31: =C27/C23 -> 217.52651 | D31: =D27/D23 -> 236.61851 | E31: =E27/E23 -> 234.75294 | F31: =D31*E31/C31 -> 255.35689 | G31: =E31+F31 -> 490.10983
A32: Colombia (MM COP) | B32: C | C32: =C28/C24 -> 128956.26 | D32: =D28/D24 -> 137148.09 | E32: =E28/E24 -> 138390.94 | F32: =D32*E32/C32 -> 147182.11 | G32: =E32+F32 -> 285573.05
A33: 2026E Chile en CLP | B33: C | F33: =F30 -> 253827.42 | G33: =E26+F30 -> 498415.42
A34: 2026E Perú en CLP | B34: C | F34: =F31*F23 -> 69816.072 | G34: =E27+F31*F23 -> 131348.07
A35: 2026E Colombia en CLP | B35: C | F35: =F32*F24 -> 41323.423 | G35: =E28+F32*F24 -> 75222.423
A37: C. Pipeline de GLA (m² agregados por año de apertura) y maduración | B37: Tag | C37: 2025A | D37: 2026E | E37: 2027E | F37: 2028E | G37: 2029E | H37: 2030E | I37: 2031E | J37: Fuente / supuesto
A38: Factor de ingreso: año de apertura | B38: S | D38: 0.35 | J38: [S] apertura a mitad de año (50%) × 70% de productividad en el primer año
A39: Factor de ingreso: segundo año | B39: S | D39: 0.9 | J39: [S]
A40: Factor de ingreso: tercer año en adelante | B40: S | D40: 1 | J40: [S]
A41: GLA nuevo Chile por año de apertura (m²) | B41: R | D41: 7600 | E41: 37150 | F41: 23150 | J41: Release 2T26, "Proyectos de Expansión en Curso" (Trébol, Oeste, Norte, La Serena)
A42: GLA nuevo Perú por año de apertura (m²) | B42: R | D42: 1300 | E42: 35800 | F42: 18700 | J42: Release 2T26 (Trujillo, Piura, Angamos, La Marina)
A43: "Otros proyectos Chile" incluidos (1 = sí) | B43: S | D43: 1 | J43: v7: activado — pipeline completo con fecha (170.200 m²); Memoria 2025, p. 45: apertura en 2028
A44: "Otros proyectos Chile": año de apertura si se incluyen | B44: S | D44: 2028 | J44: v7: 2028 (en v6 estaba 2029 y el interruptor en 0)
A45: "Otros proyectos Chile": m² | B45: R | D45: 46500 | J45: Release 2T26
A46: GLA base Chile jun-26 (m²) | B46: R | D46: 1461288 | J46: Release 2T26, indicadores por país
A47: GLA base Perú jun-26 (m²) | B47: R | D47: 618093 | J47: Ídem
A48: GLA base Colombia jun-26 (m²) | B48: R | D48: 280754 | J48: Ídem
A49: GLA nuevo equivalente Chile (m² × factor) | B49: C | E49: =$D$41*IF((2027-2026)<0,0,IF((2027-2026)=0,$D$38,IF((2027-2026)=1,$D$39,$D$40)))+$E$41*IF((2027-2027)<0,0,IF((2027-2027)=0,$D$38,IF((2027-2027)=1,$D$39,$D$40)))+$F$41*IF((2027-2028)<0,0,IF((2027-2028)=0,$D$38,IF((2027-2028)=1,$D$39,$D$40)))+$D$43*$D$45*IF((2027-$D$44)<0,0,IF((2027-$D$44)=0,$D$38,IF((2027-$D$44)=1,$D$39,$D$40))) -> 19842.5 | F49: =$D$41*IF((2028-2026)<0,0,IF((2028-2026)=0,$D$38,IF((2028-2026)=1,$D$39,$D$40)))+$E$41*IF((2028-2027)<0,0,IF((2028-2027)=0,$D$38,IF((2028-2027)=1,$D$39,$D$40)))+$F$41*IF((2028-2028)<0,0,IF((2028-2028)=0,$D$38,IF((2028-2028)=1,$D$39,$D$40)))+$D$43*$D$45*IF((2028-$D$44)<0,0,IF((2028-$D$44)=0,$D$38,IF((2028-$D$44)=1,$D$39,$D$40))) -> 65412.5 | G49: =$D$41*IF((2029-2026)<0,0,IF((2029-2026)=0,$D$38,IF((2029-2026)=1,$D$39,$D$40)))+$E$41*IF((2029-2027)<0,0,IF((2029-2027)=0,$D$38,IF((2029-2027)=1,$D$39,$D$40)))+$F$41*IF((2029-2028)<0,0,IF((2029-2028)=0,$D$38,IF((2029-2028)=1,$D$39,$D$40)))+$D$43*$D$45*IF((2029-$D$44)<0,0,IF((2029-$D$44)=0,$D$38,IF((2029-$D$44)=1,$D$39,$D$40))) -> 107435 | H49: =$D$41*IF((2030-2026)<0,0,IF((2030-2026)=0,$D$38,IF((2030-2026)=1,$D$39,$D$40)))+$E$41*IF((2030-2027)<0,0,IF((2030-2027)=0,$D$38,IF((2030-2027)=1,$D$39,$D$40)))+$F$41*IF((2030-2028)<0,0,IF((2030-2028)=0,$D$38,IF((2030-2028)=1,$D$39,$D$40)))+$D$43*$D$45*IF((2030-$D$44)<0,0,IF((2030-$D$44)=0,$D$38,IF((2030-$D$44)=1,$D$39,$D$40))) -> 114400 | I49: =$D$41*IF((2031-2026)<0,0,IF((2031-2026)=0,$D$38,IF((2031-2026)=1,$D$39,$D$40)))+$E$41*IF((2031-2027)<0,0,IF((2031-2027)=0,$D$38,IF((2031-2027)=1,$D$39,$D$40)))+$F$41*IF((2031-2028)<0,0,IF((2031-2028)=0,$D$38,IF((2031-2028)=1,$D$39,$D$40)))+$D$43*$D$45*IF((2031-$D$44)<0,0,IF((2031-$D$44)=0,$D$38,IF((2031-$D$44)=1,$D$39,$D$40))) -> 114400 | J49: Cohortes 2026–2028 (+ Otros si se activan). La cohorte 2026 entra con factor de segundo año en 2027; su aporte 2026 ya está en el puente
A50: GLA nuevo equivalente Perú (m² × factor) | B50: C | E50: =$D$42*IF((2027-2026)<0,0,IF((2027-2026)=0,$D$38,IF((2027-2026)=1,$D$39,$D$40)))+$E$42*IF((2027-2027)<0,0,IF((2027-2027)=0,$D$38,IF((2027-2027)=1,$D$39,$D$40)))+$F$42*IF((2027-2028)<0,0,IF((2027-2028)=0,$D$38,IF((2027-2028)=1,$D$39,$D$40))) -> 13700 | F50: =$D$42*IF((2028-2026)<0,0,IF((2028-2026)=0,$D$38,IF((2028-2026)=1,$D$39,$D$40)))+$E$42*IF((2028-2027)<0,0,IF((2028-2027)=0,$D$38,IF((2028-2027)=1,$D$39,$D$40)))+$F$42*IF((2028-2028)<0,0,IF((2028-2028)=0,$D$38,IF((2028-2028)=1,$D$39,$D$40))) -> 40065 | G50: =$D$42*IF((2029-2026)<0,0,IF((2029-2026)=0,$D$38,IF((2029-2026)=1,$D$39,$D$40)))+$E$42*IF((2029-2027)<0,0,IF((2029-2027)=0,$D$38,IF((2029-2027)=1,$D$39,$D$40)))+$F$42*IF((2029-2028)<0,0,IF((2029-2028)=0,$D$38,IF((2029-2028)=1,$D$39,$D$40))) -> 53930 | H50: =$D$42*IF((2030-2026)<0,0,IF((2030-2026)=0,$D$38,IF((2030-2026)=1,$D$39,$D$40)))+$E$42*IF((2030-2027)<0,0,IF((2030-2027)=0,$D$38,IF((2030-2027)=1,$D$39,$D$40)))+$F$42*IF((2030-2028)<0,0,IF((2030-2028)=0,$D$38,IF((2030-2028)=1,$D$39,$D$40))) -> 55800 | I50: =$D$42*IF((2031-2026)<0,0,IF((2031-2026)=0,$D$38,IF((2031-2026)=1,$D$39,$D$40)))+$E$42*IF((2031-2027)<0,0,IF((2031-2027)=0,$D$38,IF((2031-2027)=1,$D$39,$D$40)))+$F$42*IF((2031-2028)<0,0,IF((2031-2028)=0,$D$38,IF((2031-2028)=1,$D$39,$D$40))) -> 55800 | J50: Ídem
A52: D. Ingresos por país (moneda local, salvo indicación) | B52: Tag | C52: 2025A | D52: 2026E | E52: 2027E | F52: 2028E | G52: 2029E | H52: 2030E | I52: 2031E | J52: Fuente / supuesto
A53: Crecimiento real de parking (todos los países) | B53: S | E53: 0.09 | F53: 0.06 | G53: 0.04 | H53: 0.03 | I53: 0.02 | J53: [S] Parking UDM +23,7% nominal (release 2T26); se asume convergencia rápida. Supuesto clave
A54: Chile (MM CLP)
A55: Ocupación Chile | B55: R / S | D55: 0.961 | E55: 0.961 | F55: 0.961 | G55: 0.961 | H55: 0.961 | I55: 0.961 | J55: 2026 = 2T26 [R]; se mantiene [S]
A56: Crecimiento real same-store (sin parking) | B56: S | E56: 0.015 | F56: 0.0125 | G56: 0.01 | H56: 0.0075 | I56: 0.006 | J56: [S] desde ~SSR real reciente hacia 0,6%, punto medio del rango de crecimiento real que usa la compañía en su tasación (Nota 11 jun-25: 0,1%–1,1%)
A57: Parking / ingresos 2026 | B57: R | D57: 0.121 | J57: Release 2T26, contribución parking UDM por país
A58: Parking | B58: C | D58: =G30*D57 -> 60308.266 | E58: =D58*(1+E6)*(1+E53) -> 67839.562 | F58: =E58*(1+F6)*(1+F53) -> 74067.234 | G58: =F58*(1+G6)*(1+G53) -> 79340.821 | H58: =G58*(1+H6)*(1+H53) -> 84172.677 | I58: =H58*(1+I6)*(1+I53) -> 88431.814
A59: Arriendo y otros, mismo GLA | B59: C | D59: =G30-D58 -> 438107.15 | E59: =D59*(1+E6)*(1+E56)*E55/D55 -> 458908.48 | F59: =E59*(1+F6)*(1+F56)*F55/E55 -> 478584.18 | G59: =F59*(1+G6)*(1+G56)*G55/F55 -> 497871.13 | H59: =G59*(1+H6)*(1+H56)*H55/G55 -> 516653.31 | I59: =H59*(1+I6)*(1+I56)*I55/H55 -> 535345.83
A60: Ingreso anual por m² de GLA base (local) | B60: C | D60: =(D59+D58)/$D$46*1000000 -> 341079.53 | E60: =(E59+E58)/$D$46*1000000 -> 360468.33 | F60: =(F59+F58)/$D$46*1000000 -> 378194.73 | G60: =(G59+G58)/$D$46*1000000 -> 395002.18 | H60: =(H59+H58)/$D$46*1000000 -> 411161.93 | I60: =(I59+I58)/$D$46*1000000 -> 426868.38 | J60: Unidades locales por m² (CLP, PEN, COP). Se aplica al GLA nuevo
A61: Ingresos del GLA nuevo | B61: C | E61: =E60*E49/1000000 -> 7152.5928 | F61: =F60*F49/1000000 -> 24738.663 | G61: =G60*G49/1000000 -> 42437.059 | H61: =H60*H49/1000000 -> 47036.925 | I61: =I60*I49/1000000 -> 48833.743
A62: Ingresos Chile (MM CLP) | B62: C | D62: =G30 -> 498415.42 | E62: =E59+E58+E61 -> 533900.64 | F62: =F59+F58+F61 -> 577390.08 | G62: =G59+G58+G61 -> 619649.01 | H62: =H59+H58+H61 -> 647862.92 | I62: =I59+I58+I61 -> 672611.39
A63: Crecimiento en moneda local | B63: C | E63: =E62/D62-1 -> 0.071196065 | F63: =F62/E62-1 -> 0.081456061 | G63: =G62/F62-1 -> 0.073189561 | H63: =H62/G62-1 -> 0.045532082 | I63: =I62/H62-1 -> 0.038200169
A64: Perú (MM PEN)
A65: Ocupación Perú | B65: R / S | D65: 0.938 | E65: 0.942 | F65: 0.946 | G65: 0.946 | H65: 0.946 | I65: 0.946 | J65: 2026 = 2T26 [R]; Perú recupera 94,6% (nivel 2025) hacia 2028 [S]
A66: Crecimiento real same-store (sin parking) | B66: S | E66: 0.015 | F66: 0.012 | G66: 0.009 | H66: 0.006 | I66: 0.004 | J66: [S] hacia 0,4%, punto medio Nota 11 (−0,4%–1,2%)
A67: Parking / ingresos 2026 | B67: R | D67: 0.064 | J67: Release 2T26, contribución parking UDM por país
A68: Parking | B68: C | D68: =G31*D67 -> 31.367029 | E68: =D68*(1+E7)*(1+E53) -> 35.079003 | F68: =E68*(1+F7)*(1+F53) -> 38.076153 | G68: =F68*(1+G7)*(1+G53) -> 40.391184 | H68: =G68*(1+H7)*(1+H53) -> 42.434977 | I68: =H68*(1+I7)*(1+I53) -> 44.14935
A69: Arriendo y otros, mismo GLA | B69: C | D69: =G31-D68 -> 458.7428 | E69: =D69*(1+E7)*(1+E66)*E65/D65 -> 479.76739 | F69: =E69*(1+F7)*(1+F66)*F65/E65 -> 499.28835 | G69: =F69*(1+G7)*(1+G66)*G65/F65 -> 513.85758 | H69: =G69*(1+H7)*(1+H66)*H65/G65 -> 527.27954 | I69: =H69*(1+I7)*(1+I66)*I65/H65 -> 539.97643
A70: Ingreso anual por m² de GLA base (local) | B70: C | D70: =(D69+D68)/$D$47*1000000 -> 792.93865 | E70: =(E69+E68)/$D$47*1000000 -> 832.95944 | F70: =(F69+F68)/$D$47*1000000 -> 869.39102 | G70: =(G69+G68)/$D$47*1000000 -> 896.70772 | H70: =(H69+H68)/$D$47*1000000 -> 921.72945 | I70: =(I69+I68)/$D$47*1000000 -> 945.04514 | J70: Unidades locales por m² (CLP, PEN, COP). Se aplica al GLA nuevo
A71: Ingresos del GLA nuevo | B71: C | E71: =E70*E50/1000000 -> 11.411544 | F71: =F70*F50/1000000 -> 34.832151 | G71: =G70*G50/1000000 -> 48.359448 | H71: =H70*H50/1000000 -> 51.432503 | I71: =I70*I50/1000000 -> 52.733519
A72: Ingresos Perú (MM PEN) | B72: C | D72: =G31 -> 490.10983 | E72: =E69+E68+E71 -> 526.25794 | F72: =F69+F68+F71 -> 572.19665 | G72: =G69+G68+G71 -> 602.60821 | H72: =H69+H68+H71 -> 621.14702 | I72: =I69+I68+I71 -> 636.8593
A73: Crecimiento en moneda local | B73: C | E73: =E72/D72-1 -> 0.073755125 | F73: =F72/E72-1 -> 0.087293147 | G73: =G72/F72-1 -> 0.053148791 | H73: =H72/G72-1 -> 0.030764283 | I73: =I72/H72-1 -> 0.025295589
A74: Colombia (MM COP)
A75: Ocupación Colombia | B75: R / S | D75: 0.975 | E75: 0.975 | F75: 0.975 | G75: 0.975 | H75: 0.975 | I75: 0.975 | J75: 2026 = 2T26 [R]; se mantiene [S]
A76: Crecimiento real same-store (sin parking) | B76: S | E76: 0.025 | F76: 0.023 | G76: 0.022 | H76: 0.021 | I76: 0.021 | J76: [S] hacia 2,1%, punto medio Nota 11 (0,8%–3,4%)
A77: Parking / ingresos 2026 | B77: R | D77: 0.09 | J77: Release 2T26, contribución parking UDM por país
A78: Parking | B78: C | D78: =G32*D77 -> 25701.575 | E78: =D78*(1+E8)*(1+E53) -> 29527.511 | F78: =E78*(1+F8)*(1+F53) -> 32582.427 | G78: =F78*(1+G8)*(1+G53) -> 35071.725 | H78: =G78*(1+H8)*(1+H53) -> 37207.593 | I78: =H78*(1+I8)*(1+I53) -> 39090.297
A79: Arriendo y otros, mismo GLA | B79: C | D79: =G32-D78 -> 259871.48 | E79: =D79*(1+E8)*(1+E76)*E75/D75 -> 280752.15 | F79: =E79*(1+F8)*(1+F76)*F75/E75 -> 298985.04 | G79: =F79*(1+G8)*(1+G76)*G75/F75 -> 316257.4 | H79: =G79*(1+H8)*(1+H76)*H75/G75 -> 332585.77 | I79: =H79*(1+I8)*(1+I76)*I75/H75 -> 349757.17
A80: Ingreso anual por m² de GLA base (local) | B80: C | D80: =(D79+D78)/$D$48*1000000 -> 1017164.7 | E80: =(E79+E78)/$D$48*1000000 -> 1105165.6 | F80: =(F79+F78)/$D$48*1000000 -> 1180989.3 | G80: =(G79+G78)/$D$48*1000000 -> 1251377.1 | H80: =(H79+H78)/$D$48*1000000 -> 1317143.7 | I80: =(I79+I78)/$D$48*1000000 -> 1385011.3 | J80: Unidades locales por m² (CLP, PEN, COP). Se aplica al GLA nuevo
A81: Ingresos Colombia (MM COP) | B81: C | D81: =G32 -> 285573.05 | E81: =E79+E78 -> 310279.66 | F81: =F79+F78 -> 331567.46 | G81: =G79+G78 -> 351329.13 | H81: =H79+H78 -> 369793.36 | I81: =I79+I78 -> 388847.47
A82: Crecimiento en moneda local | B82: C | E82: =E81/D81-1 -> 0.0865159 | F82: =F81/E81-1 -> 0.068608439 | G82: =G81/F81-1 -> 0.05960073 | H82: =H81/G81-1 -> 0.052555386 | I82: =I81/H81-1 -> 0.051526364
A83: Gran Plaza (escenario, fuera del caso base)
A84: Incluir Gran Plaza (1 = sí) | B84: S | D84: 0 | J84: Interruptor
A85: Año de cierre (aporta medio año) | B85: S | D85: 2027 | J85: [S] fecha de cierre no informada; verificar hecho esencial CMF
A86: Valor empresa (MM COP) | B86: R | D86: 1178000 | J86: Release 2T26, carta y lámina "Adquisición Gran Plaza"
A87: Cap rate de la transacción (sobre NOI UDM) | B87: R | D87: 0.094 | J87: Ídem
A88: Margen NOI/ingresos supuesto | B88: S | D88: 0.751 | J88: [S] = margen EBITDA UDM de Colombia (release 2T26)
A89: Ingresos Gran Plaza (MM COP) | B89: C | E89: =$D$84*IF(2027<$D$85,0,IF(2027=$D$85,0.5,1))*$D$86*$D$87/$D$88*(1+E8)^(2027-2026) -> 0 | F89: =$D$84*IF(2028<$D$85,0,IF(2028=$D$85,0.5,1))*$D$86*$D$87/$D$88*(1+F8)^(2028-2026) -> 0 | G89: =$D$84*IF(2029<$D$85,0,IF(2029=$D$85,0.5,1))*$D$86*$D$87/$D$88*(1+G8)^(2029-2026) -> 0 | H89: =$D$84*IF(2030<$D$85,0,IF(2030=$D$85,0.5,1))*$D$86*$D$87/$D$88*(1+H8)^(2030-2026) -> 0 | I89: =$D$84*IF(2031<$D$85,0,IF(2031=$D$85,0.5,1))*$D$86*$D$87/$D$88*(1+I8)^(2031-2026) -> 0 | J89: NOI implícito = VE × cap rate (≈110.700 MM COP), indexado a IPC Colombia
A90: Consolidado (MM CLP)
A91: Chile | B91: C | C91: =Inputs!C36 -> 469964 | D91: =G33 -> 498415.42 | E91: =E62 -> 533900.64 | F91: =F62 -> 577390.08 | G91: =G62 -> 619649.01 | H91: =H62 -> 647862.92 | I91: =I62 -> 672611.39
A92: Perú | B92: C | C92: =Inputs!C40 -> 121320 | D92: =G34 -> 131348.07 | E92: =E72*E15 -> 145169.36 | F92: =F72*F15 -> 159839.6 | G92: =G72*G15 -> 171607 | H92: =H72*H15 -> 178620.55 | I92: =I72*I15 -> 184934.34
A93: Colombia (incl. Gran Plaza si se activa) | B93: C | C93: =Inputs!C38 -> 62627 | D93: =G35 -> 75222.423 | E93: =(E81+E89)*E16 -> 88109.424 | F93: =(F81+F89)*F16 -> 89432.141 | G93: =(G81+G89)*G16 -> 92226.442 | H93: =(H81+H89)*H16 -> 96838.393 | I93: =(I81+I89)*I16 -> 101828.12
A94: Eliminaciones / ajuste a consolidado (% de la suma) | B94: C / S | D94: -0.0014 | E94: 0 | F94: 0 | G94: 0 | H94: 0 | I94: 0 | J94: 2026 = 1S26 (339.530 consolidado vs 340.019 suma de segmentos) [C]; luego 0 [S]
A95: Ingresos ordinarios consolidados | B95: C | C95: =Inputs!C6 -> 653911 | D95: =(D91+D92+D93)*(1+D94) -> 703998.94 | E95: =(E91+E92+E93)*(1+E94) -> 767179.42 | F95: =(F91+F92+F93)*(1+F94) -> 826661.82 | G95: =(G91+G92+G93)*(1+G94) -> 883482.45 | H95: =(H91+H92+H93)*(1+H94) -> 923321.86 | I95: =(I91+I92+I93)*(1+I94) -> 959373.85
A96: Crecimiento ingresos consolidados (CLP) | B96: C | D96: =D95/C95-1 -> 0.07659748 | E96: =E95/D95-1 -> 0.089745147 | F96: =F95/E95-1 -> 0.077533882 | G96: =G95/F95-1 -> 0.068735037 | H96: =H95/G95-1 -> 0.045093604 | I96: =I95/H95-1 -> 0.039045966
A97: Consenso ingresos (Bloomberg DES, MM CLP) | B97: P | D97: 699790 | E97: 770370 | J97: Bloomberg DES 27-09-2026 (699,79 y 770,37 mil MM CLP)
A98: Modelo vs consenso | B98: C | D98: =D95/D97-1 -> 0.0060145687 | E98: =E95/E97-1 -> -0.0041416162
A100: E. EBITDA | B100: Tag | C100: 2025A | D100: 2026E | E100: 2027E | F100: 2028E | G100: 2029E | H100: 2030E | I100: 2031E | J100: Fuente / supuesto
A101: Margen EBITDA Chile | B101: S | D101: 0.8 | E101: 0.8 | F101: 0.8 | G101: 0.8 | H101: 0.8 | I101: 0.8 | J101: [S] ~promedio 2024 (79,5%) y UDM 2T26 (80,4%); no se extrapola el máximo
A102: Margen EBITDA Perú | B102: S | D102: 0.82 | E102: 0.82 | F102: 0.82 | G102: 0.82 | H102: 0.82 | I102: 0.82 | J102: [S] UDM 2T26 83,5%; 2024 pro forma 78,9% (antes de integrar Open Plaza)
A103: Margen EBITDA Colombia | B103: S | D103: 0.74 | E103: 0.74 | F103: 0.74 | G103: 0.74 | H103: 0.74 | I103: 0.74 | J103: [S] UDM 2T26 75,1%; 2024 67,7% (rampa de Cali)
A104: EBITDA (definición compañía) | B104: C | C104: =Inputs!C10 -> 526228 | D104: =(D91*D101+D92*D102+D93*D103)*(1+D94) -> 561315.41 | E104: =(E91*E101+E92*E102+E93*E103)*(1+E94) -> 611360.36 | F104: =(F91*F101+F92*F102+F93*F103)*(1+F94) -> 659160.32 | G104: =(G91*G101+G92*G102+G93*G103)*(1+G94) -> 704684.52 | H104: =(H91*H101+H92*H102+H93*H103)*(1+H94) -> 736419.6 | I104: =(I91*I101+I92*I102+I93*I103)*(1+I94) -> 765088.08 | J104: Gran Plaza, si se activa, entra con el margen de Colombia (la diferencia con el NOI es menor)
A105: Margen EBITDA consolidado | B105: C | C105: =C104/C95 -> 0.80473948 | D105: =D104/D95 -> 0.79732422 | E105: =E104/E95 -> 0.79689358 | F105: =F104/F95 -> 0.79737603 | G105: =G104/G95 -> 0.79762141 | H105: =H104/H95 -> 0.79757626 | I105: =I104/I95 -> 0.7974869
...

Sheet Forecast_link
A1: Forecast_link — insumos proyectados 2026E–2031E (vinculados a la hoja Forecast)
A2: Vinculado a la hoja Forecast (motor operativo). Si valuation mantiene un modelo propio, reemplazar estos vínculos por sus cifras: deben ser idénticas a las del DCF/NAV.
A4: Línea (MM CLP) | B4: 2026E | C4: 2027E | D4: 2028E | E4: 2029E | F4: 2030E | G4: 2031E
A5: Ingresos ordinarios | B5: =Forecast!D95 -> 703998.94 | C5: =Forecast!E95 -> 767179.42 | D5: =Forecast!F95 -> 826661.82 | E5: =Forecast!G95 -> 883482.45 | F5: =Forecast!H95 -> 923321.86 | G5: =Forecast!I95 -> 959373.85
A6: EBITDA (definición compañía) | B6: =Forecast!D104 -> 561315.41 | C6: =Forecast!E104 -> 611360.36 | D6: =Forecast!F104 -> 659160.32 | E6: =Forecast!G104 -> 704684.52 | F6: =Forecast!H104 -> 736419.6 | G6: =Forecast!I104 -> 765088.08
A7: FFO atribuible | B7: =Forecast!D114 -> 428521.01 | C7: =Forecast!E114 -> 457343.87 | D7: =Forecast!F114 -> 479815.31 | E7: =Forecast!G114 -> 500558.62 | F7: =Forecast!H114 -> 509123.66 | G7: =Forecast!I114 -> 535305.59
A8: Utilidad líquida distribuible (normalizada) | B8: =Forecast!D119 -> 380038.82 | C8: =Forecast!E119 -> 415490.8 | D8: =Forecast!F119 -> 440070.47 | E8: =Forecast!G119 -> 462674.09 | F8: =Forecast!H119 -> 477016.6 | G8: =Forecast!I119 -> 509052.03
A9: Revalorización de PI atribuible, neta de impuesto diferido | B9: =Forecast!D150 -> 259116.35 | C9: =Forecast!E150 -> 178038.57 | D9: =Forecast!F150 -> 174018.45 | E9: =Forecast!G150 -> 176308.3 | F9: =Forecast!H150 -> 179885.12 | G9: =Forecast!I150 -> 185999.38
A10: Total activos al cierre | B10: =Forecast!D153 -> 8230928.7 | C10: =Forecast!E153 -> 8767723.9 | D10: =Forecast!F153 -> 9209694 | E10: =Forecast!G153 -> 9502564.1 | F10: =Forecast!H153 -> 9802581.1 | G10: =Forecast!I153 -> 10113052
A11: Otros resultados integrales atribuibles (conversión, coberturas) | B11: 0 | C11: 0 | D11: 0 | E11: 0 | F11: 0 | G11: 0
A13: Regla de proyección de la revalorización [S, a decidir con valuation]: con tasas de descuento constantes, la PI crece por indexación + capex; la revalorización = PI inicial × inflación de largo plazo, neta de impuesto diferido. Cualquier compresión de tasas debe ser explícita y consistente con el escenario del DCF.
A14: Patrimonio proyectado: E1 lo calcula por roll-forward = patrimonio previo + utilidad reportada − payout × utilidad distribuible + ORI.

Sheet FCFF_DCF
A1: FCFF y DCF — interfaz forecast (supuestos de financial analysis) ↔ valuation (WACC, g, cap rate de salida)
A2: Fecha de valorización: 30-06-2026 (coincide con la última DFN y minoritarios reportados). Para llevar a la fecha de corte (D1), capitalizar el patrimonio al costo del patrimonio y restar dividendos pagados en el intermedio.
A3: Amarillo = inputs que entrega valuation. Flujos en CLP nominales → la WACC debe ser nominal en CLP. Celdas vacías dejan el bloque de resultado en blanco; la grilla de sensibilidad funciona sin inputs.
A5: A. Inputs de valuation
A6: WACC nominal CLP | J6: Valuation [S]. Debe ser nominal en CLP (BCP + ERP + riesgo país ponderado), consistente con flujos en CLP
A7: Crecimiento terminal nominal (g) | J7: Valuation [S]. Referencia: inflación LP Chile 3,0% + crecimiento real 0%–1% (Nota 11)
A8: Retorno sobre nueva inversión en perpetuidad (RONIC) | J8: [S] Si se deja vacío = WACC (el crecimiento terminal no crea valor; supuesto neutral)
A9: Cap rate de salida (sobre EBITDA 2032E) | J9: Valuation [S]. Referencias: Gran Plaza 9,4% (2026); WACC real Nota 11 Chile ~5,5%
A10: RONIC usado | C10: =IF(C8="",C6,C8) -> 0
A11: DFN 30-06-2026 (definición compañía) | C11: =Inputs!C64 -> 1285740 | J11: [R] Release 2T26 / Análisis Razonado 1S26
A12: Participaciones no controladoras (libro) 30-06-2026 | C12: 50841 | J12: [R] Release 2T26, estado de situación. Libro como proxy del valor de mercado [S]
A13: Acciones (MM) | C13: =Inputs!C125 -> 2190
A14: Precio de referencia (CLP) | C14: 3642 | J14: [R] Bloomberg DES, impresión 27-09-2026. Reemplazar por el precio de la fecha de corte (D1)
A15: EBITDA 1S26 real (para aislar el 2S26) | C15: 270573 | J15: [R] Release 2T26
A17: B. Flujo de caja libre de la firma (MM CLP) | C17: 2S26E | D17: 2027E | E17: 2028E | F17: 2029E | G17: 2030E | H17: 2031E | J17: Fuente / supuesto
A18: EBITDA | C18: =Forecast!D104-$C$15 -> 290742.41 | D18: =Forecast!E104 -> 611360.36 | E18: =Forecast!F104 -> 659160.32 | F18: =Forecast!G104 -> 704684.52 | G18: =Forecast!H104 -> 736419.6 | H18: =Forecast!I104 -> 765088.08 | J18: 2S26E = EBITDA 2026E (Forecast) − 1S26 real
A19: Impuesto operativo en caja (tasa del forecast × EBITDA) | C19: =-Forecast!D110*C18 -> -48844.724 | D19: =-Forecast!E110*D18 -> -116158.47 | E19: =-Forecast!F110*E18 -> -141719.47 | F19: =-Forecast!G110*F18 -> -169124.28 | G19: =-Forecast!H110*G18 -> -198833.29 | H19: =-Forecast!I110*H18 -> -206573.78 | J19: Misma tasa de impuesto en caja del forecast, aplicada sin escudo de intereses (flujo desapalancado) [S]
A20: Capex total | C20: =-(Forecast!D137+Forecast!D139) -> -149905.97 | D20: =-Forecast!E142 -> -290119.34 | E20: =-Forecast!F142 -> -200864.13 | F20: =-Forecast!G142 -> -48591.535 | G20: =-Forecast!H142 -> -50782.702 | H20: =-Forecast!I142 -> -52765.562 | J20: 2S26E = capex de proyectos + mantención del 2S26 (Forecast). Sin greenfield ni capex de crecimiento post-2028 (ver anexo)
A21: Variación de capital de trabajo | C21: 0 | D21: 0 | E21: 0 | F21: 0 | G21: 0 | H21: 0 | J21: Δ capital de trabajo = 0 [S], declarado en el anexo
A22: FCFF | C22: =SUM(C18:C21) -> 91991.708 | D22: =SUM(D18:D21) -> 205082.55 | E22: =SUM(E18:E21) -> 316576.72 | F22: =SUM(F18:F21) -> 486968.7 | G22: =SUM(G18:G21) -> 486803.6 | H22: =SUM(H18:H21) -> 505748.74
A23: Período de descuento (años, mitad de período) | C23: 0.25 | D23: 1 | E23: 2 | F23: 3 | G23: 4 | H23: 5 | J23: Mitad de período: 2S26 a 0,25 años; luego mitad de cada año desde el 30-06-2026
A24: Factor de descuento | C24: =IF($C$6="","",1/(1+$C$6)^C23) | D24: =IF($C$6="","",1/(1+$C$6)^D23) | E24: =IF($C$6="","",1/(1+$C$6)^E23) | F24: =IF($C$6="","",1/(1+$C$6)^F23) | G24: =IF($C$6="","",1/(1+$C$6)^G23) | H24: =IF($C$6="","",1/(1+$C$6)^H23)
A25: Valor presente del FCFF | C25: =IF($C$6="","",C22*C24) | D25: =IF($C$6="","",D22*D24) | E25: =IF($C$6="","",E22*E24) | F25: =IF($C$6="","",F22*F24) | G25: =IF($C$6="","",G22*G24) | H25: =IF($C$6="","",H22*H24)
A27: C. Valor terminal y valor por acción | C27: Gordon | D27: Cap rate salida
A28: NOPAT 2032E = EBITDA 2031E × (1+g) × (1 − tasa 2031E) | C28: =IF($C$7="","",H18*(1+$C$7)*(1-Forecast!I110)) | J28: EBITDA ≈ EBIT (D&A 2025: 3.610) → NOPAT ≈ EBITDA × (1 − t). Tasa terminal = 27%
A29: Tasa de reinversión terminal = (g − IPC LP Chile) / RONIC | C29: =IF(OR($C$6="",$C$7=""),"",MAX(0,$C$7-Forecast!$I$6)/$C$10) | J29: Value driver: VT = NOPAT × (1 − reinversión) / (WACC − g). Solo el crecimiento REAL exige reinversión: la parte de inflación llega por la indexación de los contratos (UF/IPC) sin capex. Corrige que el forecast no tenga reinversión post-2028
A30: Valor terminal al 31-12-2031 | C30: =IF(OR($C$6="",$C$7=""),"",C28*(1-C29)/($C$6-$C$7)) | D30: =IF(OR($C$7="",$C$9=""),"",H18*(1+$C$7)/$C$9) | J30: Gordon: perpetuidad con reinversión explícita. Cap rate: EBITDA 2032E / cap rate (EBITDA incluye gastos corporativos → conservador vs NOI)
A31: Valor presente del valor terminal (5,5 años) | C31: =IF(OR($C$6="",C30=""),"",C30/(1+$C$6)^5.5) | D31: =IF(OR($C$6="",D30=""),"",D30/(1+$C$6)^5.5)
A32: Valor presente FCFF explícito | C32: =IF($C$6="","",SUM($C$25:$H$25)) | D32: =IF($C$6="","",SUM($C$25:$H$25))
A33: Valor empresa | C33: =IF(C31="","",C31+C32) | D33: =IF(D31="","",D31+D32)
A34: − DFN | C34: =IF(C33="","",-$C$11) | D34: =IF(D33="","",-$C$11)
A35: − Minoritarios | C35: =IF(C33="","",-$C$12) | D35: =IF(D33="","",-$C$12)
A36: Valor del patrimonio | C36: =IF(C33="","",SUM(C33:C35)) | D36: =IF(D33="","",SUM(D33:D35))
A37: Valor por acción (CLP) | C37: =IF(C36="","",C36/$C$13) | D37: =IF(D36="","",D36/$C$13)
A38: Upside vs precio de referencia | C38: =IF(C37="","",C37/$C$14-1) | D38: =IF(D37="","",D37/$C$14-1)
A40: Chequeo: valor terminal / valor empresa | C40: =IF(C33="","",C31/C33) | D40: =IF(D33="","",D31/D33)
A41: Chequeo: EV / EBITDA 2027E implícito | C41: =IF(C33="","",C33/D18) | D41: =IF(D33="","",D33/D18)
A42: Chequeo: cap rate implícito del valor terminal (EBITDA 2032E / VT) | C42: =IF(C30="","",H18*(1+$C$7)/C30)
A43: Chequeo: WACC real implícita = (1+WACC)/(1+IPC LP Chile) − 1 | C43: =IF($C$6="","",(1+$C$6)/(1+Forecast!I6)-1) | J43: Debe estar cerca de la WACC real de la Nota 11 si valuation usa supuestos de mercado similares a la compañía; una diferencia grande debe explicarse
A44: Referencia: WACC real Nota 11 Chile jun-26 (punto medio) | C44: =E7_WACC!G24 -> 0.0555
A47: D. Sensibilidad: valor por acción (CLP), WACC nominal vs g (RONIC = WACC; reinversión solo sobre g real)
B48: WACC \ g | C48: 0.025 | D48: 0.03 | E48: 0.035 | F48: 0.04
B49: 0.08 | C49: =(SUMPRODUCT($C$22:$H$22,1/(1+$B49)^$C$23:$H$23)+H$18*(1+C$48)*(1-Forecast!$I$110)*(1-MAX(0,C$48-Forecast!$I$6)/$B49)/($B49-C$48)/(1+$B49)^5.5-$C$11-$C$12)/$C$13 -> 3251.1901 | D49: =(SUMPRODUCT($C$22:$H$22,1/(1+$B49)^$C$23:$H$23)+H$18*(1+D$48)*(1-Forecast!$I$110)*(1-MAX(0,D$48-Forecast!$I$6)/$B49)/($B49-D$48)/(1+$B49)^5.5-$C$11-$C$12)/$C$13 -> 3579.1498 | E49: =(SUMPRODUCT($C$22:$H$22,1/(1+$B49)^$C$23:$H$23)+H$18*(1+E$48)*(1-Forecast!$I$110)*(1-MAX(0,E$48-Forecast!$I$6)/$B49)/($B49-E$48)/(1+$B49)^5.5-$C$11-$C$12)/$C$13 -> 3739.9033 | F49: =(SUMPRODUCT($C$22:$H$22,1/(1+$B49)^$C$23:$H$23)+H$18*(1+F$48)*(1-Forecast!$I$110)*(1-MAX(0,F$48-Forecast!$I$6)/$B49)/($B49-F$48)/(1+$B49)^5.5-$C$11-$C$12)/$C$13 -> 3938.2354
B50: 0.085 | C50: =(SUMPRODUCT($C$22:$H$22,1/(1+$B50)^$C$23:$H$23)+H$18*(1+C$48)*(1-Forecast!$I$110)*(1-MAX(0,C$48-Forecast!$I$6)/$B50)/($B50-C$48)/(1+$B50)^5.5-$C$11-$C$12)/$C$13 -> 2909.6429 | D50: =(SUMPRODUCT($C$22:$H$22,1/(1+$B50)^$C$23:$H$23)+H$18*(1+D$48)*(1-Forecast!$I$110)*(1-MAX(0,D$48-Forecast!$I$6)/$B50)/($B50-D$48)/(1+$B50)^5.5-$C$11-$C$12)/$C$13 -> 3177.3208 | E50: =(SUMPRODUCT($C$22:$H$22,1/(1+$B50)^$C$23:$H$23)+H$18*(1+E$48)*(1-Forecast!$I$110)*(1-MAX(0,E$48-Forecast!$I$6)/$B50)/($B50-E$48)/(1+$B50)^5.5-$C$11-$C$12)/$C$13 -> 3300.2683 | F50: =(SUMPRODUCT($C$22:$H$22,1/(1+$B50)^$C$23:$H$23)+H$18*(1+F$48)*(1-Forecast!$I$110)*(1-MAX(0,F$48-Forecast!$I$6)/$B50)/($B50-F$48)/(1+$B50)^5.5-$C$11-$C$12)/$C$13 -> 3448.409
B51: 0.09 | C51: =(SUMPRODUCT($C$22:$H$22,1/(1+$B51)^$C$23:$H$23)+H$18*(1+C$48)*(1-Forecast!$I$110)*(1-MAX(0,C$48-Forecast!$I$6)/$B51)/($B51-C$48)/(1+$B51)^5.5-$C$11-$C$12)/$C$13 -> 2621.1911 | D51: =(SUMPRODUCT($C$22:$H$22,1/(1+$B51)^$C$23:$H$23)+H$18*(1+D$48)*(1-Forecast!$I$110)*(1-MAX(0,D$48-Forecast!$I$6)/$B51)/($B51-D$48)/(1+$B51)^5.5-$C$11-$C$12)/$C$13 -> 2843.0497 | E51: =(SUMPRODUCT($C$22:$H$22,1/(1+$B51)^$C$23:$H$23)+H$18*(1+E$48)*(1-Forecast!$I$110)*(1-MAX(0,E$48-Forecast!$I$6)/$B51)/($B51-E$48)/(1+$B51)^5.5-$C$11-$C$12)/$C$13 -> 2939.2686 | F51: =(SUMPRODUCT($C$22:$H$22,1/(1+$B51)^$C$23:$H$23)+H$18*(1+F$48)*(1-Forecast!$I$110)*(1-MAX(0,F$48-Forecast!$I$6)/$B51)/($B51-F$48)/(1+$B51)^5.5-$C$11-$C$12)/$C$13 -> 3052.9673
B52: 0.095 | C52: =(SUMPRODUCT($C$22:$H$22,1/(1+$B52)^$C$23:$H$23)+H$18*(1+C$48)*(1-Forecast!$I$110)*(1-MAX(0,C$48-Forecast!$I$6)/$B52)/($B52-C$48)/(1+$B52)^5.5-$C$11-$C$12)/$C$13 -> 2374.4385 | D52: =(SUMPRODUCT($C$22:$H$22,1/(1+$B52)^$C$23:$H$23)+H$18*(1+D$48)*(1-Forecast!$I$110)*(1-MAX(0,D$48-Forecast!$I$6)/$B52)/($B52-D$48)/(1+$B52)^5.5-$C$11-$C$12)/$C$13 -> 2560.7266 | E52: =(SUMPRODUCT($C$22:$H$22,1/(1+$B52)^$C$23:$H$23)+H$18*(1+E$48)*(1-Forecast!$I$110)*(1-MAX(0,E$48-Forecast!$I$6)/$B52)/($B52-E$48)/(1+$B52)^5.5-$C$11-$C$12)/$C$13 -> 2637.5072 | F52: =(SUMPRODUCT($C$22:$H$22,1/(1+$B52)^$C$23:$H$23)+H$18*(1+F$48)*(1-Forecast!$I$110)*(1-MAX(0,F$48-Forecast!$I$6)/$B52)/($B52-F$48)/(1+$B52)^5.5-$C$11-$C$12)/$C$13 -> 2726.7665
B53: 0.1 | C53: =(SUMPRODUCT($C$22:$H$22,1/(1+$B53)^$C$23:$H$23)+H$18*(1+C$48)*(1-Forecast!$I$110)*(1-MAX(0,C$48-Forecast!$I$6)/$B53)/($B53-C$48)/(1+$B53)^5.5-$C$11-$C$12)/$C$13 -> 2161.0289 | D53: =(SUMPRODUCT($C$22:$H$22,1/(1+$B53)^$C$23:$H$23)+H$18*(1+D$48)*(1-Forecast!$I$110)*(1-MAX(0,D$48-Forecast!$I$6)/$B53)/($B53-D$48)/(1+$B53)^5.5-$C$11-$C$12)/$C$13 -> 2319.2024 | E53: =(SUMPRODUCT($C$22:$H$22,1/(1+$B53)^$C$23:$H$23)+H$18*(1+E$48)*(1-Forecast!$I$110)*(1-MAX(0,E$48-Forecast!$I$6)/$B53)/($B53-E$48)/(1+$B53)^5.5-$C$11-$C$12)/$C$13 -> 2381.5039 | F53: =(SUMPRODUCT($C$22:$H$22,1/(1+$B53)^$C$23:$H$23)+H$18*(1+F$48)*(1-Forecast!$I$110)*(1-MAX(0,F$48-Forecast!$I$6)/$B53)/($B53-F$48)/(1+$B53)^5.5-$C$11-$C$12)/$C$13 -> 2452.9309
A56: E. Sensibilidad: valor por acción (CLP), WACC nominal vs cap rate de salida (g del EBITDA 2032E = 3%)
B57: WACC \ cap rate | C57: 0.075 | D57: 0.08 | E57: 0.085 | F57: 0.09 | G57: 0.095
B58: 0.08 | C58: =(SUMPRODUCT($C$22:$H$22,1/(1+$B58)^$C$23:$H$23)+H$18*(1+0.03)/C$57/(1+$B58)^5.5-$C$11-$C$12)/$C$13 -> 3280.6554 | D58: =(SUMPRODUCT($C$22:$H$22,1/(1+$B58)^$C$23:$H$23)+H$18*(1+0.03)/D$57/(1+$B58)^5.5-$C$11-$C$12)/$C$13 -> 3084.2775 | E58: =(SUMPRODUCT($C$22:$H$22,1/(1+$B58)^$C$23:$H$23)+H$18*(1+0.03)/E$57/(1+$B58)^5.5-$C$11-$C$12)/$C$13 -> 2911.0029 | F58: =(SUMPRODUCT($C$22:$H$22,1/(1+$B58)^$C$23:$H$23)+H$18*(1+0.03)/F$57/(1+$B58)^5.5-$C$11-$C$12)/$C$13 -> 2756.981 | G58: =(SUMPRODUCT($C$22:$H$22,1/(1+$B58)^$C$23:$H$23)+H$18*(1+0.03)/G$57/(1+$B58)^5.5-$C$11-$C$12)/$C$13 -> 2619.1719
B59: 0.085 | C59: =(SUMPRODUCT($C$22:$H$22,1/(1+$B59)^$C$23:$H$23)+H$18*(1+0.03)/C$57/(1+$B59)^5.5-$C$11-$C$12)/$C$13 -> 3191.2446 | D59: =(SUMPRODUCT($C$22:$H$22,1/(1+$B59)^$C$23:$H$23)+H$18*(1+0.03)/D$57/(1+$B59)^5.5-$C$11-$C$12)/$C$13 -> 2999.7926 | E59: =(SUMPRODUCT($C$22:$H$22,1/(1+$B59)^$C$23:$H$23)+H$18*(1+0.03)/E$57/(1+$B59)^5.5-$C$11-$C$12)/$C$13 -> 2830.8645 | F59: =(SUMPRODUCT($C$22:$H$22,1/(1+$B59)^$C$23:$H$23)+H$18*(1+0.03)/F$57/(1+$B59)^5.5-$C$11-$C$12)/$C$13 -> 2680.7061 | G59: =(SUMPRODUCT($C$22:$H$22,1/(1+$B59)^$C$23:$H$23)+H$18*(1+0.03)/G$57/(1+$B59)^5.5-$C$11-$C$12)/$C$13 -> 2546.3539
B60: 0.09 | C60: =(SUMPRODUCT($C$22:$H$22,1/(1+$B60)^$C$23:$H$23)+H$18*(1+0.03)/C$57/(1+$B60)^5.5-$C$11-$C$12)/$C$13 -> 3104.3895 | D60: =(SUMPRODUCT($C$22:$H$22,1/(1+$B60)^$C$23:$H$23)+H$18*(1+0.03)/D$57/(1+$B60)^5.5-$C$11-$C$12)/$C$13 -> 2917.7182 | E60: =(SUMPRODUCT($C$22:$H$22,1/(1+$B60)^$C$23:$H$23)+H$18*(1+0.03)/E$57/(1+$B60)^5.5-$C$11-$C$12)/$C$13 -> 2753.0082 | F60: =(SUMPRODUCT($C$22:$H$22,1/(1+$B60)^$C$23:$H$23)+H$18*(1+0.03)/F$57/(1+$B60)^5.5-$C$11-$C$12)/$C$13 -> 2606.5994 | G60: =(SUMPRODUCT($C$22:$H$22,1/(1+$B60)^$C$23:$H$23)+H$18*(1+0.03)/G$57/(1+$B60)^5.5-$C$11-$C$12)/$C$13 -> 2475.602
B61: 0.095 | C61: =(SUMPRODUCT($C$22:$H$22,1/(1+$B61)^$C$23:$H$23)+H$18*(1+0.03)/C$57/(1+$B61)^5.5-$C$11-$C$12)/$C$13 -> 3020.0051 | D61: =(SUMPRODUCT($C$22:$H$22,1/(1+$B61)^$C$23:$H$23)+H$18*(1+0.03)/D$57/(1+$B61)^5.5-$C$11-$C$12)/$C$13 -> 2837.974 | E61: =(SUMPRODUCT($C$22:$H$22,1/(1+$B61)^$C$23:$H$23)+H$18*(1+0.03)/E$57/(1+$B61)^5.5-$C$11-$C$12)/$C$13 -> 2677.3583 | F61: =(SUMPRODUCT($C$22:$H$22,1/(1+$B61)^$C$23:$H$23)+H$18*(1+0.03)/F$57/(1+$B61)^5.5-$C$11-$C$12)/$C$13 -> 2534.5888 | G61: =(SUMPRODUCT($C$22:$H$22,1/(1+$B61)^$C$23:$H$23)+H$18*(1+0.03)/G$57/(1+$B61)^5.5-$C$11-$C$12)/$C$13 -> 2406.8477
B62: 0.1 | C62: =(SUMPRODUCT($C$22:$H$22,1/(1+$B62)^$C$23:$H$23)+H$18*(1+0.03)/C$57/(1+$B62)^5.5-$C$11-$C$12)/$C$13 -> 2938.0095 | D62: =(SUMPRODUCT($C$22:$H$22,1/(1+$B62)^$C$23:$H$23)+H$18*(1+0.03)/D$57/(1+$B62)^5.5-$C$11-$C$12)/$C$13 -> 2760.4829 | E62: =(SUMPRODUCT($C$22:$H$22,1/(1+$B62)^$C$23:$H$23)+H$18*(1+0.03)/E$57/(1+$B62)^5.5-$C$11-$C$12)/$C$13 -> 2603.8417 | F62: =(SUMPRODUCT($C$22:$H$22,1/(1+$B62)^$C$23:$H$23)+H$18*(1+0.03)/F$57/(1+$B62)^5.5-$C$11-$C$12)/$C$13 -> 2464.6051 | G62: =(SUMPRODUCT($C$22:$H$22,1/(1+$B62)^$C$23:$H$23)+H$18*(1+0.03)/G$57/(1+$B62)^5.5-$C$11-$C$12)/$C$13 -> 2340.0251
A64: Grillas ilustrativas: no son el precio objetivo. El precio objetivo se calcula con la WACC y g de valuation en el bloque C.

Sheet DCF_Valuation
B1: DCF de FCFF — Mallplaza (Plaza S.A.) · CLP nominales · fecha de valorización 30-06-2026 (2T26)
B2: Leyenda: azul con fondo celeste = dato observado [R] · negro = calculado [C] · fondo amarillo = supuesto [S] · fondo verde = proyección [P] (viene de la hoja Forecast) · verde = vínculo a otra hoja
B3: Unidad: MM CLP salvo indicación. Fuentes: EEFF dic-23 (reformulado), releases 4T24 y 2T26, Inputs, Forecast; WACC del modelo de valuation (Mall_plaza_Valuacion.xlsm, hoja FFCF).
B5: Ítem | C5: Tipo | D5: 2022A | E5: 2023A | F5: 2024A | G5: 2025A | H5: LTM 2T26 | I5: 1S26A | J5: 2S26E | K5: 2027E | L5: 2028E | M5: 2029E | N5: 2030E | O5: 2031E | P5: Fuente / cálculo
B7: II–IV. Ingresos y construcción del EBITDA ajustado
A8: 1 | B8: Ingresos ordinarios | C8: R / P | D8: 370899 | E8: =Inputs!C4 -> 419904 | F8: =Inputs!C5 -> 494605 | G8: =Inputs!C6 -> 653911 | H8: =Inputs!C82 -> 677333 | I8: =Inputs!C8 -> 339530 | J8: =Forecast!D95-I8 -> 364468.94 | K8: =Forecast!E95 -> 767179.42 | L8: =Forecast!F95 -> 826661.82 | M8: =Forecast!G95 -> 883482.45 | N8: =Forecast!H95 -> 923321.86 | O8: =Forecast!I95 -> 959373.85 | P8: 2022 reformulado (EEFF dic-23, EERR). 2023–1S26: EEFF y releases (Inputs). 2S26E = 2026E (Forecast) − 1S26 real
A9: 2 | B9: Crecimiento de ingresos | C9: C | E9: =E8/D8-1 -> 0.13212492 | F9: =F8/E8-1 -> 0.17790019 | G9: =G8/F8-1 -> 0.32208732 | K9: =K8/(I8+J8)-1 -> 0.089745147 | L9: =L8/K8-1 -> 0.077533882 | M9: =M8/L8-1 -> 0.068735037 | N9: =N8/M8-1 -> 0.045093604 | O9: =O8/N8-1 -> 0.039045966 | P9: 2024: incluye 1 mes de Perú; 2025: 12 meses (perímetro). 2027E vs 2026E completo
A10: 3a | B10: Resultado operacional (Ganancias de actividades operacionales) | C10: R / C | D10: 363621 | E10: 513768 | F10: =F15-F11+F13-F14 -> 535873 | G10: =G15-G11+G13-G14 -> 1968050 | H10: =G10-720093+I10 -> 1730612 | I10: 482655 | P10: 2022–2023: EERR EEFF dic-23 (reformulado). 1S26 y 1S25 (720.093): release 2T26. 2024–2025 reconstruido desde EBITDA, D&A y otros ingresos/gastos [C]
A11: 3b | B11: (+) Depreciación y amortización | C11: R / C / S | D11: =Inputs!C77-(324954-44420) -> 2165 | E11: 2154 | F11: 2112 | G11: =Inputs!C17 -> 3610 | H11: =G11-1837+I11 -> 4766 | I11: 2993 | J11: =$H$18*J8 -> 2564.5568 | K11: =$H$18*K8 -> 5398.1972 | L11: =$H$18*L8 -> 5816.7404 | M11: =$H$18*M8 -> 6216.5543 | N11: =$H$18*N8 -> 6496.8811 | O11: =$H$18*O8 -> 6750.5581 | P11: 2022 implícita (EBITDA − ganancia bruta + GAV). 2023–2024: release 4T24. 1S26: release 2T26 (1.382 + 1.611). Proyección: D&A/ingresos LTM [S]
A12: 3 | B12: EBITDA contable (incluye revalorización de PI) | C12: C | D12: =D10+D11 -> 365786 | E12: =E10+E11 -> 515922 | F12: =F10+F11 -> 537985 | G12: =G10+G11 -> 1971660 | H12: =H10+H11 -> 1735378 | I12: =I10+I11 -> 485648 | J12: =J15+J13-J14 -> 433146.13 | K12: =K15+K13-K14 -> 858036.25 | L12: =L15+L13-L14 -> 900266.25 | M12: =M15+M13-M14 -> 948963.08 | N12: =N15+N13-N14 -> 985653.91 | O12: =O15+O13-O14 -> 1022793.8 | P12: Resultado operacional + D&A. Es el "EBITDA" que entregan algunas bases de datos (trampa 1 del WP: campo EBITDA de Bloomberg)
A13: 4a | B13: (−) Otros ingresos por función (revalorización de PI a valor razonable) | C13: R / P | D13: 85361 | E13: 195562 | F13: 162507 | G13: =Inputs!C15 -> 1448943 | H13: =G13-471020+I13 -> 1194529 | I13: 216606 | J13: =Forecast!D148-I13 -> 142404.73 | K13: =Forecast!E148 -> 246675.89 | L13: =Forecast!F148 -> 241105.93 | M13: =Forecast!G148 -> 244278.56 | N13: =Forecast!H148 -> 249234.32 | O13: =Forecast!I148 -> 257705.75 | P13: Valor razonable: 2022 79.489, 2025 1.447.136 (Inputs); el resto son ingresos menores no recurrentes. 1S25: 471.020 (release 2T26). Proyección: regla de Forecast
A14: 4b | B14: (+) Otros gastos por función (no recurrentes) | C14: R / S | D14: 2274 | E14: 1825 | F14: 5159 | G14: =Inputs!C16 -> 3511 | H14: =G14-957+I14 -> 4086 | I14: 1532 | J14: 0 | K14: 0 | L14: 0 | M14: 0 | N14: 0 | O14: 0 | P14: Release 4T24 / 2T26; proyección 0 [S]
A15: 5 | B15: EBITDA ajustado (= EBITDA definición compañía) | C15: C / P | D15: =D12-D13+D14 -> 282699 | E15: =E12-E13+E14 -> 322185 | F15: =Inputs!C9 -> 380637 | G15: =Inputs!C10 -> 526228 | H15: =H12-H13+H14 -> 544935 | I15: =I12-I13+I14 -> 270574 | J15: =Forecast!D104-I15 -> 290741.41 | K15: =Forecast!E104 -> 611360.36 | L15: =Forecast!F104 -> 659160.32 | M15: =Forecast!G104 -> 704684.52 | N15: =Forecast!H104 -> 736419.6 | O15: =Forecast!I104 -> 765088.08 | P15: EBITDA que entra al DCF: excluye la revalorización (no caja). 2S26E = 2026E − 1S26
A16: 5b | B16: Control: EBITDA ajustado − EBITDA reportado por la compañía | C16: C | D16: =D15-Inputs!C77 -> 0 | E16: =E15-Inputs!C78 -> 0 | F16: =F12-F13+F14-Inputs!C9 -> 0 | G16: =G12-G13+G14-Inputs!C10 -> 0 | H16: =H15-Inputs!C79 -> 0 | I16: =I15-270573 -> 1 | P16: Debe ser 0 (±1 por redondeo): el ajuste reproduce exactamente el EBITDA que publica la compañía
A17: 5c | B17: Margen EBITDA ajustado | C17: C | D17: =D15/D8 -> 0.76219941 | E17: =E15/E8 -> 0.76728252 | F17: =F15/F8 -> 0.76957774 | G17: =G15/G8 -> 0.80473948 | H17: =H15/H8 -> 0.80453042 | I17: =I15/I8 -> 0.79690749 | J17: =J15/J8 -> 0.79771244 | K17: =K15/K8 -> 0.79689358 | ... O17: =O15/O8 -> 0.7974869
A18: 6 | B18: D&A / ingresos | C18: C | H18: =H11/H8 -> 0.0070364208 | P18: Se usa para proyectar D&A [S]
A19: 7 | B19: EBIT (EBITDA ajustado − D&A) | C19: C | D19: =D15-D11 -> 280534 | E19: =E15-E11 -> 320031 | F19: =F15-F11 -> 378525 | G19: =G15-G11 -> 522618 | H19: =H15-H11 -> 540169 | I19: =I15-I11 -> 267581 | J19: =J15-J11 -> 288176.85 | K19: =K15-K11 -> 605962.16 | ... O19: =O15-O11 -> 758337.52
B21: V. Construcción del FCFF (2S26E–2031E)
A22: 8a | B22: Tasa de impuesto operacional | C22: S / P | J22: =Forecast!D110 -> 0.168 | K22: =Forecast!E110 -> 0.19 | L22: =Forecast!F110 -> 0.215 | M22: =Forecast!G110 -> 0.24 | N22: =Forecast!H110 -> 0.27 | O22: =Forecast!I110 -> 0.27 | P22: Trayectoria de impuesto en caja del forecast (16,8% → 27%) [S]. Alternativa: tasa legal ponderada 28,22% (FFCF!J37 del modelo de valuation)
A23: 8 | B23: (−) Impuestos operacionales sobre EBIT | C23: C | J23: =-J22*J19 -> -48413.711 | K23: =-K22*K19 -> -115132.81 | L23: =-L22*L19 -> -140468.87 | M23: =-M22*M19 -> -167632.31 | N23: =-N22*N19 -> -197079.13 | O23: =-O22*O19 -> -204751.13 | P23: Sobre EBIT, sin escudo de intereses (flujo desapalancado)
A24: 9 | B24: NOPAT | C24: C | J24: =J19+J23 -> 239763.14 | K24: =K19+K23 -> 490829.35 | L24: =L19+L23 -> 512874.71 | M24: =M19+M23 -> 530835.65 | N24: =N19+N23 -> 532843.58 | O24: =O19+O23 -> 553586.39
A25: 10 | B25: (+) D&A | C25: C | J25: =J11 -> 2564.5568 | K25: =K11 -> 5398.1972 | L25: =L11 -> 5816.7404 | M25: =M11 -> 6216.5543 | N25: =N11 -> 6496.8811 | O25: =O11 -> 6750.5581
A26: 11 | B26: (−) Capex | C26: P | J26: =-(Forecast!D137+Forecast!D139) -> -149905.97 | K26: =-Forecast!E142 -> -290119.34 | L26: =-Forecast!F142 -> -200864.13 | M26: =-Forecast!G142 -> -48591.535 | N26: =-Forecast!H142 -> -50782.702 | O26: =-Forecast!I142 -> -52765.562 | P26: Proyectos remanentes (release 2T26) + mantención/TI 5,5% de ingresos. 2S26E excluye el capex real del 1S26 (ya pagado antes de la fecha de valorización). Sin greenfield ni Gran Plaza
A27: 12 | B27: (−/+) Variación de capital de trabajo | C27: S | J27: 0 | K27: 0 | L27: 0 | M27: 0 | N27: 0 | O27: 0 | P27: ΔNWC = 0 [S], declarado en el anexo
A28: 13 | B28: FCFF | C28: C | J28: =J24+J25+J26-J27 -> 92421.722 | K28: =K24+K25+K26-K27 -> 206108.21 | L28: =L24+L25+L26-L27 -> 317827.32 | M28: =M24+M25+M26-M27 -> 488460.67 | N28: =N24+N25+N26-N27 -> 488557.76 | O28: =O24+O25+O26-O27 -> 507571.39 | P28: NOPAT + D&A − capex − ΔNWC
B30: VI–VIII. Descuento
A31: 14 | B31: WACC nominal CLP (modelo de valuation) | C31: S | J31: 0.1003 | P31: FFCF!B120 = 10,03% (Mall_plaza_Valuacion.xlsm). Se respeta; ver auditoría abajo antes de usarla como definitiva
A32: 15a | B32: Período de descuento (años desde 30-06-2026, mitad de período) | C32: S | J32: 0.25 | K32: 1 | L32: 2 | M32: 3 | N32: 4 | O32: 5 | P32: Convención de mitad de período
A33: 15 | B33: Factor de descuento | C33: C | J33: =1/(1+$J$31)^J32 -> 0.97638752 | K33: =1/(1+$J$31)^K32 -> 0.90884304 | L33: =1/(1+$J$31)^L32 -> 0.82599568 | M33: =1/(1+$J$31)^M32 -> 0.75070042 | N33: =1/(1+$J$31)^N32 -> 0.68226886 | O33: =1/(1+$J$31)^O32 -> 0.6200753 | P33: 1 / (1 + WACC)^t
A34: 16 | B34: Valor presente del FCFF | C34: C | J34: =J28*J33 -> 90239.416 | K34: =K28*K33 -> 187320.01 | L34: =L28*L33 -> 262523.99 | M34: =M28*M33 -> 366687.63 | N34: =N28*N33 -> 333327.75 | O34: =O28*O33 -> 314732.48
B36: VII. Valor terminal (Gordon)
A37: 17a | B37: Crecimiento perpetuo nominal (g) | C37: S | J37: 0.03 | P37: [S] = meta de inflación BCCh (3%): crecimiento real 0% a perpetuidad, coherente con un FCFF terminal sin capex de crecimiento. Rango Nota 11: 0,1%–1,1% real
A38: 17b | B38: FCFF 2032E = FCFF 2031E × (1 + g) | C38: C | J38: =O28*(1+J37) -> 522798.53
A39: 17 | B39: Valor terminal al 31-12-2031 = FCFF 2032E / (WACC − g) | C39: C | J39: =J38/(J31-J37) -> 7436679
A40: 18 | B40: Valor presente del VT = VT / (1 + WACC)^5,5 | C40: C | J40: =J39/(1+J31)^5.5 -> 4396103.5
B42: IX. Enterprise Value → Equity Value
A43: 19a | B43: Suma VP FCFF explícito | C43: C | J43: =SUM(J34:O34) -> 1554831.3
A44: 19 | B44: Enterprise Value | C44: C | J44: =J43+J40 -> 5950934.8
A45: 20a | B45: (−) Deuda financiera neta 30-06-2026 | C45: R | J45: =-Inputs!C64 -> -1285740 | P45: Release 2T26 / Análisis Razonado 1S26 (1.285.740)
A46: 20b | B46: (−) Participaciones no controladoras (libro) 30-06-2026 | C46: R | J46: -50841 | P46: Release 2T26, estado de situación. Libro como proxy [S]
A47: 21 | B47: Equity Value | C47: C | J47: =J44+J45+J46 -> 4614353.8
A48: 22a | B48: Acciones (MM) | C48: R | J48: =Inputs!C125 -> 2190
A49: 22 | B49: Valor por acción (CLP) | C49: C | J49: =J47/J48 -> 2107.0109
A50: 22b | B50: Precio implícito en el modelo de valuation (CLP) | C50: R | J50: =7905900/2190 -> 3610 | P50: FFCF!G26: market cap 7.905.900 MM CLP / 2.190 MM acciones
A51: 22c | B51: Diferencia vs precio | C51: C | J51: =J49/J50-1 -> -0.41634048
B53: X. Chequeos
A54: X1 | B54: VP del valor terminal / EV | C54: C | J54: =J40/J44 -> 0.73872487
A55: X2 | B55: EV / EBITDA ajustado LTM | C55: C | J55: =J44/H15 -> 10.920449
A56: X3 | B56: Cap rate implícito del VT = EBITDA 2032E / VT | C56: C | J56: =O15*(1+J37)/J39 -> 0.10596675 | P56: Referencias: Gran Plaza 9,4% (2026); EBITDA LTM / PI jun-26 = 7,5%
A57: X4 | B57: EV / Propiedades de inversión jun-26 (NAV contable) | C57: C | J57: =J44/Inputs!C67 -> 0.81410253 | P57: < 1 = el DCF vale menos que la tasación de la propia compañía
A58: X5 | B58: EV de mercado implícito / PI jun-26 | C58: C | J58: =(7905900+Inputs!C64+50841)/Inputs!C67 -> 1.2643941
B60: Sensibilidad: valor por acción (CLP) — WACC (filas) vs g (columnas)
D61: 0.025 | E61: 0.03 | F61: 0.035
C62: 0.09 | D62: =(SUMPRODUCT($J$28:$O$28,1/(1+$C62)^$J$32:$O$32)+$O$28*(1+D$61)/($C62-D$61)/(1+$C62)^5.5+$J$45+$J$46)/$J$48 -> 2395.5762 | E62: =(SUMPRODUCT($J$28:$O$28,1/(1+$C62)^$J$32:$O$32)+$O$28*(1+E$61)/($C62-E$61)/(1+$C62)^5.5+$J$45+$J$46)/$J$48 -> 2597.1987 | F62: =(SUMPRODUCT($J$28:$O$28,1/(1+$C62)^$J$32:$O$32)+$O$28*(1+F$61)/($C62-F$61)/(1+$C62)^5.5+$J$45+$J$46)/$J$48 -> 2835.48
C63: 0.095 | D63: =(SUMPRODUCT($J$28:$O$28,1/(1+$C63)^$J$32:$O$32)+$O$28*(1+D$61)/($C63-D$61)/(1+$C63)^5.5+$J$45+$J$46)/$J$48 -> 2170.3689 | E63: =(SUMPRODUCT($J$28:$O$28,1/(1+$C63)^$J$32:$O$32)+$O$28*(1+E$61)/($C63-E$61)/(1+$C63)^5.5+$J$45+$J$46)/$J$48 -> 2339.6655 | F63: =(SUMPRODUCT($J$28:$O$28,1/(1+$C63)^$J$32:$O$32)+$O$28*(1+F$61)/($C63-F$61)/(1+$C63)^5.5+$J$45+$J$46)/$J$48 -> 2537.1781
C64: 0.1003 | D64: =(SUMPRODUCT($J$28:$O$28,1/(1+$C64)^$J$32:$O$32)+$O$28*(1+D$61)/($C64-D$61)/(1+$C64)^5.5+$J$45+$J$46)/$J$48 -> 1964.6231 | E64: =(SUMPRODUCT($J$28:$O$28,1/(1+$C64)^$J$32:$O$32)+$O$28*(1+E$61)/($C64-E$61)/(1+$C64)^5.5+$J$45+$J$46)/$J$48 -> 2107.0109 | F64: =(SUMPRODUCT($J$28:$O$28,1/(1+$C64)^$J$32:$O$32)+$O$28*(1+F$61)/($C64-F$61)/(1+$C64)^5.5+$J$45+$J$46)/$J$48 -> 2271.2038
C65: 0.105 | D65: =(SUMPRODUCT($J$28:$O$28,1/(1+$C65)^$J$32:$O$32)+$O$28*(1+D$61)/($C65-D$61)/(1+$C65)^5.5+$J$45+$J$46)/$J$48 -> 1805.226 | E65: =(SUMPRODUCT($J$28:$O$28,1/(1+$C65)^$J$32:$O$32)+$O$28*(1+E$61)/($C65-E$61)/(1+$C65)^5.5+$J$45+$J$46)/$J$48 -> 1928.4631 | F65: =(SUMPRODUCT($J$28:$O$28,1/(1+$C65)^$J$32:$O$32)+$O$28*(1+F$61)/($C65-F$61)/(1+$C65)^5.5+$J$45+$J$46)/$J$48 -> 2069.3055
C66: 0.11 | D66: =(SUMPRODUCT($J$28:$O$28,1/(1+$C66)^$J$32:$O$32)+$O$28*(1+D$61)/($C66-D$61)/(1+$C66)^5.5+$J$45+$J$46)/$J$48 -> 1655.2396 | E66: =(SUMPRODUCT($J$28:$O$28,1/(1+$C66)^$J$32:$O$32)+$O$28*(1+E$61)/($C66-E$61)/(1+$C66)^5.5+$J$45+$J$46)/$J$48 -> 1761.7914 | F66: =(SUMPRODUCT($J$28:$O$28,1/(1+$C66)^$J$32:$O$32)+$O$28*(1+F$61)/($C66-F$61)/(1+$C66)^5.5+$J$45+$J$46)/$J$48 -> 1882.5501
B68: Sensibilidad: valor por acción (CLP) — WACC vs tasa de impuesto del año terminal (g = 3%)
D69: 0.168 | E69: 0.22 | F69: 0.27
C70: 0.09 | D70: =(SUMPRODUCT($J$28:$O$28,1/(1+$C70)^$J$32:$O$32)+((O$19*(1-D$69)+O$11+O$26)*(1+$J$37))/($C70-$J$37)/(1+$C70)^5.5+$J$45+$J$46)/$J$48 -> 2974.6482 | E70: =(SUMPRODUCT($J$28:$O$28,1/(1+$C70)^$J$32:$O$32)+((O$19*(1-E$69)+O$11+O$26)*(1+$J$37))/($C70-$J$37)/(1+$C70)^5.5+$J$45+$J$46)/$J$48 -> 2782.223 | F70: =(SUMPRODUCT($J$28:$O$28,1/(1+$C70)^$J$32:$O$32)+((O$19*(1-F$69)+O$11+O$26)*(1+$J$37))/($C70-$J$37)/(1+$C70)^5.5+$J$45+$J$46)/$J$48 -> 2597.1987
C71: 0.095 | D71: =(SUMPRODUCT($J$28:$O$28,1/(1+$C71)^$J$32:$O$32)+((O$19*(1-D$69)+O$11+O$26)*(1+$J$37))/($C71-$J$37)/(1+$C71)^5.5+$J$45+$J$46)/$J$48 -> 2679.4197 | E71: =(SUMPRODUCT($J$28:$O$28,1/(1+$C71)^$J$32:$O$32)+((O$19*(1-E$69)+O$11+O$26)*(1+$J$37))/($C71-$J$37)/(1+$C71)^5.5+$J$45+$J$46)/$J$48 -> 2506.2117 | F71: =(SUMPRODUCT($J$28:$O$28,1/(1+$C71)^$J$32:$O$32)+((O$19*(1-F$69)+O$11+O$26)*(1+$J$37))/($C71-$J$37)/(1+$C71)^5.5+$J$45+$J$46)/$J$48 -> 2339.6655
C72: 0.1003 | D72: =(SUMPRODUCT($J$28:$O$28,1/(1+$C72)^$J$32:$O$32)+((O$19*(1-D$69)+O$11+O$26)*(1+$J$37))/($C72-$J$37)/(1+$C72)^5.5+$J$45+$J$46)/$J$48 -> 2412.9179 | E72: =(SUMPRODUCT($J$28:$O$28,1/(1+$C72)^$J$32:$O$32)+((O$19*(1-E$69)+O$11+O$26)*(1+$J$37))/($C72-$J$37)/(1+$C72)^5.5+$J$45+$J$46)/$J$48 -> 2256.9653 | F72: =(SUMPRODUCT($J$28:$O$28,1/(1+$C72)^$J$32:$O$32)+((O$19*(1-F$69)+O$11+O$26)*(1+$J$37))/($C72-$J$37)/(1+$C72)^5.5+$J$45+$J$46)/$J$48 -> 2107.0109
C73: 0.105 | D73: =(SUMPRODUCT($J$28:$O$28,1/(1+$C73)^$J$32:$O$32)+((O$19*(1-D$69)+O$11+O$26)*(1+$J$37))/($C73-$J$37)/(1+$C73)^5.5+$J$45+$J$46)/$J$48 -> 2208.5559 | E73: =(SUMPRODUCT($J$28:$O$28,1/(1+$C73)^$J$32:$O$32)+((O$19*(1-E$69)+O$11+O$26)*(1+$J$37))/($C73-$J$37)/(1+$C73)^5.5+$J$45+$J$46)/$J$48 -> 2065.7635 | F73: =(SUMPRODUCT($J$28:$O$28,1/(1+$C73)^$J$32:$O$32)+((O$19*(1-F$69)+O$11+O$26)*(1+$J$37))/($C73-$J$37)/(1+$C73)^5.5+$J$45+$J$46)/$J$48 -> 1928.4631
C74: 0.11 | D74: =(SUMPRODUCT($J$28:$O$28,1/(1+$C74)^$J$32:$O$32)+((O$19*(1-D$69)+O$11+O$26)*(1+$J$37))/($C74-$J$37)/(1+$C74)^5.5+$J$45+$J$46)/$J$48 -> 2017.9385 | E74: =(SUMPRODUCT($J$28:$O$28,1/(1+$C74)^$J$32:$O$32)+((O$19*(1-E$69)+O$11+O$26)*(1+$J$37))/($C74-$J$37)/(1+$C74)^5.5+$J$45+$J$46)/$J$48 -> 1887.3537 | F74: =(SUMPRODUCT($J$28:$O$28,1/(1+$C74)^$J$32:$O$32)+((O$19*(1-F$69)+O$11+O$26)*(1+$J$37))/($C74-$J$37)/(1+$C74)^5.5+$J$45+$J$46)/$J$48 -> 1761.7914
B76: Auditoría de la WACC del modelo de valuation (FFCF) — no se reemplaza; observaciones para el equipo
B77: Rf | D77: 5,43% "Chile" (FFCF!E11). Confirmar instrumento: si es el BCP 10Y nominal en CLP, ya incluye riesgo país Chile → no sumar CRP Chile (doble conteo)
B78: CRP | D78: 1,41% = ponderación Chile/Perú/Colombia por ingresos. Si Rf es BCP, usar solo Perú y Colombia: 17,72%×1,55% + 10,52%×3,70% ≈ 0,66%
B79: Kd | D79: 3,60% "última emisión": es tasa REAL en UF. En una WACC nominal CLP debe ser nominal: (1,036)(1+inflación LP 3%) − 1 ≈ 6,7%
B80: Escudo fiscal | D80: FFCF!B120 = E/V×Ke + D/V×Kd: falta (1 − t), aunque la fórmula de B7 lo incluye
B81: Betas | D81: Costa Verde (0,025) e IRSA (0,427) son atípicas; la mediana las neutraliza, pero conviene excluirlas y justificarlo
B82: Fecha | D82: FFCF dice "hasta 30 septiembre"; el DCF y la DFN están al 30-06-2026. Alinear (D1)
B83: Plantilla | D83: Las hojas de estados del .xlsm son la plantilla Bloomberg XFA sin datos (ticker FCX US, USD). Si se refrescan, cambiar a MALLPLAZ CI y CLP
B84: Ilustrativo | D84: Con Rf BCP 5,43%, CRP 0,66%, Kd nominal 6,7% y escudo 27%: Ke ≈ 10,56%, WACC ≈ 9,6%. Solo referencia; la WACC la define valuation

Sheet Peers_inputs
A1: Peers — Bloomberg FA, datos declarados (ARD), MM CLP. Export 28-09-2026 (WP §85)
A2: Azul = dato [R] de Bloomberg (verificar contra EEFF CMF 2025); negro = cálculo [C]. Método de revalorización distinto por par (ver notas). Validación: ROE reportado = §56 en los 8 años.
A4: Parque Arauco (PARAUCO CI) | B4: 2021 | C4: 2022 | D4: 2023 | E4: 2024 | F4: 2025 | G4: Campo Bloomberg
A5: Ingresos | C5: 243119.54 | D5: 264312.61 | E5: 316775.71 | F5: 383792.58 | G5: ARD_REVENUES
A6: EBITDA (definición compañía) | C6: 170697 | D6: 188159 | E6: 227727 | F6: 272233 | G6: ARD_REF_EBITDA_IS
A7: Resultado operacional | C7: 271632.11 | D7: 228661.96 | E7: 271106.29 | F7: 328348.13 | G7: ARD_OPERATING_INCOME
A8: D&A | C8: 5128.377 | D8: 5280.937 | E8: 6518.906 | F8: 4739.59 | G8: ARDR_DEPRECIATION_AMORTIZATION
A9: Utilidad atribuible | C9: 101031.63 | D9: 112345.33 | E9: 120571.31 | F9: 149972.7 | G9: ARD_NET_INC
A10: Utilidad antes de minoritarios | C10: 137551.97 | D10: 129114.89 | E10: 149541.58 | F10: 213796.3 | G10: ARD_PROF_AFTER_TAX_BEF_MINORITY
A11: Propiedades de inversión | B11: 2183835.8 | C11: 2341871.5 | D11: 2750846.3 | E11: 3042457 | F11: 3606680.8 | G11: ARD_TOTAL_PROPERTY_INVESTMENTS (excluye negocios conjuntos)
A12: Patrimonio atribuible | B12: 1077424.5 | C12: 1144928.9 | D12: 1298911.3 | E12: 1464457.7 | F12: 1594521.9 | G12: ARD_TOT_SHARE_EQY_EXCL_MINORITY
A13: Préstamos corto plazo | C13: 116991.74 | D13: 167120.27 | E13: 187477.08 | F13: 153323.03 | G13: ARD_ST_BORROW
A14: Deuda largo plazo | C14: 1034638.3 | D14: 1183607.7 | E14: 1394283 | F14: 1547183.9 | G14: ARD_LT_DEBT
A15: Efectivo y equivalentes | C15: 243042.95 | D15: 319187 | E15: 387091.46 | F15: 153099.71 | G15: ARD_CASH_AND_EQUIVALENTS
A16: Activos totales | C16: 2938210.6 | D16: 3482971.1 | E16: 3930479.5 | F16: 4284682.6 | G16: ARD_TOT_ASSETS
A18: Cencosud Shopping (CENCOMAL CI) | B18: 2021 | C18: 2022 | D18: 2023 | E18: 2024 | F18: 2025 | G18: Campo Bloomberg
A19: Ingresos | C19: 286949.85 | D19: 314784.93 | E19: 353183.7 | F19: 377940.6 | G19: ARD_REVENUES
A20: Margen EBITDA ajustado | C20: 0.9 | D20: 0.9 | E20: 0.908 | F20: 0.901 | G20: ARDR_ADJUSTED_EBITDA_MARGIN (no hay ARD_REF_EBITDA_IS en el export)
A21: Otro (ingreso)/gasto operacional neto (negativo = ganancia) | C21: -29523.565 | D21: 10515.477 | E21: -66670.135 | F21: -96648.526 | G21: ARD_OTH_OPERATING_INC_EXP_NET
A22: Utilidad atribuible | C22: 181875.55 | D22: 187329.71 | E22: 266953.08 | F22: 303966.19 | G22: ARD_NET_INC
A23: Propiedades de inversión | B23: 3794629.2 | C23: 3871649.1 | D23: 3955476.3 | E23: 4122201.8 | F23: 4395015.5 | G23: ARD_TOTAL_PROPERTY_INVESTMENTS
A24: Patrimonio atribuible | B24: 2663057.7 | C24: 2679608.6 | D24: 2744754.9 | E24: 2828031.7 | F24: 2989170.6 | G24: ARD_TOT_SHARE_EQY_EXCL_MINORITY
A25: Préstamos corto plazo | C25: 3415.014 | D25: 3704.413 | E25: 2545.265 | F25: 2632.142 | G25: ARD_ST_BORROW
A26: Deuda largo plazo | C26: 671134.62 | D26: 702753.14 | E26: 734811.85 | F26: 759521.59 | G26: ARD_LT_DEBT
A27: Efectivo y equivalentes | C27: 46100.451 | D27: 52508.911 | E27: 115011.66 | F27: 44347.593 | G27: ARD_CASH_AND_EQUIVALENTS
A28: Activos totales | C28: 4059976.2 | D28: 4147695.6 | E28: 4291155.7 | F28: 4501457.1 | G28: ARD_TOT_ASSETS
A30: Tasa de impuesto para normalizar [S] (legal Chile) | B30: 0.27
A32: Cálculos [C] | C32: 2022 | D32: 2023 | E32: 2024 | F32: 2025
A33: PA — Margen EBITDA | C33: =C6/C5 -> 0.70211139 | D33: =D6/D5 -> 0.71188053 | E33: =E6/E5 -> 0.71889034 | F33: =F6/F5 -> 0.70932325
A34: PA — Revalorización (residuo: res. operacional − (EBITDA − D&A)) | C34: =C7-(C6-C8) -> 106063.49 | D34: =D7-(D6-D8) -> 45783.893 | E34: =E7-(E6-E8) -> 49898.193 | F34: =F7-(F6-F8) -> 60854.721
A35: PA — % atribuible a la controladora (utilidad) | C35: =C9/C10 -> 0.7344979 | D35: =D9/D10 -> 0.87011914 | E35: =E9/E10 -> 0.8062728 | F35: =F9/F10 -> 0.70147472
A36: PA — Utilidad atribuible normalizada | C36: =C9-C34*(1-$B$30)*C35 -> 44162.148 | D36: =D9-D34*(1-$B$30)*D35 -> 83264.002 | E36: =E9-E34*(1-$B$30)*E35 -> 91202.272 | F36: =F9-F34*(1-$B$30)*F35 -> 118810.43
A37: PA — Patrimonio atribuible promedio | C37: =(B12+C12)/2 -> 1111176.7 | D37: =(C12+D12)/2 -> 1221920.1 | E37: =(D12+E12)/2 -> 1381684.5 | F37: =(E12+F12)/2 -> 1529489.8
A38: PA — ROE reportado | C38: =C9/C37 -> 0.090923105 | D38: =D9/D37 -> 0.091941638 | E38: =E9/E37 -> 0.087263993 | F38: =F9/F37 -> 0.098054072
A39: PA — ROE normalizado | C39: =C36/C37 -> 0.039743587 | D39: =D36/D37 -> 0.068141937 | E39: =E36/E37 -> 0.066008029 | F39: =F36/F37 -> 0.077679777
A40: PA — Revalorización / PI de apertura | C40: =C34/B11 -> 0.048567519 | D40: =D34/C11 -> 0.01955013 | E40: =E34/D11 -> 0.018139215 | F40: =F34/E11 -> 0.020001834
A41: PA — EBITDA / PI de cierre | C41: =C6/C11 -> 0.072889139 | D41: =D6/D11 -> 0.068400406 | E41: =E6/E11 -> 0.074849702 | F41: =F6/F11 -> 0.075480203
A42: PA — LTV (deuda neta / PI) | C42: =(C13+C14-C15)/C11 -> 0.38797476 | D42: =(D13+D14-D15)/D11 -> 0.37499042 | E42: =(E13+E14-E15)/E11 -> 0.39266572 | F42: =(F13+F14-F15)/F11 -> 0.42903913
A43: PA — Deuda neta / EBITDA | C43: =(C13+C14-C15)/C6 -> 5.3228063 | D43: =(D13+D14-D15)/D6 -> 5.4822835 | E43: =(E13+E14-E15)/E6 -> 5.2460559 | F43: =(F13+F14-F15)/F6 -> 5.684128
A44: PA — Activos / patrimonio atribuible | C44: =C16/C12 -> 2.5662823 | D44: =D16/D12 -> 2.6814542 | E44: =E16/E12 -> 2.6839146 | F44: =F16/F12 -> 2.6871269
A46: CS — EBITDA (ingresos × margen ajustado) | C46: =C19*C20 -> 258254.87 | D46: =D19*D20 -> 283306.44 | E46: =E19*E20 -> 320690.8 | F46: =F19*F20 -> 340524.49
A47: CS — Revalorización (= −otro ingreso/gasto operacional neto) | C47: =-C21 -> 29523.565 | D47: =-D21 -> -10515.477 | E47: =-E21 -> 66670.135 | F47: =-F21 -> 96648.526
A48: CS — Utilidad atribuible normalizada | C48: =C22-C47*(1-$B$30) -> 160323.34 | D48: =D22-D47*(1-$B$30) -> 195006.01 | E48: =E22-E47*(1-$B$30) -> 218283.88 | F48: =F22-F47*(1-$B$30) -> 233412.77
A49: CS — Patrimonio atribuible promedio | C49: =(B24+C24)/2 -> 2671333.2 | D49: =(C24+D24)/2 -> 2712181.7 | E49: =(D24+E24)/2 -> 2786393.3 | F49: =(E24+F24)/2 -> 2908601.2
A50: CS — ROE reportado | C50: =C22/C49 -> 0.068084187 | D50: =D22/D49 -> 0.069069748 | E50: =E22/E49 -> 0.09580596 | F50: =F22/F49 -> 0.10450597
A51: CS — ROE normalizado | C51: =C48/C49 -> 0.060016229 | D51: =D48/D49 -> 0.071900052 | E51: =E48/E49 -> 0.078339223 | F51: =F48/F49 -> 0.080249149
A52: CS — Revalorización / PI de apertura | C52: =C47/B23 -> 0.0077803556 | D52: =D47/C23 -> -0.0027160201 | E52: =E47/D23 -> 0.016855147 | F52: =F47/E23 -> 0.02344585
A53: CS — EBITDA / PI de cierre | C53: =C46/C23 -> 0.0667041 | D53: =D46/D23 -> 0.071623849 | E53: =E46/E23 -> 0.077795998 | F53: =F46/F23 -> 0.0774797
A54: CS — LTV (deuda neta / PI) | C54: =(C25+C26-C27)/C23 -> 0.1623208 | D54: =(D25+D26-D27)/D23 -> 0.16532741 | E54: =(E25+E26-E27)/E23 -> 0.15097404 | F54: =(F25+F26-F27)/F23 -> 0.16332278
A55: CS — Deuda neta / EBITDA | C55: =(C25+C26-C27)/C46 -> 2.4334456 | D55: =(D25+D26-D27)/D46 -> 2.3082732 | E55: =(E25+E26-E27)/E46 -> 1.9406402 | F55: =(F25+F26-F27)/F46 -> 2.1079428
A56: CS — Activos / patrimonio atribuible | C56: =C28/C24 -> 1.5151378 | D56: =D28/D24 -> 1.5111352 | E56: =E28/E24 -> 1.5173648 | F56: =F28/F24 -> 1.5059218
A58: Control: ROE reportado debe ser PA 9,09% / 9,19% / 8,73% / 9,81% y CS 6,81% / 6,91% / 9,58% / 10,45% (Bloomberg FA Ratios, WP §56).
A59: PA: la revalorización es un residuo; puede incluir otras partidas operacionales menores. Atribución por proporción de la utilidad [S]. La PI excluye negocios conjuntos (inversión por método de participación 209.196 en 2025): sobrestima LTV y DN/EBITDA.
A60: Mallplaza se normaliza con su utilidad distribuible auditada (Nota 20e), no con la tasa legal: diferencia de método declarada (WP §85.1).
A61: Pendiente: validar contra EEFF 2025 de ambos pares (CMF) y extraer sus tasas de descuento de la nota de PI (WP §88, #2/#19).

Sheet E1_DuPont
A1: Exhibit 1 — Operating record and DuPont: 2019A–2031E
A2: Bloque A (indiferente al régimen contable): 2019A–2025A + LTM. Bloque B (balance a valor razonable): 2022A en adelante; 2019–2021 no comparables (modelo del costo, WP §3). Proyecciones: hoja Forecast_link.
A4: A. Operating record (MM CLP) | B4: 2019A | C4: 2020A | D4: 2021A | E4: 2022A | F4: 2023A | G4: 2024A | H4: 2025A | I4: LTM 2T26 | J4: 2026E | K4: 2027E | L4: 2028E | M4: 2029E | N4: 2030E | O4: 2031E
A5: Ingresos | B5: =IF(Inputs!$C$90="","",Inputs!$C$90) | C5: =IF(Inputs!$C$91="","",Inputs!$C$91) | D5: =IF(Inputs!$C$80="","",Inputs!$C$80) -> 276695 | E5: =IF(Inputs!$C$81="","",Inputs!$C$81) -> 370899 | F5: =IF(Inputs!$C$4="","",Inputs!$C$4) -> 419904 | G5: =IF(Inputs!$C$5="","",Inputs!$C$5) -> 494605 | H5: =IF(Inputs!$C$6="","",Inputs!$C$6) -> 653911 | I5: =IF(Inputs!$C$82="","",Inputs!$C$82) -> 677333 | J5: =IF(Forecast_link!B5="","",Forecast_link!B5) -> 703998.94 | K5: =IF(Forecast_link!C5="","",Forecast_link!C5) -> 767179.42 | L5: =IF(Forecast_link!D5="","",Forecast_link!D5) -> 826661.82 | M5: =IF(Forecast_link!E5="","",Forecast_link!E5) -> 883482.45 | N5: =IF(Forecast_link!F5="","",Forecast_link!F5) -> 923321.86 | O5: =IF(Forecast_link!G5="","",Forecast_link!G5) -> 959373.85
A6: EBITDA | B6: =IF(Inputs!$C$92="","",Inputs!$C$92) | C6: =IF(Inputs!$C$75="","",Inputs!$C$75) -> 116114 | D6: =IF(Inputs!$C$76="","",Inputs!$C$76) -> 208621 | E6: =IF(Inputs!$C$77="","",Inputs!$C$77) -> 282699 | F6: =IF(Inputs!$C$78="","",Inputs!$C$78) -> 322185 | G6: =IF(Inputs!$C$9="","",Inputs!$C$9) -> 380637 | H6: =IF(Inputs!$C$10="","",Inputs!$C$10) -> 526228 | I6: =IF(Inputs!$C$79="","",Inputs!$C$79) -> 544935 | J6: =IF(Forecast_link!B6="","",Forecast_link!B6) -> 561315.41 | K6: =IF(Forecast_link!C6="","",Forecast_link!C6) -> 611360.36 | L6: =IF(Forecast_link!D6="","",Forecast_link!D6) -> 659160.32 | M6: =IF(Forecast_link!E6="","",Forecast_link!E6) -> 704684.52 | N6: =IF(Forecast_link!F6="","",Forecast_link!F6) -> 736419.6 | O6: =IF(Forecast_link!G6="","",Forecast_link!G6) -> 765088.08
A7: Crecimiento de ingresos | C7: =IF(OR(C5="",B5=""),"",C5/B5-1) | D7: =IF(OR(D5="",C5=""),"",D5/C5-1) | E7: =IF(OR(E5="",D5=""),"",E5/D5-1) -> 0.34046152 | F7: =IF(OR(F5="",E5=""),"",F5/E5-1) -> 0.13212492 | G7: =IF(OR(G5="",F5=""),"",G5/F5-1) -> 0.17790019 | H7: =IF(OR(H5="",G5=""),"",H5/G5-1) -> 0.32208732 | J7: =IF(OR(J5="",H5=""),"",J5/H5-1) -> 0.07659748 | K7: =IF(OR(K5="",J5=""),"",K5/J5-1) -> 0.089745147 | L7: =IF(OR(L5="",K5=""),"",L5/K5-1) -> 0.077533882 | M7: =IF(OR(M5="",L5=""),"",M5/L5-1) -> 0.068735037 | N7: =IF(OR(N5="",M5=""),"",N5/M5-1) -> 0.045093604 | O7: =IF(OR(O5="",N5=""),"",O5/N5-1) -> 0.039045966
A8: Margen EBITDA | B8: =IF(OR(B5="",B6=""),"",B6/B5) | C8: =IF(OR(C5="",C6=""),"",C6/C5) | D8: =IF(OR(D5="",D6=""),"",D6/D5) -> 0.75397459 | E8: =IF(OR(E5="",E6=""),"",E6/E5) -> 0.76219941 | F8: =IF(OR(F5="",F6=""),"",F6/F5) -> 0.76728252 | G8: =IF(OR(G5="",G6=""),"",G6/G5) -> 0.76957774 | H8: =IF(OR(H5="",H6=""),"",H6/H5) -> 0.80473948 | I8: =IF(OR(I5="",I6=""),"",I6/I5) -> 0.80453042 | ... O8: =IF(OR(O5="",O6=""),"",O6/O5) -> 0.7974869
A9: FFO atribuible | E9: =IF(Inputs!$C$83="","",Inputs!$C$83) -> 218931 | F9: =IF(Inputs!$C$84="","",Inputs!$C$84) -> 257227 | G9: =IF(Inputs!$C$85="","",Inputs!$C$85) -> 303195 | H9: =IF(Inputs!$C$20="","",Inputs!$C$20) -> 405300 | I9: =IF(Inputs!$C$86="","",Inputs!$C$86) -> 419907 | J9: =IF(Forecast_link!B7="","",Forecast_link!B7) -> 428521.01 | K9: =IF(Forecast_link!C7="","",Forecast_link!C7) -> 457343.87 | L9: =IF(Forecast_link!D7="","",Forecast_link!D7) -> 479815.31 | M9: =IF(Forecast_link!E7="","",Forecast_link!E7) -> 500558.62 | N9: =IF(Forecast_link!F7="","",Forecast_link!F7) -> 509123.66 | O9: =IF(Forecast_link!G7="","",Forecast_link!G7) -> 535305.59
A10: Margen FFO | E10: =IF(OR(E5="",E9=""),"",E9/E5) -> 0.59027121 | F10: =IF(OR(F5="",F9=""),"",F9/F5) -> 0.61258526 | G10: =IF(OR(G5="",G9=""),"",G9/G5) -> 0.61300432 | H10: =IF(OR(H5="",H9=""),"",H9/H5) -> 0.61980912 | I10: =IF(OR(I5="",I9=""),"",I9/I5) -> 0.61994174 | J10: =IF(OR(J5="",J9=""),"",J9/J5) -> 0.60869554 | K10: =IF(OR(K5="",K9=""),"",K9/K5) -> 0.59613678 | L10: =IF(OR(L5="",L9=""),"",L9/L5) -> 0.58042515 | ... O10: =IF(OR(O5="",O9=""),"",O9/O5) -> 0.55797391
A11: 2022: ingresos EEFF reformulados (370.899); el FFO de la compañía usa 383.864 (base costo) → margen 59,0% vs 57,0% reportado (WP §28).
A13: B. DuPont (fair-value balance sheet) | B13: 2019A | C13: 2020A | D13: 2021A | E13: 2022A | F13: 2023A | G13: 2024A | H13: 2025A | I13: LTM 2T26 | J13: 2026E | K13: 2027E | L13: 2028E | M13: 2029E | N13: 2030E | O13: 2031E
A14: Utilidad atribuible reportada | E14: =IF(Inputs!$C$87="","",Inputs!$C$87) -> 157667 | F14: =IF(Inputs!$C$88="","",Inputs!$C$88) -> 349759 | G14: =IF(Inputs!$C$12="","",Inputs!$C$12) -> 335934 | H14: =IF(Inputs!$C$13="","",Inputs!$C$13) -> 1431012 | J14: =IF(OR(J15="",Forecast_link!B9=""),"",J15+Forecast_link!B9) -> 639155.17 | K14: =IF(OR(K15="",Forecast_link!C9=""),"",K15+Forecast_link!C9) -> 593529.37 | L14: =IF(OR(L15="",Forecast_link!D9=""),"",L15+Forecast_link!D9) -> 614088.92 | M14: =IF(OR(M15="",Forecast_link!E9=""),"",M15+Forecast_link!E9) -> 638982.38 | N14: =IF(OR(N15="",Forecast_link!F9=""),"",N15+Forecast_link!F9) -> 656901.72 | O14: =IF(OR(O15="",Forecast_link!G9=""),"",O15+Forecast_link!G9) -> 695051.41
A15: Utilidad distribuible (normalizada) | E15: =IF(Inputs!$C$97="","",Inputs!$C$97) -> 95856 | F15: =IF(Inputs!$C$89="","",Inputs!$C$89) -> 197540 | G15: =IF(Inputs!$C$21="","",Inputs!$C$21) -> 238305 | H15: =IF(Inputs!$C$22="","",Inputs!$C$22) -> 369312 | J15: =IF(Forecast_link!B8="","",Forecast_link!B8) -> 380038.82 | K15: =IF(Forecast_link!C8="","",Forecast_link!C8) -> 415490.8 | L15: =IF(Forecast_link!D8="","",Forecast_link!D8) -> 440070.47 | M15: =IF(Forecast_link!E8="","",Forecast_link!E8) -> 462674.09 | N15: =IF(Forecast_link!F8="","",Forecast_link!F8) -> 477016.6 | O15: =IF(Forecast_link!G8="","",Forecast_link!G8) -> 509052.03
A16: Total activos al cierre | E16: =IF(Inputs!$C$94="","",Inputs!$C$94) -> 4513943 | F16: =IF(Inputs!$C$23="","",Inputs!$C$23) -> 4796336 | G16: =IF(Inputs!$C$24="","",Inputs!$C$24) -> 5915073 | H16: =IF(Inputs!$C$25="","",Inputs!$C$25) -> 7583643 | J16: =IF(Forecast_link!B10="","",Forecast_link!B10) -> 8230928.7 | K16: =IF(Forecast_link!C10="","",Forecast_link!C10) -> 8767723.9 | L16: =IF(Forecast_link!D10="","",Forecast_link!D10) -> 9209694 | M16: =IF(Forecast_link!E10="","",Forecast_link!E10) -> 9502564.1 | N16: =IF(Forecast_link!F10="","",Forecast_link!F10) -> 9802581.1 | O16: =IF(Forecast_link!G10="","",Forecast_link!G10) -> 10113052
A17: Patrimonio atribuible al cierre | E17: =IF(Inputs!$C$96="","",Inputs!$C$96) -> 2263298 | F17: =IF(Inputs!$C$26="","",Inputs!$C$26) -> 2601053 | G17: =IF(Inputs!$C$27="","",Inputs!$C$27) -> 3157863 | H17: =IF(Inputs!$C$28="","",Inputs!$C$28) -> 4482905 | J17: =IF(OR(H17="",J14=""),"",H17+J14-Inputs!$C$98*J15+N(Forecast_link!B11)) -> 4970044.6 | K17: =IF(OR(J17="",K14=""),"",J17+K14-Inputs!$C$98*K15+N(Forecast_link!C11)) -> 5397377.7 | L17: =IF(OR(K17="",L14=""),"",K17+L14-Inputs!$C$98*L15+N(Forecast_link!D11)) -> 5835438.4 | M17: =IF(OR(L17="",M14=""),"",L17+M14-Inputs!$C$98*M15+N(Forecast_link!E11)) -> 6289351.2 | N17: =IF(OR(M17="",N14=""),"",M17+N14-Inputs!$C$98*N15+N(Forecast_link!F11)) -> 6755446.3 | O17: =IF(OR(N17="",O14=""),"",N17+O14-Inputs!$C$98*O15+N(Forecast_link!G11)) -> 7246876.8
A18: Apertura 2022A (reformulada 01-01-2022) | E18: =IF(Inputs!$C$93="","",Inputs!$C$93) -> 4094996
A19: patrimonio apertura 2022A | E19: =IF(Inputs!$C$95="","",Inputs!$C$95) -> 2167172
A20: Activos promedio | E20: =IF(OR(E16="",E18=""),"",(E16+E18)/2) -> 4304469.5 | F20: =IF(OR(F16="",E16=""),"",(F16+E16)/2) -> 4655139.5 | G20: =IF(OR(G16="",F16=""),"",(G16+F16)/2) -> 5355704.5 | H20: =IF(OR(H16="",G16=""),"",(H16+G16)/2) -> 6749358 | J20: =IF(OR(J16="",H16=""),"",(J16+H16)/2) -> 7907285.9 | K20: =IF(OR(K16="",J16=""),"",(K16+J16)/2) -> 8499326.3 | L20: =IF(OR(L16="",K16=""),"",(L16+K16)/2) -> 8988709 | M20: =IF(OR(M16="",L16=""),"",(M16+L16)/2) -> 9356129 | N20: =IF(OR(N16="",M16=""),"",(N16+M16)/2) -> 9652572.6 | O20: =IF(OR(O16="",N16=""),"",(O16+N16)/2) -> 9957816.8
A21: Patrimonio atribuible promedio | E21: =IF(OR(E17="",E19=""),"",(E17+E19)/2) -> 2215235 | F21: =IF(OR(F17="",E17=""),"",(F17+E17)/2) -> 2432175.5 | G21: =IF(OR(G17="",F17=""),"",(G17+F17)/2) -> 2879458 | H21: =IF(OR(H17="",G17=""),"",(H17+G17)/2) -> 3820384 | J21: =IF(OR(J17="",H17=""),"",(J17+H17)/2) -> 4726474.8 | K21: =IF(OR(K17="",J17=""),"",(K17+J17)/2) -> 5183711.2 | L21: =IF(OR(L17="",K17=""),"",(L17+K17)/2) -> 5616408.1 | M21: =IF(OR(M17="",L17=""),"",(M17+L17)/2) -> 6062394.8 | N21: =IF(OR(N17="",M17=""),"",(N17+M17)/2) -> 6522398.7 | O21: =IF(OR(O17="",N17=""),"",(O17+N17)/2) -> 7001161.6
A23: Margen neto reportado | B23: n.c. | C23: n.c. | D23: n.c. | E23: =IF(OR(E14="",E5="",N(E5)=0),"",E14/E5) -> 0.42509416 | F23: =IF(OR(F14="",F5="",N(F5)=0),"",F14/F5) -> 0.83294991 | G23: =IF(OR(G14="",G5="",N(G5)=0),"",G14/G5) -> 0.67919653 | H23: =IF(OR(H14="",H5="",N(H5)=0),"",H14/H5) -> 2.1883896 | J23: =IF(OR(J14="",J5="",N(J5)=0),"",J14/J5) -> 0.90789224 | K23: =IF(OR(K14="",K5="",N(K5)=0),"",K14/K5) -> 0.77365132 | L23: =IF(OR(L14="",L5="",N(L5)=0),"",L14/L5) -> 0.74285385 | M23: =IF(OR(M14="",M5="",N(M5)=0),"",M14/M5) -> 0.72325419 | N23: =IF(OR(N14="",N5="",N(N5)=0),"",N14/N5) -> 0.71145475 | O23: =IF(OR(O14="",O5="",N(O5)=0),"",O14/O5) -> 0.72448442
A24: Margen neto normalizado | B24: n.c. | C24: n.c. | D24: n.c. | E24: =IF(OR(E15="",E5="",N(E5)=0),"",E15/E5) -> 0.25844233 | F24: =IF(OR(F15="",F5="",N(F5)=0),"",F15/F5) -> 0.47044086 | G24: =IF(OR(G15="",G5="",N(G5)=0),"",G15/G5) -> 0.48180872 | H24: =IF(OR(H15="",H5="",N(H5)=0),"",H15/H5) -> 0.56477411 | J24: =IF(OR(J15="",J5="",N(J5)=0),"",J15/J5) -> 0.53982868 | K24: =IF(OR(K15="",K5="",N(K5)=0),"",K15/K5) -> 0.54158231 | L24: =IF(OR(L15="",L5="",N(L5)=0),"",L15/L5) -> 0.53234643 | M24: =IF(OR(M15="",M5="",N(M5)=0),"",M15/M5) -> 0.52369358 | N24: =IF(OR(N15="",N5="",N(N5)=0),"",N15/N5) -> 0.5166309 | O24: =IF(OR(O15="",O5="",N(O5)=0),"",O15/O5) -> 0.53060861
A25: Rotación de activos | B25: n.c. | C25: n.c. | D25: n.c. | E25: =IF(OR(E5="",E20="",N(E20)=0),"",E5/E20) -> 0.086166019 | F25: =IF(OR(F5="",F20="",N(F20)=0),"",F5/F20) -> 0.090202238 | G25: =IF(OR(G5="",G20="",N(G20)=0),"",G5/G20) -> 0.092351062 | H25: =IF(OR(H5="",H20="",N(H20)=0),"",H5/H20) -> 0.096884919 | J25: =IF(OR(J5="",J20="",N(J20)=0),"",J5/J20) -> 0.089031679 | K25: =IF(OR(K5="",K20="",N(K20)=0),"",K5/K20) -> 0.090263557 | L25: =IF(OR(L5="",L20="",N(L20)=0),"",L5/L20) -> 0.091966691 | M25: =IF(OR(M5="",M20="",N(M20)=0),"",M5/M20) -> 0.094428203 | N25: =IF(OR(N5="",N20="",N(N20)=0),"",N5/N20) -> 0.095655521 | O25: =IF(OR(O5="",O20="",N(O20)=0),"",O5/O20) -> 0.096343795
A26: Apalancamiento (activos / patrimonio) | B26: n.c. | C26: n.c. | D26: n.c. | E26: =IF(OR(E20="",E21="",N(E21)=0),"",E20/E21) -> 1.9431209 | F26: =IF(OR(F20="",F21="",N(F21)=0),"",F20/F21) -> 1.9139817 | G26: =IF(OR(G20="",G21="",N(G21)=0),"",G20/G21) -> 1.8599697 | H26: =IF(OR(H20="",H21="",N(H21)=0),"",H20/H21) -> 1.7666701 | J26: =IF(OR(J20="",J21="",N(J21)=0),"",J20/J21) -> 1.6729775 | K26: =IF(OR(K20="",K21="",N(K21)=0),"",K20/K21) -> 1.6396219 | L26: =IF(OR(L20="",L21="",N(L21)=0),"",L20/L21) -> 1.6004373 | M26: =IF(OR(M20="",M21="",N(M21)=0),"",M20/M21) -> 1.5433058 | N26: =IF(OR(N20="",N21="",N(N21)=0),"",N20/N21) -> 1.4799115 | O26: =IF(OR(O20="",O21="",N(O21)=0),"",O20/O21) -> 1.4223092
A27: ROE reportado | B27: n.c. | C27: n.c. | D27: n.c. | E27: =IF(OR(E14="",E21="",N(E21)=0),"",E14/E21) -> 0.071173939 | F27: =IF(OR(F14="",F21="",N(F21)=0),"",F14/F21) -> 0.143805 | G27: =IF(OR(G14="",G21="",N(G21)=0),"",G14/G21) -> 0.11666571 | H27: =IF(OR(H14="",H21="",N(H21)=0),"",H14/H21) -> 0.37457282 | J27: =IF(OR(J14="",J21="",N(J21)=0),"",J14/J21) -> 0.13522873 | K27: =IF(OR(K14="",K21="",N(K21)=0),"",K14/K21) -> 0.11449893 | L27: =IF(OR(L14="",L21="",N(L21)=0),"",L14/L21) -> 0.10933837 | M27: =IF(OR(M14="",M21="",N(M21)=0),"",M14/M21) -> 0.10540098 | N27: =IF(OR(N14="",N21="",N(N21)=0),"",N14/N21) -> 0.10071474 | O27: =IF(OR(O14="",O21="",N(O21)=0),"",O14/O21) -> 0.099276585
A28: ROE normalizado | B28: n.c. | C28: n.c. | D28: n.c. | E28: =IF(OR(E15="",E21="",N(E21)=0),"",E15/E21) -> 0.043271256 | F28: =IF(OR(F15="",F21="",N(F21)=0),"",F15/F21) -> 0.081219468 | G28: =IF(OR(G15="",G21="",N(G21)=0),"",G15/G21) -> 0.082760367 | H28: =IF(OR(H15="",H21="",N(H21)=0),"",H15/H21) -> 0.096668817 | J28: =IF(OR(J15="",J21="",N(J21)=0),"",J15/J21) -> 0.080406398 | K28: =IF(OR(K15="",K21="",N(K21)=0),"",K15/K21) -> 0.080153154 | L28: =IF(OR(L15="",L21="",N(L21)=0),"",L15/L21) -> 0.078354434 | M28: =IF(OR(M15="",M21="",N(M21)=0),"",M15/M21) -> 0.076318699 | N28: =IF(OR(N15="",N21="",N(N21)=0),"",N15/N21) -> 0.073135149 | O28: =IF(OR(O15="",O21="",N(O21)=0),"",O15/O21) -> 0.072709653
A29: ROA reportado | B29: n.c. | C29: n.c. | D29: n.c. | E29: =IF(OR(E14="",E20="",N(E20)=0),"",E14/E20) -> 0.036628672 | F29: =IF(OR(F14="",F20="",N(F20)=0),"",F14/F20) -> 0.075133946 | G29: =IF(OR(G14="",G20="",N(G20)=0),"",G14/G20) -> 0.062724521 | H29: =IF(OR(H14="",H20="",N(H20)=0),"",H14/H20) -> 0.21202194 | J29: =IF(OR(J14="",J20="",N(J20)=0),"",J14/J20) -> 0.08083117 | K29: =IF(OR(K14="",K20="",N(K20)=0),"",K14/K20) -> 0.069832519 | L29: =IF(OR(L14="",L20="",N(L20)=0),"",L14/L20) -> 0.068317811 | M29: =IF(OR(M14="",M20="",N(M20)=0),"",M14/M20) -> 0.068295593 | N29: =IF(OR(N14="",N20="",N(N20)=0),"",N14/N20) -> 0.068054574 | O29: =IF(OR(O14="",O20="",N(O20)=0),"",O14/O20) -> 0.069799578
A30: ROA normalizado | B30: n.c. | C30: n.c. | D30: n.c. | E30: =IF(OR(E15="",E20="",N(E20)=0),"",E15/E20) -> 0.022268946 | F30: =IF(OR(F15="",F20="",N(F20)=0),"",F15/F20) -> 0.042434819 | G30: =IF(OR(G15="",G20="",N(G20)=0),"",G15/G20) -> 0.044495547 | H30: =IF(OR(H15="",H20="",N(H20)=0),"",H15/H20) -> 0.054718093 | J30: =IF(OR(J15="",J20="",N(J20)=0),"",J15/J20) -> 0.048061854 | K30: =IF(OR(K15="",K20="",N(K20)=0),"",K15/K20) -> 0.048885145 | L30: =IF(OR(L15="",L20="",N(L20)=0),"",L15/L20) -> 0.04895814 | M30: =IF(OR(M15="",M20="",N(M20)=0),"",M15/M20) -> 0.049451443 | N30: =IF(OR(N15="",N20="",N(N20)=0),"",N15/N20) -> 0.049418598 | O30: =IF(OR(O15="",O20="",N(O20)=0),"",O15/O20) -> 0.051120847
A32: Controles: ROE reportado 2024A = 11,67% y 2025A = 37,46% (Bloomberg). Identidad DuPont: margen × rotación × apalancamiento = ROE.
A33: n.c. = no comparable (modelo del costo hasta 2021; NIC 8 reformula solo desde 01-01-2022).
A34: 2022A–2023A con EEFF dic-23 reformulado: utilidad 2022 = 157.667 (no 66.445 base costo); distribuible 2023 = 197.540 [R, Nota 21e]; distribuible 2022 = 95.856 [C, proxy]. Payout 2023 sobre distribuible = 40,0%, en línea con la política.
A35: LTM 2T26 no se calcula en el bloque B: exige balance de jun-25 (EEFF jun-25, pendiente). La compañía reporta ROE LTM 28,6% con otra definición (patrimonio total, promedio de 4 trimestres).
A37: C. Peers — same normalization (WP §85) | E37: 2022A | F37: 2023A | G37: 2024A | H37: 2025A
A38: ROE normalizado — Mallplaza | E38: =E28 -> 0.043271256 | F38: =F28 -> 0.081219468 | G38: =G28 -> 0.082760367 | H38: =H28 -> 0.096668817
A39: ROE normalizado — Parque Arauco | E39: =Peers_inputs!$C$39 -> 0.039743587 | F39: =Peers_inputs!$D$39 -> 0.068141937 | G39: =Peers_inputs!$E$39 -> 0.066008029 | H39: =Peers_inputs!$F$39 -> 0.077679777
A40: ROE normalizado — Cencosud Shopping | E40: =Peers_inputs!$C$51 -> 0.060016229 | F40: =Peers_inputs!$D$51 -> 0.071900052 | G40: =Peers_inputs!$E$51 -> 0.078339223 | H40: =Peers_inputs!$F$51 -> 0.080249149
A41: ROE reportado — Mallplaza | E41: =E27 -> 0.071173939 | F41: =F27 -> 0.143805 | G41: =G27 -> 0.11666571 | H41: =H27 -> 0.37457282
A42: ROE reportado — Parque Arauco | E42: =Peers_inputs!$C$38 -> 0.090923105 | F42: =Peers_inputs!$D$38 -> 0.091941638 | G42: =Peers_inputs!$E$38 -> 0.087263993 | H42: =Peers_inputs!$F$38 -> 0.098054072
A43: ROE reportado — Cencosud Shopping | E43: =Peers_inputs!$C$50 -> 0.068084187 | F43: =Peers_inputs!$D$50 -> 0.069069748 | G43: =Peers_inputs!$E$50 -> 0.09580596 | H43: =Peers_inputs!$F$50 -> 0.10450597
A44: Revalorización / PI de apertura — Mallplaza | E44: n/d | F44: n/d | G44: =Inputs!$C$116/Inputs!$C$117 -> 0.037403105 | H44: =Inputs!$C$68/Inputs!$C$65 -> 0.27016246
A45: Revalorización / PI de apertura — Parque Arauco | E45: =Peers_inputs!$C$40 -> 0.048567519 | F45: =Peers_inputs!$D$40 -> 0.01955013 | G45: =Peers_inputs!$E$40 -> 0.018139215 | H45: =Peers_inputs!$F$40 -> 0.020001834
A46: Revalorización / PI de apertura — Cencosud Shopping | E46: =Peers_inputs!$C$52 -> 0.0077803556 | F46: =Peers_inputs!$D$52 -> -0.0027160201 | G46: =Peers_inputs!$E$52 -> 0.016855147 | H46: =Peers_inputs!$F$52 -> 0.02344585
A47: EBITDA / PI (yield sobre libro) — Mallplaza Chile | E47: n/d | F47: n/d | G47: =Inputs!$C$118/Inputs!$C$120 -> 0.084473813 | H47: =Inputs!$C$119/Inputs!$C$121 -> 0.072629524
A48: EBITDA / PI (yield sobre libro) — Parque Arauco | E48: =Peers_inputs!$C$41 -> 0.072889139 | F48: =Peers_inputs!$D$41 -> 0.068400406 | G48: =Peers_inputs!$E$41 -> 0.074849702 | H48: =Peers_inputs!$F$41 -> 0.075480203
A49: EBITDA / PI (yield sobre libro) — Cencosud Shopping | E49: =Peers_inputs!$C$53 -> 0.0667041 | F49: =Peers_inputs!$D$53 -> 0.071623849 | G49: =Peers_inputs!$E$53 -> 0.077795998 | H49: =Peers_inputs!$F$53 -> 0.0774797
A50: Apalancamiento (activos / patrimonio) — Mallplaza | E50: =E26 -> 1.9431209 | F50: =F26 -> 1.9139817 | G50: =G26 -> 1.8599697 | H50: =H26 -> 1.7666701
A51: Activos / patrimonio atribuible (cierre) — Parque Arauco | E51: =Peers_inputs!$C$44 -> 2.5662823 | F51: =Peers_inputs!$D$44 -> 2.6814542 | G51: =Peers_inputs!$E$44 -> 2.6839146 | H51: =Peers_inputs!$F$44 -> 2.6871269
A52: Activos / patrimonio atribuible (cierre) — Cencosud Shopping | E52: =Peers_inputs!$C$56 -> 1.5151378 | F52: =Peers_inputs!$D$56 -> 1.5111352 | G52: =Peers_inputs!$E$56 -> 1.5173648 | H52: =Peers_inputs!$F$56 -> 1.5059218
A53: Mallplaza normalizado = utilidad distribuible (Nota 20e); pares = utilidad − revalorización × (1 − 27%) [S]. Métodos distintos, declarados.
A54: Yield sobre libro aproximado: EBITDA consolidado / PI (incluye terrenos y proyectos); Mallplaza Chile usa resultado del segmento. Mallplaza Chile jun-26: 7,08% LTM (WP §64).
A55: Lectura (WP §85.3): en 2024 el libro de Mallplaza era el más conservador (yield 8,45% vs 7,5%–7,8%); la revalorización de 2025 cerró la brecha. Cierre definitivo: tasas de descuento de los pares (CMF).

Sheet E2_FFO_bridge
A1: Exhibit 2 — From reported profit to FFO, FY2025 (MM CLP)
A2: Reconstrucción propia; reproduce el FFO de la compañía con Δ −0,02%. Participación no controladora prorrateada por utilidad [S].
A4: Paso | B4: Monto | C4: Base (gráfico) | D4: Barra (gráfico)
A5: Ganancia consolidada | B5: =Inputs!$C$11 -> 1440978 | C5: 0 | D5: =B5 -> 1440978
A6: (−) Otros ingresos por función (revalorización) | B6: =-Inputs!$C$15 -> -1448943 | C6: =B5+B6 -> -7965 | D6: =-B6 -> 1448943
A7: (+) Otros gastos por función | B7: =Inputs!$C$16 -> 3511 | C7: =C6+IF(B6<0,0,D6) -> -7965 | D7: =B7 -> 3511
A8: (+) D&A | B8: =Inputs!$C$17 -> 3610 | C8: =C7+D7 -> -4454 | D8: =B8 -> 3610
A9: (+) Reajuste UF de la deuda | B9: =Inputs!$C$18 -> 43825 | C9: =C8+D8 -> -844 | D9: =B9 -> 43825
A10: (+) Impuesto diferido | B10: =Inputs!$C$19 -> 365071 | C10: =C9+D9 -> 42981 | D10: =B10 -> 365071
A11: FFO consolidado | B11: =SUM(B5:B10) -> 408052 | C11: 0 | D11: =B11 -> 408052
A12: (−) Participación no controladora (% de la utilidad) | B12: =-B11*Inputs!$C$14/Inputs!$C$11 -> -2822.4264
A13: FFO atribuible reconstruido | B13: =B11+B12 -> 405229.57
A14: FFO atribuible reportado (compañía) | B14: =Inputs!$C$20 -> 405300
A15: Diferencia | B15: =B13/B14-1 -> -0.00017376352
A16: Reajuste UF / FFO atribuible | B16: =B9/B13 -> 0.10814857
A18: Nota: columnas C–D solo alimentan el gráfico de cascada (base invisible).

Sheet E3_Growth
A1: Exhibit 3 — Growth: perimeter, indexation, real
A2: Deflactor Chile = UF promedio del período [C]. Colombia y Perú: tipo de cambio promedio (WP §82) e inflación local (WP §83). Bloque B = Exhibit 3 v1 (WP §84).
B4: FY2024 | C4: FY2025 | D4: 1S25 | E4: 1S26 | K4: 1S26 | L4: Reported (CLP) | M4: Real
A5: Ingresos consolidados | B5: =Inputs!$C$5 -> 494605 | C5: =Inputs!$C$6 -> 653911 | D5: =Inputs!$C$7 -> 316108 | E5: =Inputs!$C$8 -> 339530 | K5: Chile | L5: =B27 -> 0.060539575 | M5: =F27 -> 0.028266989
A6: Chile | B6: =Inputs!$C$35 -> 428322 | C6: =Inputs!$C$36 -> 469964 | D6: =Inputs!$C$29 -> 230626 | E6: =Inputs!$C$30 -> 244588 | K6: Peru | L6: =B28 -> 0.089139054 | M6: =F28 -> 0.044921018
A7: Colombia | B7: =Inputs!$C$37 -> 52671 | C7: =Inputs!$C$38 -> 62627 | D7: =Inputs!$C$31 -> 29393 | E7: =Inputs!$C$32 -> 33899 | K7: Colombia | L7: =B31 -> 0.15330181 | M7: =F31 -> 0.011081497
A8: Perú | B8: =Inputs!$C$39 -> 13612 | C8: =Inputs!$C$40 -> 121320 | D8: =Inputs!$C$33 -> 56496 | E8: =Inputs!$C$34 -> 61532 | K8: Consolidated | L8: =B32 -> 0.07409493 | M8: =F32 -> 0.029710902
A9: Rentas variables | B9: =Inputs!$C$42 -> 24833 | C9: =Inputs!$C$43 -> 38936 | D9: =Inputs!$C$44 -> 17521 | E9: =Inputs!$C$45 -> 17332 | K9: Rango auxiliar del gráfico "Reported vs real".
A10: UF promedio | B10: =Inputs!$C$46 -> 37569.64 | C10: =Inputs!$C$47 -> 39206.28 | D10: =Inputs!$C$48 -> 38841.29 | E10: =Inputs!$C$49 -> 40060.34
A12: Crecimiento | C12: FY2025 | E12: 1S26
A13: Consolidado nominal | C13: =C5/B5-1 -> 0.32208732 | E13: =E5/D5-1 -> 0.07409493 | G13: Serie | H13: FY2025 | I13: 1S26
A14: de lo cual: perímetro Perú (pp) | C14: =(C8-B8)/B5 -> 0.21776569 | G14: Nominal | H14: =C16 -> 0.097221249 | I14: =E16 -> 0.060539575
A15: Ex-Perú nominal (Chile + Colombia) | C15: =(C6+C7)/(B6+B7)-1 -> 0.10727391 | E15: =(E6+E7)/(D6+D7)-1 -> 0.071025579 | G15: UF | H15: =C17 -> 0.043562834 | I15: =E17 -> 0.031385415
A16: Chile nominal | C16: =C6/B6-1 -> 0.097221249 | E16: =E6/D6-1 -> 0.060539575 | G16: Real | H16: =C18 -> 0.05141848 | I16: =E18 -> 0.028266989
A17: Indexación UF (UF promedio) | C17: =C10/B10-1 -> 0.043562834 | E17: =E10/D10-1 -> 0.031385415
A18: Chile real | C18: =(1+C16)/(1+C17)-1 -> 0.05141848 | E18: =(1+E16)/(1+E17)-1 -> 0.028266989
A19: Colombia nominal en CLP (incluye FX) | C19: =C7/B7-1 -> 0.18902242 | E19: =E7/D7-1 -> 0.15330181
A20: Perú nominal en CLP (incluye FX) | C20: n.m. | E20: =E8/D8-1 -> 0.089139054
A21: Rentas variables / ingresos | B21: =B9/B5 -> 0.050207742 | C21: =C9/C5 -> 0.059543271 | D21: =D9/D5 -> 0.055427259 | E21: =E9/E5 -> 0.051047036
A22: Crecimiento rentas variables | C22: =C9/B9-1 -> 0.56791366 | E22: =E9/D9-1 -> -0.010787056
A23: Crecimiento ingresos no variables | C23: =(C5-C9)/(B5-B9)-1 -> 0.3090925 | E23: =(E5-E9)/(D5-D9)-1 -> 0.07907578
A25: B. By country: CLP → local currency → real | B25: Nominal CLP | C25: Efecto FX | D25: Moneda local | E25: Inflación / UF | F25: Real
A26: Chile FY2025 | B26: =C16 -> 0.097221249 | C26: 0 | D26: =(1+B26)/(1+C26)-1 -> 0.097221249 | E26: =C17 -> 0.043562834 | F26: =(1+D26)/(1+E26)-1 -> 0.05141848
A27: Chile 1S26 | B27: =E16 -> 0.060539575 | C27: 0 | D27: =(1+B27)/(1+C27)-1 -> 0.060539575 | E27: =E17 -> 0.031385415 | F27: =(1+D27)/(1+E27)-1 -> 0.028266989
A28: Perú 1S26 | B28: =E20 -> 0.089139054 | C28: =Inputs!$C$109/Inputs!$C$108-1 -> 0.0092168157 | D28: =(1+B28)/(1+C28)-1 -> 0.079192337 | E28: =Inputs!$C$112 -> 0.032798 | F28: =(1+D28)/(1+E28)-1 -> 0.044921018
A29: Colombia FY2024 | B29: =Inputs!$C$37/Inputs!$C$100-1 -> 0.44859736 | C29: =Inputs!$C$102/Inputs!$C$101-1 -> 0.17218697 | D29: =(1+B29)/(1+C29)-1 -> 0.23580742 | E29: =Inputs!$C$113 -> 0.052 | F29: =(1+D29)/(1+E29)-1 -> 0.17472189
A30: Colombia FY2025 | B30: =C19 -> 0.18902242 | C30: =Inputs!$C$103/Inputs!$C$102-1 -> 0.013395512 | D30: =(1+B30)/(1+C30)-1 -> 0.1733054 | E30: =Inputs!$C$114 -> 0.051 | F30: =(1+D30)/(1+E30)-1 -> 0.1163705
A31: Colombia 1S26 | B31: =E19 -> 0.15330181 | C31: =Inputs!$C$105/Inputs!$C$104-1 -> 0.074676436 | D31: =(1+B31)/(1+C31)-1 -> 0.073161901 | E31: =Inputs!$C$115 -> 0.0614 | F31: =(1+D31)/(1+E31)-1 -> 0.011081497
A32: Consolidado 1S26 (real ponderado por ingresos FY2025) | B32: =E13 -> 0.07409493 | F32: =(F27*Inputs!$C$36+F28*Inputs!$C$40+F31*Inputs!$C$38)/Inputs!$C$6 -> 0.029710902
A33: Perú FY2025 n.m. (perímetro: consolidado desde 04-12-2024). Chile: efecto FX = 0 por definición.
A34: Colombia 1S26: inflación = variación anual a jun-26 (DANE), PROXY del promedio 1S26/1S25; el real exacto quedaría ~+1% a +2%.
A35: Colombia FY2024–FY2025: un real de dos dígitos probablemente incluye GLA nuevo. No publicar como crecimiento same-store hasta verificar GLA por año (WP §84.2, pendiente #37).

Sheet E4_Cash
A1: Exhibit 4 — Cash conversion and dividend cover (MM CLP)
A2: Flujo operativo según EEFF (intereses en financiación). 1S26 incluye capital de trabajo estacional (WP §61).
B4: FY2024 | C4: FY2025 | D4: 1S26
A5: EBITDA | B5: =Inputs!$C$9 -> 380637 | C5: =Inputs!$C$10 -> 526228 | D5: =270574 -> 270574
A6: Flujo operativo | B6: =Inputs!$C$50 -> 300822 | C6: =Inputs!$C$51 -> 441135 | D6: =Inputs!$C$52 -> 258193
A7: (−) Capex total | B7: =-Inputs!$C$53 -> -76321 | C7: =-Inputs!$C$54 -> -103642 | D7: =-Inputs!$C$55 -> -84241
A8: (−) Intereses netos pagados | B8: =-Inputs!$C$56 -> -33436 | C8: =-Inputs!$C$57 -> -57423 | D8: =-Inputs!$C$58 -> -21601
A9: Flujo libre antes de amortizar deuda | B9: =SUM(B6:B8) -> 191065 | C9: =SUM(C6:C8) -> 280070 | D9: =SUM(D6:D8) -> 152351
A10: Dividendos pagados | B10: =Inputs!$C$59 -> 125751 | C10: =Inputs!$C$60 -> 108499 | D10: =Inputs!$C$61 -> 87617
A11: Cobertura de dividendos (x) | B11: =B9/B10 -> 1.5193915 | C11: =C9/C10 -> 2.5813141 | D11: =D9/D10 -> 1.7388292
A12: Capex / ingresos | B12: =-B7/Inputs!$C$5 -> 0.15430697 | C12: =-C7/Inputs!$C$6 -> 0.15849558 | D12: =-D7/Inputs!$C$8 -> 0.24811062
A13: Flujo operativo / EBITDA | B13: =B6/B5 -> 0.79031203 | C13: =C6/C5 -> 0.83829633 | D13: =D6/D5 -> 0.95424172

Sheet E5_Leverage
A1: Exhibit 5 — Leverage: three lenses and the revaluation effect
A2: LTV = DFN / propiedades de inversión. Contrafactual: PI dic-25 sin revalorización 2025.
B4: dic-24 | C4: dic-25 | D4: jun-26
A5: Deuda financiera neta | B5: =Inputs!$C$62 -> 1438401 | C5: =Inputs!$C$63 -> 1311024 | D5: =Inputs!$C$64 -> 1285740
A6: Propiedades de inversión | B6: =Inputs!$C$65 -> 5356540 | C6: =Inputs!$C$66 -> 6961880 | D6: =Inputs!$C$67 -> 7309810
A7: LTV | B7: =B5/B6 -> 0.26853174 | C7: =C5/C6 -> 0.18831465 | D7: =D5/D6 -> 0.1758924
A8: DFN / EBITDA (compañía) | B8: =Inputs!$C$69 -> 3.78 | C8: =Inputs!$C$70 -> 2.49 | D8: =Inputs!$C$71 -> 2.36
A9: DFN / Patrimonio (covenant) | B9: =Inputs!$C$72 -> 0.45 | C9: =Inputs!$C$73 -> 0.29 | D9: =Inputs!$C$74 -> 0.26
A11: Descomposición de la caída del LTV 2024→2025 | B11: pp
A12: LTV dic-24 | B12: =B7 -> 0.26853174
A13: LTV dic-25 contrafactual (PI sin revalorización) | B13: =C5/(C6-Inputs!$C$68) -> 0.23773071
A14: Efecto menor deuda neta y adiciones | B14: =B13-B12 -> -0.03080103
A15: Efecto revalorización | B15: =C7-B13 -> -0.049416058
A16: LTV dic-25 | B16: =C7 -> 0.18831465
A17: Revalorización / caída total | B17: =B15/(B16-B12) -> 0.61602907
A19: ALERTA: umbral del covenant publicado inconsistente (0,4x jun-24; "0,5x" dic-24; 2,0x dic-25). No mostrar holgura hasta verificar escrituras (WP §72).
A21: Peers (dic-25 / FY2025) | B21: Mallplaza | C21: Parque Arauco | D21: Cencosud Shopping
A22: LTV (deuda neta / PI) | B22: =C7 -> 0.18831465 | C22: =Peers_inputs!$F$42 -> 0.42903913 | D22: =Peers_inputs!$F$54 -> 0.16332278
A23: Deuda neta / EBITDA | B23: =C8 -> 2.49 | C23: =Peers_inputs!$F$43 -> 5.684128 | D23: =Peers_inputs!$F$55 -> 2.1079428
A24: Activos / patrimonio atribuible (cierre) | B24: =Inputs!$C$25/Inputs!$C$28 -> 1.6916805 | C24: =Peers_inputs!$F$44 -> 2.6871269 | D24: =Peers_inputs!$F$56 -> 1.5059218
A25: Mallplaza: DFN definición covenant (Nota 26). Pares: préstamos CP + deuda LP − caja (Bloomberg). Parque Arauco excluye negocios conjuntos de la PI: LTV y DN/EBITDA sobrestimados. Para Industry más que para FA.

Sheet E6_Debt
A1: Exhibit 6 — Bond maturities and coupon vs effective rate (dic-25)
A2: Bonos en UF, valor libro MM CLP (EEFF dic-25, Nota 14). Deuda bancaria (PEN/COP) aparte. Nunca usar DDIS (WP §54).
A4: Serie | B4: Vencimiento | C4: Valor libro | D4: Cupón | E4: Tasa efectiva | G4: Año | H4: Vencimientos bonos
A5: AA | B5: 2027 | C5: 39887 | D5: 0.028 | E5: 0.0332 | G5: 2027 | H5: =SUMIFS($C$5:$C$18,$B$5:$B$18,2027) -> 39887
A6: AD | B6: 2028 | C6: 59226 | D6: 0.036 | E6: 0.0421 | G6: 2028 | H6: =SUMIFS($C$5:$C$18,$B$5:$B$18,2028) -> 59226
A7: S | B7: 2029 | C7: 161405 | D7: 0.017 | E7: 0.0132 | G7: 2029 | H7: =SUMIFS($C$5:$C$18,$B$5:$B$18,2029) -> 161405
A8: C | B8: 2030 | C8: 6063 | D8: 0.045 | E8: 0.0472 | G8: 2030 | H8: =SUMIFS($C$5:$C$18,$B$5:$B$18,2030) -> 6063
A9: D | B9: 2031 | C9: 118970 | D9: 0.0385 | E9: 0.04 | G9: 2031 | H9: =SUMIFS($C$5:$C$18,$B$5:$B$18,2031) -> 198317
A10: E | B10: 2031 | C10: 79347 | D10: 0.0385 | E10: 0.0399 | G10: 2032 | H10: =SUMIFS($C$5:$C$18,$B$5:$B$18,2032) -> 89214
A11: U | B11: 2032 | C11: 89214 | D11: 0.036 | E11: 0.0476 | G11: 2033 | H11: =SUMIFS($C$5:$C$18,$B$5:$B$18,2033) -> 154709
A12: H | B12: 2033 | C12: 97208 | D12: 0.035 | E12: 0.039 | G12: 2034 | H12: =SUMIFS($C$5:$C$18,$B$5:$B$18,2034) -> 119065
A13: AE | B13: 2033 | C13: 57501 | D13: 0.036 | E13: 0.0433 | G13: 2035 | H13: =SUMIFS($C$5:$C$18,$B$5:$B$18,2035) -> 120963
A14: K | B14: 2034 | C14: 119065 | D14: 0.039 | E14: 0.0392 | G14: 2043 | H14: =SUMIFS($C$5:$C$18,$B$5:$B$18,2043) -> 128521
A15: N | B15: 2035 | C15: 120963 | D15: 0.038 | E15: 0.0376 | G15: 2045 | H15: =SUMIFS($C$5:$C$18,$B$5:$B$18,2045) -> 80219
A16: Z | B16: 2043 | C16: 128521 | D16: 0.042 | E16: 0.0366 | G16: 2047 | H16: =SUMIFS($C$5:$C$18,$B$5:$B$18,2047) -> 120126
A17: P | B17: 2045 | C17: 80219 | D17: 0.021 | E17: 0.0209
A18: AC | B18: 2047 | C18: 120126 | D18: 0.034 | E18: 0.0344
A19: Total bonos | C19: =SUM(C5:C18) -> 1277715 | D19: =SUMPRODUCT(C5:C18,D5:D18)/C19 -> 0.033647418 | E19: =SUMPRODUCT(C5:C18,E5:E18)/C19 -> 0.034761239
A20: Deuda bancaria (PEN/COP) | C20: =Inputs!$C$99 -> 301600
A21: Deuda financiera total | C21: =C19+C20 -> 1579315
A22: Control vs Nota 25 (1.579.315) | C22: =C21-1579315 -> 0
A24: Refinanciamiento serie S (2029) a la tasa efectiva de la AE: costo anual adicional | C24: =C7*(E13-E7) -> 4858.2905

Sheet E7_WACC
A1: Exhibit 7 — Discount rate vs the company's stated benchmark
A2: Benchmark = soberano USD 10Y = UST 10Y + spread país, el insumo que declara la Nota 11 (WP §15.2). WACC = punto medio del rango real después de impuestos de la Nota 11 (Nota 10 en intermedios). Fin de mes.
A3: Fuentes: Bloomberg HP 28-09-2026 (USGG10YR Index, USGGT10Y Index, GTUSDCL10YR, GTUSDPE10YR, Colombia USD 10Y genérico — confirmar ticker), fuente BGN para soberanos; Nota 11 EEFF dic-23 (vía dic-24), jun-24, dic-24, dic-25, jun-26 (WP §69, §81).
A5: Serie (fin de mes) | B5: dic-23 | C5: jun-24 | D5: dic-24 | E5: jun-25 | F5: dic-25 | G5: jun-26 | H5: Tag / fuente | J5: Fecha | K5: Nota 11 WACC Chile (real) | L5: Stated benchmark: Chile USD 10Y
A6: UST 10Y | B6: 0.038791 | C6: 0.043961 | D6: 0.04569 | E6: 0.04228 | F6: 0.04167 | G6: 0.044652 | H6: R — USGG10YR Index | J6: dic-23 | K6: =(B24-$B$24)*10000 -> 0 | L6: =(B8-$B$8)*10000 -> 0
A7: TIPS 10Y (real) | B7: 0.017056 | C7: 0.02107 | D7: 0.022277 | E7: 0.019286 | F7: 0.018984 | G7: 0.022221 | H7: R — USGGT10Y Index | J7: jun-24 | K7: =(C24-$B$24)*10000 -> -2.5 | L7: =(C8-$B$8)*10000 -> 39
A8: Chile USD 10Y | B8: 0.04889 | C8: 0.05279 | D8: 0.05448 | E8: 0.052 | F8: 0.04852 | G8: 0.05116 | H8: R — GTUSDCL10YR, BGN | J8: dic-24 | K8: =(D24-$B$24)*10000 -> 13 | L8: =(D8-$B$8)*10000 -> 55.9
A9: Perú USD 10Y | B9: 0.05019 | C9: 0.05553 | D9: 0.05826 | E9: 0.05421 | F9: 0.05244 | G9: 0.05379 | H9: R — GTUSDPE10YR, BGN | J9: dic-25 | K9: =(F24-$B$24)*10000 -> -85 | L9: =(F8-$B$8)*10000 -> -3.7
A10: Colombia USD 10Y | B10: 0.06746 | C10: 0.07513 | D10: 0.07704 | E10: 0.07933 | F10: 0.07056 | G10: 0.06541 | H10: R — genérico Colombia USD 10Y, BGN [P: confirmar ticker] | J10: jun-26 | K10: =(G24-$B$24)*10000 -> -93.5 | L10: =(G8-$B$8)*10000 -> 22.7
A11: WACC Chile — mínimo | B11: 0.0616 | C11: 0.062 | D11: 0.0656 | E11: 0.0602 | F11: 0.0546 | G11: 0.0547 | H11: R — Nota 11 | J11: Rango auxiliar del gráfico: cambio acumulado desde dic-23 en pb (compara movimientos, no niveles: el WACC es real y el benchmark nominal en USD). Omite jun-25 (WACC pendiente).
A12: WACC Chile — máximo | B12: 0.0681 | C12: 0.0672 | D12: 0.0667 | E12: 0.0615 | F12: 0.0581 | G12: 0.0563 | H12: R — Nota 11
A13: WACC Perú — mínimo | B13: 0.0626 | C13: 0.0632 | D13: 0.0672 | E13: 0.0627 | F13: 0.0562 | G13: 0.0575 | H13: R — Nota 11
A14: WACC Perú — máximo | B14: 0.069 | C14: 0.0683 | D14: 0.0683 | E14: 0.064 | F14: 0.0597 | G14: 0.059 | H14: R — Nota 11
A15: WACC Colombia — mínimo | B15: 0.0756 | C15: 0.0766 | D15: 0.0816 | E15: 0.0804 | F15: 0.0723 | G15: 0.072 | H15: R — Nota 11
A16: WACC Colombia — máximo | B16: 0.0819 | C16: 0.0816 | D16: 0.0826 | E16: 0.0817 | F16: 0.0756 | G16: 0.0735 | H16: R — Nota 11
A17: jun-25: EEFF intermedios jun-25, Nota 11 (tasas de descuento). Dic-22 (no graficado): Chile 5,97%–6,61%, Perú 5,91%–6,55%, Colombia 7,45%–8,07% (EEFF dic-23, Nota 12).
A19: Cálculos [C] | B19: dic-23 | C19: jun-24 | D19: dic-24 | E19: jun-25 | F19: dic-25 | G19: jun-26
A20: Breakeven EE.UU. (UST − TIPS) | B20: =B6-B7 -> 0.021735 | C20: =C6-C7 -> 0.022891 | D20: =D6-D7 -> 0.023413 | E20: =E6-E7 -> 0.022994 | F20: =F6-F7 -> 0.022686 | G20: =G6-G7 -> 0.022431
A21: Spread país Chile (Chile USD − UST) | B21: =B8-B6 -> 0.010099 | C21: =C8-C6 -> 0.008829 | D21: =D8-D6 -> 0.00879 | E21: =E8-E6 -> 0.00972 | F21: =F8-F6 -> 0.00685 | G21: =G8-G6 -> 0.006508
A22: Spread país Perú | B22: =B9-B6 -> 0.011399 | C22: =C9-C6 -> 0.011569 | D22: =D9-D6 -> 0.01257 | E22: =E9-E6 -> 0.01193 | F22: =F9-F6 -> 0.01077 | G22: =G9-G6 -> 0.009138
A23: Spread país Colombia | B23: =B10-B6 -> 0.028669 | C23: =C10-C6 -> 0.031169 | D23: =D10-D6 -> 0.03135 | E23: =E10-E6 -> 0.03705 | F23: =F10-F6 -> 0.02889 | G23: =G10-G6 -> 0.020758
A24: WACC Chile — punto medio | B24: =IF(OR(B11="",B12=""),"",(B11+B12)/2) -> 0.06485 | C24: =IF(OR(C11="",C12=""),"",(C11+C12)/2) -> 0.0646 | D24: =IF(OR(D11="",D12=""),"",(D11+D12)/2) -> 0.06615 | E24: =IF(OR(E11="",E12=""),"",(E11+E12)/2) -> 0.06085 | F24: =IF(OR(F11="",F12=""),"",(F11+F12)/2) -> 0.05635 | G24: =IF(OR(G11="",G12=""),"",(G11+G12)/2) -> 0.0555
A25: WACC Perú — punto medio | B25: =IF(OR(B13="",B14=""),"",(B13+B14)/2) -> 0.0658 | C25: =IF(OR(C13="",C14=""),"",(C13+C14)/2) -> 0.06575 | D25: =IF(OR(D13="",D14=""),"",(D13+D14)/2) -> 0.06775 | E25: =IF(OR(E13="",E14=""),"",(E13+E14)/2) -> 0.06335 | F25: =IF(OR(F13="",F14=""),"",(F13+F14)/2) -> 0.05795 | G25: =IF(OR(G13="",G14=""),"",(G13+G14)/2) -> 0.05825
A26: WACC Colombia — punto medio | B26: =IF(OR(B15="",B16=""),"",(B15+B16)/2) -> 0.07875 | C26: =IF(OR(C15="",C16=""),"",(C15+C16)/2) -> 0.0791 | D26: =IF(OR(D15="",D16=""),"",(D15+D16)/2) -> 0.0821 | E26: =IF(OR(E15="",E16=""),"",(E15+E16)/2) -> 0.08105 | F26: =IF(OR(F15="",F16=""),"",(F15+F16)/2) -> 0.07395 | G26: =IF(OR(G15="",G16=""),"",(G15+G16)/2) -> 0.07275
A28: Residuo = Δ WACC − Δ benchmark (pb) | B28: Chile | C28: Perú | D28: Colombia
A29: 2024 (dic-23 → dic-24) | B29: =((D24-B24)-(D8-B8))*10000 -> -42.9 | C29: =((D25-B25)-(D9-B9))*10000 -> -61.2 | D29: =((D26-B26)-(D10-B10))*10000 -> -62.3
A30: 2025 (dic-24 → dic-25) | B30: =((F24-D24)-(F8-D8))*10000 -> -38.4 | C30: =((F25-D25)-(F9-D9))*10000 -> -39.8 | D30: =((F26-D26)-(F10-D10))*10000 -> -16.7
A31: 1S26 (dic-25 → jun-26) | B31: =((G24-F24)-(G8-F8))*10000 -> -34.9 | C31: =((G25-F25)-(G9-F9))*10000 -> -10.5 | D31: =((G26-F26)-(G10-F10))*10000 -> 39.5
A32: Acumulado dic-23 → jun-26 | B32: =((G24-B24)-(G8-B8))*10000 -> -116.2 | C32: =((G25-B25)-(G9-B9))*10000 -> -111.5 | D32: =((G26-B26)-(G10-B10))*10000 -> -39.5
A33: Peso en PI jun-26 | B33: =Inputs!$C$122/(Inputs!$C$122+Inputs!$C$123+Inputs!$C$124) -> 0.74598505 | C33: =Inputs!$C$123/(Inputs!$C$122+Inputs!$C$123+Inputs!$C$124) -> 0.17635041 | D33: =Inputs!$C$124/(Inputs!$C$122+Inputs!$C$123+Inputs!$C$124) -> 0.077664536
A34: Residuo acumulado ponderado por PI (pb) | B34: =SUMPRODUCT(B32:D32,B33:D33) -> -109.41428
A36: Regla ex ante (ventana dic-24 → jun-26, WP §81.4) | B36: Chile | C36: Perú | D36: Colombia
A37: Umbral: se mantiene si el mercado explica menos de [S] | B37: 0.5
A38: Umbral: se reescribe si el mercado explica más de [S] | B38: 0.8
A39: Δ benchmark (pb) | B39: =(G8-D8)*10000 -> -33.2 | C39: =(G9-D9)*10000 -> -44.7 | D39: =(G10-D10)*10000 -> -116.3
A40: Δ WACC (pb) | B40: =(G24-D24)*10000 -> -106.5 | C40: =(G25-D25)*10000 -> -95 | D40: =(G26-D26)*10000 -> -93.5
A41: % explicado por el mercado | B41: =IF(B40=0,"",B39/B40) -> 0.31173709 | C41: =IF(C40=0,"",C39/C40) -> 0.47052632 | D41: =IF(D40=0,"",D39/D40) -> 1.2438503
A42: Resultado | B42: =IF(B41="","",IF(B41<$B$37,"Se mantiene",IF(B41>$B$38,"No se mantiene","Zona intermedia"))) -> Se mantiene | C42: =IF(C41="","",IF(C41<$B$37,"Se mantiene",IF(C41>$B$38,"No se mantiene","Zona intermedia"))) -> Se mantiene | D42: =IF(D41="","",IF(D41<$B$37,"Se mantiene",IF(D41>$B$38,"No se mantiene","Zona intermedia"))) -> No se mantiene
A44: Mercado al 28-09-2026 (post jun-26) | B44: Nivel | C44: Δ vs jun-26 (pb) | D44: Fuente
A45: UST 10Y | B45: 0.052277 | C45: =(B45-G6)*10000 -> 76.25 | D45: R — HP USGG10YR, 28-09-2026 17:12
A46: Chile USD 10Y | B46: 0.05956 | C46: =(B46-G8)*10000 -> 84 | D46: R — WB, 28-09-2026
A47: Perú USD 10Y | B47: 0.06146 | C47: =(B47-G9)*10000 -> 76.7 | D47: R — WB, 28-09-2026
A48: Colombia USD 10Y | B48: 0.07557 | C48: =(B48-G10)*10000 -> 101.6 | D48: R — WB, 28-09-2026
A49: WB muestra bonos benchmark específicos (Chile 4.95 36, Perú 6.55 37, Colombia 7¾ 36); nivel comparable con el genérico, no idéntico.
A51: Residuo por semestre 2025 (pb) = Δ WACC − Δ benchmark | B51: Chile | C51: Perú | D51: Colombia
A52: 1S25 (dic-24 → jun-25) | B52: =((E24-D24)-(E8-D8))*10000 -> -28.2 | C52: =((E25-D25)-(E9-D9))*10000 -> -3.5 | D52: =((E26-D26)-(E10-D10))*10000 -> -33.4
A53: 2S25 (jun-25 → dic-25) | B53: =((F24-E24)-(F8-E8))*10000 -> -10.2 | C53: =((F25-E25)-(F9-E9))*10000 -> -36.3 | D53: =((F26-E26)-(F10-E10))*10000 -> 16.7
A54: Tasa del impuesto diferido [S] | B54: 0.27
A55: Acciones (MM) | B55: =Inputs!$C$125 -> 2190
A56: WACC Chile base jun-26 | B56: =G24 -> 0.0555
A58: Escenario | B58: WACC Chile | C58: Δ valor PI | D58: Δ valor PI (MM CLP) | E58: Neto de impuesto diferido | F58: CLP por acción
A59: WACC sigue su benchmark desde dic-23 | B59: =B24+(G8-B8) -> 0.06712 | C59: =($B$56-$B$53)/(B59-$B$53)-1 -> -0.0011317682 | D59: =C59*$B$52 -> 0.031915863 | E59: =D59*(1-$B$54) -> 0.02329858 | F59: =E59/$B$55 -> 1.0638621e-05
A60: Traspaso del alza post jun-26 (Chile USD) | B60: =B56+(B46-G8) -> 0.0639 | C60: =($B$56-$B$53)/(B60-$B$53)-1 -> -0.00081840236 | D60: =C60*$B$52 -> 0.023078947 | E60: =D60*(1-$B$54) -> 0.016847631 | F60: =E60/$B$55 -> 7.6929822e-06
A61: Orden de magnitud, no estimación: supone que todo el movimiento del benchmark se traspasa al WACC real y g constante. Insumo para valuation / Risks.

Sheet E8_ROIC_RONIC
A1: Exhibit 8 — ROIC (capital invertido a valor razonable) y RONIC de la expansión
A2: ROIC = NOPAT / capital invertido promedio, con capital = patrimonio atribuible + DFN, a valor razonable (NIC 40). Reproduce el 7,3% del Anexo 3 de Análisis Financiero. RONIC = yield on cost × (1 − t), real.
A3: Convención del libro: azul = dato; verde = vínculo a otra hoja; negro = fórmula; amarillo = insumo que viene del modelo de valoración v2 (otro libro).
A5: A. ROIC (MM CLP) | B5: dic-24 | C5: dic-25
A6: EBITDA (definición compañía) | B6: =Inputs!$C$9 -> 380637 | C6: =Inputs!$C$10 -> 526228
A7: D&A (2024: razón D&A/ingresos de 2025, supuesto [S]) | B7: =B8*B9 -> 2730.5307 | C7: =Inputs!$C$17 -> 3610
A8: D&A / ingresos | B8: =C8 -> 0.005520629 | C8: =C7/C9 -> 0.005520629
A9: Ingresos ordinarios | B9: =Inputs!$C$5 -> 494605 | C9: =Inputs!$C$6 -> 653911
A10: EBIT = EBITDA − D&A | B10: =B6-B7 -> 377906.47 | C10: =C6-C7 -> 522618
A11: Tasa de impuesto operacional de largo plazo | B11: =$C$11 -> 0.27 | C11: 0.27
A12: NOPAT = EBIT × (1 − t) | B12: =B10*(1-B11) -> 275871.72 | C12: =C10*(1-C11) -> 381511.14
A14: Patrimonio atribuible al cierre | B14: =Inputs!$C$27 -> 3157863 | C14: =Inputs!$C$28 -> 4482905
A15: Deuda financiera neta (covenant) | B15: =Inputs!$C$62 -> 1438401 | C15: =Inputs!$C$63 -> 1311024
A16: Capital invertido al cierre = patrimonio + DFN | B16: =B14+B15 -> 4596264 | C16: =C14+C15 -> 5793929
A17: Capital invertido promedio dic-24 / dic-25 | C17: =AVERAGE(B16:C16) -> 5195096.5
A18: Propiedades de inversión al cierre | B18: =Inputs!$C$65 -> 5356540 | C18: =Inputs!$C$66 -> 6961880
A20: B. ROIC 2025 según la definición del capital | C20: ROIC
A21: Capital promedio (patrimonio + DFN) — definición usada | C21: =C12/C17 -> 0.073436776
A22: Capital de cierre (patrimonio + DFN) | C22: =C12/C16 -> 0.065846706
A23: Propiedades de inversión de cierre | C23: =C12/C18 -> 0.054800017
A24: Valor publicado en el Anexo 3 de Análisis Financiero | C24: 0.073
A25: Tasa de impuesto operacional (insumo de la sección A y B) | C25: =C11 -> 0.27
A26: Diferencia vs Anexo 3 (pp) | C26: =(C21-C24)*100 -> 0.043677639
A27: Nota: 2024 y 2023 no se reproducen de forma exacta (falta la D&A de 2024 y la DFN de dic-22/dic-23 en Inputs); solo el 2025 queda con su fórmula completa.
A29: C. ROIC frente a la WACC (insumos de v2, hoja WACC) | C29: Valor
A30: WACC nominal CLP, terminal | C30: 0.10413887
A31: WACC real, terminal | C31: 0.071979483
A32: ROIC 2025 − WACC nominal (pp) | C32: =(C21-C30)*100 -> -3.0702091
A33: ROIC 2025 − WACC real (pp) | C33: =(C21-C31)*100 -> 0.14572935
A34: Lectura: el ROIC es un retorno sobre capital tasado hoy (pesos actuales), comparable con la WACC real; contra la nominal mezcla bases. La conclusión de que crecer resta valor descansa en el RONIC (sección D).
A36: D. RONIC de la expansión (modelo v2, hoja Expansion) | C36: Valor
A37: Yield on cost derivado = EBITDA maduro por m² / costo por m² (2026) | C37: 0.069018971
A38: Tasa de impuesto operacional de largo plazo | C38: =C11 -> 0.27
A39: RONIC real después de impuestos = yield × (1 − t) | C39: =C37*(1-C38) -> 0.050383849
A40: WACC real, terminal | C40: =C31 -> 0.071979483
A41: RONIC − WACC real (pp) | C41: =(C39-C40)*100 -> -2.1595634
A42: ¿Crecer crea valor? (RONIC > WACC real) | C42: =IF(C39>C40,"Sí","No: resta valor") -> No: resta valor
A43: Crecimiento terminal nominal (g) | C43: 0.03
A44: Inflación de largo plazo Chile | C44: 0.03
A45: g real = (1 + g) / (1 + π) − 1 | C45: =(1+C43)/(1+C44)-1 -> 0
A46: Tasa de reinversión terminal = g real / RONIC | C46: =C45/C39 -> 0
A47: Fuente: Mallplaza_Valoracion_Consolidada_v2.xlsx — Expansion!C36:C38, WACC!I43:I44, Supuestos!B59, B34, B88. Los valores amarillos se pegan a mano desde v2; actualizarlos si cambia el modelo.
